Workbook

Sheet הערות כלליות
A1: תיאור | B1: לשוניות | C1: שאלות | D1: שם חדש
A2: מפלגה/קואליציה מועדפת - יש נוסחים שונים | B2: עניין פוליטי, זיקה רגשית, העדפות, ציפיות
A3: התאמה לראשות ממשלה - יש נוסחים שונים | B3: תכונות
A4: ציפיות קואליציה - יש נוסחים שונים | B4: ציפיות
A5: מי יטפל טוב יותר בבעיות כלכליות - יש נוסחים שונים ומעבר בין שאלה המתייחסת למועמד ושאלה המתייחסת למפלגה | B5: כלכלה-חברה
A6: דירוג סיכון מלחמה בצפון - נוסחים שונים: 1992 - מלחמה עם הערבים, 2006 - מלחמה בצפון, 2009 - מלחמה עם חיזבאללה, 2015 - מלחמה עם סוריה | B6: חוץ ובטחון
A7: תחנות רדיו - יש נוסחים שונים לשאלה "לאיזו תחנת רדיו אתה מאזין" | B7: תקשורת

Sheet איחוד שאלות
A1: שם | B1: שם חדש | C1: מדרגה 1 | D1: מדרגה 2 | E1: מדרגה 3 | F1: מדרגה 4 | G1: מדרגה 5 | H1: לשונית | I1: מדרגה 1 | J1: מדרגה 2 | K1: מדרגה 3 | L1: מדרגה 4 | M1: מדרגה 5 | N1: שם
A2: ID | B2: ID | C2: {=_xlfn.TEXTSPLIT('איחוד שאלות'!$B2,"_")} -> ID | H2: דמוגרפיה | I2: ID | N2: ID
A3: תאריך | B3: questionnaire_date | C3: {=_xlfn.TEXTSPLIT('איחוד שאלות'!$B3,"_")} -> questionnaire | D3: date | H3: דמוגרפיה | I3: questionnaire | J3: date | N3: תאריך
A4: תאריך פוסט בחירות | B4: questionnaire_date_post | C4: {=_xlfn.TEXTSPLIT('איחוד שאלות'!$B4,"_")} -> questionnaire | D4: date | E4: post | H4: דמוגרפיה | I4: questionnaire | J4: date | K4: post | N4: תאריך פוסט בחירות
A5: מקום הראיון | B5: questionnaire_location | C5: {=_xlfn.TEXTSPLIT('איחוד שאלות'!$B5,"_")} -> questionnaire | D5: location | H5: דמוגרפיה | I5: questionnaire | J5: location | N5: מקום הראיון
A6: סקטור | B6: demography_identity_sector | C6: {=_xlfn.TEXTSPLIT('איחוד שאלות'!$B6,"_")} -> demography | D6: identity | E6: sector | H6: דמוגרפיה | I6: demography | J6: identity | K6: sector | N6: סקטור
A7: פאנל | B7: questionnaire_panel | C7: {=_xlfn.TEXTSPLIT('איחוד שאלות'!$B7,"_")} -> questionnaire | D7: panel | H7: דמוגרפיה | I7: questionnaire | J7: panel | N7: פאנל
A8: גרסה | B8: questionnaire_version | C8: {=_xlfn.TEXTSPLIT('איחוד שאלות'!$B8,"_")} -> questionnaire | D8: version | H8: דמוגרפיה | I8: questionnaire | J8: version | N8: גרסה
A9: שפה | B9: questionnaire_language | C9: {=_xlfn.TEXTSPLIT('איחוד שאלות'!$B9,"_")} -> questionnaire | D9: language | H9: דמוגרפיה | I9: questionnaire | J9: language | N9: שפה
A10: גיל | B10: demography_age | C10: {=_xlfn.TEXTSPLIT('איחוד שאלות'!$B10,"_")} -> demography | D10: age | H10: דמוגרפיה | I10: demography | J10: age | N10: גיל
A11: כיצד היית מגדיר את עצמך? (עדה) | B11: demography_identity_jewishetnicity | C11: {=_xlfn.TEXTSPLIT('איחוד שאלות'!$B11,"_")} -> demography | D11: identity | E11: jewishetnicity | H11: דמוגרפיה | I11: demography | J11: identity | K11: jewishetnicity | N11: כיצד היית מגדיר את עצמך? (עדה)
A12: עדה | B12: demography_identity_jewishetnicity | C12: {=_xlfn.TEXTSPLIT('איחוד שאלות'!$B12,"_")} -> demography | D12: identity | E12: jewishetnicity | H12: דמוגרפיה | I12: demography | J12: identity | K12: jewishetnicity | N12: עדה
A13: לאיזו קבוצת גיל אתה משתייך? | B13: demography_age_group | C13: {=_xlfn.TEXTSPLIT('איחוד שאלות'!$B13,"_")} -> demography | D13: age | E13: group | H13: דמוגרפיה | I13: demography | J13: age | K13: group | N13: לאיזו קבוצת גיל אתה משתייך?
A14: מגדר | B14: demography_identity_gender | C14: {=_xlfn.TEXTSPLIT('איחוד שאלות'!$B14,"_")} -> demography | D14: identity | E14: gender | H14: דמוגרפיה | I14: demography | J14: identity | K14: gender | N14: מגדר
A15: מהי השכלתך? | B15: demography_educ | C15: {=_xlfn.TEXTSPLIT('איחוד שאלות'!$B15,"_")} -> demography | D15: educ | H15: דמוגרפיה | I15: demography | J15: educ | N15: מהי השכלתך?
A16: כמה שנים למדת במסגרת מסודרת? | B16: demography_educ_years | C16: {=_xlfn.TEXTSPLIT('איחוד שאלות'!$B16,"_")} -> demography | D16: educ | E16: years | H16: דמוגרפיה | I16: demography | J16: educ | K16: years | N16: כמה שנים למדת במסגרת מסודרת?
A17: האם למדת את לימודייך התיכוניים או העל-תיכוניים במסגרת דתית כלשהי? | B17: demography_educ_religious | C17: {=_xlfn.TEXTSPLIT('איחוד שאלות'!$B17,"_")} -> demography | D17: educ | E17: religious | H17: דמוגרפיה | I17: demography | J17: educ | K17: religious | N17: האם למדת את לימודייך התיכוניים או העל-תיכוניים במסגרת דתית כלשהי?
A18: מהי ההשכלה של בן/בת זוגך? | B18: demography_educ_partner | C18: {=_xlfn.TEXTSPLIT('איחוד שאלות'!$B18,"_")} -> demography | D18: educ | E18: partner | H18: דמוגרפיה | I18: demography | J18: educ | K18: partner | N18: מהי ההשכלה של בן/בת זוגך?
A19: האם יש לך תואר אקדמי? | B19: demography_educ_academy | C19: {=_xlfn.TEXTSPLIT('איחוד שאלות'!$B19,"_")} -> demography | D19: educ | E19: academy | H19: דמוגרפיה | I19: demography | J19: educ | K19: academy | N19: האם יש לך תואר אקדמי?
A20: מהו מוסד הלימודים האחרון בו למדת? | B20: demography_educ_last | C20: {=_xlfn.TEXTSPLIT('איחוד שאלות'!$B20,"_")} -> demography | D20: educ | E20: last | H20: דמוגרפיה | I20: demography | J20: educ | K20: last | N20: מהו מוסד הלימודים האחרון בו למדת?
A21: האם אתה אזרח ישראלי? | B21: attribute_identity_citizen | C21: {=_xlfn.TEXTSPLIT('איחוד שאלות'!$B21,"_")} -> attribute | D21: identity | E21: citizen | H21: דמוגרפיה | I21: attribute | J21: identity | K21: citizen | N21: האם אתה אזרח ישראלי?
A22: באיזו ארץ נולדת? | B22: demography_birthcountry_self | C22: {=_xlfn.TEXTSPLIT('איחוד שאלות'!$B22,"_")} -> demography | D22: birthcountry | E22: self | H22: דמוגרפיה | I22: demography | J22: birthcountry | K22: self | N22: באיזו ארץ נולדת?
A23: ארץ לידה/מוצא אב | B23: demography_birthcountry_father | C23: {=_xlfn.TEXTSPLIT('איחוד שאלות'!$B23,"_")} -> demography | D23: birthcountry | E23: father | H23: דמוגרפיה | I23: demography | J23: birthcountry | K23: father | N23: ארץ לידה/מוצא אב
A24: היכן נולד אביך? | B24: demography_birthcountry_father | C24: {=_xlfn.TEXTSPLIT('איחוד שאלות'!$B24,"_")} -> demography | D24: birthcountry | E24: father | H24: דמוגרפיה | I24: demography | J24: birthcountry | K24: father | N24: היכן נולד אביך?
A25: היכן נולדה אמך? | B25: demography_birthcountry_mother | C25: {=_xlfn.TEXTSPLIT('איחוד שאלות'!$B25,"_")} -> demography | D25: birthcountry | E25: mother | H25: דמוגרפיה | I25: demography | J25: birthcountry | K25: mother | N25: היכן נולדה אמך?
A26: באיזו ארץ נולד/ה בן/בת זוגך? | B26: demography_birthcountry_partner | C26: {=_xlfn.TEXTSPLIT('איחוד שאלות'!$B26,"_")} -> demography | D26: birthcountry | E26: partner | H26: דמוגרפיה | I26: demography | J26: birthcountry | K26: partner | N26: באיזו ארץ נולד/ה בן/בת זוגך?
A27: אם לא נולד בארץ, באיזו שנה עלית ארצה? | B27: demography_imm_year | C27: {=_xlfn.TEXTSPLIT('איחוד שאלות'!$B27,"_")} -> demography | D27: imm | E27: year | H27: דמוגרפיה | I27: demography | J27: imm | K27: year | N27: אם לא נולד בארץ, באיזו שנה עלית ארצה?
A28: האם נולדת באחת מארצות ברה"מ ועלית ארצה אחרי 1988? | B28: demography_imm_USSR | C28: {=_xlfn.TEXTSPLIT('איחוד שאלות'!$B28,"_")} -> demography | D28: imm | E28: USSR | H28: דמוגרפיה | I28: demography | J28: imm | K28: USSR | N28: האם נולדת באחת מארצות ברה"מ ועלית ארצה אחרי 1988?
A29: באיזו עיר בברה"מ לשעבר גרת לפני שעלית ארצה? | B29: demography_imm_USSR_residence | C29: {=_xlfn.TEXTSPLIT('איחוד שאלות'!$B29,"_")} -> demography | D29: imm | E29: USSR | F29: residence | H29: דמוגרפיה | I29: demography | J29: imm | K29: USSR | L29: residence | N29: באיזו עיר בברה"מ לשעבר גרת לפני שעלית ארצה?
A30: מה היה הלאום שהיה רשום בפספורט הסובייטי הפנימי שלך? | B30: demography_imm_USSR_nationality | C30: {=_xlfn.TEXTSPLIT('איחוד שאלות'!$B30,"_")} -> demography | D30: imm | E30: USSR | F30: nationality | H30: דמוגרפיה | I30: demography | J30: imm | K30: USSR | L30: nationality | N30: מה היה הלאום שהיה רשום בפספורט הסובייטי הפנימי שלך?
A31: לגבי החברים שלך בארץ, היית אומר שהרוב: | B31: ???_friends_imm_USSR | C31: {=_xlfn.TEXTSPLIT('איחוד שאלות'!$B31,"_")} -> ??? | D31: friends | E31: imm | F31: USSR | H31: דמוגרפיה | I31: ??? | J31: friends | K31: imm | L31: USSR | N31: לגבי החברים שלך בארץ, היית אומר שהרוב:
A32: איזה מבין המונחים הבאים מגדיר בצורה הטובה ביותר את זהותך? | B32: demography_identity_hierarchy_1 | C32: {=_xlfn.TEXTSPLIT('איחוד שאלות'!$B32,"_")} -> demography | D32: identity | E32: hierarchy | F32: 1 | H32: דמוגרפיה | I32: demography | J32: identity | K32: hierarchy | L32: 1 | N32: איזה מבין המונחים הבאים מגדיר בצורה הטובה ביותר את זהותך?
A33: והשני? | B33: demography_identity_hierarchy_2 | C33: {=_xlfn.TEXTSPLIT('איחוד שאלות'!$B33,"_")} -> demography | D33: identity | E33: hierarchy | F33: 2 | H33: דמוגרפיה | I33: demography | J33: identity | K33: hierarchy | L33: 2 | N33: והשני?
A34: והשלישי? | B34: demography_identity_hierarchy_3 | C34: {=_xlfn.TEXTSPLIT('איחוד שאלות'!$B34,"_")} -> demography | D34: identity | E34: hierarchy | F34: 3 | H34: דמוגרפיה | I34: demography | J34: identity | K34: hierarchy | L34: 3 | N34: והשלישי?
A35: והרביעי? | B35: demography_identity_hierarchy_4 | C35: {=_xlfn.TEXTSPLIT('איחוד שאלות'!$B35,"_")} -> demography | D35: identity | E35: hierarchy | F35: 4 | H35: דמוגרפיה | I35: demography | J35: identity | K35: hierarchy | L35: 4 | N35: והרביעי?
A36: לאיזה מעמד חברתי אתה משייך את עצמך? | B36: demography_identity_class | C36: {=_xlfn.TEXTSPLIT('איחוד שאלות'!$B36,"_")} -> demography | D36: identity | E36: class | H36: דמוגרפיה | I36: demography | J36: identity | K36: class | N36: לאיזה מעמד חברתי אתה משייך את עצמך?
A37: ההוצאה החודשית הממוצעת של משפחה בישראל היא כ-16,500 ₪. בהתחשב בכל ההוצאות של משפחתכם, האם אתם מוציאים: | B37: demography_wealth_household_expense | C37: {=_xlfn.TEXTSPLIT('איחוד שאלות'!$B37,"_")} -> demography | D37: wealth | E37: household | F37: expense | H37: דמוגרפיה | I37: demography | J37: wealth | K37: household | L37: expense | N37: ההוצאה החודשית הממוצעת של משפחה בישראל היא כ-16,500 ₪. בהתחשב בכל ההוצאות של משפחתכם, האם אתם מוציאים:
A38: כמה כסף מוציאה המשפחה שלכם בממוצע בחודש? | B38: demography_wealth_household_expense | C38: {=_xlfn.TEXTSPLIT('איחוד שאלות'!$B38,"_")} -> demography | D38: wealth | E38: household | F38: expense | H38: דמוגרפיה | I38: demography | J38: wealth | K38: household | L38: expense | N38: כמה כסף מוציאה המשפחה שלכם בממוצע בחודש?
A39: חשוב על הכנסותיהם של כל בני הבית ועל כל ההכנסות במתקבלות במשק הבית בכללו. מהו מקור ההכנסה העיקרי של משק הבית שלך? | B39: demography_wealth_household_incomeprimery | C39: {=_xlfn.TEXTSPLIT('איחוד שאלות'!$B39,"_")} -> demography | D39: wealth | E39: household | F39: incomeprimery | H39: דמוגרפיה | I39: demography | J39: wealth | K39: household | L39: incomeprimery | N39: חשוב על הכנסותיהם של כל בני הבית ועל כל ההכנסות במתקבלות במשק הבית בכללו. מהו מקור ההכנסה העיקרי של משק הבית שלך?
A40: מהי ההכנסה של משק הבית שלך מכל המקורות, אחרי ניכוי מיסים וניכויי חובה אחרים? | B40: demography_wealth_household_incomehousehold | C40: {=_xlfn.TEXTSPLIT('איחוד שאלות'!$B40,"_")} -> demography | D40: wealth | E40: household | F40: incomehousehold | H40: דמוגרפיה | I40: demography | J40: wealth | K40: household | L40: incomehousehold | N40: מהי ההכנסה של משק הבית שלך מכל המקורות, אחרי ניכוי מיסים וניכויי חובה אחרים?
A41: איזה חלק מההכנסה של משק הבית מהווה ההכנסה שלך? | B41: demography_wealth_household_incomeproportion | C41: {=_xlfn.TEXTSPLIT('איחוד שאלות'!$B41,"_")} -> demography | D41: wealth | E41: household | F41: incomeproportion | H41: דמוגרפיה | I41: demography | J41: wealth | K41: household | L41: incomeproportion | N41: איזה חלק מההכנסה של משק הבית מהווה ההכנסה שלך?
A42: מהי ההכנסה החודשית ברוטו שלך בלבד? | B42: demography_wealth_incomepersonal | C42: {=_xlfn.TEXTSPLIT('איחוד שאלות'!$B42,"_")} -> demography | D42: wealth | E42: incomepersonal | H42: דמוגרפיה | I42: demography | J42: wealth | K42: incomepersonal | N42: מהי ההכנסה החודשית ברוטו שלך בלבד?
A43: מה מספר החדרים שיש לכם בבית? | B43: demography_household_rooms | C43: {=_xlfn.TEXTSPLIT('איחוד שאלות'!$B43,"_")} -> demography | D43: household | E43: rooms | H43: דמוגרפיה | I43: demography | J43: household | K43: rooms | N43: מה מספר החדרים שיש לכם בבית?
A44: מה מספר הנפשות המתגוררות בבית? (כולל חיילים) | B44: demography_household_residents | C44: {=_xlfn.TEXTSPLIT('איחוד שאלות'!$B44,"_")} -> demography | D44: household | E44: residents | H44: דמוגרפיה | I44: demography | J44: household | K44: residents | N44: מה מספר הנפשות המתגוררות בבית? (כולל חיילים)
A45: צפיפות בבית | B45: demography_household_consistency | C45: {=_xlfn.TEXTSPLIT('איחוד שאלות'!$B45,"_")} -> demography | D45: household | E45: consistency | H45: דמוגרפיה | I45: demography | J45: household | K45: consistency | N45: צפיפות בבית
A46: מהי דתך? | B46: demography_identity_religion | C46: {=_xlfn.TEXTSPLIT('איחוד שאלות'!$B46,"_")} -> demography | D46: identity | E46: religion | H46: דמוגרפיה | I46: demography | J46: identity | K46: religion | N46: מהי דתך?
A47: כיצד היית מגדיר את עצמך מבחינה דתית? | B47: demography_identity_religiousety | C47: {=_xlfn.TEXTSPLIT('איחוד שאלות'!$B47,"_")} -> demography | D47: identity | E47: religiousety | H47: דמוגרפיה | I47: demography | J47: identity | K47: religiousety | N47: כיצד היית מגדיר את עצמך מבחינה דתית?
A48: באיזו מידה אתה נוהג לשמור על המסורת הדתית? | B48: behavior_religiousety | C48: {=_xlfn.TEXTSPLIT('איחוד שאלות'!$B48,"_")} -> behavior | D48: religiousety | H48: דמוגרפיה | I48: behavior | J48: religiousety | N48: באיזו מידה אתה נוהג לשמור על המסורת הדתית?
A49: האם אתה נוסע בשבת? | B49: behavior_religiousety_shabat | C49: {=_xlfn.TEXTSPLIT('איחוד שאלות'!$B49,"_")} -> behavior | D49: religiousety | E49: shabat | H49: דמוגרפיה | I49: behavior | J49: religiousety | K49: shabat | N49: האם אתה נוסע בשבת?
A50: האם אתה אוכל רק אוכל כשר? | B50: behavior_religiousety_kosher | C50: {=_xlfn.TEXTSPLIT('איחוד שאלות'!$B50,"_")} -> behavior | D50: religiousety | E50: kosher | H50: דמוגרפיה | I50: behavior | J50: religiousety | K50: kosher | N50: האם אתה אוכל רק אוכל כשר?
A51: כמה פעמים בשנה אתה נוהג לבקר בבית כנסת? | B51: behavior_religiousety_synagoge | C51: {=_xlfn.TEXTSPLIT('איחוד שאלות'!$B51,"_")} -> behavior | D51: religiousety | E51: synagoge | H51: דמוגרפיה | I51: behavior | J51: religiousety | K51: synagoge | N51: כמה פעמים בשנה אתה נוהג לבקר בבית כנסת?
A52: האם אתה עובד מחוץ למשק הבית? | B52: demography_occupation_domestic | C52: {=_xlfn.TEXTSPLIT('איחוד שאלות'!$B52,"_")} -> demography | D52: occupation | E52: domestic | H52: דמוגרפיה | I52: demography | J52: occupation | K52: domestic | N52: האם אתה עובד מחוץ למשק הבית?
A53: מהו מצבך התעסוקתי? | B53: demography_occupation_status | C53: {=_xlfn.TEXTSPLIT('איחוד שאלות'!$B53,"_")} -> demography | D53: occupation | E53: status | H53: דמוגרפיה | I53: demography | J53: occupation | K53: status | N53: מהו מצבך התעסוקתי?
A54: מהו המצב התעסוקתי של בן/בת זוגך? | B54: demography_occupation_status_partner | C54: {=_xlfn.TEXTSPLIT('איחוד שאלות'!$B54,"_")} -> demography | D54: occupation | E54: status | F54: partner | H54: דמוגרפיה | I54: demography | J54: occupation | K54: status | L54: partner | N54: מהו המצב התעסוקתי של בן/בת זוגך?
A55: האם אתה עובד במשרה מלאה או חלקית? | B55: demography_occupation_extent | C55: {=_xlfn.TEXTSPLIT('איחוד שאלות'!$B55,"_")} -> demography | D55: occupation | E55: extent | H55: דמוגרפיה | I55: demography | J55: occupation | K55: extent | N55: האם אתה עובד במשרה מלאה או חלקית?
A56: תאר בצורה מפורטת את עיסוקך או את עבודתך העיקרית | B56: demography_occupation_description | C56: {=_xlfn.TEXTSPLIT('איחוד שאלות'!$B56,"_")} -> demography | D56: occupation | E56: description | H56: דמוגרפיה | I56: demography | J56: occupation | K56: description | N56: תאר בצורה מפורטת את עיסוקך או את עבודתך העיקרית
A57: באיזה מגזר אתה עובד או עבדת? | B57: demography_occupation_sector | C57: {=_xlfn.TEXTSPLIT('איחוד שאלות'!$B57,"_")} -> demography | D57: occupation | E57: sector | H57: דמוגרפיה | I57: demography | J57: occupation | K57: sector | N57: באיזה מגזר אתה עובד או עבדת?
A58: האם אתה מודאג שתאבד את מקום העבודה או מקור הפרנסה שלך? | B58: affect_threat_occupation_fired | C58: {=_xlfn.TEXTSPLIT('איחוד שאלות'!$B58,"_")} -> affect | D58: threat | E58: occupation | F58: fired | H58: דמוגרפיה | I58: affect | J58: threat | K58: occupation | L58: fired | N58: האם אתה מודאג שתאבד את מקום העבודה או מקור הפרנסה שלך?
A59: מהו מצבך המשפחתי? | B59: demography_household_status | C59: {=_xlfn.TEXTSPLIT('איחוד שאלות'!$B59,"_")} -> demography | D59: household | E59: status | H59: דמוגרפיה | I59: demography | J59: household | K59: status | N59: מהו מצבך המשפחתי?
A60: האם יש לך ילדים? | B60: demography_household_children | C60: {=_xlfn.TEXTSPLIT('איחוד שאלות'!$B60,"_")} -> demography | D60: household | E60: children | H60: דמוגרפיה | I60: demography | J60: household | K60: children | N60: האם יש לך ילדים?
A61: אם כן, כמה ילדים? | B61: demography_household_children_num | C61: {=_xlfn.TEXTSPLIT('איחוד שאלות'!$B61,"_")} -> demography | D61: household | E61: children | F61: num | H61: דמוגרפיה | I61: demography | J61: household | K61: children | L61: num | N61: אם כן, כמה ילדים?
A62: האם יש לך ילדים בקבוצת הגיל הבאה: עד גיל 16 | B62: demography_household_childern_16 | C62: {=_xlfn.TEXTSPLIT('איחוד שאלות'!$B62,"_")} -> demography | D62: household | E62: childern | F62: 16 | H62: דמוגרפיה | I62: demography | J62: household | K62: childern | L62: 16 | N62: האם יש לך ילדים בקבוצת הגיל הבאה: עד גיל 16
A63: האם יש לך ילדים בקבוצת הגיל הבאה: 16-18 | B63: demography_household_childern_18 | C63: {=_xlfn.TEXTSPLIT('איחוד שאלות'!$B63,"_")} -> demography | D63: household | E63: childern | F63: 18 | H63: דמוגרפיה | I63: demography | J63: household | K63: childern | L63: 18 | N63: האם יש לך ילדים בקבוצת הגיל הבאה: 16-18
A64: האם יש לך ילדים בקבוצת הגיל הבאה: 19-23 | B64: demography_household_childern_23 | C64: {=_xlfn.TEXTSPLIT('איחוד שאלות'!$B64,"_")} -> demography | D64: household | E64: childern | F64: 23 | H64: דמוגרפיה | I64: demography | J64: household | K64: childern | L64: 23 | N64: האם יש לך ילדים בקבוצת הגיל הבאה: 19-23
A65: האם יש לך ילדים שחיים איתך בבית? | B65: demography_household_childern_inhousehold | C65: {=_xlfn.TEXTSPLIT('איחוד שאלות'!$B65,"_")} -> demography | D65: household | E65: childern | F65: inhousehold | H65: דמוגרפיה | I65: demography | J65: household | K65: childern | L65: inhousehold | N65: האם יש לך ילדים שחיים איתך בבית?
A66: האם שירתת בצה"ל או שהינך משרת בצה"ל? | B66: behavior_IDF_service | C66: {=_xlfn.TEXTSPLIT('איחוד שאלות'!$B66,"_")} -> behavior | D66: IDF | E66: service | H66: דמוגרפיה | I66: behavior | J66: IDF | K66: service | N66: האם שירתת בצה"ל או שהינך משרת בצה"ל?
A67: האם אתה משרת כיום במילואים? | B67: behavior_IDF_reserve | C67: {=_xlfn.TEXTSPLIT('איחוד שאלות'!$B67,"_")} -> behavior | D67: IDF | E67: reserve | H67: דמוגרפיה | I67: behavior | J67: IDF | K67: reserve | N67: האם אתה משרת כיום במילואים?
A68: כמה ימי מילואים שירתת בשנה האחרונה? | B68: behavior_IDF_reserve_dayslastyear | C68: {=_xlfn.TEXTSPLIT('איחוד שאלות'!$B68,"_")} -> behavior | D68: IDF | E68: reserve | F68: dayslastyear | H68: דמוגרפיה | I68: behavior | J68: IDF | K68: reserve | L68: dayslastyear | N68: כמה ימי מילואים שירתת בשנה האחרונה?
A69: האם במילואים אתה משרת/שירתת בתפקיד קרבי או לא קרבי? | B69: behavior_IDF_reserve_combatant | C69: {=_xlfn.TEXTSPLIT('איחוד שאלות'!$B69,"_")} -> behavior | D69: IDF | E69: reserve | F69: combatant | H69: דמוגרפיה | I69: behavior | J69: IDF | K69: reserve | L69: combatant | N69: האם במילואים אתה משרת/שירתת בתפקיד קרבי או לא קרבי?
A70: כמה שנים שיררת בשירות סדיר? | B70: behavior_IDF_service_years | C70: {=_xlfn.TEXTSPLIT('איחוד שאלות'!$B70,"_")} -> behavior | D70: IDF | E70: service | F70: years | H70: דמוגרפיה | I70: behavior | J70: IDF | K70: service | L70: years | N70: כמה שנים שיררת בשירות סדיר?
A71: האם בשירות הסדיר היית בתפקיד קרבי או לא קרבי? | B71: behavior_IDF_service_combatant | C71: {=_xlfn.TEXTSPLIT('איחוד שאלות'!$B71,"_")} -> behavior | D71: IDF | E71: service | F71: combatant | H71: דמוגרפיה | I71: behavior | J71: IDF | K71: service | L71: combatant | N71: האם בשירות הסדיר היית בתפקיד קרבי או לא קרבי?
A72: מהי דרגתך הצבאית כיום או באיזו דרגה השתחררת משירות מילואים? | B72: demography_IDF_rank | C72: {=_xlfn.TEXTSPLIT('איחוד שאלות'!$B72,"_")} -> demography | D72: IDF | E72: rank | H72: דמוגרפיה | I72: demography | J72: IDF | K72: rank | N72: מהי דרגתך הצבאית כיום או באיזו דרגה השתחררת משירות מילואים?
A73: מי ראש המשפחה? | B73: demography_household_head | C73: {=_xlfn.TEXTSPLIT('איחוד שאלות'!$B73,"_")} -> demography | D73: household | E73: head | H73: דמוגרפיה | I73: demography | J73: household | K73: head | N73: מי ראש המשפחה?
A74: כמה שנים אביך למד בבית ספר או בכל מסגרת אחרת? | B74: demography_educ_father | C74: {=_xlfn.TEXTSPLIT('איחוד שאלות'!$B74,"_")} -> demography | D74: educ | E74: father | H74: דמוגרפיה | I74: demography | J74: educ | K74: father | N74: כמה שנים אביך למד בבית ספר או בכל מסגרת אחרת?
A75: כמה שנים אימך למדה בבית ספר או בכל מסגרת אחרת? | B75: demography_educ_mother | C75: {=_xlfn.TEXTSPLIT('איחוד שאלות'!$B75,"_")} -> demography | D75: educ | E75: mother | H75: דמוגרפיה | I75: demography | J75: educ | K75: mother | N75: כמה שנים אימך למדה בבית ספר או בכל מסגרת אחרת?
A76: מה המקצוע של ראש המשפחה? | B76: demography_household_occupation_description_head | C76: {=_xlfn.TEXTSPLIT('איחוד שאלות'!$B76,"_")} -> demography | D76: household | E76: occupation | F76: description | G76: head | H76: דמוגרפיה | I76: demography | J76: household | K76: occupation | L76: description | M76: head | N76: מה המקצוע של ראש המשפחה?
A77: מה מצבו התעסוקתי של ראש המשפחה? | B77: demography_household_occupation_status_head | C77: {=_xlfn.TEXTSPLIT('איחוד שאלות'!$B77,"_")} -> demography | D77: household | E77: occupation | F77: status | G77: head | H77: דמוגרפיה | I77: demography | J77: household | K77: occupation | L77: status | M77: head | N77: מה מצבו התעסוקתי של ראש המשפחה?
A78: מי הם בעלי המפעל בו אתה עובד? | B78: demography_occupation_ownership | C78: {=_xlfn.TEXTSPLIT('איחוד שאלות'!$B78,"_")} -> demography | D78: occupation | E78: ownership | H78: דמוגרפיה | I78: demography | J78: occupation | K78: ownership | N78: מי הם בעלי המפעל בו אתה עובד?
A79: האם המפעל בו אתה עובד הוא תעשייתי? | B79: demography_occupation_industrial | C79: {=_xlfn.TEXTSPLIT('איחוד שאלות'!$B79,"_")} -> demography | D79: occupation | E79: industrial | H79: דמוגרפיה | I79: demography | J79: occupation | K79: industrial | N79: האם המפעל בו אתה עובד הוא תעשייתי?
A80: האם אתה חבר הסתדרות? | B80: behavior_association_histadrut | C80: {=_xlfn.TEXTSPLIT('איחוד שאלות'!$B80,"_")} -> behavior | D80: association | E80: histadrut | H80: דמוגרפיה | I80: behavior | J80: association | K80: histadrut | N80: האם אתה חבר הסתדרות?
A81: האם יש לך ביטוח רפואי? | B81: demography_welfare_healthcare | C81: {=_xlfn.TEXTSPLIT('איחוד שאלות'!$B81,"_")} -> demography | D81: welfare | E81: healthcare | H81: דמוגרפיה | I81: demography | J81: welfare | K81: healthcare | N81: האם יש לך ביטוח רפואי?
A82: מהי השפה העיקרית המדוברת בביתך? | B82: demography_household_language | C82: {=_xlfn.TEXTSPLIT('איחוד שאלות'!$B82,"_")} -> demography | D82: household | E82: language | H82: דמוגרפיה | I82: demography | J82: household | K82: language | N82: מהי השפה העיקרית המדוברת בביתך?
A83: האם יש לך בבית מכונת כביסה? | B83: demography_household_washingmachine | C83: {=_xlfn.TEXTSPLIT('איחוד שאלות'!$B83,"_")} -> demography | D83: household | E83: washingmachine | H83: דמוגרפיה | I83: demography | J83: household | K83: washingmachine | N83: האם יש לך בבית מכונת כביסה?
A84: האם יש בבעלותך מכונית? | B84: demography_household_car | C84: {=_xlfn.TEXTSPLIT('איחוד שאלות'!$B84,"_")} -> demography | D84: household | E84: car | H84: דמוגרפיה | I84: demography | J84: household | K84: car | N84: האם יש בבעלותך מכונית?
A85: האם בזמן הבחירות האחרונות גרת באותו מקום שאתה גר כיום? | B85: demography_household_residence_lastelections | C85: {=_xlfn.TEXTSPLIT('איחוד שאלות'!$B85,"_")} -> demography | D85: household | E85: residence | F85: lastelections | H85: דמוגרפיה | I85: demography | J85: household | K85: residence | L85: lastelections | N85: האם בזמן הבחירות האחרונות גרת באותו מקום שאתה גר כיום?
A86: האם היית חבר בתנועת נוער? | B86: behavior_association_youth_organization | C86: {=_xlfn.TEXTSPLIT('איחוד שאלות'!$B86,"_")} -> behavior | D86: association | E86: youth | F86: organization | H86: דמוגרפיה | I86: behavior | J86: association | K86: youth | L86: organization | N86: האם היית חבר בתנועת נוער?
A87: האם היית חבר קיבוץ? מאיזה זרם? | B87: behavior_association_kibbutz | C87: {=_xlfn.TEXTSPLIT('איחוד שאלות'!$B87,"_")} -> behavior | D87: association | E87: kibbutz | H87: דמוגרפיה | I87: behavior | J87: association | K87: kibbutz | N87: האם היית חבר קיבוץ? מאיזה זרם?
A88: מהו לדעתך מצבה של ישראל באופן כללי? | B88: perception_israel_condition | C88: {=_xlfn.TEXTSPLIT('איחוד שאלות'!$B88,"_")} -> perception | D88: israel | E88: condition | H88: ישראל כללי | I88: perception | J88: israel | K88: condition | N88: מהו לדעתך מצבה של ישראל באופן כללי?
A89: מה דעתך על הדרך שבה מטפלת הממשלה בבעיות שישנן כיום במדינה? | B89: perception_satisfaction_government | C89: {=_xlfn.TEXTSPLIT('איחוד שאלות'!$B89,"_")} -> perception | D89: satisfaction | E89: government | H89: ישראל כללי | I89: perception | J89: satisfaction | K89: government | N89: מה דעתך על הדרך שבה מטפלת הממשלה בבעיות שישנן כיום במדינה?
A90: מהי לדעתך הבעיה החשובה ביותר שעל הממשלה לטפל בה? | B90: perception_problem_hierarchy_1 | C90: {=_xlfn.TEXTSPLIT('איחוד שאלות'!$B90,"_")} -> perception | D90: problem | E90: hierarchy | F90: 1 | H90: ישראל כללי | I90: perception | J90: problem | K90: hierarchy | L90: 1 | N90: מהי לדעתך הבעיה החשובה ביותר שעל הממשלה לטפל בה?
A91: והבעיה השנייה הכי חשובה? | B91: perception_problem_hierarchy_2 | C91: {=_xlfn.TEXTSPLIT('איחוד שאלות'!$B91,"_")} -> perception | D91: problem | E91: hierarchy | F91: 2 | H91: ישראל כללי | I91: perception | J91: problem | K91: hierarchy | L91: 2 | N91: והבעיה השנייה הכי חשובה?
A92: והבעיה השלישית הכי חשובה? | B92: perception_problem_hierarchy_3 | C92: {=_xlfn.TEXTSPLIT('איחוד שאלות'!$B92,"_")} -> perception | D92: problem | E92: hierarchy | F92: 3 | H92: ישראל כללי | I92: perception | J92: problem | K92: hierarchy | L92: 3 | N92: והבעיה השלישית הכי חשובה?
A93: האם אתה מאמין שהממשלה תפתור בקרוב את שתי הבעיות שציינת? | B93: perception_expectation_solution_government | C93: {=_xlfn.TEXTSPLIT('איחוד שאלות'!$B93,"_")} -> perception | D93: expectation | E93: solution | F93: government | H93: ישראל כללי | I93: perception | J93: expectation | K93: solution | L93: government | N93: האם אתה מאמין שהממשלה תפתור בקרוב את שתי הבעיות שציינת?
A94: מי מהמועמדים לראשות הממשלה יוכל לטפל טוב יותר בבעיה? | B94: perception_expectation_solution_candidates | C94: {=_xlfn.TEXTSPLIT('איחוד שאלות'!$B94,"_")} -> perception | D94: expectation | E94: solution | F94: candidates | H94: ישראל כללי | I94: perception | J94: expectation | K94: solution | L94: candidates | N94: מי מהמועמדים לראשות הממשלה יוכל לטפל טוב יותר בבעיה?
A95: איזו מפלגה תוכל לטפל טוב יותר בבעיה שציינת? | B95: perception_expectation_solution_party | C95: {=_xlfn.TEXTSPLIT('איחוד שאלות'!$B95,"_")} -> perception | D95: expectation | E95: solution | F95: party | H95: ישראל כללי | I95: perception | J95: expectation | K95: solution | L95: party | N95: איזו מפלגה תוכל לטפל טוב יותר בבעיה שציינת?
A96: מהי לדעתך הבעיה החשובה ביותר שעל הממשלה לטפל בה? (אחרי הבחירות) | B96: post_perception_problem | C96: {=_xlfn.TEXTSPLIT('איחוד שאלות'!$B96,"_")} -> post | D96: perception | E96: problem | H96: ישראל כללי | I96: post | J96: perception | K96: problem | N96: מהי לדעתך הבעיה החשובה ביותר שעל הממשלה לטפל בה? (אחרי הבחירות)
A97: בסך הכל, מי יטפל טוב יותר בכלל בעיות המדינה - הצוות של המערך או הצוות של הליכוד? | B97: perception_expectation_solution_team84 | C97: {=_xlfn.TEXTSPLIT('איחוד שאלות'!$B97,"_")} -> perception | D97: expectation | E97: solution | F97: team84 | H97: ישראל כללי | I97: perception | J97: expectation | K97: solution | L97: team84 | N97: בסך הכל, מי יטפל טוב יותר בכלל בעיות המדינה - הצוות של המערך או הצוות של הליכוד?
A98: מבין הדברים הבאים, מה לדעתך הכי מאיים על המערכת הפוליטית כיום? | B98: affect_threat_politicalsystem | C98: {=_xlfn.TEXTSPLIT('איחוד שאלות'!$B98,"_")} -> affect | D98: threat | E98: politicalsystem | H98: ישראל כללי | I98: affect | J98: threat | K98: politicalsystem | N98: מבין הדברים הבאים, מה לדעתך הכי מאיים על המערכת הפוליטית כיום?
A99: באיזו מידה אתה מרוצה מהאופן בו המערכת הפוליטית בישראל מתפקדת כיום? | B99: perception_satisfaction_politicalsystem | C99: {=_xlfn.TEXTSPLIT('איחוד שאלות'!$B99,"_")} -> perception | D99: satisfaction | E99: politicalsystem | H99: ישראל כללי | I99: perception | J99: satisfaction | K99: politicalsystem | N99: באיזו מידה אתה מרוצה מהאופן בו המערכת הפוליטית בישראל מתפקדת כיום?
A100: כאשר אתה חושב על תולדות מדינת ישראל ועם ישראל, איזה אירוע מהעבר נראה לך החשוב ביותר? | B100: preference_importance_historical_event | C100: {=_xlfn.TEXTSPLIT('איחוד שאלות'!$B100,"_")} -> preference | D100: importance | E100: historical | F100: event | H100: ישראל כללי | I100: preference | J100: importance | K100: historical | L100: event | N100: כאשר אתה חושב על תולדות מדינת ישראל ועם ישראל, איזה אירוע מהעבר נראה לך החשוב ביותר?
...

Sheet סופי סופי
A1: לשונית | B1: מדרגה1 | C1: מדרגה 2 | D1: מדרגה 3 | E1: מדרגה 4 | F1: מדרגה 5 | G1: מדרגה 6 | H1: שאלה
A2: ישראל כללי | B2: affect | C2: affinity | D2: country | E2: USA | F2: leaning | H2: לאן, בכל זאת נוטה דעתך לגבי ארה"ב, לכיוון דעה טובה או לכיוון דעה רעה?
A3: ישראל כללי | B3: affect | C3: affinity | D3: country | E3: USA | H3: מהי הרגשתך לגבי ארה"ב? האם יש לך דעה טובה או רעה עליה?
A4: שלום | B4: affect | C4: affinity | D4: groups | E4: arabs | F4: friend | H4: האם היית מוכן לקשור קשרי ידידות עם בן הלאום הערבי?
A5: שלום | B5: affect | C5: affinity | D5: groups | E5: arabs | F5: household | H5: האם היית מוכן לגור בבית שגרה בו משפחה ערבית?
A6: זיקה רגשית | B6: affect | C6: affinity | D6: groups | E6: arabs | H6: מה יחסך לערבים?
A7: זיקה רגשית | B7: affect | C7: affinity | D7: groups | E7: jewishetnicity | F7: ashkenazis | H7: מה יחסך לאשכנזים?
A8: כלכלה-חברה | B8: affect | C8: affinity | D8: groups | E8: jewishetnicity | F8: friends | H8: האם היית מוכן לקשור קשרי ידידות עם בן עדה שונה משלך?
A9: כלכלה-חברה | B9: affect | C9: affinity | D9: groups | E9: jewishetnicity | F9: household | H9: האם היית מוכן לגור בבית שבו גרים גם בני עדה שונה משלך?
A10: כלכלה-חברה | B10: affect | C10: affinity | D10: groups | E10: jewishetnicity | F10: marriage | H10: האם היית מוכן להינשא לבת עדה שונה משלך?
A11: זיקה רגשית | B11: affect | C11: affinity | D11: groups | E11: jewishetnicity | F11: sephardic | H11: מה יחסך לספרדים?
A12: זיקה רגשית | B12: affect | C12: affinity | D12: groups | E12: leftists | H12: על סולם שבו 0 משמעו דחייה ושנאה, 10 משמעו תמיכה ואהדה ו-5 משמעו אמצע, מה יחסך לשמאלנים?
A13: ימין-שמאל | B13: affect | C13: affinity | D13: groups | E13: leftright | F13: appreciated | H13: כשאנשים אומרים דברים טובים על (ימנים/שמאלנים/תומכים של המרכז) זה גורם לך הרגשה טובה
A14: ימין-שמאל | B14: affect | C14: affinity | D14: groups | E14: leftright | F14: close | H14: כשאתה פוגש תומך אחר של (הימין/שמאל/מרכז) אתה מרגיש קשור אליו
A15: ימין-שמאל | B15: affect | C15: affinity | D15: groups | E15: leftright | F15: insult | H15: באיזו מידה אתה מסכים או לא מסכים עם כל אחת מן הטענות הבאות: כשמישהו מעביר ביקורת על (ימנים/שמאלנים/תומכים של המרכז) זה מרגיש לך כמו עלבון אישי
A16: זיקה רגשית | B16: affect | C16: affinity | D16: groups | E16: party | F16: appreciated | H16: כשאנשים אומרים דברים טובים על תומכים של (המפלגה שציין) זה גורם לך להרגשה טובה
A17: זיקה רגשית | B17: affect | C17: affinity | D17: groups | E17: party | F17: close | H17: כשאתה פוגש מישהו שתומך ב(המפלגה שציין) אתה מרגיש קשור אליו
A18: זיקה רגשית | B18: affect | C18: affinity | D18: groups | E18: party | F18: insult | H18: באיזו מידה אתה מסכים או לא מסכים עם כל אחת מן הטענות הבאות: כשמישהו מעביר ביקורת על תומכים של (המפלגה שציין) זה מרגיש לך כמו עלבון אישי
A19: זיקה רגשית | B19: affect | C19: affinity | D19: groups | E19: religious | H19: מה יחסך לדתיים?
A20: זיקה רגשית | B20: affect | C20: affinity | D20: groups | E20: rightist | H20: על סולם שבו 0 משמעו דחייה ושנאה, 10 משמעו תמיכה ואהדה ו-5 משמעו אמצע, מה יחסך לימנים?
A21: זיקה רגשית | B21: affect | C21: affinity | D21: groups | E21: secular | H21: מה יחסך לחילונים?
A22: זיקה רגשית | B22: affect | C22: affinity | D22: groups | E22: ultraorthodox | H22: מה יחסך לחרדים?
A23: זיקה רגשית | B23: affect | C23: affinity | D23: organisations | E23: gushemunim | H23: מה יחסך לתנועת גוש אמונים?
A24: זיקה רגשית | B24: affect | C24: affinity | D24: organisations | E24: hatnuahaislamit | H24: מה יחסך לתנועה האסלאמית?
A25: זיקה רגשית | B25: affect | C25: affinity | D25: organisations | E25: moetzetyesha | H25: מה יחסך למועצת יש"ע?
A26: זיקה רגשית | B26: affect | C26: affinity | D26: organisations | E26: shalomachshav | H26: מה יחסך לתנועת שלום עכשיו?
A27: זיקה רגשית | B27: affect | C27: affinity | D27: parties | E27: 2 | H27: מהי המפלגה השנייה הכי קרובה אליך?
A28: זיקה רגשית | B28: affect | C28: affinity | D28: parties | E28: 3 | H28: מהי המפלגה השלישית הכי קרובה אליך?
A29: זיקה רגשית | B29: affect | C29: affinity | D29: parties | E29: 4 | H29: מהמפלגות הנותרות, איך היית מדרג את מידת הקרבה אלייך: מי הראשונה?
A30: זיקה רגשית | B30: affect | C30: affinity | D30: parties | E30: 5 | H30: מהמפלגות הנותרות, איך היית מדרג את מידת הקרבה אלייך: מי השנייה?
... A36: זיקה רגשית | B36: affect | C36: affinity | D36: parties | E36: binary | H36: באופן כללי, האם אתה רואה את עצמך קרוב למפלגה מסוימת?
A37: זיקה רגשית | B37: affect | C37: affinity | D37: parties | E37: closest | F37: XXXX | H37: לאיזו מפלגה אתה חש הכי קרוב?
A38: זיקה רגשית | B38: affect | C38: affinity | D38: parties | E38: closest | F38: XXXX | H38: מהי המפלגה המועדפת עליך?
A39: זיקה רגשית | B39: affect | C39: affinity | D39: parties | E39: closest | F39: XXXX | H39: באיזו מפלגה אתה תומך יותר מכל היתר?
A40: זיקה רגשית | B40: affect | C40: affinity | D40: parties | E40: closest | F40: XXXX | H40: ובמקום השני?
A41: זיקה רגשית | B41: affect | C41: affinity | D41: parties | E41: closest | F41: XXXX | H41: ובמקום השלישי?
A42: זיקה רגשית | B42: affect | C42: affinity | D42: parties | E42: closest | F42: XXXX | H42: מהי המפלגה הכי פחות מועדפת עליך?
A43: זיקה רגשית | B43: affect | C43: affinity | D43: parties | E43: closest | F43: XXXX | H43: ובמקום השני?
A44: זיקה רגשית | B44: affect | C44: affinity | D44: parties | E44: closest | F44: XXXX | H44: ובמקום השלישי?
A45: ייצוגיות | B45: affect | C45: affinity | D45: parties | E45: closest | H45: לאיזו מפלגה אתה מרגיש הכי קרוב?
A46: זיקה רגשית | B46: affect | C46: affinity | D46: parties | E46: fartherst | H46: מהי המפלגה הרחוקה ממך ביותר?
A47: זיקה רגשית | B47: affect | C47: affinity | D47: parties | E47: haavoda | H47: מה יחסך לכל אחת מן המפלגות הבאות? העבודה/המערך
A48: זיקה רגשית | B48: affect | C48: affinity | D48: parties | E48: habayithayehudi | H48: מה יחסך לכל אחת מהמפלגות הבאות? הבית היהודי/מפד"ל
A49: זיקה רגשית | B49: affect | C49: affinity | D49: parties | E49: hadash | H49: מה יחסך לכל אחת מן המפלגות הבאות? חד"ש
A50: זיקה רגשית | B50: affect | C50: affinity | D50: parties | E50: hareshimahameshutefet | H50: מה יחסך לכל אחת מן המפלגות הבאות? הרשימה המשותפת
A51: זיקה רגשית | B51: affect | C51: affinity | D51: parties | E51: hatnua | H51: מה יחסך לכל אחת מן המפלגות הבאות? התנועה
A52: זיקה רגשית | B52: affect | C52: affinity | D52: parties | E52: kadima | H52: מה יחסך לכל אחת מן המפלגות הבאות? קדימה
A53: זיקה רגשית | B53: affect | C53: affinity | D53: parties | E53: kahollavan | H53: מה יחסך לכל אחת מן המפלגות הבאות? כחול-לבן
A54: זיקה רגשית | B54: affect | C54: affinity | D54: parties | E54: kulanu | H54: מה יחסך לכל אחת מן המפלגות הבאות? כולנו
A55: זיקה רגשית | B55: affect | C55: affinity | D55: parties | E55: likud | H55: מה יחסך לכל אחת מן המפלגות הבאות? הליכוד
A56: זיקה רגשית | B56: affect | C56: affinity | D56: parties | E56: meretz | H56: מה יחסך לכל אחת מן המפלגות הבאות? מרצ
... A80: זיקה רגשית | B80: affect | C80: affinity | D80: politicians | E80: davidlevy | H80: ועל אותו סולם, מה יחסך לאישים הבאים? דוד לוי
A81: זיקה רגשית | B81: affect | C81: affinity | D81: politicians | E81: dayan | F81: importance | H81: לפניך רשימה של מנהיגים. מה יחסך אל כל אחד מהם, והאם יחס זה היה גורם חשוב מאד בהצבעתך? משה דיין
A82: זיקה רגשית | B82: affect | C82: affinity | D82: politicians | E82: deri | H82: ועל אותו סולם, מה יחסך לאישים הבאים? אריה דרעי
A83: זיקה רגשית | B83: affect | C83: affinity | D83: politicians | E83: eliyishai | H83: ועל אותו סולם, מה יחסך לאישים הבאים? אלי ישי
A84: זיקה רגשית | B84: affect | C84: affinity | D84: politicians | E84: favorite | H84: ציין את שם המועמד המרכזי לגביך ברשמית המפלגה עבורה אתה עומד להצביע בכנסת?
A85: זיקה רגשית | B85: affect | C85: affinity | D85: politicians | E85: gabay | H85: ועל אותו סולם, מה יחסך לאישים הבאים? אבי גבאי
A86: זיקה רגשית | B86: affect | C86: affinity | D86: politicians | E86: galon | H86: ועל אותו סולם, מה יחסך לאישים הבאים? זהבה גלאון
A87: זיקה רגשית | B87: affect | C87: affinity | D87: politicians | E87: gantz | H87: ועל אותו סולם, מה יחסך לאישים הבאים? בני גנץ
A88: זיקה רגשית | B88: affect | C88: affinity | D88: politicians | E88: golda | F88: importance | H88: לפניך רשימה של מנהיגים. מה יחסך אל כל אחד מהם, והאם יחס זה היה גורם חשוב מאד בהצבעתך? גולדה מאיר
A89: זיקה רגשית | B89: affect | C89: affinity | D89: politicians | E89: haneenzoabi | H89: ועל אותו סולם, מה יחסך לאישים הבאים? חנין זועבי
A90: זיקה רגשית | B90: affect | C90: affinity | D90: politicians | E90: herzog | H90: ועל אותו סולם, מה יחסך לאישים הבאים? יצחק הרצוג
A91: זיקה רגשית | B91: affect | C91: affinity | D91: politicians | E91: horowitz | H91: ועל אותו סולם, מה יחסך לאישים הבאים? ניצן הורוביץ
A92: זיקה רגשית | B92: affect | C92: affinity | D92: politicians | E92: ibrahimsarsur | H92: ועל אותו סולם, מה יחסך לאישים הבאים? איברהים צרצור
A93: זיקה רגשית | B93: affect | C93: affinity | D93: politicians | E93: jamalzahalka | H93: ועל אותו סולם, מה יחסך לאישים הבאים? ג'מאל זחאלקה
A94: זיקה רגשית | B94: affect | C94: affinity | D94: politicians | E94: kahane | H94: ועל אותו סולם, מה יחסך לאישים הבאים? הרב כהנא
A95: זיקה רגשית | B95: affect | C95: affinity | D95: politicians | E95: kahlon | H95: ועל אותו סולם, מה יחסך לאישים הבאים? משה כחלון
A96: זיקה רגשית | B96: affect | C96: affinity | D96: politicians | E96: lapid | H96: ועל אותו סולם, מה יחסך לאישים הבאים? יאיר לפיד
A97: זיקה רגשית | B97: affect | C97: affinity | D97: politicians | E97: liberman | H97: ועל אותו סולם, מה יחסך לאישים הבאים? אביגדור ליברמן
A98: זיקה רגשית | B98: affect | C98: affinity | D98: politicians | E98: livni | H98: ועל אותו סולם, מה יחסך לאישים הבאים? ציפי לבני
A99: זיקה רגשית | B99: affect | C99: affinity | D99: politicians | E99: mansourabbas | H99: ועל אותו סולם, מה יחסך לאישים הבאים? מנסור עבאס
A100: זיקה רגשית | B100: affect | C100: affinity | D100: politicians | E100: masudghnaim | H100: ועל אותו סולם, מה יחסך לאישים הבאים? מסעוד גנאים
A101: זיקה רגשית | B101: affect | C101: affinity | D101: politicians | E101: menachembegin | F101: importance | H101: לפניך רשימה של מנהיגים. מה יחסך אל כל אחד מהם, והאם יחס זה היה גורם חשוב מאד בהצבעתך? מנחם בגין
A102: זיקה רגשית | B102: affect | C102: affinity | D102: politicians | E102: menachembegin | H102: ועל אותו סולם, מה יחסך לאישים הבאים? מנחם בגין
A103: זיקה רגשית | B103: affect | C103: affinity | D103: politicians | E103: michaeli | H103: ועל אותו סולם, מה יחסך לאישים הבאים? מרב מיכאלי
A104: זיקה רגשית | B104: affect | C104: affinity | D104: politicians | E104: mohammadbarakeh | H104: ועל אותו סולם, מה יחסך לאישים הבאים? מוחמד בראכה
A105: זיקה רגשית | B105: affect | C105: affinity | D105: politicians | E105: mtanesshehadeh | H105: ועל אותו סולם, מה יחסך לאישים הבאים? מטאנס שחאדה
A106: זיקה רגשית | B106: affect | C106: affinity | D106: politicians | E106: natansharansky | H106: ועל אותו סולם, מה יחסך לאישים הבאים? נתן שרנסקי
A107: זיקה רגשית | B107: affect | C107: affinity | D107: politicians | E107: netanyahu | H107: ועל אותו סולם, מה יחסך לאישים הבאים? בנימין נתניהו
A108: זיקה רגשית | B108: affect | C108: affinity | D108: politicians | E108: odeh | H108: ועל אותו סולם, מה יחסך לאישים הבאים? איימן עודה
A109: זיקה רגשית | B109: affect | C109: affinity | D109: politicians | E109: olmert | H109: ועל אותו סולם, מה יחסך לאישים הבאים? אהוד אולמרט
A110: זיקה רגשית | B110: affect | C110: affinity | D110: politicians | E110: peres | H110: ועל אותו סולם, מה יחסך לאישים הבאים? שמעון פרס
A111: זיקה רגשית | B111: affect | C111: affinity | D111: politicians | E111: peretz | H111: ועל אותו סולם, מה יחסך לאישים הבאים? עמיר פרץ
A112: זיקה רגשית | B112: affect | C112: affinity | D112: politicians | E112: pinchassapir | F112: importance | H112: לפניך רשימה של מנהיגים. מה יחסך אל כל אחד מהם, והאם יחס זה היה גורם חשוב מאד בהצבעתך? פנחס ספיר
A113: זיקה רגשית | B113: affect | C113: affinity | D113: politicians | E113: rabin | H113: ועל אותו סולם, מה יחסך לאישים הבאים? יצחק רבין
A114: זיקה רגשית | B114: affect | C114: affinity | D114: politicians | E114: saar | H114: ועל אותו סולם, מה יחסך לאישים הבאים? גדעון סער
A115: זיקה רגשית | B115: affect | C115: affinity | D115: politicians | E115: shaked | H115: ועל אותו סולם, מה יחסך לאישים הבאים? איילת שקד
A116: זיקה רגשית | B116: affect | C116: affinity | D116: politicians | E116: shamir | H116: ועל אותו סולם, מה יחסך לאישים הבאים? יצחק שמיר
A117: זיקה רגשית | B117: affect | C117: affinity | D117: politicians | E117: sharon | F117: importance | H117: לפניך רשימה של מנהיגים. מה יחסך אל כל אחד מהם, והאם יחס זה היה גורם חשוב מאד בהצבעתך? אריק שרון
A118: זיקה רגשית | B118: affect | C118: affinity | D118: politicians | E118: sharon | H118: ועל אותו סולם, מה יחסך לאישים הבאים? אריאל שרון
A119: זיקה רגשית | B119: affect | C119: affinity | D119: politicians | E119: smotrich | H119: ועל אותו סולם, מה יחסך לאישים הבאים? בצלאל סמוטריץ'
A120: זיקה רגשית | B120: affect | C120: affinity | D120: politicians | E120: tibi | H120: ועל אותו סולם, מה יחסך לאישים הבאים? אחמד טיבי
A121: זיקה רגשית | B121: affect | C121: affinity | D121: politicians | E121: toumasuleiman | H121: ועל אותו סולם, מה יחסך לאישים הבאים? עאידה תומא-סולימן
A122: זיקה רגשית | B122: affect | C122: affinity | D122: politicians | E122: yachimovich | H122: ועל אותו סולם, מה יחסך לאישים הבאים? שלי יחימוביץ
A123: זיקה רגשית | B123: affect | C123: affinity | D123: politicians | E123: yigalallon | F123: importance | H123: לפניך רשימה של מנהיגים. מה יחסך אל כל אחד מהם, והאם יחס זה היה גורם חשוב מאד בהצבעתך? יגאל אלון
A124: זיקה רגשית | B124: affect | C124: affinity | D124: politicians | E124: yitzhakmordechai | H124: ועל אותו סולם, מה יחסך לאישים הבאים? איציק מרדכי
A125: זיקה רגשית | B125: affect | C125: affinity | D125: politicians | E125: yitzhaknavon | H125: ועל אותו סולם, מה יחסך לאישים הבאים? יצחק נבון
A126: זיקה רגשית | B126: affect | C126: affinity | D126: politicians | E126: yossibeilin | H126: ועל אותו סולם, מה יחסך לאישים הבאים? יוסי ביילין
A127: זיקה רגשית | B127: affect | C127: affinity | D127: politicians | E127: zandberg | H127: ועל אותו סולם, מה יחסך לאישים הבאים? תמר זנדברג
A128: זיקה רגשית | B128: affect | C128: emotion | D128: anger | E128: crisis19 | H128: לאנשים יש רגשות שונים כלפי מה שקרה אחרי הבחירות באפריל האחרון. באיזו מידה אתה מרגיש: כעס
...

Sheet דמוגרפיה
A1: שאלה | B1: 2025 | C1: 2022 | D1: 2021 | E1: 2020 | F1: 43709 | G1: 43556 | H1: 2015 | I1: 2013 | J1: 2009 | K1: 2006 | L1: 2003 | M1: 2001 | N1: 1999 | O1: 1996 | P1: 1992 | Q1: 1987* | R1: 1988* | S1: 1988 | T1: 1984 | U1: 1981 - 3 | V1: 1981 - 2 | W1: 1981 - 1 | X1: 1977 - 4 | Y1: 1977 - 3 | Z1: 1977 - 2 | AA1: 1977 - 1 | AB1: 1973 - 5 | AC1: 1973 - 4 | AD1: 1973 - 3 | AE1: 1973 - 2 | AF1: 1973 - 1 | AG1: 1969 - 3 | AH1: 1969 - 2 | AI1: 1969 - 1 | AK1: מספר חזרות | AM1: ספירה 84-19 | AO1: סה"כ מעל שתי חזרות
A2: ID | B2: resp_id | C2: ID | D2: resp_id | E2: id | F2: c_resp_id_~e | G2: resp_id | H2: ID | I2: id | K2: caseid | L2: id1 | M2: a1 | N2: v1 | P2: a1 | Q2: v1 | T2: v1 | U2: v1 | V2: v1 | W2: v1 | X2: v1 | Y2: v1 | Z2: v1 | AA2: v1 | AB2: v1 | AC2: v1 | AD2: v1 | AE2: v1 | AF2: v1 | AG2: b2 | AH2: a2 | AI2: a1 | AK2: =COUNTA(C2:AI2) -> 29 | AM2: =COUNTA(G2:P2,S2:T2) -> 9 | AO2: =COUNTIF(AM2:AM87,">=2") -> 43
A3: תאריך | B3: date | C3: date | D3: date | E3: date | F3: c_date_before | G3: date | H3: date | I3: date | M3: b51 | N3: c41 | O3: cccc26 | P3: i70 | R3: c66 | S3: g91 | V3: a161 | AA3: v3 | AB3: h66 | AC3: g68 | AG3: c60 | AH3: d32 | AK3: =COUNTA(C3:AI3) -> 19 | AM3: =COUNTA(G3:P3,S3:T3) -> 8
A4: תאריך פוסט בחירות | C4: date_after | D4: date_after | E4: date_after | F4: d_date_after | G4: date_after | H4: after_date | I4: a_date | AK4: =COUNTA(C4:AI4) -> 7 | AM4: =COUNTA(G4:P4,S4:T4) -> 3
A5: מקום הראיון | H5: v146 | I5: v151 | J5: v193 | K5: c90 | L5: b93 | M5: b48 | N5: c40 | O5: cccc28 | P5: i68 | R5: c64 | S5: g87 | T5: a65 | U5: b159 | V5: a160 | W5: v151 | AA5: v2 | AB5: h65 | AC5: g67 | AG5: c57 | AH5: d29 | AK5: =COUNTA(C5:AI5) -> 20 | AM5: =COUNTA(G5:P5,S5:T5) -> 11
A6: סקטור | C6: sector | D6: sector | E6: sector | F6: c149 | G6: v149 | H6: v148 | I6: v153 | J6: v195 | N6: cccc41 | AK6: =COUNTA(C6:AI6) -> 9 | AM6: =COUNTA(G6:P6,S6:T6) -> 5
A7: פאנל | J7: panel | R7: c67 | S7: g93 | AK7: =COUNTA(C7:AI7) -> 3 | AM7: =COUNTA(G7:P7,S7:T7) -> 2
A8: גרסה | C8: VERSION | F8: girsa_c | G8: version | H8: version | I8: version | J8: version | K8: c94 | L8: b99 | AK8: =COUNTA(C8:AI8) -> 8 | AM8: =COUNTA(G8:P8,S8:T8) -> 6
A9: שפה | C9: LANGUAGE | M9: b55 | AK9: =COUNTA(C9:AI9) -> 2 | AM9: =COUNTA(G9:P9,S9:T9) -> 1
A10: גיל | B10: age | C10: age | D10: age | E10: age | G10: age | H10: age | I10: age | J10: age_1 | K10: c54 | L10: b74 | M10: b24 | N10: c20 | O10: ccc57 | P10: i61 | Q10: a95 | R10: c57 | S10: g78 | T10: a54 | U10: b137 | V10: a151 | W10: v134 | X10: c24 | Y10: b17 | Z10: a17 | AA10: v116 | AB10: h60 | AC10: g62 | AD10: f54 | AE10: e17 | AF10: b25 | AG10: c30 | AH10: d11 | AI10: c79 | AK10: =COUNTA(C10:AI10) -> 32 | AM10: =COUNTA(G10:P10,S10:T10) -> 12
A11: עדה | O11: sephashk | AK11: =COUNTA(C11:AI11) -> 1 | AM11: =COUNTA(G11:P11,S11:T11) -> 1
A12: לאיזו קבוצת גיל אתה משתייך? | B12: agegroup | C12: age_group | D12: agegroup | E12: agegroup | G12: agegroup | H12: agegroup | I12: age_group | J12: agegroup_1 | AK12: =COUNTA(C12:AI12) -> 7 | AM12: =COUNTA(G12:P12,S12:T12) -> 4
A13: מגדר | B13: gender | C13: sex | D13: gender | E13: gender | G13: gender | H13: sex | I13: sex | J13: sex_1 | K13: c89 | L13: b92 | M13: b47 | N13: c39 | O13: ccc56 | P13: i67 | Q13: a119 | S13: g104 | T13: a58 | U13: b138 | V13: a146 | W13: v135 | X13: c19 | Y13: b12 | Z13: a12 | AA13: v111 | AB13: h57 | AC13: g59 | AD13: f52 | AE13: e16 | AF13: b23 | AG13: c29 | AH13: d4 | AI13: c71 | AK13: =COUNTA(C13:AI13) -> 31 | AM13: =COUNTA(G13:P13,S13:T13) -> 12
A14: מהי השכלתך? | B14: educ | C14: educ | D14: educ | E14: educ | G14: educ | H14: v128 | I14: v137 | AK14: =COUNTA(C14:AI14) -> 6 | AM14: =COUNTA(G14:P14,S14:T14) -> 3
A15: כמה שנים למדת במסגרת מסודרת? | H15: v127 | I15: v136 | J15: v181_1 | K15: c75 | L15: b82 | M15: b38 | N15: c28 | O15: ccc63 | P15: i62 | Q15: a99 | R15: c58 | S15: g80 | T15: a53 | U15: b139 | V15: a147 | W15: v136 | X15: c20 | Y15: b13 | Z15: a13 | AA15: v112 | AB15: h59 | AC15: g61 | AD15: f53 | AF15: b26 | AG15: c32 | AH15: d16 | AI15: c85 | AK15: =COUNTA(C15:AI15) -> 27 | AM15: =COUNTA(G15:P15,S15:T15) -> 11
A16: האם אתה אזרח ישראלי? | B16: Citizenship | C16: CITIZEN | E16: v5 | G16: v5 | H16: v5 | I16: v5 | J16: v5 | AK16: =COUNTA(C16:AI16) -> 6 | AM16: =COUNTA(G16:P16,S16:T16) -> 4
A17: באיזו ארץ נולדת? | H17: v115 | J17: v176 | K17: c57 | AG17: c43 | AH17: d5 | AI17: c73 | AK17: =COUNTA(C17:AI17) -> 6 | AM17: =COUNTA(G17:P17,S17:T17) -> 3
A18: ארץ לידה/מוצא אב | B18: v513 | C18: v513 | D18: v513 | E18: v513 | G18: v131 | H18: v117 | I18: v133 | L18: b77 | M18: b33 | N18: c26 | O18: ccc59 | P18: i52 | Q18: a97 | R18: c48 | S18: g68 | T18: a49 | U18: b140 | V18: a157 | W18: v137 | X18: a29 | Y18: b22 | Z18: a22 | AA18: v123 | AB18: h64 | AC18: g66 | AD18: f58 | AE18: e19 | AF18: b38 | AG18: c45 | AH18: d8 | AI18: c76 | AK18: =COUNTA(C18:AI18) -> 30 | AM18: =COUNTA(G18:P18,S18:T18) -> 10
A19: אם לא נולד בארץ, באיזו שנה עלית ארצה? | B19: v134 | C19: v134 | D19: v134 | E19: v134 | G19: v134 | H19: v118 | I19: v134 | J19: v177 | K19: c60 | L19: b79 | M19: b35 | N19: c27 | O19: ccc61 | P19: i53 | Q19: a98 | R19: c49 | S19: g70 | T19: a50 | U19: b141 | V19: a158 | W19: v138 | X19: c30 | Y19: b23 | Z19: a23 | AA19: v124 | AF19: b39 | AG19: c48 | AH19: d15 | AI19: c84 | AK19: =COUNTA(C19:AI19) -> 28 | AM19: =COUNTA(G19:P19,S19:T19) -> 12
A20: כיצד היית מגדיר את עצמך? (עדה) | B20: v131 | C20: v131 | E20: v135 | G20: v135 | H20: v120 | O20: ccc55 | P20: i51 | Q20: a96 | R20: c47 | S20: g67 | T20: a47 | AK20: =COUNTA(C20:AI20) -> 10 | AM20: =COUNTA(G20:P20,S20:T20) -> 6
A21: האם נולדת באחת מארצות ברה"מ ועלית ארצה אחרי 1988? | M21: b37 | AK21: =COUNTA(C21:AI21) -> 1 | AM21: =COUNTA(G21:P21,S21:T21) -> 1
A22: איזה מבין המונחים הבאים מגדיר בצורה הטובה ביותר את זהותך? | C22: v707a | J22: v164 | K22: c43 | M22: b29 | N22: c22 | O22: ccc47 | AK22: =COUNTA(C22:AI22) -> 6 | AM22: =COUNTA(G22:P22,S22:T22) -> 5
A23: והשני? | C23: v707b | J23: v165 | K23: c44 | M23: b30 | N23: c23 | O23: ccc48 | AK23: =COUNTA(C23:AI23) -> 6 | AM23: =COUNTA(G23:P23,S23:T23) -> 5
A24: והשלישי? | C24: v707c | J24: v166 | K24: c45 | M24: b31 | N24: c24 | O24: ccc49 | AK24: =COUNTA(C24:AI24) -> 6 | AM24: =COUNTA(G24:P24,S24:T24) -> 5
A25: והרביעי? | J25: v167 | K25: c46 | M25: b32 | N25: c25 | O25: ccc50 | AK25: =COUNTA(C25:AI25) -> 5 | AM25: =COUNTA(G25:P25,S25:T25) -> 5
A26: האם למדת את לימודייך התיכוניים או העל-תיכוניים במסגרת דתית כלשהי? | C26: v137 | D26: v137 | E26: v137 | G26: v137 | H26: v129 | I26: v138 | AK26: =COUNTA(C26:AI26) -> 6 | AM26: =COUNTA(G26:P26,S26:T26) -> 3
A27: ההוצאה החודשית הממוצעת של משפחה בישראל היא כ-16,500 ₪. בהתחשב בכל ההוצאות של משפחתכם, האם אתם מוציאים: | B27: v139 | C27: v139 | D27: v139 | E27: v139 | G27: v139 | H27: v134 | J27: v184 | K27: c80 | L27: b85 | M27: b41 | N27: c30 | O27: ccc74 | P27: i65 | Q27: a105 | R27: c62 | S27: g85 | T27: a55 | AK27: =COUNTA(C27:AI27) -> 16 | AM27: =COUNTA(G27:P27,S27:T27) -> 11
A28: כמה כסף מוציאה המשפחה שלכם בממוצע בחודש? | U28: b158 | W28: v150 | AK28: =COUNTA(C28:AI28) -> 2 | AM28: =COUNTA(G28:P28,S28:T28) -> 0
A29: מה מספר החדרים שיש לכם בבית? | C29: v140 | D29: v140 | E29: v140 | G29: v140 | H29: v135 | I29: v146 | J29: v186 | K29: c82 | L29: b87 | M29: b42 | N29: c34 | O29: ccc65 | P29: i63 | Q29: a106 | R29: c60 | S29: g83 | U29: b149 | V29: a148 | W29: v144 | X29: c21 | Y29: b14 | Z29: a14 | AA29: v113 | AF29: b40 | AK29: =COUNTA(C29:AI29) -> 24 | AM29: =COUNTA(G29:P29,S29:T29) -> 11
A30: מה מספר הנפשות המתגוררות בבית? (כולל חיילים) | C30: v141 | D30: v141 | E30: v141 | G30: v141 | H30: v136 | I30: v147 | J30: v187 | K30: c84 | L30: b88 | M30: b44 | N30: c35 | O30: ccc67 | P30: i64 | Q30: a107 | R30: c61 | S30: g84 | U30: b151 | V30: a149 | W30: v145 | X30: c22 | Y30: b15 | Z30: a15 | AA30: v114 | AF30: b41 | AG30: c52 | AK30: =COUNTA(C30:AI30) -> 25 | AM30: =COUNTA(G30:P30,S30:T30) -> 11
A31: צפיפות בבית | T31: a57 | AG31: c50 | AH31: d26 | AI31: c56 | AK31: =COUNTA(C31:AI31) -> 4 | AM31: =COUNTA(G31:P31,S31:T31) -> 1
A32: מהי דתך? | B32: v143 | C32: v143_code | D32: v143_code | E32: v143_code | G32: v143_code | H32: v138 | I32: v149 | J32: v189_1 | K32: c87 | L32: b90 | M32: b28 | O32: ccc75 | AK32: =COUNTA(C32:AI32) -> 11 | AM32: =COUNTA(G32:P32,S32:T32) -> 8
A33: כיצד היית מגדיר את עצמך מבחינה דתית? | B33: religiosity | C33: v144 | D33: v144 | E33: v144 | G33: v144 | H33: v139 | I33: v150 | J33: v190 | K33: c88 | L33: b91 | M33: b27 | N33: c38 | AK33: =COUNTA(C33:AI33) -> 11 | AM33: =COUNTA(G33:P33,S33:T33) -> 8
A34: מהו מצבך המשפחתי? | G34: v129 | H34: v111 | I34: v126 | P34: i54 | Q34: a69 | R34: c24 | S34: g34 | U34: b144 | V34: a154 | W34: v142 | AA34: v119 | AE34: e18 | AF34: b43 | AG34: c36 | AH34: d13 | AI34: c81 | AK34: =COUNTA(C34:AI34) -> 16 | AM34: =COUNTA(G34:P34,S34:T34) -> 5
A35: באיזו מידה אתה נוהג לשמור על המסורת הדתית? | B35: v132 | C35: v130 | G35: v130 | H35: v114 | I35: v132 | J35: v175 | K35: c56 | L35: b76 | M35: b26 | N35: c21 | O35: ccc70 | P35: i50 | Q35: a100 | R35: c46 | S35: g66 | T35: a48 | U35: b145 | V35: a155 | W35: v143 | X35: c26 | Y35: b19 | Z35: a19 | AA35: v120 | AB35: h62 | AC35: g64 | AD35: f56 | AF35: b37 | AG35: c20 | AH35: c30 | AI35: c49 | AK35: =COUNTA(C35:AI35) -> 29 | AM35: =COUNTA(G35:P35,S35:T35) -> 12
A36: האם אתה נוסע בשבת? | U36: b146 | AI36: c68 | AK36: =COUNTA(C36:AI36) -> 2 | AM36: =COUNTA(G36:P36,S36:T36) -> 0
A37: האם אתה אוכל רק אוכל כשר? | U37: b147 | AI37: c70 | AK37: =COUNTA(C37:AI37) -> 2 | AM37: =COUNTA(G37:P37,S37:T37) -> 0
A38: כמה פעמים בשנה אתה נוהג לבקר בבית כנסת? | U38: b148 | AH38: c29 | AK38: =COUNTA(C38:AI38) -> 2 | AM38: =COUNTA(G38:P38,S38:T38) -> 0
A39: היכן נולד אביך? | G39: v132 | H39: v116 | J39: v179 | K39: c69 | AG39: c44 | AH39: d7 | AI39: c74 | AK39: =COUNTA(C39:AI39) -> 7 | AM39: =COUNTA(G39:P39,S39:T39) -> 4
A40: היכן נולדה אמך? | G40: v133 | J40: v180 | K40: c72 | AG40: c47 | AH40: d10 | AI40: c77 | AK40: =COUNTA(C40:AI40) -> 6 | AM40: =COUNTA(G40:P40,S40:T40) -> 3
A41: האם אתה עובד מחוץ למשק הבית? | N41: c31 | O41: ccc71 | Q41: a109 | T41: a59 | AK41: =COUNTA(C41:AI41) -> 4 | AM41: =COUNTA(G41:P41,S41:T41) -> 3
A42: מהו מצבך התעסוקתי? | H42: v130 | I42: v139 | N42: c32 | O42: ccc72 | P42: i66 | Q42: a110 | R42: c63 | S42: g86 | T42: a60 | U42: b142 | V42: a156 | W42: v139 | X42: c27 | Y42: b20 | Z42: a20 | AA42: v121 | AF42: b29 | AK42: =COUNTA(C42:AI42) -> 17 | AM42: =COUNTA(G42:P42,S42:T42) -> 7
A43: מהו המצב התעסוקתי של בן/בת זוגך? | W43: v140 | X43: c28 | Y43: b21 | Z43: a21 | AA43: v122 | AK43: =COUNTA(C43:AI43) -> 5 | AM43: =COUNTA(G43:P43,S43:T43) -> 0
A44: באיזו ארץ נולד/ה בן/בת זוגך? | AG44: c54 | AH44: d14 | AI44: c82 | AK44: =COUNTA(C44:AI44) -> 3 | AM44: =COUNTA(G44:P44,S44:T44) -> 0
A45: מהי ההשכלה של בן/בת זוגך? | AG45: c55 | AH45: d18 | AI45: c87 | AK45: =COUNTA(C45:AI45) -> 3 | AM45: =COUNTA(G45:P45,S45:T45) -> 0
A46: האם אתה עובד במשרה מלאה או חלקית? | H46: v131 | I46: v140 | AK46: =COUNTA(C46:AI46) -> 2 | AM46: =COUNTA(G46:P46,S46:T46) -> 2
A47: תאר בצורה מפורטת את עיסוקך או את עבודתך העיקרית | C47: v138_code | G47: v138_code | H47: v132 | I47: v141 | J47: v183 | K47: c78 | AB47: h63 | AC47: g65 | AD47: f57 | AF47: b28 | AH47: d24 | AK47: =COUNTA(C47:AI47) -> 11 | AM47: =COUNTA(G47:P47,S47:T47) -> 5
A48: באיזה מגזר אתה עובד או עבדת? | H48: v133 | I48: v142 | AK48: =COUNTA(C48:AI48) -> 2 | AM48: =COUNTA(G48:P48,S48:T48) -> 2
A49: האם אתה מודאג שתאבד את מקום העבודה או מקור הפרנסה שלך? | J49: v185 | K49: c81 | L49: b86 | N49: c33 | AK49: =COUNTA(C49:AI49) -> 4 | AM49: =COUNTA(G49:P49,S49:T49) -> 4
A50: לאיזה מעמד חברתי אתה משייך את עצמך? | G50: v142 | H50: v137 | I50: v148 | J50: v188 | K50: c86 | L50: b89 | N50: c37 | O50: ccc73 | Q50: a108 | R50: c59 | S50: g82 | T50: a56 | U50: b143 | V50: a153 | W50: v141 | AA50: v118 | AG50: c22 | AH50: c42 | AI50: c58 | AK50: =COUNTA(C50:AI50) -> 19 | AM50: =COUNTA(G50:P50,S50:T50) -> 10
A51: האם יש לך ילדים? | H51: v112 | I51: v127 | AK51: =COUNTA(C51:AI51) -> 2 | AM51: =COUNTA(G51:P51,S51:T51) -> 2
A52: אם כן, כמה ילדים? | H52: v112_a | AG52: c51 | AK52: =COUNTA(C52:AI52) -> 2 | AM52: =COUNTA(G52:P52,S52:T52) -> 1
A53: האם יש לך ילדים בקבוצת הגיל הבאה: עד גיל 16 | Q53: a102 | AK53: =COUNTA(C53:AI53) -> 1 | AM53: =COUNTA(G53:P53,S53:T53) -> 0
A54: האם יש לך ילדים בקבוצת הגיל הבאה: 16-18 | Q54: a103 | AK54: =COUNTA(C54:AI54) -> 1 | AM54: =COUNTA(G54:P54,S54:T54) -> 0
A55: האם יש לך ילדים בקבוצת הגיל הבאה: 19-23 | Q55: a104 | AK55: =COUNTA(C55:AI55) -> 1 | AM55: =COUNTA(G55:P55,S55:T55) -> 0
A56: האם יש לך ילדים שחיים איתך בבית? | H56: v113 | I56: v128 | AK56: =COUNTA(C56:AI56) -> 2 | AM56: =COUNTA(G56:P56,S56:T56) -> 2
A57: חשוב על הכנסותיהם של כל בני הבית ועל כל ההכנסות במתקבלות במשק הבית בכללו. מהו מקור ההכנסה העיקרי של משק הבית שלך? | I57: v143 | AK57: =COUNTA(C57:AI57) -> 1 | AM57: =COUNTA(G57:P57,S57:T57) -> 1
A58: מהי ההכנסה של משק הבית שלך מכל המקורות, אחרי ניכוי מיסים וניכויי חובה אחרים? | I58: v144 | V58: a152 | X58: c25 | Y58: b18 | Z58: a18 | AA58: v117 | AF58: b35 | AG58: c40 | AH58: d27 | AI58: c67 | AK58: =COUNTA(C58:AI58) -> 10 | AM58: =COUNTA(G58:P58,S58:T58) -> 1
A59: איזה חלק מההכנסה של משק הבית מהווה ההכנסה שלך? | I59: v145 | AK59: =COUNTA(C59:AI59) -> 1 | AM59: =COUNTA(G59:P59,S59:T59) -> 1
A60: מהי ההכנסה החודשית ברוטו שלך בלבד? | X60: c23 | Y60: b16 | Z60: a16 | AA60: v115 | AB60: h61 | AC60: g63 | AD60: f55 | AF60: b34 | AK60: =COUNTA(C60:AI60) -> 8 | AM60: =COUNTA(G60:P60,S60:T60) -> 0
A61: האם יש לך תואר אקדמי? | J61: v182 | K61: c77 | L61: b84 | M61: b40 | N61: c29 | AK61: =COUNTA(C61:AI61) -> 5 | AM61: =COUNTA(G61:P61,S61:T61) -> 5
A62: מהו מוסד הלימודים האחרון בו למדת? | J62: v191 | AK62: =COUNTA(C62:AI62) -> 1 | AM62: =COUNTA(G62:P62,S62:T62) -> 1
A63: באיזו עיר בברה"מ לשעבר גרת לפני שעלית ארצה? | K63: c63 | AK63: =COUNTA(C63:AI63) -> 1 | AM63: =COUNTA(G63:P63,S63:T63) -> 1
A64: מה היה הלאום שהיה רשום בפספורט הסובייטי הפנימי שלך? | K64: c65 | AK64: =COUNTA(C64:AI64) -> 1 | AM64: =COUNTA(G64:P64,S64:T64) -> 1
A65: לגבי החברים שלך בארץ, היית אומר שהרוב: | K65: c67 | AK65: =COUNTA(C65:AI65) -> 1 | AM65: =COUNTA(G65:P65,S65:T65) -> 1
A66: האם שירתת בצה"ל או שהינך משרת בצה"ל? | P66: i59 | Q66: a83 | R66: c54 | S66: g75 | AI66: c65 | AK66: =COUNTA(C66:AI66) -> 5 | AM66: =COUNTA(G66:P66,S66:T66) -> 2
A67: האם אתה משרת כיום במילואים? | Q67: a84 | R67: c55 | S67: g76 | AK67: =COUNTA(C67:AI67) -> 3 | AM67: =COUNTA(G67:P67,S67:T67) -> 1
A68: כמה ימי מילואים שירתת בשנה האחרונה? | Q68: a85 | AK68: =COUNTA(C68:AI68) -> 1 | AM68: =COUNTA(G68:P68,S68:T68) -> 0
A69: האם במילואים אתה משרת/שירתת בתפקיד קרבי או לא קרבי? | Q69: a86 | AK69: =COUNTA(C69:AI69) -> 1 | AM69: =COUNTA(G69:P69,S69:T69) -> 0
A70: כמה שנים שיררת בשירות סדיר? | Q70: a87 | AK70: =COUNTA(C70:AI70) -> 1 | AM70: =COUNTA(G70:P70,S70:T70) -> 0
A71: האם בשירות הסדיר היית בתפקיד קרבי או לא קרבי? | Q71: a88 | AK71: =COUNTA(C71:AI71) -> 1 | AM71: =COUNTA(G71:P71,S71:T71) -> 0
A72: מהי דרגתך הצבאית כיום או באיזו דרגה השתחררת משירות מילואים? | Q72: a90 | AK72: =COUNTA(C72:AI72) -> 1 | AM72: =COUNTA(G72:P72,S72:T72) -> 0
A73: מי ראש המשפחה? | AF73: b24 | AK73: =COUNTA(C73:AI73) -> 1 | AM73: =COUNTA(G73:P73,S73:T73) -> 0
A74: כמה שנים אביך למד בבית ספר או בכל מסגרת אחרת? | AF74: b27 | AG74: c33 | AH74: d19 | AI74: c88 | AK74: =COUNTA(C74:AI74) -> 4 | AM74: =COUNTA(G74:P74,S74:T74) -> 0
A75: כמה שנים אימך למדה בבית ספר או בכל מסגרת אחרת? | AG75: c34 | AH75: d21 | AI75: c90 | AK75: =COUNTA(C75:AI75) -> 3 | AM75: =COUNTA(G75:P75,S75:T75) -> 0
A76: מה המקצוע של ראש המשפחה? | AF76: b30 | AG76: c37 | AK76: =COUNTA(C76:AI76) -> 2 | AM76: =COUNTA(G76:P76,S76:T76) -> 0
A77: מה מצבו התעסוקתי של ראש המשפחה? | AF77: b31 | AG77: c36 | AK77: =COUNTA(C77:AI77) -> 2 | AM77: =COUNTA(G77:P77,S77:T77) -> 0
A78: מי הם בעלי המפעל בו אתה עובד? | AF78: b32 | AK78: =COUNTA(C78:AI78) -> 1 | AM78: =COUNTA(G78:P78,S78:T78) -> 0
A79: האם המפעל בו אתה עובד הוא תעשייתי? | AF79: b33 | AK79: =COUNTA(C79:AI79) -> 1 | AM79: =COUNTA(G79:P79,S79:T79) -> 0
A80: האם אתה חבר הסתדרות? | P80: i57 | R80: c52 | S80: g73 | U80: b123 | W80: v130 | AA80: v109 | AG80: c23 | AH80: c44 | AI80: c59 | AK80: =COUNTA(C80:AI80) -> 9 | AM80: =COUNTA(G80:P80,S80:T80) -> 2
A81: האם יש לך ביטוח רפואי? | AF81: b36 | AK81: =COUNTA(C81:AI81) -> 1 | AM81: =COUNTA(G81:P81,S81:T81) -> 0
A82: מהי השפה העיקרית המדוברת בביתך? | AG82: c41 | AH82: d23 | AI82: c91 | AK82: =COUNTA(C82:AI82) -> 3 | AM82: =COUNTA(G82:P82,S82:T82) -> 0
A83: האם יש לך בבית מכונת כביסה? | AI83: c51 | AK83: =COUNTA(C83:AI83) -> 1 | AM83: =COUNTA(G83:P83,S83:T83) -> 0
A84: האם יש בבעלותך מכונית? | AI84: c54 | AK84: =COUNTA(C84:AI84) -> 1 | AM84: =COUNTA(G84:P84,S84:T84) -> 0
A85: האם בזמן הבחירות האחרונות גרת באותו מקום שאתה גר כיום? | AI85: c61 | AK85: =COUNTA(C85:AI85) -> 1 | AM85: =COUNTA(G85:P85,S85:T85) -> 0
A86: האם היית חבר בתנועת נוער? | AF86: v17 | AI86: c62 | AK86: =COUNTA(C86:AI86) -> 2 | AM86: =COUNTA(G86:P86,S86:T86) -> 0
A87: האם היית חבר קיבוץ? מאיזה זרם? | AI87: c64 | AK87: =COUNTA(C87:AI87) -> 1 | AM87: =COUNTA(G87:P87,S87:T87) -> 0
A88: באיזו תדירות את/ה נוהג/ת להגיע לבית תפילה דתי (בית כנסת, מסגד, כנסיה וכו' )? | B88: v133
A89: מה שם הישוב בו את/ה גר/ה? | B89: District_CBS

Sheet ישראל כללי
A1: שאלה | B1: 2025 | C1: 2022 | D1: 2021 | E1: 2020 | F1: 43709 | G1: 43556 | H1: 2015 | I1: 2013 | J1: 2009 | K1: 2006 | L1: 2003 | M1: 2001 | N1: 1999 | O1: 1996 | P1: 1992 | Q1: 1987* | R1: 1988* | S1: 1988 | T1: 1984 | U1: 1981 - 3 | V1: 1981 - 2 | W1: 1981 - 1 | X1: 1977 - 4 | Y1: 1977 - 3 | Z1: 1977 - 2 | AA1: 1977 - 1 | AB1: 1973 - 5 | AC1: 1973 - 4 | AD1: 1973 - 3 | AE1: 1973 - 2 | AF1: 1973 - 1 | AG1: 1969 - 3 | AH1: 1969 - 2 | AI1: 1969 - 1 | AK1: מספר חזרות | AM1: ספירה 84-19 | AO1: סה"כ מעל שתי חזרות
A2: מהו לדעתך מצבה של ישראל באופן כללי? | C2: v6 | D2: v6 | E2: v6 | G2: v6 | H2: v6 | I2: v6 | J2: v6 | K2: a6 | L2: a6 | M2: a6 | N2: v3 | O2: c6 | P2: a2 | R2: b2 | S2: f6 | T2: v2 | U2: b2 | V2: a2 | W2: v2 | AA2: v4 | AK2: =COUNTA(C2:AI2) -> 20 | AM2: =COUNTA(G2:P2,S2:T2) -> 12 | AO2: =COUNTIF(AM2:AM150,">=2") -> 14
A3: מה דעתך על הדרך שבה מטפלת הממשלה בבעיות שישנן כיום במדינה? | G3: v7 | H3: v7 | I3: v7 | J3: v7 | K3: a7 | L3: a7 | M3: a7 | N3: v4 | O3: c7 | P3: a3 | R3: b3 | S3: f7 | T3: v3 | U3: b3 | V3: a3 | W3: v3 | AA3: v5 | AI3: a83 | AK3: =COUNTA(C3:AI3) -> 18 | AM3: =COUNTA(G3:P3,S3:T3) -> 12
A4: מהי לדעתך הבעיה החשובה ביותר שעל הממשלה לטפל בה? | B4: v8 | C4: v8_code1 | D4: v8c | E4: v8_code | F4: c8_code | G4: v8_code | H4: v8 | I4: v8 | J4: v8 | K4: a8 | L4: a8 | M4: a8 | N4: v5 | O4: c8 | P4: a7 | Q4: a52 | R4: b8 | S4: f11 | T4: v4 | U4: b6 | V4: a4 | W4: v4 | Y4: b2 | Z4: a2 | AA4: v6 | AC4: g2 | AD4: f42 | AE4: c51 | AF4: v27 | AH4: b23 | AI4: b29 | AK4: =COUNTA(C4:AI4) -> 30 | AM4: =COUNTA(G4:P4,S4:T4) -> 12
A5: והבעיה השנייה הכי חשובה? | C5: v8_code2 | AC5: g3 | AD5: f43 | AE5: c52 | AF5: v28 | AH5: b24 | AI5: b30 | AK5: =COUNTA(C5:AI5) -> 7 | AM5: =COUNTA(G5:P5,S5:T5) -> 0
A6: והבעיה השלישית הכי חשובה? | C6: v8_code3 | AH6: b25 | AI6: b31 | AK6: =COUNTA(C6:AI6) -> 3 | AM6: =COUNTA(G6:P6,S6:T6) -> 0
A7: האם אתה מאמין שהממשלה תפתור בקרוב את שתי הבעיות שציינת? | AE7: c53 | AF7: v29 | AK7: =COUNTA(C7:AI7) -> 2 | AM7: =COUNTA(G7:P7,S7:T7) -> 0
A8: מי מהמועמדים לראשות הממשלה יוכל לטפל טוב יותר בבעיה? | N8: v6 | O8: c10 | U8: b5 | AK8: =COUNTA(C8:AI8) -> 3 | AM8: =COUNTA(G8:P8,S8:T8) -> 2
A9: איזו מפלגה תוכל לטפל טוב יותר בבעיה שציינת? | O9: c11 | P9: a8 | R9: b9 | S9: f13 | T9: v6 | W9: v6 | AA9: v9 | AK9: =COUNTA(C9:AI9) -> 7 | AM9: =COUNTA(G9:P9,S9:T9) -> 4
A10: מהי לדעתך הבעיה החשובה ביותר שעל הממשלה לטפל בה? (אחרי הבחירות) | N10: d2 | AK10: =COUNTA(C10:AI10) -> 1 | AM10: =COUNTA(G10:P10,S10:T10) -> 1
A11: בסך הכל, מי יטפל טוב יותר בכלל בעיות המדינה - הצוות של המערך או הצוות של הליכוד? | T11: v25 | AK11: =COUNTA(C11:AI11) -> 1 | AM11: =COUNTA(G11:P11,S11:T11) -> 1
A12: מבין הדברים הבאים, מה לדעתך הכי מאיים על המערכת הפוליטית כיום? | AK12: =COUNTA(C12:AI12) -> 0 | AM12: =COUNTA(G12:P12,S12:T12) -> 0
A13: באיזו מידה אתה מרוצה מהאופן בו המערכת הפוליטית בישראל מתפקדת כיום? | C13: v116 | D13: v116 | E13: v116 | G13: v116 | AK13: =COUNTA(C13:AI13) -> 4 | AM13: =COUNTA(G13:P13,S13:T13) -> 1
A14: כאשר אתה חושב על תולדות מדינת ישראל ועם ישראל, איזה אירוע מהעבר נראה לך החשוב ביותר? | I14: a_v17 | AK14: =COUNTA(C14:AI14) -> 1 | AM14: =COUNTA(G14:P14,S14:T14) -> 1
A15: כאשר אתה חושב על העתיד של מדינת ישראל ועם ישראל, איזה אירוע או התרחשות הייתה רוצה לראות? | I15: a_v18 | AK15: =COUNTA(C15:AI15) -> 1 | AM15: =COUNTA(G15:P15,S15:T15) -> 1
A16: מיהי, לדעתך, הדמות המשמעותית ביותר בתולדות מדינת ישראל ועם ישראל? | I16: a_v19 | AK16: =COUNTA(C16:AI16) -> 1 | AM16: =COUNTA(G16:P16,S16:T16) -> 1
A17: באיזו מידה אתה מסכים או לא מסכים עם המשפטים הבאים: לפעמים הפוליטיקה נראית כ"כ מסובכת שאדם כמוני לא יכול להבין באמת מה קורה | B17: v33 | C17: v33 | H17: v33 | I17: v32 | AK17: =COUNTA(C17:AI17) -> 3 | AM17: =COUNTA(G17:P17,S17:T17) -> 2
A18: באיזו מידה אתה מסכים או לא מסכים עם המשפטים הבאים: יש לגרש מהארץ את העובדים הזרים שאין להם רשיון עבודה וגם את ילדיהם | I18: v40 | AK18: =COUNTA(C18:AI18) -> 1 | AM18: =COUNTA(G18:P18,S18:T18) -> 1
A19: לפעמים, אנשים שואלים את עצמם מה צריכות להיות המטרות של המדינה לעשר השנים הבאות? מבין המטרות הבאות, מה לדעתך, המטרה החשובה ביותר של המדינה? | H19: v107 | I19: v115 | AK19: =COUNTA(C19:AI19) -> 2 | AM19: =COUNTA(G19:P19,S19:T19) -> 2
A20: ומה לדעתך, המטרה השנייה בחשיבותה? | H20: v108 | I20: v116 | AK20: =COUNTA(C20:AI20) -> 2 | AM20: =COUNTA(G20:P20,S20:T20) -> 2
A21: כיצד היית מדרג את מצבך האישי בימים אלו? | J21: v57 | K21: a55 | O21: cc61 | P21: i33 | Q21: a56 | U21: b61 | W21: v25 | AH21: a11 | AI21: a34 | AK21: =COUNTA(C21:AI21) -> 9 | AM21: =COUNTA(G21:P21,S21:T21) -> 4
A22: ולפני 5 שנים מה היה מצבך האישי? | J22: v58 | K22: a56 | O22: cc62 | P22: i34 | Q22: a57 | U22: b62 | W22: v26 | AH22: a12 | AI22: a35 | AK22: =COUNTA(C22:AI22) -> 9 | AM22: =COUNTA(G22:P22,S22:T22) -> 4
A23: ובעוד 5 שנים מה יהיה מצבך האישי? | J23: v59 | K23: a57 | O23: cc63 | P23: i35 | Q23: a58 | U23: b63 | W23: v27 | AH23: a13 | AI23: a36 | AK23: =COUNTA(C23:AI23) -> 9 | AM23: =COUNTA(G23:P23,S23:T23) -> 4
A24: האם החלפת המפלגה בשלטון תשנה את המצב האישי שלך? | AE24: d44 | AK24: =COUNTA(C24:AI24) -> 1 | AM24: =COUNTA(G24:P24,S24:T24) -> 0
A25: באיזו מידה אתה תומך או מתנגד לצירוף של שרים מטעם מפלגות ערביות לממשלה? | C25: v704 | M25: b13 | N25: c11 | O25: ccc20 | AK25: =COUNTA(C25:AI25) -> 4 | AM25: =COUNTA(G25:P25,S25:T25) -> 3
A26: מה צריך להיות יותר חשוב לאזרחי המדינה, האינטרסים האישיים שלהם או האינטרסים של המדינה כולה? | N26: i55 | O26: cc44 | P26: a75 | U26: b59 | AH26: b17 | AI26: b14 | AK26: =COUNTA(C26:AI26) -> 6 | AM26: =COUNTA(G26:P26,S26:T26) -> 3
A27: האם לפי הערכתך עלולה להתפתח מלחמת אזרחים בארץ בעקבות ההסדרים לגבי עתיד השטחים? | O27: c53 | AK27: =COUNTA(C27:AI27) -> 1 | AM27: =COUNTA(G27:P27,S27:T27) -> 1
A28: יש החושבים שישראל יכולה להשיג את כל היעדים החשובים לה: שלום, א"י השלמה, שמירה על רוב יהודי, שמירה על משטר דמוקרטי מבלי לוותר על אף דבר. אחרים חושבים שאי אפשר להשיג את כל היעדים הללו בו זמנית, וכדי להשיג יעדים מסויימים צריך להתפשר על יעדים אחרים. מה דעתך? | O28: cc73 | P28: i31 | AK28: =COUNTA(C28:AI28) -> 2 | AM28: =COUNTA(G28:P28,S28:T28) -> 2
A29: האם יש לך קשרים עם ערבים? | O29: ccc42 | AK29: =COUNTA(C29:AI29) -> 1 | AM29: =COUNTA(G29:P29,S29:T29) -> 1
A30: באיזו מידה כל אחד מהמצבים הבאים מהווה איום בעיניך: מספר שווה של יהודים וערבים במדינה | P30: i17 | AK30: =COUNTA(C30:AI30) -> 1 | AM30: =COUNTA(G30:P30,S30:T30) -> 1
A31: באיזו מידה כל אחד מהמצבים הבאים מהווה איום בעיניך: הפסקת הסיוע מארה"ב | P31: i20 | AK31: =COUNTA(C31:AI31) -> 1 | AM31: =COUNTA(G31:P31,S31:T31) -> 1
A32: מהם הסיכויים שיתקיים כל אחד מהמצבים הבאים בעתיד הנראה לעין: מספר שווה של יהודים וערבים במדינה | P32: i26 | AK32: =COUNTA(C32:AI32) -> 1 | AM32: =COUNTA(G32:P32,S32:T32) -> 1
A33: מהם הסיכויים שיתקיים כל אחד מהמצבים הבאים בעתיד הנראה לעין: הפסקת הסיוע של ארה"ב | P33: i29 | AK33: =COUNTA(C33:AI33) -> 1 | AM33: =COUNTA(G33:P33,S33:T33) -> 1
A34: לפניך רשימת דעות בנושאים שונים. ציין באיזו מידה אתה מסכים או מתנגד לכל אחת מהן: מבין כל ההשקפות הקיימות בעולם כנראה שיש רק אחת בלבד שהיא נכונה | Q34: v74 | AK34: =COUNTA(C34:AI34) -> 1 | AM34: =COUNTA(G34:P34,S34:T34) -> 0
A35: אין אף מצב בו נראה כי עדיף שאנשים יקחו בעצם את החוק לידיים | Q35: v75 | AK35: =COUNTA(C35:AI35) -> 1 | AM35: =COUNTA(G35:P35,S35:T35) -> 0
A36: במצבים בהם יש ניגוד אינטרסים בין טובת הכלל וטובת הפרט במדינה יש בדר"כ להעדיף את טובת הפרט | Q36: v76 | AK36: =COUNTA(C36:AI36) -> 1 | AM36: =COUNTA(G36:P36,S36:T36) -> 0
A37: לא להחזיר שטחים מא"י הוא בחזקת יהרג ובל יעבור | Q37: v77 | AK37: =COUNTA(C37:AI37) -> 1 | AM37: =COUNTA(G37:P37,S37:T37) -> 0
A38: אלוהים ישמור עלינו אם נהיה ראויים לכך אפילו אם לא נהיה מוכנים למלחמה הבאה | Q38: v78 | AK38: =COUNTA(C38:AI38) -> 1 | AM38: =COUNTA(G38:P38,S38:T38) -> 0
A39: באיזו מידה אתה מאמין או לא מאמין בעתיד קיומנו בארץ לטווח ארוך? | Q39: v79 | R39: b27 | S39: f31 | AK39: =COUNTA(C39:AI39) -> 3 | AM39: =COUNTA(G39:P39,S39:T39) -> 1
A40: האם נטל השירות הצבאי מתחלק באופן צודק או לא צודק? | Q40: v104 | AK40: =COUNTA(C40:AI40) -> 1 | AM40: =COUNTA(G40:P40,S40:T40) -> 0
A41: ממה שאתה שומע או מתרשם, האם שרות המילואים מנוצל ביעילות או מבוזבז? | Q41: v105 | AK41: =COUNTA(C41:AI41) -> 1 | AM41: =COUNTA(G41:P41,S41:T41) -> 0
A42: האם משך שרות החובה בצה"ל ארוך מדי, במידה הנכונה או קצר מדי? | Q42: v106 | AK42: =COUNTA(C42:AI42) -> 1 | AM42: =COUNTA(G42:P42,S42:T42) -> 0
A43: לפניך רשימה של אמרות וביטויים שגורים המתייחסים למצב העם והמדינה. ציין לגבי כל אחד מהם באיזו מידה אתה מסכים או מתנגד לו: לא ינום ולא יישן שומר ישראל | Q43: v121 | AK43: =COUNTA(C43:AI43) -> 1 | AM43: =COUNTA(G43:P43,S43:T43) -> 0
A44: שנית מצדה לא תיפול | Q44: v122 | AK44: =COUNTA(C44:AI44) -> 1 | AM44: =COUNTA(G44:P44,S44:T44) -> 0
A45: העולם כולו נגדנו | Q45: v123 | AK45: =COUNTA(C45:AI45) -> 1 | AM45: =COUNTA(G45:P45,S45:T45) -> 0
A46: נצח ישראל לא ישקר | Q46: v124 | AK46: =COUNTA(C46:AI46) -> 1 | AM46: =COUNTA(G46:P46,S46:T46) -> 0
A47: ישראל הינה ותמשיך להיות בחזקת "עם לבדד ישכון" | Q47: v125 | AK47: =COUNTA(C47:AI47) -> 1 | AM47: =COUNTA(G47:P47,S47:T47) -> 0
A48: טוב למות בעד ארצנו | Q48: v126 | AK48: =COUNTA(C48:AI48) -> 1 | AM48: =COUNTA(G48:P48,S48:T48) -> 0
A49: הקם להורגך השכם להורגו | Q49: v127 | AK49: =COUNTA(C49:AI49) -> 1 | AM49: =COUNTA(G49:P49,S49:T49) -> 0
A50: ההגנה הטובה ביותר היא ההתקפה | Q50: v128 | AK50: =COUNTA(C50:AI50) -> 1 | AM50: =COUNTA(G50:P50,S50:T50) -> 0
A51: נצחון צבאי תורם לקידום השלום | Q51: v129 | AK51: =COUNTA(C51:AI51) -> 1 | AM51: =COUNTA(G51:P51,S51:T51) -> 0
... A84: האם מישהו מבני משפחתך הקרובה נפטר או נפגע קשה חלילה בשואה? | Q84: a116 | AK84: =COUNTA(C84:AI84) -> 1 | AM84: =COUNTA(G84:P84,S84:T84) -> 0
A85: לפניך שורה של מעשים. לגבי כל אחד מהם קבע באיזו מידה הוא מתאים או לא מתאים לאזרחות טובה: משלם מס אמת | V85: a18 | AK85: =COUNTA(C85:AI85) -> 1 | AM85: =COUNTA(G85:P85,S85:T85) -> 0
A86: לפניך שורה של מעשים. לגבי כל אחד מהם קבע באיזו מידה הוא מתאים או לא מתאים לאזרחות טובה: לא מצביע ביום הבחירות | V86: a19 | AK86: =COUNTA(C86:AI86) -> 1 | AM86: =COUNTA(G86:P86,S86:T86) -> 0
A87: לפניך שורה של מעשים. לגבי כל אחד מהם קבע באיזו מידה הוא מתאים או לא מתאים לאזרחות טובה: מתכנן ללמוד בחו"ל | V87: a20 | AK87: =COUNTA(C87:AI87) -> 1 | AM87: =COUNTA(G87:P87,S87:T87) -> 0
A88: לפניך שורה של מעשים. לגבי כל אחד מהם קבע באיזו מידה הוא מתאים או לא מתאים לאזרחות טובה: מרשה לעצמו לעבור על החוק אם אין שוטר במקום | V88: a21 | AK88: =COUNTA(C88:AI88) -> 1 | AM88: =COUNTA(G88:P88,S88:T88) -> 0
A89: לפניך שורה של מעשים. לגבי כל אחד מהם קבע באיזו מידה הוא מתאים או לא מתאים לאזרחות טובה: לא מתכנן עתידו בהתאם לצרכי הכלל | V89: a22 | AK89: =COUNTA(C89:AI89) -> 1 | AM89: =COUNTA(G89:P89,S89:T89) -> 0
A90: לפניך שורה של מעשים. לגבי כל אחד מהם קבע באיזו מידה הוא מתאים או לא מתאים לאזרחות טובה: יורד מן הארץ כדי לשפר את מצבו | V90: a23 | AK90: =COUNTA(C90:AI90) -> 1 | AM90: =COUNTA(G90:P90,S90:T90) -> 0
A91: לפניך שורה של מעשים. לגבי כל אחד מהם קבע באיזו מידה הוא מתאים או לא מתאים לאזרחות טובה: דואג לעצמו לפני דאגה לכלל | V91: a24 | AK91: =COUNTA(C91:AI91) -> 1 | AM91: =COUNTA(G91:P91,S91:T91) -> 0
A92: האם אתה מאמין למה שהמפלגות אומרות במערכת הבחירות? | AB92: h48 | AC92: g25 | AE92: d8 | AK92: =COUNTA(C92:AI92) -> 3 | AM92: =COUNTA(G92:P92,S92:T92) -> 0
A93: האם שירתת במילואים, בזמן או בעקבות מלחמת יום כיפור? | AB93: h58 | AK93: =COUNTA(C93:AI93) -> 1 | AM93: =COUNTA(G93:P93,S93:T93) -> 0
A94: באיזו מידה אתה מרוצה מהצורה בה מתנהלת מערכת הבחירות לכנסת? | AC94: g4 | AE94: c6 | AK94: =COUNTA(C94:AI94) -> 2 | AM94: =COUNTA(G94:P94,S94:T94) -> 0
A95: מדוע? | AE95: c7 | AK95: =COUNTA(C95:AI95) -> 1 | AM95: =COUNTA(G95:P95,S95:T95) -> 0
A96: באיזו מידה הפעילות במערכת הבחירות מוסיפה לך יוקרה בקרב חבריך? | AE96: d11 | AK96: =COUNTA(C96:AI96) -> 1 | AM96: =COUNTA(G96:P96,S96:T96) -> 0
A97: באיזו מידה מועילה לך הפעילות במערכת הבחירות ליצירת קשרים, לקידום בעבודה, להנאה חומרות וכו'? | AE97: d12 | AK97: =COUNTA(C97:AI97) -> 1 | AM97: =COUNTA(G97:P97,S97:T97) -> 0
A98: האם בעלך מגוייס? | AC98: g60 | AK98: =COUNTA(C98:AI98) -> 1 | AM98: =COUNTA(G98:P98,S98:T98) -> 0
A99: באיזו מידה הוטב או הורע מצבה של ישראל, באופן כללי, בעקבות מלחמת יום כיפור? | AD99: f2 | AK99: =COUNTA(C99:AI99) -> 1 | AM99: =COUNTA(G99:P99,S99:T99) -> 0
A100: באיזו מידה אחראי כל אחד מן הגורמים הבאים לשינוי שחל במצבנו: הממשלה | AD100: f3 | AK100: =COUNTA(C100:AI100) -> 1 | AM100: =COUNTA(G100:P100,S100:T100) -> 0
A101: באיזו מידה אחראי כל אחד מן הגורמים הבאים לשינוי שחל במצבנו: הפיקוד הבכיר של צה"ל | AD101: f4 | AK101: =COUNTA(C101:AI101) -> 1 | AM101: =COUNTA(G101:P101,S101:T101) -> 0
A102: באיזו מידה אחראי כל אחד מן הגורמים הבאים לשינוי שחל במצבנו: ארצות ערב | AD102: f5 | AK102: =COUNTA(C102:AI102) -> 1 | AM102: =COUNTA(G102:P102,S102:T102) -> 0
A103: באיזו מידה אחראי כל אחד מן הגורמים הבאים לשינוי שחל במצבנו: המעצמות הגדולות | AD103: f6 | AK103: =COUNTA(C103:AI103) -> 1 | AM103: =COUNTA(G103:P103,S103:T103) -> 0
A104: באיזו מידה אתה מאמין וסומך על עבודת הממשלה תחת מנהיגותה של הגב' גולדה מאיר במשך 4 השנים האחרונות? | AD104: f41 | AK104: =COUNTA(C104:AI104) -> 1 | AM104: =COUNTA(G104:P104,S104:T104) -> 0
A105: איך אתה רואה את הפוליטיקה בישראל? | AE105: c27 | AK105: =COUNTA(C105:AI105) -> 1 | AM105: =COUNTA(G105:P105,S105:T105) -> 0
A106: באיזו מידה חשוב לך להרגיש שאתה חלק מהמדינה והעם? | AE106: c45 | AK106: =COUNTA(C106:AI106) -> 1 | AM106: =COUNTA(G106:P106,S106:T106) -> 0
A107: באיזו מידה ההשתתפות בבחירות מאפשרות לך להרגיש שאתה חלק מהמדינה והעם? | AE107: d22 | AK107: =COUNTA(C107:AI107) -> 1 | AM107: =COUNTA(G107:P107,S107:T107) -> 0
A108: באיזו מידה חשוב לך להתנהג כמו החברים שלך? | AE108: c48 | AK108: =COUNTA(C108:AI108) -> 1 | AM108: =COUNTA(G108:P108,S108:T108) -> 0
A109: באיזו מידה ההשתתפות בבחירות מאפשרת לך להתנהג כמו חבריך? | AE109: d25 | AK109: =COUNTA(C109:AI109) -> 1 | AM109: =COUNTA(G109:P109,S109:T109) -> 0
A110: באיזו מידה חשוב לך להשפיע איזה מפלגה תהיה בשלטון? | AE110: c50 | AK110: =COUNTA(C110:AI110) -> 1 | AM110: =COUNTA(G110:P110,S110:T110) -> 0
A111: באיזו מידה השתתפות בבחירות מאפשרת לך להשפיע איזה מפלגה תהיה בשלטון? | AE111: d27 | AK111: =COUNTA(C111:AI111) -> 1 | AM111: =COUNTA(G111:P111,S111:T111) -> 0
A112: באיזו מידה השתתפות בבחירות גורמת לך הנאה בגלל שאתה משתתף במאורע חגיגי? | AE112: d28 | AK112: =COUNTA(C112:AI112) -> 1 | AM112: =COUNTA(G112:P112,S112:T112) -> 0
A113: מה דעתך על הדרך שבה מנהלת העירייה את ענייני העיר? | AI113: a86 | AK113: =COUNTA(C113:AI113) -> 1 | AM113: =COUNTA(G113:P113,S113:T113) -> 0
A114: מהי לדעתך הבעיה החשובה ביותר שעל העירייה שלך לטפל בה? | AE114: e11 | AF114: b17 | AK114: =COUNTA(C114:AI114) -> 2 | AM114: =COUNTA(G114:P114,S114:T114) -> 0
A115: עד כמה ברור לך מהם הדרכים הטובות ביותר בהן צריכה העירייה לנהל את ענייני העיר? | AI115: a87 | AK115: =COUNTA(C115:AI115) -> 1 | AM115: =COUNTA(G115:P115,S115:T115) -> 0
A116: איזו מפלגה מסוגלת לפתור את הבעיה החשובה ביותר של העיר שלך? | AE116: e12 | AK116: =COUNTA(C116:AI116) -> 1 | AM116: =COUNTA(G116:P116,S116:T116) -> 0
A117: באיזו מידה אתה מרוצה מהשירותים שאתה מקבל מהעירייה? | AE117: e13 | AK117: =COUNTA(C117:AI117) -> 1 | AM117: =COUNTA(G117:P117,S117:T117) -> 0
A118: האם לדעתך רצוי להחליף את ראש העיר שלך? | AE118: e14 | AK118: =COUNTA(C118:AI118) -> 1 | AM118: =COUNTA(G118:P118,S118:T118) -> 0
A119: האם אתה מסכים לדעה שיש לבחור ראשי ערים בבחירות אישיות, או שהנך חושב שרצוי לבחרם לפי רשימות מפלגתיות? | AI119: b10 | AK119: =COUNTA(C119:AI119) -> 1 | AM119: =COUNTA(G119:P119,S119:T119) -> 0
A120: האם המפלגה שאתה תומך בה או נוטה לתמוך בה כיום זהה לתנועת הנוער שהיית חבר בה? | AF120: v18 | AK120: =COUNTA(C120:AI120) -> 1 | AM120: =COUNTA(G120:P120,S120:T120) -> 0
A121: עד כמה ברור לך מהן הבעיות היסודיות החשובות ביותר כיום בחיי מדינת ישראל? | AH121: b22 | AI121: b28 | AK121: =COUNTA(C121:AI121) -> 2 | AM121: =COUNTA(G121:P121,S121:T121) -> 0
A122: עד כמה ברור לך מהן הדרכים הטובות ביותר בהן צריכה הממשלה לנהל את ענייני המדינה? | AI122: a84 | AK122: =COUNTA(C122:AI122) -> 1 | AM122: =COUNTA(G122:P122,S122:T122) -> 0
A123: איזה מן הנושאים הנ"ל הינו החשוב לך ביותר בקביעת עמדתך כלפי המפלגה אותה אתה אוהד? | AH123: b27 | AI123: b34 | AK123: =COUNTA(C123:AI123) -> 2 | AM123: =COUNTA(G123:P123,S123:T123) -> 0
A124: לכל מפלגה יש חוגי תומכים משלה. מבין הקבוצות הבאות, מיהו לדעתך חוג התומכים העיקרי של המפלגות הבאות: המערך (גיל) | AH124: b70 | AI124: c3 | AK124: =COUNTA(C124:AI124) -> 2 | AM124: =COUNTA(G124:P124,S124:T124) -> 0
A125: לכל מפלגה יש חוגי תומכים משלה. מבין הקבוצות הבאות, מיהו לדעתך חוג התומכים העיקרי של המפלגות הבאות: המערך (עדה) | AH125: b71 | AI125: c4 | AK125: =COUNTA(C125:AI125) -> 2 | AM125: =COUNTA(G125:P125,S125:T125) -> 0
A126: לכל מפלגה יש חוגי תומכים משלה. מבין הקבוצות הבאות, מיהו לדעתך חוג התומכים העיקרי של המפלגות הבאות: המערך (מקצוע) | AH126: b72 | AI126: c5 | AK126: =COUNTA(C126:AI126) -> 2 | AM126: =COUNTA(G126:P126,S126:T126) -> 0
A127: לכל מפלגה יש חוגי תומכים משלה. מבין הקבוצות הבאות, מיהו לדעתך חוג התומכים העיקרי של המפלגות הבאות: חירות (גיל) | AH127: b74 | AI127: c7 | AK127: =COUNTA(C127:AI127) -> 2 | AM127: =COUNTA(G127:P127,S127:T127) -> 0
A128: לכל מפלגה יש חוגי תומכים משלה. מבין הקבוצות הבאות, מיהו לדעתך חוג התומכים העיקרי של המפלגות הבאות: חירות (עדה) | AH128: b75 | AI128: c8 | AK128: =COUNTA(C128:AI128) -> 2 | AM128: =COUNTA(G128:P128,S128:T128) -> 0
A129: לכל מפלגה יש חוגי תומכים משלה. מבין הקבוצות הבאות, מיהו לדעתך חוג התומכים העיקרי של המפלגות הבאות: חירות (מקצוע) | AH129: b76 | AI129: c9 | AK129: =COUNTA(C129:AI129) -> 2 | AM129: =COUNTA(G129:P129,S129:T129) -> 0
A130: לכל מפלגה יש חוגי תומכים משלה. מבין הקבוצות הבאות, מיהו לדעתך חוג התומכים העיקרי של המפלגות הבאות: העולם הזה (גיל) | AH130: b78 | AI130: c11 | AK130: =COUNTA(C130:AI130) -> 2 | AM130: =COUNTA(G130:P130,S130:T130) -> 0
A131: לכל מפלגה יש חוגי תומכים משלה. מבין הקבוצות הבאות, מיהו לדעתך חוג התומכים העיקרי של המפלגות הבאות: העולם הזה (עדה) | AH131: b79 | AI131: c12 | AK131: =COUNTA(C131:AI131) -> 2 | AM131: =COUNTA(G131:P131,S131:T131) -> 0
A132: לכל מפלגה יש חוגי תומכים משלה. מבין הקבוצות הבאות, מיהו לדעתך חוג התומכים העיקרי של המפלגות הבאות: העולם הזה (מקצוע) | AH132: b80 | AI132: c13 | AK132: =COUNTA(C132:AI132) -> 2 | AM132: =COUNTA(G132:P132,S132:T132) -> 0
...

Sheet עניין פוליטי
A1: שאלה | B1: 2025 | C1: 2022 | D1: 2021 | E1: 2020 | F1: 43709 | G1: 43556 | H1: 2015 | I1: 2013 | J1: 2009 | K1: 2006 | L1: 2003 | M1: 2001 | N1: 1999 | O1: 1996 | P1: 1992 | Q1: 1987* | R1: 1988* | S1: 1988 | T1: 1984 | U1: 1981 - 3 | V1: 1981 - 2 | W1: 1981 - 1 | X1: 1977 - 4 | Y1: 1977 - 3 | Z1: 1977 - 2 | AA1: 1977 - 1 | AB1: 1973 - 5 | AC1: 1973 - 4 | AD1: 1973 - 3 | AE1: 1973 - 2 | AF1: 1973 - 1 | AG1: 1969 - 3 | AH1: 1969 - 2 | AI1: 1969 - 1 | AK1: מספר חזרות | AM1: ספירה 84-19 | AO1: סה"כ מעל שתי חזרות
A2: באיזו מידה אתה וחבריך יכולים להשפיע על מדיניות הממשלה? | C2: v46 | D2: v46 | E2: v46 | G2: v46 | H2: v50 | I2: v44 | J2: v56 | K2: a54 | L2: a75 | M2: a74 | N2: i57 | O2: cc48 | P2: a61 | Q2: a16 | R2: b72 | S2: f75 | T2: v40 | U2: b30 | V2: a35 | W2: v70 | AA2: v32 | AC2: g33 | AE2: d6 | AF2: v66 | AH2: b14 | AI2: a73 | AK2: =COUNTA(C2:AI2) -> 26 | AM2: =COUNTA(G2:P2,S2:T2) -> 12 | AO2: =COUNTIF(AM2:AM47,">=2") -> 3
A3: באיזו מידה אתה נוהג לשוחח עם חבריך ובני משפחתך על עניינים פוליטיים? | B3: v45 | C3: v45 | D3: v45 | E3: v45 | G3: v45 | H3: v49 | I3: v43 | J3: v55 | K3: a53 | L3: a74 | M3: a73 | N3: i56 | O3: cc45 | P3: a60 | Q3: a75 | R3: b59 | S3: f62 | V3: a31 | W3: v19 | AA3: v28 | AE3: c25 | AF3: v11 | AK3: =COUNTA(C3:AI3) -> 21 | AM3: =COUNTA(G3:P3,S3:T3) -> 11
A4: כאשר אתה נפגש עם חבריך, האם אתם דנים על עניינים פוליטיים? | Q4: a113 | R4: b71 | S4: f74 | V4: a32 | AA4: v29 | AF4: v8 | AK4: =COUNTA(C4:AI4) -> 6 | AM4: =COUNTA(G4:P4,S4:T4) -> 1
A5: באיזו מידה אתה נוהג או לא נוהג להביע את דעתך בנושאי בטחון בדרכים שונות, כגון שיחות עם בני משפחה וחברים, כתיבת מכתבים למערכת העיתונים, חתומה על עצומות ועוד? | Q5: a15 | AK5: =COUNTA(C5:AI5) -> 1 | AM5: =COUNTA(G5:P5,S5:T5) -> 0
A6: באיזו מידה חשוב לך להביע את דעותיך בעניינים פוליטיים? | AE6: c46 | AK6: =COUNTA(C6:AI6) -> 1 | AM6: =COUNTA(G6:P6,S6:T6) -> 0
A7: באיזו מידה השתתפות בבחירות מאפשרת לך להביע את דעותיך בעניינים פוליטיים? | AE7: d23 | AK7: =COUNTA(C7:AI7) -> 1 | AM7: =COUNTA(G7:P7,S7:T7) -> 0
A8: באיזו מידה הדעות של בני משפחתך בנושאי השטחים ומדיניות הבטחון דומות לדעות שלך? | R8: b58 | S8: f61 | AK8: =COUNTA(C8:AI8) -> 2 | AM8: =COUNTA(G8:P8,S8:T8) -> 1
A9: עם מי מבני משפחתך הינך משוחח כיום על עניינים פוליטיים במידה הרבה ביותר? | Q9: a76 | R9: b60 | S9: f63 | AK9: =COUNTA(C9:AI9) -> 3 | AM9: =COUNTA(G9:P9,S9:T9) -> 1
A10: בתקופה בה התגוררת בבית הוריך, עם מי נהגת לשוחח על עניינים פוליטיים במידה הרבה ביותר? | Q10: a77 | AK10: =COUNTA(C10:AI10) -> 1 | AM10: =COUNTA(G10:P10,S10:T10) -> 0
A11: האם נהגת לשוחח עם אביך בענייני פוליטיקה? | AF11: v20 | AK11: =COUNTA(C11:AI11) -> 1 | AM11: =COUNTA(G11:P11,S11:T11) -> 0
A12: האם אתה חבר, אוהד או פעיל של מפלגה כלשהי? | H12: v89 | I12: v93 | J12: v151 | K12: b72 | L12: b72 | M12: b23 | N12: c18 | O12: ccc45 | P12: i55 | Q12: a59 | R12: c50 | S12: g71 | T12: a51 | U12: b156 | V12: a145 | AA12: v110 | AC12: g58 | AE12: d42 | AF12: b11 | AG12: b47 | AH12: b37 | AI12: b42 | AK12: =COUNTA(C12:AI12) -> 22 | AM12: =COUNTA(G12:P12,S12:T12) -> 11
A13: האם בתקופה שלפני הבחירות אתה נוהג להשתתף באסיפות המאורגנות ע"י המפלגות ואם כן באיזו תדירות? | W13: v17 | AF13: v6 | AH13: a4 | AI13: a3 | AK13: =COUNTA(C13:AI13) -> 4 | AM13: =COUNTA(G13:P13,S13:T13) -> 0
A14: האם אתה נוהג להשתתף בחוגי בית של המפלגות ואם כן באיזו תדירות? | W14: v18 | AE14: c23 | AI14: a5 | AK14: =COUNTA(C14:AI14) -> 3 | AM14: =COUNTA(G14:P14,S14:T14) -> 0
A15: האם בתקופה שלפני הבחירות מתקיימים חוגי בית בביתך? | AI15: a6 | AK15: =COUNTA(C15:AI15) -> 1 | AM15: =COUNTA(G15:P15,S15:T15) -> 0
A16: יש אנשים שמתעניינים במערכת הבחירות מכיוון שיש לה אופי של התמודדות ספורטיבית. באיזו מידה גם אתה מתעניין מסיבה זו? | AC16: g26 | AE16: d9 | AK16: =COUNTA(C16:AI16) -> 2 | AM16: =COUNTA(G16:P16,S16:T16) -> 0
A17: האם אתה פעיל במערכת הבחירות הנוכחית? (עובד למען אחת המפלגות בהתנדבות או בשכר) | AC17: g27 | AE17: d10 | AK17: =COUNTA(C17:AI17) -> 2 | AM17: =COUNTA(G17:P17,S17:T17) -> 0
A18: האם בתקופת הבחירות אתה מתעניין בפוליטיקה יותר מאשר בדר"כ? | AE18: c2 | AK18: =COUNTA(C18:AI18) -> 1 | AM18: =COUNTA(G18:P18,S18:T18) -> 0
A19: באיזו מידה אתה מתעניין במערכת הבחירות: להסתדרות | AE19: c3 | AK19: =COUNTA(C19:AI19) -> 1 | AM19: =COUNTA(G19:P19,S19:T19) -> 0
A20: באיזו מידה אתה מתעניין במערכת הבחירות: לעירייה | AE20: c4 | AK20: =COUNTA(C20:AI20) -> 1 | AM20: =COUNTA(G20:P20,S20:T20) -> 0
A21: באיזו מידה אתה מתעניין במערכת הבחירות: לכנסת | AE21: c5 | AK21: =COUNTA(C21:AI21) -> 1 | AM21: =COUNTA(G21:P21,S21:T21) -> 0
A22: איזה נושאים פוליטיים מעניינים אותך בעיקר? | AE22: c9 | AK22: =COUNTA(C22:AI22) -> 1 | AM22: =COUNTA(G22:P22,S22:T22) -> 0
A23: באיזו מידה אתה מתעניין בפוליטיקה בדר"כ? | AE23: c26 | AF23: v4 | AK23: =COUNTA(C23:AI23) -> 2 | AM23: =COUNTA(G23:P23,S23:T23) -> 0
A24: בדר"כ, האם אתה נוהג לבקר בהרצאות על נושאים פוליטיים? | AF24: v5 | AI24: a2 | AK24: =COUNTA(C24:AI24) -> 2 | AM24: =COUNTA(G24:P24,S24:T24) -> 0
A25: האם אתה פעיל בארגון ציבורי כלשהו? | AE25: d43 | AK25: =COUNTA(C25:AI25) -> 1 | AM25: =COUNTA(G25:P25,S25:T25) -> 0
A26: באיזו מידה מערכת הבחירות הנוכחית עוזרת לך להכיר יותר טוב את המנהיגים הפוליטיים? | AC26: g8 | AE26: d15 | AK26: =COUNTA(C26:AI26) -> 2 | AM26: =COUNTA(G26:P26,S26:T26) -> 0
A27: באיזו מידה חשוב לך להכיר יותר טוב את המנהיגים הפוליטיים? | AE27: c41 | AK27: =COUNTA(C27:AI27) -> 1 | AM27: =COUNTA(G27:P27,S27:T27) -> 0
A28: באיזו מידה מערכת הבחירות עוזרת לך להבין יותר את הבעיות הפוליטיות בארץ? | AC28: g6 | AE28: d13 | AK28: =COUNTA(C28:AI28) -> 2 | AM28: =COUNTA(G28:P28,S28:T28) -> 0
A29: באיזו מידה חשוב לך להבין יותר טוב את הבעיות הפוליטיות בארץ? | AE29: c39 | AK29: =COUNTA(C29:AI29) -> 1 | AM29: =COUNTA(G29:P29,S29:T29) -> 0
A30: האם אביך התעניין בפוליטיקה? | AF30: v19 | AK30: =COUNTA(C30:AI30) -> 1 | AM30: =COUNTA(G30:P30,S30:T30) -> 0
A31: לאחרונה יש הטוענים שקיים פער כלכלי וחברתי במדינה. האם אתה מתעניין בנושאים אלו? | AF31: v40 | AK31: =COUNTA(C31:AI31) -> 1 | AM31: =COUNTA(G31:P31,S31:T31) -> 0
A32: באיזו מידה אתה מתעניין בבעיות הכלכליות של מדינת ישראל? | AH32: b11 | AI32: a64 | AK32: =COUNTA(C32:AI32) -> 2 | AM32: =COUNTA(G32:P32,S32:T32) -> 0
A33: האם בדר"כ אתה מתעניין בבעיות חוץ וביטחון? | AF33: v48 | AI33: a61 | AK33: =COUNTA(C33:AI33) -> 2 | AM33: =COUNTA(G33:P33,S33:T33) -> 0
A34: באיזו מידה אתה מתעניין בתוצאות הבחירות לכנסת? | AG34: c13 | AK34: =COUNTA(C34:AI34) -> 1 | AM34: =COUNTA(G34:P34,S34:T34) -> 0
A35: באיזו מידה לדעתך צריך האזרח הרגיל במדינת ישראל להתעניין בבעיות הכלכליות של המדינה? | AH35: b12 | AI35: a65 | AK35: =COUNTA(C35:AI35) -> 2 | AM35: =COUNTA(G35:P35,S35:T35) -> 0
A36: באיזו מידה לדעתך צריך האזרח הרגיל במדינת ישראל להתעניין בבעיות החוץ והביטחון של המדינה? | AI36: a62 | AK36: =COUNTA(C36:AI36) -> 1 | AM36: =COUNTA(G36:P36,S36:T36) -> 0
A37: באיזו מידה אתה מתעניין בבעיות החברתיות של מדינת ישראל? | AI37: a67 | AK37: =COUNTA(C37:AI37) -> 1 | AM37: =COUNTA(G37:P37,S37:T37) -> 0
A38: באיזו מידה לדעתך צריך האזרח הרגיל במדינת ישראל להתעניין בבעיות החברתיות של המדינה? | AI38: a68 | AK38: =COUNTA(C38:AI38) -> 1 | AM38: =COUNTA(G38:P38,S38:T38) -> 0
A39: באיזו מידה אתה מתעניין בפוליטיקה מקומית של מדינת ישראל? | AI39: a70 | AK39: =COUNTA(C39:AI39) -> 1 | AM39: =COUNTA(G39:P39,S39:T39) -> 0
A40: באיזו מידה לדעתך צריך האזרח הרגיל במדינת ישראל להתעניין בפוליטיקה מקומית של המדינה? | AI40: a71 | AK40: =COUNTA(C40:AI40) -> 1 | AM40: =COUNTA(G40:P40,S40:T40) -> 0
A41: האם אתה משוחח עם מכרים, ידידים, חברים לעבודה או בני משפחה על נושאים אקטואליים הקשורים למדינת ישראל? אם כן - באיזו תכיפות אתה מנהל שיחות כאלה בנושא: מדיניות חוץ וביטחון | AI41: a76 | AK41: =COUNTA(C41:AI41) -> 1 | AM41: =COUNTA(G41:P41,S41:T41) -> 0
A42: האם אתה משוחח עם מכרים, ידידים, חברים לעבודה או בני משפחה על נושאים אקטואליים הקשורים למדינת ישראל? אם כן - באיזו תכיפות אתה מנהל שיחות כאלה בנושא: כלכלה | AI42: a77 | AK42: =COUNTA(C42:AI42) -> 1 | AM42: =COUNTA(G42:P42,S42:T42) -> 0
A43: האם אתה משוחח עם מכרים, ידידים, חברים לעבודה או בני משפחה על נושאים אקטואליים הקשורים למדינת ישראל? אם כן - באיזו תכיפות אתה מנהל שיחות כאלה בנושא: בעיות חברתיות | AI43: a78 | AK43: =COUNTA(C43:AI43) -> 1 | AM43: =COUNTA(G43:P43,S43:T43) -> 0
A44: האם אתה נותן אמון באינפורמציה הפוליטית שאתה מקבל בשיחות עם חבריך? | AI44: a88 | AK44: =COUNTA(C44:AI44) -> 1 | AM44: =COUNTA(G44:P44,S44:T44) -> 0
A45: האם השתתפת בשנה שנתיים האחרונות בהפגנה? בנושא תהליך השלום | O45: ccc16 | AK45: =COUNTA(C45:AI45) -> 1 | AM45: =COUNTA(G45:P45,S45:T45) -> 1
A46: האם השתתפת בשנה שנתיים האחרונות בהפגנה? בעקבות רצח רבין | O46: ccc17 | AK46: =COUNTA(C46:AI46) -> 1 | AM46: =COUNTA(G46:P46,S46:T46) -> 1
A47: האם השתתפת בהפגנה בשנה האחרונה? | D47: v606 | AK47: =COUNTA(C47:AI47) -> 1 | AM47: =COUNTA(G47:P47,S47:T47) -> 0
A48: מאז ה - 7 באוקטובר, האם השתתפת בהפגנות, ואם כן באילו? יש לבחור את כל האפשרויות הרלוונטיות: | B48: v413

Sheet ימין-שמאל
A1: שאלה | B1: 2025 | C1: 2022 | D1: 2021 | E1: 2020 | F1: 43709 | G1: 43556 | H1: 2015 | I1: 2013 | J1: 2009 | K1: 2006 | L1: 2003 | M1: 2001 | N1: 1999 | O1: 1996 | P1: 1992 | Q1: 1987* | R1: 1988* | S1: 1988 | T1: 1984 | U1: 1981 - 3 | V1: 1981 - 2 | W1: 1981 - 1 | X1: 1977 - 4 | Y1: 1977 - 3 | Z1: 1977 - 2 | AA1: 1977 - 1 | AB1: 1973 - 5 | AC1: 1973 - 4 | AD1: 1973 - 3 | AE1: 1973 - 2 | AF1: 1973 - 1 | AG1: 1969 - 3 | AH1: 1969 - 2 | AI1: 1969 - 1 | AK1: מספר חזרות | AM1: ספירה 84-19 | AO1: סה"כ מעל שתי חזרות
A2: בבחירות האלה דיברו הרבה על ימין ועל שמאל בפוליטיקה, מה זה להבנתך ימין? | E2: E8A_after | G2: V8A_after | H2: after_v13b_1 | AK2: =COUNTA(C2:AI2) -> 3 | AM2: =COUNTA(G2:P2,S2:T2) -> 2 | AO2: =COUNTIF(AM2:AM55,">=2") -> 21
A3: בבחירות האלה דיברו הרבה על ימין ועל שמאל בפוליטיקה, מה זה להבנתך שמאל? | E3: E8B_after | G3: V8B_after | H3: after_v13b_2 | AK3: =COUNTA(C3:AI3) -> 3 | AM3: =COUNTA(G3:P3,S3:T3) -> 2
A4: עם איזה זרם פוליטי אתה מזדהה? | C4: v53 | G4: v53 | H4: v71 | I4: v103 | J4: v134 | K4: b61 | L4: b73 | N4: c19 | O4: ccc46 | P4: i56 | R4: c51 | S4: g72 | T4: a52 | U4: b157 | V4: a133 | W4: v73 | AA4: v104 | AE4: d31 | AF4: v69 | AG4: c19 | AH4: c40 | AI4: c48 | AK4: =COUNTA(C4:AI4) -> 22 | AM4: =COUNTA(G4:P4,S4:T4) -> 11
A5: הרבה מדברים על שמאל וימין בפוליטיקה. היכן היית מדרג את עצמך על פני רצף שמאל-ימין, כאשר 1 הקצה הימני ו-7 הקצה השמאלי? | B5: v111 | C5: v111 | D5: v111 | E5: v111 | F5: c111 | G5: v111 | H5: v103 | I5: v88 | J5: v135 | K5: b62 | L5: a49 | M5: a66 | N5: i19 | O5: c69 | P5: a110 | Q5: a60 | R5: b126 | S5: f125 | T5: v43 | U5: b80 | W5: v116 | AK5: =COUNTA(C5:AI5) -> 20 | AM5: =COUNTA(G5:P5,S5:T5) -> 12
A6: האם אתה יכול לראות את עצמך בתנאים מסוימים עובר למחנה השמאל או למחנה הימין? | N6: i20 | AK6: =COUNTA(C6:AI6) -> 1 | AM6: =COUNTA(G6:P6,S6:T6) -> 1
A7: דירגת את עצמך יותר לכיוון מחנה השמאל/ימין. האם אתה יכול לראות את עצמך בתנאים מסוימים עובר למחנה האחר? | N7: i21 | AK7: =COUNTA(C7:AI7) -> 1 | AM7: =COUNTA(G7:P7,S7:T7) -> 1
A8: הרבה מדברים על "שמאל" ו-"ימין" בפוליטיקה. כיצד היית מדרג את עצמך על פני רצף "שמאל-ימין" כאשר 0 משמעו שמאל, 10 משמעו ימין ו-5 משמעו אמצע? | C8: v620 | D8: v621 | J8: v90 | K8: b7 | AK8: =COUNTA(C8:AI8) -> 4 | AM8: =COUNTA(G8:P8,S8:T8) -> 2
A9: הרבה מדברים על שמאל וימין בתחום המדיני-ביטחוני. כיצד היית מדרג את עצמך על רצף זה? | I9: v67 | Q9: v58 | R9: b44 | S9: f47 | T9: v44 | U9: b81 | W9: v117 | AK9: =COUNTA(C9:AI9) -> 7 | AM9: =COUNTA(G9:P9,S9:T9) -> 3
A10: הרבה מדברים על שמאל וימין בתחום הכלכלי. כיצד היית מדרג את עצמך על רצף זה? | T10: v45 | U10: b83 | W10: v118 | AK10: =COUNTA(C10:AI10) -> 3 | AM10: =COUNTA(G10:P10,S10:T10) -> 1
A11: הרבה מדברים על שמאל וימין בתחום מדיניות החוץ. כיצד היית מדרג את עצמך על רצף זה? | U11: b82 | AK11: =COUNTA(C11:AI11) -> 1 | AM11: =COUNTA(G11:P11,S11:T11) -> 0
A12: עד כמה חשובה לך הזהות שלך כ(ימני/שמאלני/תומך מרכז)? | G12: v54 | AK12: =COUNTA(C12:AI12) -> 1 | AM12: =COUNTA(G12:P12,S12:T12) -> 1
A13: באיזו מידה אתה מסכים או לא מסכים עם כל אחת מן הטענות הבאות: כשמישהו מעביר ביקורת על (ימנים/שמאלנים/תומכים של המרכז) זה מרגיש לך כמו עלבון אישי | G13: v55 | AK13: =COUNTA(C13:AI13) -> 1 | AM13: =COUNTA(G13:P13,S13:T13) -> 1
A14: כשאתה פוגש תומך אחר של (הימין/שמאל/מרכז) אתה מרגיש קשור אליו | G14: v56 | AK14: =COUNTA(C14:AI14) -> 1 | AM14: =COUNTA(G14:P14,S14:T14) -> 1
A15: כשאנשים אומרים דברים טובים על (ימנים/שמאלנים/תומכים של המרכז) זה גורם לך הרגשה טובה | G15: v57 | AK15: =COUNTA(C15:AI15) -> 1 | AM15: =COUNTA(G15:P15,S15:T15) -> 1
A16: בבחירות האלה דיברו הרבה על ימין ושמאל בפוליטיקה. מהם לדעתך הדברים העיקריים שמבחינים בין שמאל לימין? | H16: after_v13a | U16: b76 | AK16: =COUNTA(C16:AI16) -> 2 | AM16: =COUNTA(G16:P16,S16:T16) -> 1
A17: האם לדעתך קיימים הבדלים בעמדותיהן של המפלגות לגבי הבעיה שציינת? | T17: v5 | U17: b4 | W17: v5 | AA17: v7 | AE17: c54 | AF17: c30 | AK17: =COUNTA(C17:AI17) -> 6 | AM17: =COUNTA(G17:P17,S17:T17) -> 1
A18: האם ברור לך מה ההבדלים בעמדותיהן של המפלגות לגבי בעיה זו? | AA18: v8 | AK18: =COUNTA(C18:AI18) -> 1 | AM18: =COUNTA(G18:P18,S18:T18) -> 0
A19: האם לדעתך קיימים או לא קיימים הבדלים בעמדותיהן של המפלגות העיקריות בארץ בנושאים הבאים: מדיניות כלכלית-חברתית | C19: v58 | G19: v58 | H19: v59 | AF19: v43 | AK19: =COUNTA(C19:AI19) -> 4 | AM19: =COUNTA(G19:P19,S19:T19) -> 2
A20: האם לדעתך קיימים או לא קיימים הבדלים בעמדותיהן של המפלגות העיקריות בארץ בנושאים הבאים: כלכלה | I20: v51 | J20: v76 | K20: a85 | L20: a51 | M20: a68 | N20: i33 | O20: c74 | P20: a53 | R20: b63 | S20: f66 | T20: v19 | U20: b16 | W20: v15 | AA20: v21 | AK20: =COUNTA(C20:AI20) -> 14 | AM20: =COUNTA(G20:P20,S20:T20) -> 10
A21: האם לדעתך קיימים או לא קיימים הבדלים בעמדותיהן של המפלגות העיקריות בארץ בנושאים הבאים: מדיניות חברתית | I21: v52 | J21: v77 | K21: a86 | L21: a52 | M21: a69 | N21: i34 | AK21: =COUNTA(C21:AI21) -> 6 | AM21: =COUNTA(G21:P21,S21:T21) -> 6
A22: האם לדעתך קיימים או לא קיימים הבדלים בעמדותיהן של המפלגות העיקריות בארץ בנושאים הבאים: דת ומדינה | C22: v59 | G22: v59 | H22: v60 | I22: v53 | J22: v78 | K22: a87 | L22: a53 | M22: a70 | N22: i35 | AK22: =COUNTA(C22:AI22) -> 9 | AM22: =COUNTA(G22:P22,S22:T22) -> 8
A23: האם לדעתך קיימים או לא קיימים הבדלים בעמדותיהן של המפלגות העיקריות בארץ בנושאים הבאים: שלום ושטחים | C23: v60 | G23: v60 | H23: v61 | I23: v54 | J23: v79 | K23: a88 | L23: a54 | M23: a71 | N23: i37 | O23: c75 | P23: a51 | T23: v12 | W23: v9 | AA23: v12 | AF23: v51 | AK23: =COUNTA(C23:AI23) -> 15 | AM23: =COUNTA(G23:P23,S23:T23) -> 11
A24: האם לדעתך קיימים או לא קיימים הבדלים בעמדותיהן של המפלגות העיקריות בארץ בנושאים הבאים: בטחון וטרור | C24: v61 | G24: v61 | H24: v62 | I24: v55 | J24: v80 | K24: a89 | L24: a55 | M24: a72 | N24: i38 | O24: c76 | Q24: v16 | R24: b57 | S24: f60 | U24: b7 | AC24: g53 | AD24: f48 | AK24: =COUNTA(C24:AI24) -> 16 | AM24: =COUNTA(G24:P24,S24:T24) -> 10
A25: האם לדעתך קיימים או לא קיימים הבדלים בעמדותיהן של המפלגות העיקריות בארץ בנושאים הבאים: ביחס שלהן לדמוקרטיה | C25: v62 | G25: v62 | H25: v63 | I25: v57 | AK25: =COUNTA(C25:AI25) -> 4 | AM25: =COUNTA(G25:P25,S25:T25) -> 3
A26: האם לדעתך קיימים או לא קיימים הבדלים בעמדותיהן של המפלגות העיקריות בארץ בנושאים הבאים: האיום האיראני | I26: v56 | AK26: =COUNTA(C26:AI26) -> 1 | AM26: =COUNTA(G26:P26,S26:T26) -> 1
A27: האם לדעתך קיימים או לא קיימים הבדלים בעמדותיהן של המפלגות העיקריות בארץ בנושאים הבאים: ירושלים | J27: v75 | K27: a84 | L27: a50 | M27: a67 | N27: i32 | O27: c73 | AK27: =COUNTA(C27:AI27) -> 6 | AM27: =COUNTA(G27:P27,S27:T27) -> 6
A28: האם לדעתך קיימים או לא קיימים הבדלים בעמדותיהן של המפלגות העיקריות בארץ בנושאים הבאים: לבנון | N28: i36 | AK28: =COUNTA(C28:AI28) -> 1 | AM28: =COUNTA(G28:P28,S28:T28) -> 1
A29: האם לדעתך קיימים או לא קיימים הבדלים בעמדותיהן של המפלגות העיקריות בארץ בנושאים הבאים: שחיתות | AE29: d3 | AK29: =COUNTA(C29:AI29) -> 1 | AM29: =COUNTA(G29:P29,S29:T29) -> 0
A30: היכן היית מדרג את המפלגות הבאות על פני רצף "שמאל-ימין" כאשר 0 משמעו שמאל, 10 משמעו ימין ו-5 משמעו אמצע: ליכוד | C30: v620a | D30: v620A | J30: v91 | K30: b11 | AK30: =COUNTA(C30:AI30) -> 4 | AM30: =COUNTA(G30:P30,S30:T30) -> 2
A31: היכן היית מדרג את המפלגות הבאות על פני רצף "שמאל-ימין" כאשר 0 משמעו שמאל, 10 משמעו ימין ו-5 משמעו אמצע: עבודה | C31: v620c | D31: v620C | J31: v92 | K31: b13 | AK31: =COUNTA(C31:AI31) -> 4 | AM31: =COUNTA(G31:P31,S31:T31) -> 2
A32: היכן היית מדרג את המפלגות הבאות על פני רצף "שמאל-ימין" כאשר 0 משמעו שמאל, 10 משמעו ימין ו-5 משמעו אמצע: קדימה | J32: v93 | K32: b15 | AK32: =COUNTA(C32:AI32) -> 2 | AM32: =COUNTA(G32:P32,S32:T32) -> 2
A33: היכן היית מדרג את המפלגות הבאות על פני רצף "שמאל-ימין" כאשר 0 משמעו שמאל, 10 משמעו ימין ו-5 משמעו אמצע: ש"ס | C33: v620i | D33: v620I | J33: v94 | K33: b17 | AK33: =COUNTA(C33:AI33) -> 4 | AM33: =COUNTA(G33:P33,S33:T33) -> 2
A34: היכן היית מדרג את המפלגות הבאות על פני רצף "שמאל-ימין" כאשר 0 משמעו שמאל, 10 משמעו ימין ו-5 משמעו אמצע: הבית היהודי | C34: v620s | D34: v620S | J34: v95 | K34: b19 | AK34: =COUNTA(C34:AI34) -> 4 | AM34: =COUNTA(G34:P34,S34:T34) -> 2
A35: היכן היית מדרג את המפלגות הבאות על פני רצף "שמאל-ימין" כאשר 0 משמעו שמאל, 10 משמעו ימין ו-5 משמעו אמצע: ישראל ביתנו | C35: v620h | D35: v620H | J35: v96 | K35: b21 | AK35: =COUNTA(C35:AI35) -> 4 | AM35: =COUNTA(G35:P35,S35:T35) -> 2
A36: היכן היית מדרג את המפלגות הבאות על פני רצף "שמאל-ימין" כאשר 0 משמעו שמאל, 10 משמעו ימין ו-5 משמעו אמצע: מרצ | C36: v620f | D36: v620F | J36: v97 | K36: b23 | AK36: =COUNTA(C36:AI36) -> 4 | AM36: =COUNTA(G36:P36,S36:T36) -> 2
A37: היכן היית מדרג את המפלגות הבאות על פני רצף "שמאל-ימין" כאשר 0 משמעו שמאל, 10 משמעו ימין ו-5 משמעו אמצע: כחול-לבן | C37: v620b | D37: v620B | AK37: =COUNTA(C37:AI37) -> 2 | AM37: =COUNTA(G37:P37,S37:T37) -> 0
A38: היכן היית מדרג את המפלגות הבאות על פני רצף "שמאל-ימין" כאשר 0 משמעו שמאל, 10 משמעו ימין ו-5 משמעו אמצע: יש עתיד | C38: v620z | D38: v620Z | AK38: =COUNTA(C38:AI38) -> 2 | AM38: =COUNTA(G38:P38,S38:T38) -> 0
A39: היכן היית מדרג את המפלגות הבאות על פני רצף "שמאל-ימין" כאשר 0 משמעו שמאל, 10 משמעו ימין ו-5 משמעו אמצע: תקווה חדשה | D39: v620X | AK39: =COUNTA(C39:AI39) -> 1 | AM39: =COUNTA(G39:P39,S39:T39) -> 0
A40: היכן היית מדרג את המפלגות הבאות על פני רצף "שמאל-ימין" כאשר 0 משמעו שמאל, 10 משמעו ימין ו-5 משמעו אמצע: ימינה | D40: v620D | AK40: =COUNTA(C40:AI40) -> 1 | AM40: =COUNTA(G40:P40,S40:T40) -> 0
A41: היכן היית מדרג את המפלגות הבאות על פני רצף "שמאל-ימין" כאשר 0 משמעו שמאל, 10 משמעו ימין ו-5 משמעו אמצע: יהדות התורה | C41: v620k | D41: v620K | AK41: =COUNTA(C41:AI41) -> 2 | AM41: =COUNTA(G41:P41,S41:T41) -> 0
A42: היכן היית מדרג את המפלגות הבאות על פני רצף "שמאל-ימין" כאשר 0 משמעו שמאל, 10 משמעו ימין ו-5 משמעו אמצע: הרשימה המשותפת | C42: v620j | D42: v620J | AK42: =COUNTA(C42:AI42) -> 2 | AM42: =COUNTA(G42:P42,S42:T42) -> 0
A43: היכן היית מדרג את המפלגות הבאות על פני רצף "שמאל-ימין" כאשר 0 משמעו שמאל, 10 משמעו ימין ו-5 משמעו אמצע: רע"מ | C43: v620y | D43: v620Y | AK43: =COUNTA(C43:AI43) -> 2 | AM43: =COUNTA(G43:P43,S43:T43) -> 0
A44: האם אתה חושב שאנשים כמוך יכולים באמת להתקבל ולהרגיש בבית במחנה השני? | N44: i22 | AK44: =COUNTA(C44:AI44) -> 1 | AM44: =COUNTA(G44:P44,S44:T44) -> 1
A45: יש האומרים שההבדלים בין המפלגות הם "במה שהם אומרים" ולא "במה שהם עושים", ויש האומרים את ההפך. מה דעתך? | U45: b29 | AE45: c38 | AK45: =COUNTA(C45:AI45) -> 2 | AM45: =COUNTA(G45:P45,S45:T45) -> 0
A46: האם לדעתך הליכוד הינה רשימה ניצית או יונית? | U46: b44 | AK46: =COUNTA(C46:AI46) -> 1 | AM46: =COUNTA(G46:P46,S46:T46) -> 0
A47: האם לדעתך המערך הינה רשימה ניצית או יונית? | U47: b45 | AK47: =COUNTA(C47:AI47) -> 1 | AM47: =COUNTA(G47:P47,S47:T47) -> 0
A48: האם לדעתך ההגדרות של שמאל וימין בפוליטיקה, הן בעלות משמעות כיום בישראל או לא? | U48: b77 | AK48: =COUNTA(C48:AI48) -> 1 | AM48: =COUNTA(G48:P48,S48:T48) -> 0
A49: האם ברור לך מה ההבדלים בעמדותיהן של המפלגות השונות בנושא הוויתורים הטריטוריאליים (ויתור על שטחים)? | AA49: v13 | AH49: b29 | AI49: b36 | AK49: =COUNTA(C49:AI49) -> 3 | AM49: =COUNTA(G49:P49,S49:T49) -> 0
A50: האם ברור לך מה ההבדלים בעמדותיהן של המפלגות השונות בנושא הכלכלה? | AA50: v22 | AH50: b30 | AI50: b37 | AK50: =COUNTA(C50:AI50) -> 3 | AM50: =COUNTA(G50:P50,S50:T50) -> 0
A51: האם ברור לך מה ההבדלים בעמדותיהן של המפלגות השונות בנושא החברתי? | AH51: b31 | AI51: b38 | AK51: =COUNTA(C51:AI51) -> 2 | AM51: =COUNTA(G51:P51,S51:T51) -> 0
A52: באיזו מידה מערכת הבחירות הנוכחית עוזרת לך להכיר יותר טוב את עמדות המפלגות לגבי הבעיות הפוליטיות? | AC52: g7 | AE52: d14 | AK52: =COUNTA(C52:AI52) -> 2 | AM52: =COUNTA(G52:P52,S52:T52) -> 0
A53: באיזו מידה חשוב לך להכיר יותר טוב את העמדות את עמדות המפלגות לגבי הבעיות הפוליטיות? | AE53: c40 | AK53: =COUNTA(C53:AI53) -> 1 | AM53: =COUNTA(G53:P53,S53:T53) -> 0
A54: האם לדעתך קיימים הבדלים בין רוב המפלגות בישראל? | AE54: c37 | AK54: =COUNTA(C54:AI54) -> 1 | AM54: =COUNTA(G54:P54,S54:T54) -> 0
A55: האם לדעתך הליכוד הזה הוא שמאלי, ימני או מרכזי? | AE55: d36 | AK55: =COUNTA(C55:AI55) -> 1 | AM55: =COUNTA(G55:P55,S55:T55) -> 0

Sheet זיקה רגשית
A1: שאלה | B1: 2025 | C1: 2022 | D1: 2021 | E1: 2020 | F1: 43709 | G1: 43556 | H1: 2015 | I1: 2013 | J1: 2009 | K1: 2006 | L1: 2003 | M1: 2001 | N1: 1999 | O1: 1996 | P1: 1992 | Q1: 1987* | R1: 1988* | S1: 1988 | T1: 1984 | U1: 1981 - 3 | V1: 1981 - 2 | W1: 1981 - 1 | X1: 1977 - 4 | Y1: 1977 - 3 | Z1: 1977 - 2 | AA1: 1977 - 1 | AB1: 1973 - 5 | AC1: 1973 - 4 | AD1: 1973 - 3 | AE1: 1973 - 2 | AF1: 1973 - 1 | AG1: 1969 - 3 | AH1: 1969 - 2 | AI1: 1969 - 1 | AK1: מספר חזרות | AM1: ספירה 84-19 | AO1: סה"כ מעל שתי חזרות
A2: מה יחסך לכל אחת מן המפלגות הבאות? הליכוד | C2: v49a | D2: v49A | E2: v49A | F2: c49_a | G2: v49A | H2: v51A | I2: v45A | J2: v63 | K2: a61 | L2: a27 | M2: a47 | N2: v43 | O2: c59 | P2: a102 | R2: b111 | S2: f110 | T2: a27 | AK2: =COUNTA(C2:AI2) -> 17 | AM2: =COUNTA(G2:P2,S2:T2) -> 12 | AO2: =COUNTIF(AM2:AM179,">=2") -> 46
A3: מה יחסך לכל אחת מן המפלגות הבאות? כחול-לבן | C3: v49b | D3: v49B | E3: v49B | F3: c49_b | G3: v49B | AK3: =COUNTA(C3:AI3) -> 5 | AM3: =COUNTA(G3:P3,S3:T3) -> 1
A4: מה יחסך לכל אחת מן המפלגות הבאות? יש עתיד | C4: v49z | D4: v49Z | H4: v51F | I4: v45F | AK4: =COUNTA(C4:AI4) -> 4 | AM4: =COUNTA(G4:P4,S4:T4) -> 2
A5: מה יחסך לכל אחת מן המפלגות הבאות? שינוי | L5: a31 | AK5: =COUNTA(C5:AI5) -> 1 | AM5: =COUNTA(G5:P5,S5:T5) -> 1
A6: מה יחסך לכל אחת מן המפלגות הבאות? מפלגת המרכז | N6: v40 | AK6: =COUNTA(C6:AI6) -> 1 | AM6: =COUNTA(G6:P6,S6:T6) -> 1
A7: מה יחסך לכל אחת מן המפלגות הבאות? העבודה/המערך | C7: v49c | D7: v49C | E7: v49C | F7: v49_c | G7: v49C | H7: v51B | I7: v45B | J7: v62 | K7: a60 | L7: a28 | M7: a45 | N7: v41 | O7: c58 | P7: a101 | R7: b110 | S7: f109 | T7: a26 | AK7: =COUNTA(C7:AI7) -> 17 | AM7: =COUNTA(G7:P7,S7:T7) -> 12
A8: מה יחסך לכל אחת מן המפלגות הבאות? ישראל אחת | N8: v53 | AK8: =COUNTA(C8:AI8) -> 1 | AM8: =COUNTA(G8:P8,S8:T8) -> 1
A9: מה יחסך לכל אחת מן המפלגות הבאות? קדימה | J9: v61 | K9: a59 | AK9: =COUNTA(C9:AI9) -> 2 | AM9: =COUNTA(G9:P9,S9:T9) -> 2
A10: מה יחסך לכל אחת מן המפלגות הבאות? התנועה | I10: v51C | AK10: =COUNTA(C10:AI10) -> 1 | AM10: =COUNTA(G10:P10,S10:T10) -> 1
A11: מה יחסך לכל אחת מן המפלגות הבאות? מרצ | C11: v49f | D11: v49F | F11: c49_f | G11: v49F | H11: v51G | I11: v45G | J11: v64 | K11: a62 | L11: a29 | N11: v44 | O11: c61 | AK11: =COUNTA(C11:AI11) -> 11 | AM11: =COUNTA(G11:P11,S11:T11) -> 8
A12: מה יחסך לכל אחת מן המפלגות הבאות? ימינה | D12: v49D | E12: v49D | F12: c49_d | G12: v49D | AK12: =COUNTA(C12:AI12) -> 4 | AM12: =COUNTA(G12:P12,S12:T12) -> 1
A13: מה יחסך לכל אחת מן המפלגות הבאות? תקווה חדשה | D13: v49X | AK13: =COUNTA(C13:AI13) -> 1 | AM13: =COUNTA(G13:P13,S13:T13) -> 0
A14: מה יחסך לכל אחת מהמפלגות הבאות? הבית היהודי/מפד"ל | C14: v49s | D14: v49S | G14: v49E | H14: v51C | I14: v45D | J14: v65 | K14: a63 | L14: a30 | AK14: =COUNTA(C14:AI14) -> 8 | AM14: =COUNTA(G14:P14,S14:T14) -> 6
A15: מה יחסך לכל אחת מן המפלגות הבאות? ישראל ביתנו | C15: v49h | D15: v49H | E15: v49H | F15: c49_h | G15: v49H | H15: v51H | J15: v66 | K15: a64 | L15: a32 | AK15: =COUNTA(C15:AI15) -> 9 | AM15: =COUNTA(G15:P15,S15:T15) -> 5
A16: מה יחסך לכל אחת מן המפלגות הבאות? ש"ס | C16: v49i | D16: v49I | E16: v49I | G16: v49I | H16: v51E | I16: v45E | J16: v67 | K16: a65 | L16: a33 | AK16: =COUNTA(C16:AI16) -> 9 | AM16: =COUNTA(G16:P16,S16:T16) -> 6
A17: מה יחסך לכל אחת מן המפלגות הבאות? ישראל בעליה | L17: a34 | AK17: =COUNTA(C17:AI17) -> 1 | AM17: =COUNTA(G17:P17,S17:T17) -> 1
A18: מה יחסך לכל אחת מן המפלגות הבאות? עוצמה יהודית | E18: v49S | G18: v49S | H18: v51I | AK18: =COUNTA(C18:AI18) -> 3 | AM18: =COUNTA(G18:P18,S18:T18) -> 2
A19: מה יחסך לכל אחת מן המפלגות הבאות? יהדות התורה | C19: v49k | D19: v49K | E19: v49K | AK19: =COUNTA(C19:AI19) -> 3 | AM19: =COUNTA(G19:P19,S19:T19) -> 0
A20: מה יחסך לכל אחת מן המפלגות הבאות? כולנו | G20: v49G | H20: v51D | AK20: =COUNTA(C20:AI20) -> 2 | AM20: =COUNTA(G20:P20,S20:T20) -> 2
A21: מה יחסך לכל אחת מן המפלגות הבאות? הרשימה המשותפת | C21: v49j | D21: v49J | E21: v49J | F21: c49_j | G21: v49J | H21: v51J | AK21: =COUNTA(C21:AI21) -> 6 | AM21: =COUNTA(G21:P21,S21:T21) -> 2
A22: מה יחסך לכל אחת מן המפלגות הבאות? רע"מ-בל"ד | G22: v49R | AK22: =COUNTA(C22:AI22) -> 1 | AM22: =COUNTA(G22:P22,S22:T22) -> 1
A23: מה יחסך לכל אחת מן המפלגות הבאות? רע"מ-תע"ל | I23: v45I | AK23: =COUNTA(C23:AI23) -> 1 | AM23: =COUNTA(G23:P23,S23:T23) -> 1
A24: מה יחסך לכל אחת מן המפלגות הבאות? חד"ש | H24: v51K | I24: v45H | AK24: =COUNTA(C24:AI24) -> 2 | AM24: =COUNTA(G24:P24,S24:T24) -> 2
A25: מה יחסך לכל אחת מן המפלגות הבאות? תע"ל | H25: v51L | AK25: =COUNTA(C25:AI25) -> 1 | AM25: =COUNTA(G25:P25,S25:T25) -> 1
A26: מה יחסך לכל אחת מן המפלגות הבאות? רע"מ | C26: v49y | D26: v49Y | H26: v51M | AK26: =COUNTA(C26:AI26) -> 3 | AM26: =COUNTA(G26:P26,S26:T26) -> 1
A27: מה יחסך לכל אחת מן המפלגות הבאות? בל"ד | C27: v49t | H27: v51N | I27: v45J | AK27: =COUNTA(C27:AI27) -> 3 | AM27: =COUNTA(G27:P27,S27:T27) -> 2
A28: לאחר הבחירות, מה יחסך לכל אחת מן מפלגות הבאות: הציונות הדתית | D28: F49S_1 | AK28: =COUNTA(C28:AI28) -> 1 | AM28: =COUNTA(G28:P28,S28:T28) -> 0
A29: לאחר הבחירות, מה יחסך לכל אחת מן מפלגות הבאות: ימינה | D29: F49D_1 | AK29: =COUNTA(C29:AI29) -> 1 | AM29: =COUNTA(G29:P29,S29:T29) -> 0
A30: לאחר הבחירות, מה יחסך לכל אחת מן מפלגות הבאות: הרשימה המשותפת | D30: F49J_1 | AK30: =COUNTA(C30:AI30) -> 1 | AM30: =COUNTA(G30:P30,S30:T30) -> 0
A31: לאחר הבחירות, מה יחסך לכל אחת מן מפלגות הבאות: רע"מ | D31: F49Y_1 | AK31: =COUNTA(C31:AI31) -> 1 | AM31: =COUNTA(G31:P31,S31:T31) -> 0
A32: לאחר הבחירות, מה יחסך לכל אחת מן מפלגות הבאות: יהדות התורה | D32: F49K_1 | AK32: =COUNTA(C32:AI32) -> 1 | AM32: =COUNTA(G32:P32,S32:T32) -> 0
A33: על סולם שבו 0 משמעו דחייה ושנאה, 10 משמעו תמיכה ואהדה ו-5 משמעו אמצע, מה יחסך לימנים? | B33: v50 | C33: v50 | D33: v50 | E33: v50 | G33: v50 | AK33: =COUNTA(C33:AI33) -> 4 | AM33: =COUNTA(G33:P33,S33:T33) -> 1
A34: על סולם שבו 0 משמעו דחייה ושנאה, 10 משמעו תמיכה ואהדה ו-5 משמעו אמצע, מה יחסך לשמאלנים? | B34: v51 | C34: v51 | D34: v51 | E34: v51 | G34: v51 | AK34: =COUNTA(C34:AI34) -> 4 | AM34: =COUNTA(G34:P34,S34:T34) -> 1
A35: מה יחסך לערבים? | B35: v623 | C35: v623 | D35: v623 | L35: a37 | M35: a54 | N35: v55 | O35: c63 | P35: a106 | R35: b114 | S35: f113 | T35: a30 | AK35: =COUNTA(C35:AI35) -> 10 | AM35: =COUNTA(G35:P35,S35:T35) -> 7
A36: מה יחסך לדתיים? | M36: a48 | N36: v45 | O36: c62 | P36: a107 | R36: b116 | S36: f115 | T36: a32 | AK36: =COUNTA(C36:AI36) -> 7 | AM36: =COUNTA(G36:P36,S36:T36) -> 6
A37: מה יחסך לחרדים? | B37: v622A | C37: v622a | D37: v622 | N37: v54 | AK37: =COUNTA(C37:AI37) -> 3 | AM37: =COUNTA(G37:P37,S37:T37) -> 1
A38: מה יחסך לחילונים? | B38: v622B | C38: v622b | AK38: =COUNTA(C38:AI38) -> 1
A39: מה יחסך לדתיים-לאומיים? | B39: v622C
A40: מה יחסך לאשכנזים? | R40: b117 | S40: f116 | T40: a33 | AK40: =COUNTA(C40:AI40) -> 3 | AM40: =COUNTA(G40:P40,S40:T40) -> 2
A41: מה יחסך לספרדים? | R41: b120 | S41: f119 | T41: a36 | AK41: =COUNTA(C41:AI41) -> 3 | AM41: =COUNTA(G41:P41,S41:T41) -> 2
A42: מה יחסך למועצת יש"ע? | O42: c60 | AK42: =COUNTA(C42:AI42) -> 1 | AM42: =COUNTA(G42:P42,S42:T42) -> 1
A43: מה יחסך לתנועה האסלאמית? | O43: c64 | AK43: =COUNTA(C43:AI43) -> 1 | AM43: =COUNTA(G43:P43,S43:T43) -> 1
A44: מה יחסך לתנועת גוש אמונים? | P44: a108 | R44: b123 | S44: f122 | T44: a39 | AK44: =COUNTA(C44:AI44) -> 4 | AM44: =COUNTA(G44:P44,S44:T44) -> 3
A45: מה יחסך לתנועת שלום עכשיו? | P45: a109 | R45: b124 | S45: f123 | T45: a40 | AK45: =COUNTA(C45:AI45) -> 4 | AM45: =COUNTA(G45:P45,S45:T45) -> 3
A46: ועל אותו סולם, מה יחסך לאישים הבאים? בנימין נתניהו | B46: v52A | C46: v52a | D46: v52A | E46: v52A | F46: c52_a | G46: v52A | H46: v56A | I46: v46A | J46: v71 | K46: a70 | M46: a51 | N46: v50 | O46: c67 | AK46: =COUNTA(C46:AI46) -> 12 | AM46: =COUNTA(G46:P46,S46:T46) -> 8
A47: ועל אותו סולם, מה יחסך לאישים הבאים? אריאל שרון | K47: a73 | L47: a36 | M47: a46 | R47: b115 | S47: f114 | T47: a31 | AK47: =COUNTA(C47:AI47) -> 6 | AM47: =COUNTA(G47:P47,S47:T47) -> 5
A48: ועל אותו סולם, מה יחסך לאישים הבאים? יצחק שמיר | P48: a103 | R48: b113 | S48: f112 | T48: a29 | AK48: =COUNTA(C48:AI48) -> 4 | AM48: =COUNTA(G48:P48,S48:T48) -> 3
A49: ועל אותו סולם, מה יחסך לאישים הבאים? מנחם בגין | R49: b122 | S49: f121 | T49: a38 | AK49: =COUNTA(C49:AI49) -> 3 | AM49: =COUNTA(G49:P49,S49:T49) -> 2
A50: ועל אותו סולם, מה יחסך לאישים הבאים? אהוד אולמרט | K50: a68 | AK50: =COUNTA(C50:AI50) -> 1 | AM50: =COUNTA(G50:P50,S50:T50) -> 1
A51: ועל אותו סולם, מה יחסך לאישים הבאים? בני בגין | N51: v42 | AK51: =COUNTA(C51:AI51) -> 1 | AM51: =COUNTA(G51:P51,S51:T51) -> 1
A52: ועל אותו סולם, מה יחסך לאישים הבאים? איציק מרדכי | N52: v46 | AK52: =COUNTA(C52:AI52) -> 1 | AM52: =COUNTA(G52:P52,S52:T52) -> 1
A53: ועל אותו סולם, מה יחסך לאישים הבאים? דוד לוי | R53: b118 | S53: f117 | T53: a34 | AK53: =COUNTA(C53:AI53) -> 3 | AM53: =COUNTA(G53:P53,S53:T53) -> 2
A54: ועל אותו סולם, מה יחסך לאישים הבאים? יצחק נבון | R54: b119 | S54: f118 | T54: a35 | AK54: =COUNTA(C54:AI54) -> 3 | AM54: =COUNTA(G54:P54,S54:T54) -> 2
A55: ועל אותו סולם, מה יחסך לאישים הבאים? בני גנץ | C55: v52b | D55: v52B | E55: v52B | F55: c52_b | G55: v52B | AK55: =COUNTA(C55:AI55) -> 5 | AM55: =COUNTA(G55:P55,S55:T55) -> 1
A56: ועל אותו סולם, מה יחסך לאישים הבאים? אביגדור ליברמן | E56: v52I | F56: c52_i | G56: v52I | H56: v56H | I56: v46E | K56: a74 | AK56: =COUNTA(C56:AI56) -> 6 | AM56: =COUNTA(G56:P56,S56:T56) -> 4
A57: ועל אותו סולם, מה יחסך לאישים הבאים? יאיר לפיד | C57: v52c | D57: v52C | G57: v52C | H57: v56F | I57: v46F | AK57: =COUNTA(C57:AI57) -> 5 | AM57: =COUNTA(G57:P57,S57:T57) -> 3
A58: ועל אותו סולם, מה יחסך לאישים הבאים? עמרם מצנע | L58: a37 | AK58: =COUNTA(C58:AI58) -> 1 | AM58: =COUNTA(G58:P58,S58:T58) -> 1
A59: ועל אותו סולם, מה יחסך לאישים הבאים? יצחק רבין | O59: c66 | P59: a104 | R59: b121 | S59: f120 | T59: a37 | AK59: =COUNTA(C59:AI59) -> 5 | AM59: =COUNTA(G59:P59,S59:T59) -> 4
A60: ועל אותו סולם, מה יחסך לאישים הבאים? שמעון פרס | K60: a71 | M60: a52 | N60: v51 | O60: c68 | P60: a105 | R60: b112 | S60: f111 | T60: a28 | AK60: =COUNTA(C60:AI60) -> 8 | AM60: =COUNTA(G60:P60,S60:T60) -> 7
A61: ועל אותו סולם, מה יחסך לאישים הבאים? אהוד ברק | J61: v70 | M61: a59 | N61: v48 | AK61: =COUNTA(C61:AI61) -> 3 | AM61: =COUNTA(G61:P61,S61:T61) -> 3
A62: ועל אותו סולם, מה יחסך לאישים הבאים? שלי יחימוביץ | I62: v46B | AK62: =COUNTA(C62:AI62) -> 1 | AM62: =COUNTA(G62:P62,S62:T62) -> 1
A63: ועל אותו סולם, מה יחסך לאישים הבאים? יצחק הרצוג | H63: v56B | AK63: =COUNTA(C63:AI63) -> 1 | AM63: =COUNTA(G63:P63,S63:T63) -> 1
A64: ועל אותו סולם, מה יחסך לאישים הבאים? ציפי לבני | H64: v56Z | I64: v46C | J64: v69 | AK64: =COUNTA(C64:AI64) -> 3 | AM64: =COUNTA(G64:P64,S64:T64) -> 3
A65: ועל אותו סולם, מה יחסך לאישים הבאים? אבי גבאי | G65: v52D | AK65: =COUNTA(C65:AI65) -> 1 | AM65: =COUNTA(G65:P65,S65:T65) -> 1
A66: ועל אותו סולם, מה יחסך לאישים הבאים? עמיר פרץ | F66: c52_d | K66: a69 | AK66: =COUNTA(C66:AI66) -> 2 | AM66: =COUNTA(G66:P66,S66:T66) -> 1
A67: ועל אותו סולם, מה יחסך לאישים הבאים? מרב מיכאלי | D67: v52D | AK67: =COUNTA(C67:AI67) -> 1 | AM67: =COUNTA(G67:P67,S67:T67) -> 0
A68: ועל אותו סולם, מה יחסך לאישים הבאים? גדעון סער | D68: v52Z | AK68: =COUNTA(C68:AI68) -> 1 | AM68: =COUNTA(G68:P68,S68:T68) -> 0
A69: ועל אותו סולם, מה יחסך לאישים הבאים? נפתלי בנט | D69: v52E | G69: v52E | H69: v56C | I69: v46G | AK69: =COUNTA(C69:AI69) -> 4 | AM69: =COUNTA(G69:P69,S69:T69) -> 3
A70: ועל אותו סולם, מה יחסך לאישים הבאים? איילת שקד | F70: c52_e | AK70: =COUNTA(C70:AI70) -> 1 | AM70: =COUNTA(G70:P70,S70:T70) -> 0
A71: ועל אותו סולם, מה יחסך לאישים הבאים? בני אלון | K71: a76 | AK71: =COUNTA(C71:AI71) -> 1 | AM71: =COUNTA(G71:P71,S71:T71) -> 1
A72: ועל אותו סולם, מה יחסך לאישים הבאים? בצלאל סמוטריץ' | G72: v52F | AK72: =COUNTA(C72:AI72) -> 1 | AM72: =COUNTA(G72:P72,S72:T72) -> 1
A73: ועל אותו סולם, מה יחסך לאישים הבאים? הרב כהנא | R73: b125 | S73: f124 | AK73: =COUNTA(C73:AI73) -> 2 | AM73: =COUNTA(G73:P73,S73:T73) -> 1
A74: ועל אותו סולם, מה יחסך לאישים הבאים? יוסי ביילין | K74: a75 | AK74: =COUNTA(C74:AI74) -> 1 | AM74: =COUNTA(G74:P74,S74:T74) -> 1
A75: ועל אותו סולם, מה יחסך לאישים הבאים? זהבה גלאון | H75: v56G | I75: v46H | AK75: =COUNTA(C75:AI75) -> 2 | AM75: =COUNTA(G75:P75,S75:T75) -> 2
A76: ועל אותו סולם, מה יחסך לאישים הבאים? תמר זנדברג | G76: v52G | AK76: =COUNTA(C76:AI76) -> 1 | AM76: =COUNTA(G76:P76,S76:T76) -> 1
A77: ועל אותו סולם, מה יחסך לאישים הבאים? ניצן הורוביץ | D77: v52G | F77: c52_g | AK77: =COUNTA(C77:AI77) -> 2 | AM77: =COUNTA(G77:P77,S77:T77) -> 0
A78: ועל אותו סולם, מה יחסך לאישים הבאים? משה כחלון | G78: v52H | H78: v56D | AK78: =COUNTA(C78:AI78) -> 2 | AM78: =COUNTA(G78:P78,S78:T78) -> 2
A79: ועל אותו סולם, מה יחסך לאישים הבאים? אריה דרעי | G79: v52J | H79: v56E | M79: a53 | N79: v52 | AK79: =COUNTA(C79:AI79) -> 4 | AM79: =COUNTA(G79:P79,S79:T79) -> 4
A80: ועל אותו סולם, מה יחסך לאישים הבאים? אלי ישי | H80: v56I | I80: v46D | K80: a72 | AK80: =COUNTA(C80:AI80) -> 3 | AM80: =COUNTA(G80:P80,S80:T80) -> 3
A81: ועל אותו סולם, מה יחסך לאישים הבאים? נתן שרנסקי | K81: a77 | AK81: =COUNTA(C81:AI81) -> 1 | AM81: =COUNTA(G81:P81,S81:T81) -> 1
A82: ועל אותו סולם, מה יחסך לאישים הבאים? איימן עודה | D82: v52K | E82: v52K | F82: c52_k | G82: v52K | H82: v56J | AK82: =COUNTA(C82:AI82) -> 5 | AM82: =COUNTA(G82:P82,S82:T82) -> 2
A83: ועל אותו סולם, מה יחסך לאישים הבאים? אחמד טיבי | E83: v52R | G83: v52R | H83: v56L | AK83: =COUNTA(C83:AI83) -> 3 | AM83: =COUNTA(G83:P83,S83:T83) -> 2
A84: ועל אותו סולם, מה יחסך לאישים הבאים? מנסור עבאס | D84: v52S | G84: v52S | AK84: =COUNTA(C84:AI84) -> 2 | AM84: =COUNTA(G84:P84,S84:T84) -> 1
A85: ועל אותו סולם, מה יחסך לאישים הבאים? מטאנס שחאדה | G85: v52T | AK85: =COUNTA(C85:AI85) -> 1 | AM85: =COUNTA(G85:P85,S85:T85) -> 1
A86: ועל אותו סולם, מה יחסך לאישים הבאים? עאידה תומא-סולימן | G86: v52U | H86: v56P | AK86: =COUNTA(C86:AI86) -> 2 | AM86: =COUNTA(G86:P86,S86:T86) -> 2
A87: ועל אותו סולם, מה יחסך לאישים הבאים? מסעוד גנאים | H87: v56M | AK87: =COUNTA(C87:AI87) -> 1 | AM87: =COUNTA(G87:P87,S87:T87) -> 1
A88: ועל אותו סולם, מה יחסך לאישים הבאים? ג'מאל זחאלקה | H88: v56N | I88: v46K | AK88: =COUNTA(C88:AI88) -> 2 | AM88: =COUNTA(G88:P88,S88:T88) -> 2
A89: ועל אותו סולם, מה יחסך לאישים הבאים? חנין זועבי | H89: v56O | AK89: =COUNTA(C89:AI89) -> 1 | AM89: =COUNTA(G89:P89,S89:T89) -> 1
A90: ועל אותו סולם, מה יחסך לאישים הבאים? מוחמד בראכה | I90: v46I | AK90: =COUNTA(C90:AI90) -> 1 | AM90: =COUNTA(G90:P90,S90:T90) -> 1
A91: ועל אותו סולם, מה יחסך לאישים הבאים? איברהים צרצור | I91: v46J | AK91: =COUNTA(C91:AI91) -> 1 | AM91: =COUNTA(G91:P91,S91:T91) -> 1
A92: ועל אותו סולם, מה יחסך לאישים הבאים? עזמי בשארה | N92: v49 | AK92: =COUNTA(C92:AI92) -> 1 | AM92: =COUNTA(G92:P92,S92:T92) -> 1
A93: ועל אותו סולם, מה יחסך לאישים הבאים? ערפאת | M93: a49 | N93: v47 | O93: c65 | AK93: =COUNTA(C93:AI93) -> 3 | AM93: =COUNTA(G93:P93,S93:T93) -> 3
A94: עד כמה חשובה לך הזהות שלך כתומך ב(המפלגה שציין המרואיין)? | G94: v76 | AK94: =COUNTA(C94:AI94) -> 1 | AM94: =COUNTA(G94:P94,S94:T94) -> 1
A95: באיזו מידה אתה מסכים או לא מסכים עם כל אחת מן הטענות הבאות: כשמישהו מעביר ביקורת על תומכים של (המפלגה שציין) זה מרגיש לך כמו עלבון אישי | G95: v77 | AK95: =COUNTA(C95:AI95) -> 1 | AM95: =COUNTA(G95:P95,S95:T95) -> 1
A96: כשאתה פוגש מישהו שתומך ב(המפלגה שציין) אתה מרגיש קשור אליו | G96: v78 | AK96: =COUNTA(C96:AI96) -> 1 | AM96: =COUNTA(G96:P96,S96:T96) -> 1
A97: כשאנשים אומרים דברים טובים על תומכים של (המפלגה שציין) זה גורם לך להרגשה טובה | G97: v79 | AK97: =COUNTA(C97:AI97) -> 1 | AM97: =COUNTA(G97:P97,S97:T97) -> 1
A98: באיזו מידה את גאה להיות ישראלי? | C98: N11 | G98: v11_after | AK98: =COUNTA(C98:AI98) -> 2 | AM98: =COUNTA(G98:P98,S98:T98) -> 1
A99: עד כמה חשוב לך המוצא העדתי שלך? | H99: v121 | AK99: =COUNTA(C99:AI99) -> 1 | AM99: =COUNTA(G99:P99,S99:T99) -> 1
A100: ציין באיזו מידה כל אחד מהמשפטים הבאים נכון או לא נכון לגביך: אתה אדם שמתאים לו לקחת סיכונים | H100: v140 | AK100: =COUNTA(C100:AI100) -> 1 | AM100: =COUNTA(G100:P100,S100:T100) -> 1
...

Sheet תכונות
A1: שאלה | B1: 2022 | C1: 2021 | D1: 2020 | E1: 43709 | F1: 43556 | G1: 2015 | H1: 2013 | I1: 2009 | J1: 2006 | K1: 2003 | L1: 2001 | M1: 1999 | N1: 1996 | O1: 1992 | P1: 1987* | Q1: 1988* | R1: 1988 | S1: 1984 | T1: 1981 - 3 | U1: 1981 - 2 | V1: 1981 - 1 | W1: 1977 - 4 | X1: 1977 - 3 | Y1: 1977 - 2 | Z1: 1977 - 1 | AA1: 1973 - 5 | AB1: 1973 - 4 | AC1: 1973 - 3 | AD1: 1973 - 2 | AE1: 1973 - 1 | AF1: 1969 - 3 | AG1: 1969 - 2 | AH1: 1969 - 1 | AJ1: מספר חזרות | AL1: ספירה 84-19 | AN1: סה"כ מעל שתי חזרות
A2: לפניך רשימה של תכונות שונות של מפלגות. לגבי כל אחת מהן, ציין לאיזו מפלגה היא מתאימה ביותר: מפלגה שתדע לעמוד בתוקף במו"מ על שטחים ושלום | I2: v109 | J2: b36 | K2: a78 | L2: a81 | M2: i60 | N2: cc51 | O2: a92 | Q2: b101 | R2: f101 | S2: a11 | AJ2: =COUNTA(B2:AH2) -> 10 | AL2: =COUNTA(F2:O2,R2:S2) -> 9 | AN2: =COUNTIF(AL2:AL235,">=2") -> 40
A3: ולמי הכי פחות? | I3: v110 | J3: b37 | AJ3: =COUNTA(B3:AH3) -> 2 | AL3: =COUNTA(F3:O3,R3:S3) -> 2
A4: לפניך רשימה של תכונות שונות של מפלגות. לגבי כל אחת מהן, ציין לאיזו מפלגה היא מתאימה ביותר: מפלגה שתשמור על המשטר הדמוקרטי במדינה | I4: v111 | J4: b38 | K4: a79 | M4: i61 | N4: cc52 | O4: a93 | Q4: b102 | R4: f102 | S4: a15 | AJ4: =COUNTA(B4:AH4) -> 9 | AL4: =COUNTA(F4:O4,R4:S4) -> 8
A5: ולמי הכי פחות? | I5: v112 | J5: b39 | AJ5: =COUNTA(B5:AH5) -> 2 | AL5: =COUNTA(F5:O5,R5:S5) -> 2
A6: לפניך רשימה של תכונות שונות של מפלגות. לגבי כל אחת מהן, ציין לאיזו מפלגה היא מתאימה ביותר: מפלגה שתוכל להוביל לשלום אמת עם הערבים | I6: v113 | J6: b40 | K6: a80 | L6: a83 | M6: i62 | N6: cc53 | O6: a94 | Q6: b105 | R6: f105 | AJ6: =COUNTA(B6:AH6) -> 9 | AL6: =COUNTA(F6:O6,R6:S6) -> 8
A7: ולמי הכי פחות? | I7: v114 | J7: b41 | AJ7: =COUNTA(B7:AH7) -> 2 | AL7: =COUNTA(F7:O7,R7:S7) -> 2
A8: לפניך רשימה של תכונות שונות של מפלגות. לגבי כל אחת מהן, ציין לאיזו מפלגה היא מתאימה ביותר: מפלגה שתדע לטפל בטרור | I8: v115 | J8: b42 | K8: a81 | L8: a82 | M8: i63 | N8: cc54 | O8: a95 | Q8: b106 | R8: f106 | AJ8: =COUNTA(B8:AH8) -> 9 | AL8: =COUNTA(F8:O8,R8:S8) -> 8
A9: ולמי הכי פחות? | I9: v116 | J9: b43 | AJ9: =COUNTA(B9:AH9) -> 2 | AL9: =COUNTA(F9:O9,R9:S9) -> 2
A10: לפניך רשימה של תכונות שונות של מפלגות. לגבי כל אחת מהן, ציין לאיזו מפלגה היא מתאימה ביותר: מפלגה שתבטיח רוב יהודי במדינה | I10: v117 | J10: b44 | M10: i59 | N10: cc50 | O10: a88 | Q10: b97 | R10: f97 | S10: a7 | T10: b42 | AJ10: =COUNTA(B10:AH10) -> 9 | AL10: =COUNTA(F10:O10,R10:S10) -> 7
A11: ולמי הכי פחות? | I11: v118 | J11: b45 | AJ11: =COUNTA(B11:AH11) -> 2 | AL11: =COUNTA(F11:O11,R11:S11) -> 2
A12: לפניך רשימה של תכונות שונות של מפלגות. לגבי כל אחת מהן, ציין לאיזו מפלגה היא מתאימה ביותר: מפלגה שיש בה שחיתות | I12: v119 | J12: b46 | K12: a83 | M12: i66 | N12: cc57 | O12: a98 | AJ12: =COUNTA(B12:AH12) -> 6 | AL12: =COUNTA(F12:O12,R12:S12) -> 6
A13: ולמי הכי פחות? | I13: v120 | J13: b47 | AJ13: =COUNTA(B13:AH13) -> 2 | AL13: =COUNTA(F13:O13,R13:S13) -> 2
A14: לפניך רשימה של תכונות שונות של מפלגות. לגבי כל אחת מהן, ציין לאיזו מפלגה היא מתאימה ביותר: מפלגה שתצמצם פערים חברתיים | I14: v121 | J14: b48 | K14: a84 | M14: i68 | N14: cc60 | AJ14: =COUNTA(B14:AH14) -> 5 | AL14: =COUNTA(F14:O14,R14:S14) -> 5
A15: ולמי הכי פחות? | I15: v122 | J15: b49 | AJ15: =COUNTA(B15:AH15) -> 2 | AL15: =COUNTA(F15:O15,R15:S15) -> 2
A16: לפניך רשימה של תכונות שונות של מפלגות. לגבי כל אחת מהן, ציין לאיזו מפלגה היא מתאימה ביותר: מפלגה שתוכל להביא להפרדה בין ישראל והפלסטינים | K16: a82 | M16: i65 | N16: cc56 | AJ16: =COUNTA(B16:AH16) -> 3 | AL16: =COUNTA(F16:O16,R16:S16) -> 3
A17: לפניך רשימה של תכונות שונות של מפלגות. לגבי כל אחת מהן, ציין לאיזו מפלגה היא מתאימה ביותר: תקטין את הפיצול בעם | L17: a84 | M17: i69 | AJ17: =COUNTA(B17:AH17) -> 2 | AL17: =COUNTA(F17:O17,R17:S17) -> 2
A18: לפניך רשימה של תכונות שונות של מפלגות. לגבי כל אחת מהן, ציין לאיזו מפלגה היא מתאימה ביותר: מפלגה שתצמצם את הפער העדתי | M18: i64 | N18: cc55 | O18: a89 | Q18: b98 | R18: f98 | S18: a8 | AJ18: =COUNTA(B18:AH18) -> 6 | AL18: =COUNTA(F18:O18,R18:S18) -> 5
A19: לפניך רשימה של תכונות שונות של מפלגות. לגבי כל אחת מהן, ציין לאיזו מפלגה היא מתאימה ביותר: מפלגה שמטפחת את הכבוד העצמי של בני עדות המזרח | O19: a91 | Q19: b100 | R19: f100 | S19: a10 | AJ19: =COUNTA(B19:AH19) -> 4 | AL19: =COUNTA(F19:O19,R19:S19) -> 3
A20: לפניך רשימה של תכונות שונות של מפלגות. לגבי כל אחת מהן, ציין לאיזו מפלגה היא מתאימה ביותר: מפלגה שתדע לשמור על היחסים עם ארה"ב | M20: i67 | N20: cc59 | O20: a99 | AJ20: =COUNTA(B20:AH20) -> 3 | AL20: =COUNTA(F20:O20,R20:S20) -> 3
A21: לפניך רשימה של תכונות שונות של מפלגות. לגבי כל אחת מהן, ציין לאיזו מפלגה היא מתאימה ביותר: מפלגה עם מנהיגים מנוסים | N21: cc58 | O21: a86 | Q21: b94 | R21: f94 | S21: a4 | T21: b40 | AJ21: =COUNTA(B21:AH21) -> 6 | AL21: =COUNTA(F21:O21,R21:S21) -> 4
A22: לפניך רשימה של תכונות שונות של מפלגות. לגבי כל אחת מהן, ציין לאיזו מפלגה היא מתאימה ביותר: מפלגה שתדאג לשכבות החלשות | O22: a87 | AJ22: =COUNTA(B22:AH22) -> 1 | AL22: =COUNTA(F22:O22,R22:S22) -> 1
A23: לפניך רשימה של תכונות שונות של מפלגות. לגבי כל אחת מהן, ציין לאיזו מפלגה היא מתאימה ביותר: מפלגה שתרמה לבנין הארץ | O23: a90 | Q23: b99 | R23: f99 | S23: a9 | T23: b43 | AJ23: =COUNTA(B23:AH23) -> 5 | AL23: =COUNTA(F23:O23,R23:S23) -> 3
A24: לפניך רשימה של תכונות שונות של מפלגות. לגבי כל אחת מהן, ציין לאיזו מפלגה היא מתאימה ביותר: מפלגה שתדע לקלוט עליה | O24: a96 | AJ24: =COUNTA(B24:AH24) -> 1 | AL24: =COUNTA(F24:O24,R24:S24) -> 1
A25: לפניך רשימה של תכונות שונות של מפלגות. לגבי כל אחת מהן, ציין לאיזו מפלגה היא מתאימה ביותר: מפלגה שתדע לצמצם את האבטלה | O25: a97 | AJ25: =COUNTA(B25:AH25) -> 1 | AL25: =COUNTA(F25:O25,R25:S25) -> 1
A26: לפניך רשימה של תכונות שונות של מפלגות. לגבי כל אחת מהן, ציין לאיזו מפלגה היא מתאימה ביותר: מפלגה שנותנת ייצוג הולם לעדות המזרח | Q26: b95 | R26: f96 | S26: a5 | AJ26: =COUNTA(B26:AH26) -> 3 | AL26: =COUNTA(F26:O26,R26:S26) -> 2
A27: לפניך רשימה של תכונות שונות של מפלגות. לגבי כל אחת מהן, ציין לאיזו מפלגה היא מתאימה ביותר: מפלגה שמבטיחה את עתיד המדינה | Q27: b96 | R27: f96 | S27: a6 | T27: b41 | AJ27: =COUNTA(B27:AH27) -> 4 | AL27: =COUNTA(F27:O27,R27:S27) -> 2
A28: לפניך רשימה של תכונות שונות של מפלגות. לגבי כל אחת מהן, ציין לאיזו מפלגה היא מתאימה ביותר: מפלגה עדתית | Q28: b103 | R28: f103 | AJ28: =COUNTA(B28:AH28) -> 2 | AL28: =COUNTA(F28:O28,R28:S28) -> 1
A29: לפניך רשימה של תכונות שונות של מפלגות. לגבי כל אחת מהן, ציין לאיזו מפלגה היא מתאימה ביותר: מפלגה שתדע לשמור על כמות השטחים הנחוצה למדינה | Q29: b104 | R29: f104 | AJ29: =COUNTA(B29:AH29) -> 2 | AL29: =COUNTA(F29:O29,R29:S29) -> 1
A30: לפניך רשימה של תכונות שונות של מפלגות. לגבי כל אחת מהן, ציין לאיזו מפלגה היא מתאימה ביותר: מפלגה שתדע איך ומתי להוביל למלחמה מוצלחת | Q30: b107 | R30: f107 | AJ30: =COUNTA(B30:AH30) -> 2 | AL30: =COUNTA(F30:O30,R30:S30) -> 1
A31: לפניך רשימה של תכונות שונות של מפלגות. לגבי כל אחת מהן, ציין לאיזו מפלגה היא מתאימה ביותר: מפלגה לאומית | Q31: b108 | R31: f108 | AJ31: =COUNTA(B31:AH31) -> 2 | AL31: =COUNTA(F31:O31,R31:S31) -> 1
A32: לפניך רשימה של תכונות שונות של מפלגות. לגבי כל אחת מהן, ציין לאיזו מפלגה היא מתאימה ביותר: מפלגה שממנה אנשים מתאימים לתפקידים מרכזיים מבלי להתחשב ברקע העדתי | S32: a12 | AJ32: =COUNTA(B32:AH32) -> 1 | AL32: =COUNTA(F32:O32,R32:S32) -> 1
A33: לפניך רשימה של תכונות שונות של מפלגות. לגבי כל אחת מהן, ציין לאיזו מפלגה היא מתאימה ביותר: מפלגה שתדע לצאת מלבנון ולהבטיח את הגבול הצפוני | S33: a13 | AJ33: =COUNTA(B33:AH33) -> 1 | AL33: =COUNTA(F33:O33,R33:S33) -> 1
A34: לפניך רשימה של תכונות שונות של מפלגות. לגבי כל אחת מהן, ציין לאיזו מפלגה היא מתאימה ביותר: מפלגה שמנצלת את עדות המזרח לצרכים פוליטיים | S34: a14 | AJ34: =COUNTA(B34:AH34) -> 1 | AL34: =COUNTA(F34:O34,R34:S34) -> 1
A35: לפניך רשימה של תכונות שונות של מפלגות. לגבי כל אחת מהן, ציין לאיזו מפלגה היא מתאימה ביותר: מפלגה חזקה | T35: b32 | AJ35: =COUNTA(B35:AH35) -> 1 | AL35: =COUNTA(F35:O35,R35:S35) -> 0
A36: לפניך רשימה של תכונות שונות של מפלגות. לגבי כל אחת מהן, ציין לאיזו מפלגה היא מתאימה ביותר: מפלגה בעלת ניסיון | T36: b33 | AJ36: =COUNTA(B36:AH36) -> 1 | AL36: =COUNTA(F36:O36,R36:S36) -> 0
A37: לפניך רשימה של תכונות שונות של מפלגות. לגבי כל אחת מהן, ציין לאיזו מפלגה היא מתאימה ביותר: מפלגה חדשנית | T37: b34 | AJ37: =COUNTA(B37:AH37) -> 1 | AL37: =COUNTA(F37:O37,R37:S37) -> 0
A38: לפניך רשימה של תכונות שונות של מפלגות. לגבי כל אחת מהן, ציין לאיזו מפלגה היא מתאימה ביותר: מפלגה צעירה | T38: b35 | AJ38: =COUNTA(B38:AH38) -> 1 | AL38: =COUNTA(F38:O38,R38:S38) -> 0
A39: לפניך רשימה של תכונות שונות של מפלגות. לגבי כל אחת מהן, ציין לאיזו מפלגה היא מתאימה ביותר: מפלגה מייצגת אשכזים ומזרחים | T39: b36 | AJ39: =COUNTA(B39:AH39) -> 1 | AL39: =COUNTA(F39:O39,R39:S39) -> 0
A40: לפניך רשימה של תכונות שונות של מפלגות. לגבי כל אחת מהן, ציין לאיזו מפלגה היא מתאימה ביותר: מפלגה דואגת בעיקר לאינטרסים של האזרח | T40: b37 | AJ40: =COUNTA(B40:AH40) -> 1 | AL40: =COUNTA(F40:O40,R40:S40) -> 0
A41: לפניך רשימה של תכונות שונות של מפלגות. לגבי כל אחת מהן, ציין לאיזו מפלגה היא מתאימה ביותר: מפלגה ישרה | T41: b38 | AJ41: =COUNTA(B41:AH41) -> 1 | AL41: =COUNTA(F41:O41,R41:S41) -> 0
A42: לפניך רשימה של תכונות שונות של מפלגות. לגבי כל אחת מהן, ציין לאיזו מפלגה היא מתאימה ביותר: מפלגה אמינה | T42: b39 | AJ42: =COUNTA(B42:AH42) -> 1 | AL42: =COUNTA(F42:O42,R42:S42) -> 0
A43: לפניך רשימה של תכונות של מנהיגים. לגבי כל אחת מהתכונות ציין למי היא מתאימה יותר? האם "כושר מנהיגות" מתאים יותר ל: | F43: v70 | G43: v82 | H43: v84 | I43: v123 | J43: b51 | K43: a85 | M43: i70 | N43: cc64 | O43: a112 | AJ43: =COUNTA(B43:AH43) -> 9 | AL43: =COUNTA(F43:O43,R43:S43) -> 9
A44: ולמי הכי פחות? | I44: v124 | J44: b52 | M44: i71 | AJ44: =COUNTA(B44:AH44) -> 3 | AL44: =COUNTA(F44:O44,R44:S44) -> 3
A45: האם "אכפתיות מאנשים כמוך" מתאימה יותר ל: | F45: v71 | G45: v83 | H45: v86 | AJ45: =COUNTA(B45:AH45) -> 3 | AL45: =COUNTA(F45:O45,R45:S45) -> 3
A46: האם "יושר והגינות" מתאים יותר ל: | F46: v72 | G46: v84 | H46: v87 | AJ46: =COUNTA(B46:AH46) -> 3 | AL46: =COUNTA(F46:O46,R46:S46) -> 3
A47: האם "אמין" מתאים יותר ל: | I47: v125 | J47: b52 | K47: a86 | L47: a77 | M47: i74 | N47: cc66 | O47: a114 | AJ47: =COUNTA(B47:AH47) -> 7 | AL47: =COUNTA(F47:O47,R47:S47) -> 7
A48: ולמי הכי פחות? | I48: v126 | J48: b53 | M48: i75 | AJ48: =COUNTA(B48:AH48) -> 3 | AL48: =COUNTA(F48:O48,R48:S48) -> 3
A49: האם "יעדיף את טובת המדינה על פני שיקולים אחרים" מתאים יותר ל: | I49: v127 | J49: b54 | K49: a87 | L49: a78 | M49: i80 | N49: cc68 | O49: a116 | AJ49: =COUNTA(B49:AH49) -> 7 | AL49: =COUNTA(F49:O49,R49:S49) -> 7
A50: ולמי הכי פחות? | I50: v128 | J50: b55 | M50: i81 | AJ50: =COUNTA(B50:AH50) -> 3 | AL50: =COUNTA(F50:O50,R50:S50) -> 3
A51: האם "יכולת טובה לניהול משא ומתן" מתאים יותר ל: | I51: v129 | J51: b56 | K51: a88 | M51: i84 | N51: cc71 | O51: a118 | AJ51: =COUNTA(B51:AH51) -> 6 | AL51: =COUNTA(F51:O51,R51:S51) -> 6
A52: ולמי הכי פחות? | I52: v130 | J52: b57 | M52: i85 | AJ52: =COUNTA(B52:AH52) -> 3 | AL52: =COUNTA(F52:O52,R52:S52) -> 3
A53: האם "ישמור על שלטון החוק" מתאים יותר ל: | I53: v131 | J53: b58 | K53: a89 | L53: a80 | M53: i88 | AJ53: =COUNTA(B53:AH53) -> 5 | AL53: =COUNTA(F53:O53,R53:S53) -> 5
A54: ולמי הכי פחות? | I54: v132 | J54: b59 | M54: i89 | AJ54: =COUNTA(B54:AH54) -> 3 | AL54: =COUNTA(F54:O54,R54:S54) -> 3
A55: האם "יעמוד במצבי לחץ" מתאים יותר ל: | L55: a79 | M55: i86 | N55: cc72 | O55: a119 | AJ55: =COUNTA(B55:AH55) -> 4 | AL55: =COUNTA(F55:O55,R55:S55) -> 4
A56: ולמי הכי פחות? | M56: i87 | AJ56: =COUNTA(B56:AH56) -> 1 | AL56: =COUNTA(F56:O56,R56:S56) -> 1
A57: האם "בעל ניסיון" מתאים יותר ל: | M57: i72 | N57: cc69 | AJ57: =COUNTA(B57:AH57) -> 2 | AL57: =COUNTA(F57:O57,R57:S57) -> 2
A58: ולמי הכי פחות? | M58: i73 | AJ58: =COUNTA(B58:AH58) -> 1 | AL58: =COUNTA(F58:O58,R58:S58) -> 1
A59: האם "יוריד את המתח בין דתיים לחילונים" מתאים יותר ל: | M59: i76 | AJ59: =COUNTA(B59:AH59) -> 1 | AL59: =COUNTA(F59:O59,R59:S59) -> 1
A60: ולמי הכי פחות? | M60: i77 | AJ60: =COUNTA(B60:AH60) -> 1 | AL60: =COUNTA(F60:O60,R60:S60) -> 1
A61: האם "בעל כושר החלטה" מתאים יותר ל: | M61: i78 | N61: cc67 | O61: a115 | AJ61: =COUNTA(B61:AH61) -> 3 | AL61: =COUNTA(F61:O61,R61:S61) -> 3
A62: ולמי הכי פחות? | M62: i79 | AJ62: =COUNTA(B62:AH62) -> 1 | AL62: =COUNTA(F62:O62,R62:S62) -> 1
A63: האם "יוזמה ומעוף" מתאים יותר ל: | M63: i82 | N63: cc70 | O63: a117 | AJ63: =COUNTA(B63:AH63) -> 3 | AL63: =COUNTA(F63:O63,R63:S63) -> 3
A64: ולמי הכי פחות? | M64: i83 | AJ64: =COUNTA(B64:AH64) -> 1 | AL64: =COUNTA(F64:O64,R64:S64) -> 1
A65: האם "יצמצם פערים חברתיים" מתאים יותר ל: | M65: i90 | AJ65: =COUNTA(B65:AH65) -> 1 | AL65: =COUNTA(F65:O65,R65:S65) -> 1
A66: ולמי הכי פחות? | M66: i91 | AJ66: =COUNTA(B66:AH66) -> 1 | AL66: =COUNTA(F66:O66,R66:S66) -> 1
A67: האם "חזק" מתאים יותר ל: | N67: cc65 | O67: a113 | AJ67: =COUNTA(B67:AH67) -> 2 | AL67: =COUNTA(F67:O67,R67:S67) -> 2
A68: לפניך סולמות בני 7 דרגות המתארים תכונות שונות של מפלגות. חשוב בבקשה על המפלגה האידיאלית אותה היית רוצה לראות בשלטון ודרג אותה על סולמות אלו: צעירה-זקנה | S68: v47 | U68: a68 | AJ68: =COUNTA(B68:AH68) -> 2 | AL68: =COUNTA(F68:O68,R68:S68) -> 1
A69: לפניך סולמות בני 7 דרגות המתארים תכונות שונות של מפלגות. חשוב בבקשה על המפלגה האידיאלית אותה היית רוצה לראות בשלטון ודרג אותה על סולמות אלו: חזקה-חלשה | S69: v48 | U69: a64 | AE69: v22 | AJ69: =COUNTA(B69:AH69) -> 3 | AL69: =COUNTA(F69:O69,R69:S69) -> 1
A70: לפניך סולמות בני 7 דרגות המתארים תכונות שונות של מפלגות. חשוב בבקשה על המפלגה האידיאלית אותה היית רוצה לראות בשלטון ודרג אותה על סולמות אלו: ימנית-שמאלית | S70: v49 | U70: a65 | AE70: v23 | AJ70: =COUNTA(B70:AH70) -> 3 | AL70: =COUNTA(F70:O70,R70:S70) -> 1
A71: לפניך סולמות בני 7 דרגות המתארים תכונות שונות של מפלגות. חשוב בבקשה על המפלגה האידיאלית אותה היית רוצה לראות בשלטון ודרג אותה על סולמות אלו: מיושנת-חדשנית | S71: v50 | U71: a66 | AE71: v24 | AJ71: =COUNTA(B71:AH71) -> 3 | AL71: =COUNTA(F71:O71,R71:S71) -> 1
A72: לפניך סולמות בני 7 דרגות המתארים תכונות שונות של מפלגות. חשוב בבקשה על המפלגה האידיאלית אותה היית רוצה לראות בשלטון ודרג אותה על סולמות אלו: מעמד בינוני-מעמד פועלים | S72: v51 | U72: a67 | AE72: v25 | AJ72: =COUNTA(B72:AH72) -> 3 | AL72: =COUNTA(F72:O72,R72:S72) -> 1
A73: לפניך סולמות בני 7 דרגות המתארים תכונות שונות של מפלגות. חשוב בבקשה על המפלגה האידיאלית אותה היית רוצה לראות בשלטון ודרג אותה על סולמות אלו: ספרדית-אשכנזית | S73: v52 | U73: a69 | AJ73: =COUNTA(B73:AH73) -> 2 | AL73: =COUNTA(F73:O73,R73:S73) -> 1
A74: לפניך סולמות בני 7 דרגות המתארים תכונות שונות של מפלגות. חשוב בבקשה על המפלגה האידיאלית אותה היית רוצה לראות בשלטון ודרג אותה על סולמות אלו: דואגת בעיקר לעצמה-דואגת בעיקר לאזרחים | S74: v53 | U74: a70 | AJ74: =COUNTA(B74:AH74) -> 2 | AL74: =COUNTA(F74:O74,R74:S74) -> 1
A75: לפניך סולמות בני 7 דרגות המתארים תכונות שונות של מפלגות. חשוב בבקשה על המפלגה האידיאלית אותה היית רוצה לראות בשלטון ודרג אותה על סולמות אלו: חסרת ניסיון-בעלת ניסיון | S75: v54 | U75: a71 | AE75: v26 | AJ75: =COUNTA(B75:AH75) -> 3 | AL75: =COUNTA(F75:O75,R75:S75) -> 1
A76: לפניך סולמות בני 7 דרגות המתארים תכונות שונות של מפלגות. חשוב בבקשה על המפלגה האידיאלית אותה היית רוצה לראות בשלטון ודרג אותה על סולמות אלו: יונית-ניצית | S76: v55 | AJ76: =COUNTA(B76:AH76) -> 1 | AL76: =COUNTA(F76:O76,R76:S76) -> 1
A77: עכשיו אתה מתבקש לדרג את המערך על סולמות אלה: צעירה-זקנה | S77: v57 | U77: a77 | AE77: v72 | AJ77: =COUNTA(B77:AH77) -> 3 | AL77: =COUNTA(F77:O77,R77:S77) -> 1
A78: עכשיו אתה מתבקש לדרג את המערך על סולמות אלה: חזקה-חלשה | S78: v58 | U78: a73 | AE78: v71 | AJ78: =COUNTA(B78:AH78) -> 3 | AL78: =COUNTA(F78:O78,R78:S78) -> 1
A79: עכשיו אתה מתבקש לדרג את המערך על סולמות אלה: ימנית-שמאלית | S79: v59 | U79: a74 | AE79: v73 | AJ79: =COUNTA(B79:AH79) -> 3 | AL79: =COUNTA(F79:O79,R79:S79) -> 1
A80: עכשיו אתה מתבקש לדרג את המערך על סולמות אלה: מיושנת-חדשנית | S80: v60 | U80: a75 | AE80: v74 | AJ80: =COUNTA(B80:AH80) -> 3 | AL80: =COUNTA(F80:O80,R80:S80) -> 1
A81: עכשיו אתה מתבקש לדרג את המערך על סולמות אלה: מעמד ביניים-מעמד פועלים | S81: v61 | U81: a76 | AE81: b4 | AJ81: =COUNTA(B81:AH81) -> 3 | AL81: =COUNTA(F81:O81,R81:S81) -> 1
A82: עכשיו אתה מתבקש לדרג את המערך על סולמות אלה: ספרדית-אשכנזית | S82: v62 | U82: a78 | AE82: b3 | AJ82: =COUNTA(B82:AH82) -> 3 | AL82: =COUNTA(F82:O82,R82:S82) -> 1
A83: עכשיו אתה מתבקש לדרג את המערך על סולמות אלה: דואגת בעיקר לעצמה-דואגת בעיקר לאזרח | S83: v63 | U83: a79 | AJ83: =COUNTA(B83:AH83) -> 2 | AL83: =COUNTA(F83:O83,R83:S83) -> 1
A84: עכשיו אתה מתבקש לדרג את המערך על סולמות אלה: ישרה-מושחתת | S84: v64 | U84: a80 | AE84: b5 | AJ84: =COUNTA(B84:AH84) -> 3 | AL84: =COUNTA(F84:O84,R84:S84) -> 1
A85: עכשיו אתה מתבקש לדרג את המערך על סולמות אלה: חסרת ניסיון-בעלת ניסיון | S85: v65 | U85: a81 | AE85: b6 | AJ85: =COUNTA(B85:AH85) -> 3 | AL85: =COUNTA(F85:O85,R85:S85) -> 1
A86: עכשיו אתה מתבקש לדרג את המערך על סולמות אלה: בלתי אמינה-אמינה | S86: v66 | U86: a82 | AJ86: =COUNTA(B86:AH86) -> 2 | AL86: =COUNTA(F86:O86,R86:S86) -> 1
A87: עכשיו אתה מתבקש לדרג את המערך על סולמות אלה: יונית-ניצית | S87: v67 | AJ87: =COUNTA(B87:AH87) -> 1 | AL87: =COUNTA(F87:O87,R87:S87) -> 1
A88: עכשיו אתה מתבקש לדרג את הליכוד על סולמות אלה: צעירה-זקנה | S88: v69 | U88: a88 | AE88: v58 | AJ88: =COUNTA(B88:AH88) -> 3 | AL88: =COUNTA(F88:O88,R88:S88) -> 1
A89: עכשיו אתה מתבקש לדרג את הליכוד על סולמות אלה: חזקה-חלשה | S89: v70 | U89: a84 | AE89: v57 | AJ89: =COUNTA(B89:AH89) -> 3 | AL89: =COUNTA(F89:O89,R89:S89) -> 1
A90: עכשיו אתה מתבקש לדרג את הליכוד על סולמות אלה: ימנית-שמאלית | S90: v71 | U90: a85 | AE90: v59 | AJ90: =COUNTA(B90:AH90) -> 3 | AL90: =COUNTA(F90:O90,R90:S90) -> 1
A91: עכשיו אתה מתבקש לדרג את הליכוד על סולמות אלה: מיושנת-חדשנית | S91: v72 | U91: a86 | AE91: v60 | AJ91: =COUNTA(B91:AH91) -> 3 | AL91: =COUNTA(F91:O91,R91:S91) -> 1
A92: עכשיו אתה מתבקש לדרג את הליכוד על סולמות אלה: מעמד ביניים-מעמד פועלים | S92: v73 | U92: a87 | AE92: v62 | AJ92: =COUNTA(B92:AH92) -> 3 | AL92: =COUNTA(F92:O92,R92:S92) -> 1
A93: עכשיו אתה מתבקש לדרג את הליכוד על סולמות אלה: ספרדית-אשכנזית | S93: v74 | U93: a89 | AE93: v61 | AJ93: =COUNTA(B93:AH93) -> 3 | AL93: =COUNTA(F93:O93,R93:S93) -> 1
A94: עכשיו אתה מתבקש לדרג את הליכוד על סולמות אלה: דואגת בעיקר לעצמה-דואגת בעיקר לאזרח | S94: v75 | U94: a90 | AJ94: =COUNTA(B94:AH94) -> 2 | AL94: =COUNTA(F94:O94,R94:S94) -> 1
A95: עכשיו אתה מתבקש לדרג את הליכוד על סולמות אלה: ישרה-מושחתת | S95: v76 | U95: a91 | AE95: v63 | AJ95: =COUNTA(B95:AH95) -> 3 | AL95: =COUNTA(F95:O95,R95:S95) -> 1
A96: עכשיו אתה מתבקש לדרג את הליכוד על סולמות אלה: חסרת ניסיון-בעלת ניסיון | S96: v77 | U96: a92 | AE96: v64 | AJ96: =COUNTA(B96:AH96) -> 3 | AL96: =COUNTA(F96:O96,R96:S96) -> 1
A97: עכשיו אתה מתבקש לדרג את הליכוד על סולמות אלה: בלתי אמינה-אמינה | S97: v78 | U97: a93 | AJ97: =COUNTA(B97:AH97) -> 2 | AL97: =COUNTA(F97:O97,R97:S97) -> 1
A98: עכשיו אתה מתבקש לדרג את הליכוד על סולמות אלה: יונית-ניצית | S98: a2 | AJ98: =COUNTA(B98:AH98) -> 1 | AL98: =COUNTA(F98:O98,R98:S98) -> 1
A99: לפניך רשימת של תכונות והיפוכן. לגבי כל אחת מהן ציין מה מתאים למערכת הבחירות המתנהלת: חיובית-שלילית | T99: b110 | AJ99: =COUNTA(B99:AH99) -> 1 | AL99: =COUNTA(F99:O99,R99:S99) -> 0
A100: לפניך רשימת של תכונות והיפוכן. לגבי כל אחת מהן ציין מה מתאים למערכת הבחירות המתנהלת: קצרה-ארוכה | T100: b111 | AJ100: =COUNTA(B100:AH100) -> 1 | AL100: =COUNTA(F100:O100,R100:S100) -> 0
...

Sheet הצבעה
A1: שאלה | B1: 2025 | C1: 2022 | D1: 2021 | E1: 2020 | F1: 43709 | G1: 43556 | H1: 2015 | I1: 2013 | J1: 2009 | K1: 2006 | L1: 2003 | M1: 2001 | N1: 1999 | O1: 1996 | P1: 1992 | Q1: 1987* | R1: 1988* | S1: 1988 | T1: 1984 | U1: 1981 - 3 | V1: 1981 - 2 | W1: 1981 - 1 | X1: 1977 - 4 | Y1: 1977 - 3 | Z1: 1977 - 2 | AA1: 1977 - 1 | AB1: 1973 - 5 | AC1: 1973 - 4 | AD1: 1973 - 3 | AE1: 1973 - 2 | AF1: 1973 - 1 | AG1: 1969 - 3 | AH1: 1969 - 2 | AI1: 1969 - 1 | AK1: מספר חזרות | AM1: ספירה 84-19 | AO1: סה"כ מעל שתי חזרות
A2: ישנם גורמים שונים בגללם אנשים יצביעו דווקא למפלגה מסוימת בכנסת. מבין הגורמים הבאים, מהוא הגורם העיקרי המשפיע עליך להצבעה למפלגה מסוימת? | C2: v63 | D2: v63 | E2: v63 | G2: v63 | H2: v64 | J2: v81 | K2: a90 | L2: a56 | N2: i39 | O2: cc25 | P2: a62 | R2: b73 | S2: f76 | T2: v36 | V2: a37 | W2: v38 | X2: c2 | AA2: v37 | AD2: f17 | AG2: b51 | AH2: b43 | AI2: b48 | AK2: =COUNTA(C2:AI2) -> 22 | AM2: =COUNTA(G2:P2,S2:T2) -> 10 | AO2: =COUNTIF(AM2:AM196,">=2") -> 44
A3: יש גורמים שונים בגללם אנשים מצביעים למועמד מסויים לראשות הממשלה ולא לאחר. מבין הגורמים הבאים, מהו הגורם העיקרי המשפיע עליך להצביע למועמד שלך? | M3: a57 | N3: v58 | O3: c72 | AK3: =COUNTA(C3:AI3) -> 3 | AM3: =COUNTA(G3:P3,S3:T3) -> 3
A4: ישנם גורמים שונים עיקריים המביאים אדם להצביע למפלגה מסויימת. האם לדעתך יש גורם אחד בולט, הנראה לך כחשוב מכולם בקביעת הצבעתך? | AG4: b50 | AH4: b41 | AI4: b47 | AK4: =COUNTA(C4:AI4) -> 3 | AM4: =COUNTA(G4:P4,S4:T4) -> 0
A5: באיזו מידה ישפיע או לא ישפיע כל אחד מהנושאים הבאים על ההצבעה שלך לכנסת? מדיניות כלכלית-חברתית | C5: v64 | D5: v64 | E5: v64 | G5: v64 | H5: v65 | AE5: c60 | AF5: v46 | AK5: =COUNTA(C5:AI5) -> 7 | AM5: =COUNTA(G5:P5,S5:T5) -> 2
A6: באיזו מידה ישפיע או לא ישפיע כל אחד מהנושאים הבאים על ההצבעה שלך לכנסת? כלכלה | I6: v59 | J6: v83 | K6: a92 | L6: a58 | N6: i24 | O6: cc13 | P6: a54 | R6: b65 | S6: f68 | AA6: v24 | AK6: =COUNTA(C6:AI6) -> 10 | AM6: =COUNTA(G6:P6,S6:T6) -> 8
A7: באיזו מידה ישפיע או לא ישפיע כל אחד מהנושאים הבאים על ההצבעה שלך לכנסת? מדיניות חברתית | I7: v60 | J7: v84 | K7: a93 | L7: a59 | N7: i26 | AK7: =COUNTA(C7:AI7) -> 5 | AM7: =COUNTA(G7:P7,S7:T7) -> 5
A8: באיזו מידה ישפיע או לא ישפיע כל אחד מהנושאים הבאים על ההצבעה שלך לכנסת? דת ומדינה | C8: v65 | D8: v65 | E8: v65 | G8: v65 | H8: v66 | I8: v61 | J8: v85 | K8: a94 | L8: a60 | N8: i27 | AK8: =COUNTA(C8:AI8) -> 10 | AM8: =COUNTA(G8:P8,S8:T8) -> 7
A9: באיזו מידה ישפיע או לא ישפיע כל אחד מהנושאים הבאים על ההצבעה שלך לכנסת? שלום ושטחים | C9: v66 | D9: v66 | E9: v66 | G9: v66 | H9: v67 | I9: v62 | J9: v86 | K9: a95 | L9: a61 | N9: i29 | O9: cc14 | P9: a49 | R9: b55 | S9: f57 | T9: v14 | AA9: v15 | AE9: c63 | AF9: v54 | AK9: =COUNTA(C9:AI9) -> 18 | AM9: =COUNTA(G9:P9,S9:T9) -> 11
A10: באיזו מידה ישפיע או לא ישפיע כל אחד מהנושאים הבאים על ההצבעה שלך לכנסת? בטחון וטרור | E10: v67 | G10: v67 | H10: v68 | I10: v63 | J10: v87 | K10: a96 | L10: a62 | N10: i25 | O10: cc15 | Q10: a61 | U10: b12 | AK10: =COUNTA(C10:AI10) -> 11 | AM10: =COUNTA(G10:P10,S10:T10) -> 8
A11: באיזו מידה ישפיע או לא ישפיע כל אחד מהנושאים הבאים על ההצבעה שלך לכנסת? שחיתות | C11: v68 | D11: v68 | E11: v68 | G11: v68 | H11: v69 | I11: v65 | J11: v88 | K11: a97 | L11: a63 | AA11: v19 | AE11: d5 | AK11: =COUNTA(C11:AI11) -> 11 | AM11: =COUNTA(G11:P11,S11:T11) -> 6
A12: באיזו מידה ישפיע או לא ישפיע כל אחד מהנושאים הבאים על ההצבעה שלך לכנסת? היחס לדמוקרטיה | C12: v69 | D12: v69 | E12: v69 | G12: v69 | H12: v70 | I12: v66 | AK12: =COUNTA(C12:AI12) -> 6 | AM12: =COUNTA(G12:P12,S12:T12) -> 3
A13: באיזו מידה ישפיע או לא ישפיע כל אחד מהנושאים הבאים על ההצבעה שלך לכנסת? השיקול למנוע בחירות נוספות | C13: v504 | D13: v504 | E13: v504 | AK13: =COUNTA(C13:AI13) -> 3 | AM13: =COUNTA(G13:P13,S13:T13) -> 0
A14: באיזו מידה ישפיע או לא ישפיע כל אחד מהנושאים הבאים על ההצבעה שלך לכנסת? האיום האיראני | I14: v64 | AK14: =COUNTA(C14:AI14) -> 1 | AM14: =COUNTA(G14:P14,S14:T14) -> 1
A15: באיזו מידה ישפיע או לא ישפיע כל אחד מהנושאים הבאים על ההצבעה שלך לכנסת? ירושלים | J15: v82 | K15: a91 | L15: a57 | N15: i23 | O15: cc12 | AK15: =COUNTA(C15:AI15) -> 5 | AM15: =COUNTA(G15:P15,S15:T15) -> 5
A16: באיזו מידה ישפיע או לא ישפיע כל אחד מהנושאים הבאים על ההצבעה שלך לכנסת? לבנון | N16: i28 | O16: cc17 | AK16: =COUNTA(C16:AI16) -> 2 | AM16: =COUNTA(G16:P16,S16:T16) -> 2
A17: באיזו מידה ישפיע או לא ישפיע כל אחד מהנושאים הבאים על ההצבעה שלך לכנסת? משפט דרעי | N17: i31 | AK17: =COUNTA(C17:AI17) -> 1 | AM17: =COUNTA(G17:P17,S17:T17) -> 1
A18: באיזו מידה ישפיע או לא ישפיע כל אחד מהנושאים הבאים על ההצבעה שלך לכנסת? רצח רבין | O18: cc16 | AK18: =COUNTA(C18:AI18) -> 1 | AM18: =COUNTA(G18:P18,S18:T18) -> 1
A19: באיזו מידה ישפיע או לא ישפיע כל אחד מהנושאים הבאים על ההצבעה שלך לכנסת? משבר הקורונה | D19: v608 | AK19: =COUNTA(C19:AI19) -> 1 | AM19: =COUNTA(G19:P19,S19:T19) -> 0
A20: מבין הנושאים הבאים מה הדבר שהכי שישפיע ביותר על ההצבעה שלך בבחירות הקרובות? | J20: v89 | K20: b6 | AK20: =COUNTA(C20:AI20) -> 2 | AM20: =COUNTA(G20:P20,S20:T20) -> 2
A21: לו הבחירות לכנסת היו נערכות היום, עבור איזו רשימה היית מצביע? | B21: v104 | C21: v104 | D21: v104 | E21: v104E | F21: c104 | G21: v104 | H21: v92 | I21: v101 | J21: v154 | K21: b73 | L21: b63 | M21: b14 | N21: c12 | O21: ccc23 | P21: i41 | Q21: a63 | R21: c17 | S21: g22 | T21: a41 | U21: b89 | V21: a142 | W21: v122 | X21: c16 | Y21: b10 | Z21: a9 | AA21: v107 | AC21: g56 | AD21: f50 | AE21: e7 | AF21: b20 | AG21: b48 | AH21: b40 | AI21: b45 | AK21: =COUNTA(C21:AI21) -> 32 | AM21: =COUNTA(G21:P21,S21:T21) -> 12
A22: (עבור מי שהשיב 'לא החליט', 'לא יודע', 'מסרב להשיב') האם הנטייה שלך היא להצביע למפלגת: | C22: v104a | AK22: =COUNTA(C22:AI22) -> 1
A23: עבור איזו רשימה הצבעת בבחירות הקודמות לכנסת? | B23: v706 | C23: v706 | D23: v610 | E23: v507 | G23: v108 | H23: v101 | I23: v102 | J23: v162 | K23: c40 | L23: b70 | M23: b21 | N23: c17 | O23: ccc37 | P23: i42 | Q23: a64 | R23: c18 | S23: g24 | T23: a45 | U23: b97 | V23: a140 | W23: v126 | X23: c14 | Y23: b9 | Z23: a8 | AA23: v105 | AB23: h53 | AC23: g55 | AD23: f49 | AG23: c7 | AH23: b56 | AI23: b61 | AK23: =COUNTA(C23:AI23) -> 30 | AM23: =COUNTA(G23:P23,S23:T23) -> 12
A24: חוק בחירה ישירה - לו הבחירות לראשות הממשלה היו נערכות היום, עבור מי היית מצביע? | M24: b16 | N24: c13 | O24: ccc28 | AK24: =COUNTA(C24:AI24) -> 3 | AM24: =COUNTA(G24:P24,S24:T24) -> 3
A25: עבור מי הצבעת לראשות הממשלה בבחירות הקודמות? | L25: b68 | M25: b20 | N25: c16 | AK25: =COUNTA(C25:AI25) -> 3 | AM25: =COUNTA(G25:P25,S25:T25) -> 3
A26: אם לסיבוב השני יעלו נתניהו וברק, עבור מי היית מצביע? | N26: c14 | AK26: =COUNTA(C26:AI26) -> 1 | AM26: =COUNTA(G26:P26,S26:T26) -> 1
A27: עבור איזו רשימה הצבעת במערכת הבחירות הלפני אחרונה? (שתי מערכות אחורה) | E27: v508 | O27: ccc39 | U27: b98 | V27: a141 | W27: v127 | AA27: v106 | AK27: =COUNTA(C27:AI27) -> 6 | AM27: =COUNTA(G27:P27,S27:T27) -> 1
A28: עבור איזו רשימה הצבעת במערכת הבחירות הלפני לפני אחרונה? (שלוש מערכות אחורה) | E28: v509 | U28: b99 | AK28: =COUNTA(C28:AI28) -> 2 | AM28: =COUNTA(G28:P28,S28:T28) -> 0
A29: עבור מי הצבעת לראשות הממשלה ב-1999? | K29: c42 | L29: b69 | AK29: =COUNTA(C29:AI29) -> 2 | AM29: =COUNTA(G29:P29,S29:T29) -> 2
A30: האם הצבעת בבחירות האחרונות לכנסת? | C30: F1 | D30: F1 | E30: E1_after | F30: D1 | G30: v1_after | H30: after_v1 | I30: a_v1 | J30: q1 | K30: d5 | AK30: =COUNTA(C30:AI30) -> 9 | AM30: =COUNTA(G30:P30,S30:T30) -> 5
A31: עבור איזו רשימה הצבעת בבחירות האחרונות לכנסת? | C31: F2 | D31: F2 | E31: E2_after | F31: D2 | G31: v2_after | H31: after_v2 | I31: a_v2 | J31: q3 | K31: d6 | N31: d9 | X31: c15 | AB31: h54 | AK31: =COUNTA(C31:AI31) -> 12 | AM31: =COUNTA(G31:P31,S31:T31) -> 6
A32: האם התלבטת עבור איזו מפלגה להצביע? | N32: d10 | AK32: =COUNTA(C32:AI32) -> 1 | AM32: =COUNTA(G32:P32,S32:T32) -> 1
A33: בין מי למי התלבטת? | N33: d11 | T33: a44 | AK33: =COUNTA(C33:AI33) -> 2 | AM33: =COUNTA(G33:P33,S33:T33) -> 2
A34: בין מי למי אתה מתלבט? | W34: v123 | Y34: b11 | Z34: a10 | AK34: =COUNTA(C34:AI34) -> 3 | AM34: =COUNTA(G34:P34,S34:T34) -> 0
A35: האם בגלל פרישתו של רבין וקבלת המועמדות לראשות הממשלה של פרס אתה מתלבט כיום יותר או פחות בעד איזו מפלגה להצביע? | Z35: a11 | AK35: =COUNTA(C35:AI35) -> 1 | AM35: =COUNTA(G35:P35,S35:T35) -> 0
A36: עבור מי הצבעת לראשות הממשלה בבחירות האחרונות לכנסת? | N36: d3 | AK36: =COUNTA(C36:AI36) -> 1 | AM36: =COUNTA(G36:P36,S36:T36) -> 1
A37: כאשר היו עדין חמישה מועמדים לראש הממשלה, עבור מי מהם חשבת להצביע? | N37: d4 | AK37: =COUNTA(C37:AI37) -> 1 | AM37: =COUNTA(G37:P37,S37:T37) -> 1
A38: האם התלבטת למי מהם להצביע? | N38: d5 | AK38: =COUNTA(C38:AI38) -> 1 | AM38: =COUNTA(G38:P38,S38:T38) -> 1
A39: בין מי למי התלבטת? | N39: d6 | AK39: =COUNTA(C39:AI39) -> 1 | AM39: =COUNTA(G39:P39,S39:T39) -> 1
A40: אם סמוך לבחירות יתברר לך כי המועמד למועדף עליך לראשות הממשלה אין סיכוי לנצח, האם תשנה את הצבעתך? | N40: v59 | AK40: =COUNTA(C40:AI40) -> 1 | AM40: =COUNTA(G40:P40,S40:T40) -> 1
A41: בבחירות האלה אחוז החסימה מאפשר רק למפלגה שתקבל ארבעה מנדטים לפחות להכנס לכנסת. אם הסקרים שיפורסמו קרוב לבחירות יראו שלא בטוח שהמפלגה עבורה אתה מתכוון להצביע תעבור את אחוז החסימה, האם זה יגרום לך לשנות את הצבעתך? | G41: v105 | H41: v95 | AK41: =COUNTA(C41:AI41) -> 2 | AM41: =COUNTA(G41:P41,S41:T41) -> 2
A42: לאיזו מפלגה תעבור? | G42: v105E | H42: v97 | AK42: =COUNTA(C42:AI42) -> 2 | AM42: =COUNTA(G42:P42,S42:T42) -> 2
A43: מדוע זה לא ישנה את הצבעתך? | H43: v96 | AK43: =COUNTA(C43:AI43) -> 1 | AM43: =COUNTA(G43:P43,S43:T43) -> 1
A44: מתי קיבלת את החלטתך הסופית (להצביע עבור המפלגה שהצביע) | C44: F3 | D44: F3 | G44: v3_after | H44: after_v3 | I44: a_v3 | J44: q7 | K44: d11 | N44: d8 | AB44: h29 | AC44: g39 | AK44: =COUNTA(C44:AI44) -> 10 | AM44: =COUNTA(G44:P44,S44:T44) -> 6
A45: מה בסופו של דבר הביא אותך להצביע כמו שהצבעת? | H45: after_v4a | AK45: =COUNTA(C45:AI45) -> 1 | AM45: =COUNTA(G45:P45,S45:T45) -> 1
A46: מדוע החלטת לא להצביע בבחירות/לשים פתק לבן? | H46: after_v4b | J46: q2 | M46: b17 | O46: ccc29 | AK46: =COUNTA(C46:AI46) -> 4 | AM46: =COUNTA(G46:P46,S46:T46) -> 4
A47: באיזו מידה הסקרים שהתפרסמו כמה ימים לפני הבחירות היוו גורם בהחלטה שלך כיצד להצביע? | C47: F5 | D47: F5 | G47: v5_after | H47: after_v6 | AB47: h51 | AK47: =COUNTA(C47:AI47) -> 5 | AM47: =COUNTA(G47:P47,S47:T47) -> 2
A48: באיזו מידה אתה חושב שאנשים מושפעים בהחלטה עבור מי להצביע מסקרים אלו? | N48: c6 | O48: ccc7 | U48: b86 | AK48: =COUNTA(C48:AI48) -> 3 | AM48: =COUNTA(G48:P48,S48:T48) -> 2
A49: באיזו מידה תשדירי הבחירות בטלוויזיה יעזרו לך להחליט עבור מי להצביע? | M49: b11 | N49: c8 | O49: ccc10 | P49: i49 | W49: v23 | AB49: h42 | AC49: g21 | AD49: f19 | AE49: c18 | AF49: v39 | AK49: =COUNTA(C49:AI49) -> 10 | AM49: =COUNTA(G49:P49,S49:T49) -> 4
A50: באיזו מידה המודעות בעיתונים משפיעות על החלטתך עבור מי להצביע? | U50: b108 | Z50: a7 | AB50: h40 | AC50: g15 | AD50: f20 | AE50: c12 | AK50: =COUNTA(C50:AI50) -> 6 | AM50: =COUNTA(G50:P50,S50:T50) -> 0
A51: באיזו מידה אתה חושב שהעיתונות תעזור לך או לא להחליט בעד מי להצביע? | W51: v22 | AF51: v38 | AK51: =COUNTA(C51:AI51) -> 2 | AM51: =COUNTA(G51:P51,S51:T51) -> 0
A52: באיזו מידה אתה חושב שהשידורים ברדיו יעזרו לך או לא להחליט בעד מי להצביע? | W52: v21 | AB52: h41 | AC52: g18 | AE52: c15 | AF52: v37 | AK52: =COUNTA(C52:AI52) -> 5 | AM52: =COUNTA(G52:P52,S52:T52) -> 0
A53: באיזו מידה שיחות עם אנשים אחרים עזרו לך להחליט בעד מי להצביע? | AB53: h43 | AK53: =COUNTA(C53:AI53) -> 1 | AM53: =COUNTA(G53:P53,S53:T53) -> 0
A54: באיזו מידה אתה חושב שחוגי בית יעזרו לך להחליט בעד מי להצביע? | AD54: f21 | AE54: c24 | AK54: =COUNTA(C54:AI54) -> 2 | AM54: =COUNTA(G54:P54,S54:T54) -> 0
A55: באיזו מידה אתה חושב שאסיפות יעזרו לך להחליט בעד מי להצביע? | AD55: f22 | AK55: =COUNTA(C55:AI55) -> 1 | AM55: =COUNTA(G55:P55,S55:T55) -> 0
A56: יש אנשים שלא מצביעים בבחירות מסיבה כזו או אחרת. האם אתה מתכוון להצביע בבחירות לכנסת? | H56: v91 | I56: v100 | J56: v152 | AC56: g37 | AD56: f14 | AE56: d45 | AF56: b12 | AK56: =COUNTA(C56:AI56) -> 7 | AM56: =COUNTA(G56:P56,S56:T56) -> 3
A57: מה הסיבה שאינך מתכוון ללכת להצביע בבחירות הקרובות לכנסת? | AD57: f16 | AK57: =COUNTA(C57:AI57) -> 1 | AM57: =COUNTA(G57:P57,S57:T57) -> 0
A58: אם הסקרים שיפורסמו בימים האחרונים של מערכת הבחירות יראו שהליכוד והמחנה הציוני מקבלים פחות או יותר אותו מספר של מנדטים, האם זה יגרום לך לשנות את הצבעתך? | H58: v93 | AK58: =COUNTA(C58:AI58) -> 1 | AM58: =COUNTA(G58:P58,S58:T58) -> 1
A59: לאיזו מפלגה תעבור? | H59: v94 | AK59: =COUNTA(C59:AI59) -> 1 | AM59: =COUNTA(G59:P59,S59:T59) -> 1
A60: לאחרונה התפרסמו בתקשורת ידיעות רבות על חקירות בחשד לשחיתות של פוליטיקאים ועובדים בכירים במשרדי הממשלה וברשויות הממשלתיות. האם בעקבות ידיעות אלה שינית את החלטתך כיצד שלהצביע בבחירות? | H60: v98 | AK60: =COUNTA(C60:AI60) -> 1 | AM60: =COUNTA(G60:P60,S60:T60) -> 1
A61: אם צומת וגשר היו רצות כמפלגות נפרדות ולא יחד עם הליכוד, עבור איזו רשימה היית מצביע? | O61: ccc27 | AK61: =COUNTA(C61:AI61) -> 1 | AM61: =COUNTA(G61:P61,S61:T61) -> 1
A62: אם הליכוד וישראל ביתנו היו רצות בנפרד בבחירות הקודמות ב2013, עבור מי מהשניים היית מצביע? | H62: v102 | AK62: =COUNTA(C62:AI62) -> 1 | AM62: =COUNTA(G62:P62,S62:T62) -> 1
A63: בהנחה שיש שני מועמדים מוכשרים ומתאימים באותה מידה לתפקיד פוליטי בכיר, האחד גבר והשנייה אישה, למי היית נוטה להצביע? | H63: v104 | I63: v104 | AK63: =COUNTA(C63:AI63) -> 2 | AM63: =COUNTA(G63:P63,S63:T63) -> 2
A64: בהנחה שיש שני מועמדים מוכשרים ומתאימים באותה מידה לתפקיד פוליטי בכיר, האחד אשכנזי והשני מזרחי, למי הית נוטה להצביע? | H64: v105 | AK64: =COUNTA(C64:AI64) -> 1 | AM64: =COUNTA(G64:P64,S64:T64) -> 1
A65: באיזו מידה משפיע או לא משפיע כל אחד מהנושאים הבאים על ההצבעה שלך: אם אישה עומדת בראש הרשימה | H65: v123 | AK65: =COUNTA(C65:AI65) -> 1 | AM65: =COUNTA(G65:P65,S65:T65) -> 1
A66: באיזו מידה משפיע או לא משפיע כל אחד מהנושאים הבאים על ההצבעה שלך: אם מזרחי עומד בראש הרשימה | H66: v124 | AK66: =COUNTA(C66:AI66) -> 1 | AM66: =COUNTA(G66:P66,S66:T66) -> 1
A67: באיזו מידה משפיע או לא משפיע כל אחד מהנושאים הבאים על ההצבעה שלך: מספר הנשים ברשימה לכנסת | H67: v125 | AK67: =COUNTA(C67:AI67) -> 1 | AM67: =COUNTA(G67:P67,S67:T67) -> 1
A68: באיזו מידה משפיע או לא משפיע כל אחד מהנושאים הבאים על ההצבעה שלך: מספר המזרחים ברשימה לכנסת | H68: v126 | AK68: =COUNTA(C68:AI68) -> 1 | AM68: =COUNTA(G68:P68,S68:T68) -> 1
A69: לו הבחירות לכנסת היו נערכות היום, עבור איזו רשימה, למיטב ידיעתך, היה בן/בת הזוג שלך מצביע? | I69: v131 | J69: v155 | R69: c25 | S69: g35 | AK69: =COUNTA(C69:AI69) -> 4 | AM69: =COUNTA(G69:P69,S69:T69) -> 3
A70: ומה לגבי בן/בת זוגך, אם יש לך, כיצד למיטב ידיעתך הוא/היא הצביע/ה? | I70: a_v4 | J70: q4 | N70: d14 | AK70: =COUNTA(C70:AI70) -> 3 | AM70: =COUNTA(G70:P70,S70:T70) -> 3
A71: באיזו מידה לדעתך מערכת הבחירות תעזור לך להחליט בעד מי להצביע? | J71: v138 | W71: v20 | AA71: v98 | AB71: h39 | AC71: g5 | AF71: v36 | AK71: =COUNTA(C71:AI71) -> 6 | AM71: =COUNTA(G71:P71,S71:T71) -> 1
A72: ומבין כל הסיבות האלה, מה היתה לדעתך הסיבה העיקרית להשתתפות הנמוכה בבחירות? | K72: d21 | AK72: =COUNTA(C72:AI72) -> 1 | AM72: =COUNTA(G72:P72,S72:T72) -> 1
A73: כנראה שבבחירות הקרובות יצביעו פחות אנשים מבעבר. מהי לדעתך הסיבה העיקרית לכך? | J73: v153 | V73: a25 | AK73: =COUNTA(C73:AI73) -> 2 | AM73: =COUNTA(G73:P73,S73:T73) -> 1
A74: בבחירות האחרונות השתתפו הרבה פחות בוחרים מבעבר. עד כמה לדעתך כל סיבה כזאת חשובה או לא חשובה לאלה שלא הלכו להצביע: אין הבדל בין המפלגות | K74: d15 | AK74: =COUNTA(C74:AI74) -> 1 | AM74: =COUNTA(G74:P74,S74:T74) -> 1
A75: היה ברור מראש מי ינצח | K75: d16 | AK75: =COUNTA(C75:AI75) -> 1 | AM75: =COUNTA(G75:P75,S75:T75) -> 1
A76: ממילא לא משנה עבור מי מצביעים כי זה לא משנה את המצב | K76: d17 | AK76: =COUNTA(C76:AI76) -> 1 | AM76: =COUNTA(G76:P76,S76:T76) -> 1
A77: הפוליטיקה והפוליטיקאים נמאסו על הציבור | K77: d18 | AK77: =COUNTA(C77:AI77) -> 1 | AM77: =COUNTA(G77:P77,S77:T77) -> 1
A78: הם הרגישו שלא היה להם במי לבחור | K78: d19 | AK78: =COUNTA(C78:AI78) -> 1 | AM78: =COUNTA(G78:P78,S78:T78) -> 1
A79: לא אכפת להם, הם אדישים | K79: d20 | AK79: =COUNTA(C79:AI79) -> 1 | AM79: =COUNTA(G79:P79,S79:T79) -> 1
A80: אילו היו שני פתקים בבחירות האלה, אחד לראש הממשלה ואחד לכנסת, עבור מי היית מצביע לראשות הממשלה? | J80: v156 | K80: c36 | L80: b65 | P80: i43 | AK80: =COUNTA(C80:AI80) -> 4 | AM80: =COUNTA(G80:P80,S80:T80) -> 4
A81: אילו היו שני פתקים בבחירות האלה, אחד לראש הממשלה ואחד לכנסת, עבור מי היית מצביע לכנסת? | J81: v157 | K81: c38 | L81: b66 | P81: i44 | AK81: =COUNTA(C81:AI81) -> 4 | AM81: =COUNTA(G81:P81,S81:T81) -> 4
A82: אילו הייתה השיטה הישנה, כלומר מצביעים רק בפתק אחד לכנסת, עבור איזו מפלגה היית מצביע? | O82: ccc33 | AK82: =COUNTA(C82:AI82) -> 1 | AM82: =COUNTA(G82:P82,S82:T82) -> 1
A83: האם הצבעת בבחירות לרשויות המקומיות האחרונות? | J83: v163 | AK83: =COUNTA(C83:AI83) -> 1 | AM83: =COUNTA(G83:P83,S83:T83) -> 1
A84: האם יצרו עמך קשר ממפלגה או מקבוצה כלשהי במהלך מערכת הבחירות בניסיון להשפיע על אופי הצבעתך? | J84: q9 | K84: d14 | AK84: =COUNTA(C84:AI84) -> 2 | AM84: =COUNTA(G84:P84,S84:T84) -> 2
A85: אם ברק לא יתמודד לראשות הממשלה, והמתמודדים יהיו שרון ופרס, במי היית בוחר? | M85: b65 | AK85: =COUNTA(C85:AI85) -> 1 | AM85: =COUNTA(G85:P85,S85:T85) -> 1
A86: באיזו מידה ישפיע או לא ישפיע כל אחד מהנושאים הבאים על ההצבעה שלך לראש הממשלה? כלכלה | M86: a59 | N86: v63 | O86: cc7 | AK86: =COUNTA(C86:AI86) -> 3 | AM86: =COUNTA(G86:P86,S86:T86) -> 3
A87: באיזו מידה ישפיע או לא ישפיע כל אחד מהנושאים הבאים על ההצבעה שלך לראש הממשלה? מדיניות חברתית | M87: a60 | N87: v64 | AK87: =COUNTA(C87:AI87) -> 2 | AM87: =COUNTA(G87:P87,S87:T87) -> 2
A88: באיזו מידה ישפיע או לא ישפיע כל אחד מהנושאים הבאים על ההצבעה שלך לראש הממשלה? דת ומדינה | M88: a61 | N88: v65 | AK88: =COUNTA(C88:AI88) -> 2 | AM88: =COUNTA(G88:P88,S88:T88) -> 2
A89: באיזו מידה ישפיע או לא ישפיע כל אחד מהנושאים הבאים על ההצבעה שלך לראש הממשלה? שלום ושטחים | M89: a62 | N89: v67 | O89: cc8 | AK89: =COUNTA(C89:AI89) -> 3 | AM89: =COUNTA(G89:P89,S89:T89) -> 3
A90: באיזו מידה ישפיע או לא ישפיע כל אחד מהנושאים הבאים על ההצבעה שלך לראש הממשלה? בטחון וטרור | M90: a63 | N90: v68 | O90: cc9 | AK90: =COUNTA(C90:AI90) -> 3 | AM90: =COUNTA(G90:P90,S90:T90) -> 3
A91: באיזו מידה ישפיע או לא ישפיע כל אחד מהנושאים הבאים על ההצבעה שלך לראש הממשלה? ירושלים | M91: a58 | N91: v62 | O91: cc6 | AK91: =COUNTA(C91:AI91) -> 3 | AM91: =COUNTA(G91:P91,S91:T91) -> 3
A92: באיזו מידה ישפיע או לא ישפיע כל אחד מהנושאים הבאים על ההצבעה שלך לראש הממשלה? לבנון | N92: v66 | O92: cc11 | AK92: =COUNTA(C92:AI92) -> 2 | AM92: =COUNTA(G92:P92,S92:T92) -> 2
A93: באיזו מידה ישפיע או לא ישפיע כל אחד מהנושאים הבאים על ההצבעה שלך לראש הממשלה? רצח רבין | O93: cc10 | AK93: =COUNTA(C93:AI93) -> 1 | AM93: =COUNTA(G93:P93,S93:T93) -> 1
A94: אילו יכולת להצביע בבחירות לכנסת עבור יותר ממפלגה אחת, ללא הגבלה, עבור אילו מפלגות היית מצביע? | O94: cccc6 | R94: c20 | S94: g26 | U94: b90 | AK94: =COUNTA(C94:AI94) -> 4 | AM94: =COUNTA(G94:P94,S94:T94) -> 2
A95: לו יכלת להצביע עבור עוד שתי רשימות, מלבד לזו שאמרת, לאילו שתי רשימות היית מצביע: הראשונה | AH95: b59 | AI95: b64 | AK95: =COUNTA(C95:AI95) -> 2 | AM95: =COUNTA(G95:P95,S95:T95) -> 0
A96: לו יכלת להצביע עבור עוד שתי רשימות, מלבד לזו שאמרת, לאילו שתי רשימות היית מצביע: השנייה | AH96: b60 | AI96: b65 | AK96: =COUNTA(C96:AI96) -> 2 | AM96: =COUNTA(G96:P96,S96:T96) -> 0
A97: הגורמים הבאים משפיע או לא משפיע על החלטתך עבור מי להצביע? העמדת יצחק שמיר בראש הליכוד | P97: a122 | AK97: =COUNTA(C97:AI97) -> 1 | AM97: =COUNTA(G97:P97,S97:T97) -> 1
A98: הגורמים הבאים משפיע או לא משפיע על החלטתך עבור מי להצביע? הפריימריז בעבודה | P98: a123 | AK98: =COUNTA(C98:AI98) -> 1 | AM98: =COUNTA(G98:P98,S98:T98) -> 1
A99: הגורמים הבאים משפיע או לא משפיע על החלטתך עבור מי להצביע? הרכב רשימת העבודה | P99: a124 | AK99: =COUNTA(C99:AI99) -> 1 | AM99: =COUNTA(G99:P99,S99:T99) -> 1
A100: הגורמים הבאים משפיע או לא משפיע על החלטתך עבור מי להצביע? הרכב רשימת הליכוד | P100: a125 | AK100: =COUNTA(C100:AI100) -> 1 | AM100: =COUNTA(G100:P100,S100:T100) -> 1
...

Sheet ציפיות
A1: שאלה | B1: 2022 | C1: 2022 | D1: 2021 | E1: 2020 | F1: 43709 | G1: 43556 | H1: 2015 | I1: 2013 | J1: 2009 | K1: 2006 | L1: 2003 | M1: 2001 | N1: 1999 | O1: 1996 | P1: 1992 | Q1: 1987* | R1: 1988* | S1: 1988 | T1: 1984 | U1: 1981 - 3 | V1: 1981 - 2 | W1: 1981 - 1 | X1: 1977 - 4 | Y1: 1977 - 3 | Z1: 1977 - 2 | AA1: 1977 - 1 | AB1: 1973 - 5 | AC1: 1973 - 4 | AD1: 1973 - 3 | AE1: 1973 - 2 | AF1: 1973 - 1 | AG1: 1969 - 3 | AH1: 1969 - 2 | AI1: 1969 - 1 | AK1: מספר חזרות | AM1: ספירה 84-19 | AO1: סה"כ מעל שתי חזרות
A2: מי לדעתך ינצח? | M2: b19 | N2: c15 | O2: ccc35 | AK2: =COUNTA(D2:AI2) -> 3 | AM2: =COUNTA(G2:P2,S2:T2) -> 3 | AO2: =COUNTIF(AM2:AM72,">=2") -> 15
A3: מי לדעתך יעלה לסיבוב השני? | N3: v60 | AK3: =COUNTA(D3:AI3) -> 1 | AM3: =COUNTA(G3:P3,S3:T3) -> 1
A4: לדעתך, מה הסיכוי שציפי לבני תהיה ראש ממשלה לאחר הבחירות? | J4: v158 | AK4: =COUNTA(D4:AI4) -> 1 | AM4: =COUNTA(G4:P4,S4:T4) -> 1
A5: לדעתך, מה הסיכוי שבנימין נתניהו תהיה ראש ממשלה לאחר הבחירות? | J5: v159 | AK5: =COUNTA(D5:AI5) -> 1 | AM5: =COUNTA(G5:P5,S5:T5) -> 1
A6: לדעתך, מה הסיכוי שאהוד ברק תהיה ראש ממשלה לאחר הבחירות? | J6: v160 | AK6: =COUNTA(D6:AI6) -> 1 | AM6: =COUNTA(G6:P6,S6:T6) -> 1
A7: איזו מפלגה למיטב הערכתך תהיה המפלגה הגדולה ביותר בכנסת הבאה? | O7: ccc36 | P7: i39 | R7: c16 | S7: g20 | AK7: =COUNTA(D7:AI7) -> 4 | AM7: =COUNTA(G7:P7,S7:T7) -> 3
A8: איזו מפלגה היית רוצה שתקים את ההממשלה הבאה? | P8: i40 | R8: c15 | S8: g18 | W8: v120 | Y8: b7 | AA8: v102 | AK8: =COUNTA(D8:AI8) -> 6 | AM8: =COUNTA(G8:P8,S8:T8) -> 2
A9: איזו משתי הרשימות הגדולות היית רוצה שתקים את הממשלה הבאה - המערך או הליכוד? | U9: b106 | AK9: =COUNTA(D9:AI9) -> 1 | AM9: =COUNTA(G9:P9,S9:T9) -> 0
A10: איזו מפלגה אתה מעריך שתקים את הממשלה לאחר הבחירות? | U10: b104 | V10: a115 | W10: v121 | Y10: b6 | AA10: v101 | AK10: =COUNTA(D10:AI10) -> 5 | AM10: =COUNTA(G10:P10,S10:T10) -> 0
A11: לדעתך, מה הסיכוי שהמפלגה הבאה תהיה בקואליציה: קדימה | K11: b75 | AK11: =COUNTA(D11:AI11) -> 1 | AM11: =COUNTA(G11:P11,S11:T11) -> 1
A12: לדעתך, מה הסיכוי שהמפלגה הבאה תהיה בקואליציה: העובדה | K12: b78 | L12: b10 | AK12: =COUNTA(D12:AI12) -> 2 | AM12: =COUNTA(G12:P12,S12:T12) -> 2
A13: לדעתך, מה הסיכוי שהמפלגה הבאה תהיה בקואליציה: הליכוד | K13: b81 | L13: b7 | AK13: =COUNTA(D13:AI13) -> 2 | AM13: =COUNTA(G13:P13,S13:T13) -> 2
A14: לדעתך, מה הסיכוי שהמפלגה הבאה תהיה בקואליציה: מרצ | L14: b13 | AK14: =COUNTA(D14:AI14) -> 1 | AM14: =COUNTA(G14:P14,S14:T14) -> 1
A15: לדעתך, מה הסיכוי שהמפלגה הבאה תהיה בקואליציה: מפד"ל | L15: b16 | AK15: =COUNTA(D15:AI15) -> 1 | AM15: =COUNTA(G15:P15,S15:T15) -> 1
A16: לדעתך, מה הסיכוי שהמפלגה הבאה תהיה בקואליציה: שינוי | L16: b19 | AK16: =COUNTA(D16:AI16) -> 1 | AM16: =COUNTA(G16:P16,S16:T16) -> 1
A17: לדעתך, מה הסיכוי שהמפלגה הבאה תהיה בקואליציה: איחוד לאומי | L17: b22 | AK17: =COUNTA(D17:AI17) -> 1 | AM17: =COUNTA(G17:P17,S17:T17) -> 1
A18: לדעתך, מה הסיכוי שהמפלגה הבאה תהיה בקואליציה: ש"ס | L18: b25 | AK18: =COUNTA(D18:AI18) -> 1 | AM18: =COUNTA(G18:P18,S18:T18) -> 1
A19: לדעתך, מה הסיכוי שהמפלגה הבאה תהיה בקואליציה: ישראל בעליה | L19: b28 | AK19: =COUNTA(D19:AI19) -> 1 | AM19: =COUNTA(G19:P19,S19:T19) -> 1
A20: לדעתך, מה הסיכוי שהמפלגה הבאה תהיה בקואליציה: המפלגה שאתה מצביע | K20: b84 | AK20: =COUNTA(D20:AI20) -> 1 | AM20: =COUNTA(G20:P20,S20:T20) -> 1
A21: לדעתך, כמה חברי כנסת יהיו למפלגה הבאה: קדימה | K21: b87 | AK21: =COUNTA(D21:AI21) -> 1 | AM21: =COUNTA(G21:P21,S21:T21) -> 1
A22: לדעתך, כמה חברי כנסת יהיו למפלגה הבאה: העבודה | K22: b89 | L22: b33 | AK22: =COUNTA(D22:AI22) -> 2 | AM22: =COUNTA(G22:P22,S22:T22) -> 2
A23: לדעתך, כמה חברי כנסת יהיו למפלגה הבאה: הליכוד | K23: b91 | L23: b31 | AK23: =COUNTA(D23:AI23) -> 2 | AM23: =COUNTA(G23:P23,S23:T23) -> 2
A24: לדעתך, כמה חברי כנסת יהיו למפלגה הבאה: מרצ | L24: b35 | AK24: =COUNTA(D24:AI24) -> 1 | AM24: =COUNTA(G24:P24,S24:T24) -> 1
A25: לדעתך, כמה חברי כנסת יהיו למפלגה הבאה: מפד"ל | L25: b37 | AK25: =COUNTA(D25:AI25) -> 1 | AM25: =COUNTA(G25:P25,S25:T25) -> 1
A26: לדעתך, כמה חברי כנסת יהיו למפלגה הבאה: שינוי | L26: b39 | AK26: =COUNTA(D26:AI26) -> 1 | AM26: =COUNTA(G26:P26,S26:T26) -> 1
A27: לדעתך, כמה חברי כנסת יהיו למפלגה הבאה: איחוד לאומי | L27: b41 | AK27: =COUNTA(D27:AI27) -> 1 | AM27: =COUNTA(G27:P27,S27:T27) -> 1
A28: לדעתך, כמה חברי כנסת יהיו למפלגה הבאה: ש"ס | L28: b43 | AK28: =COUNTA(D28:AI28) -> 1 | AM28: =COUNTA(G28:P28,S28:T28) -> 1
A29: לדעתך, כמה חברי כנסת יהיו למפלגה הבאה: ישראל בעליה | L29: b45 | AK29: =COUNTA(D29:AI29) -> 1 | AM29: =COUNTA(G29:P29,S29:T29) -> 1
A30: לדעתך, כמה חברי כנסת יהיו למפלגה הבאה: המפלגה שאתה מתכוון להצביע לה | K30: b93 | AK30: =COUNTA(D30:AI30) -> 1 | AM30: =COUNTA(G30:P30,S30:T30) -> 1
A31: הסיכויים לקואליציות שונות לאחר הבחירות: קדימה-עבודה | K31: c6 | AK31: =COUNTA(D31:AI31) -> 1 | AM31: =COUNTA(G31:P31,S31:T31) -> 1
A32: הסיכויים לקואליציות שונות לאחר הבחירות: קדימה-ליכוד | K32: c9 | AK32: =COUNTA(D32:AI32) -> 1 | AM32: =COUNTA(G32:P32,S32:T32) -> 1
A33: הסיכויים לקואליציות שונות לאחר הבחירות: קדימה-ליכוד-מפלגות חרדיות | K33: c12 | AK33: =COUNTA(D33:AI33) -> 1 | AM33: =COUNTA(G33:P33,S33:T33) -> 1
A34: הסיכויים לקואליציות שונות לאחר הבחירות: קדימה-עבודה-מפלגות חרדיות | K34: c15 | AK34: =COUNTA(D34:AI34) -> 1 | AM34: =COUNTA(G34:P34,S34:T34) -> 1
A35: הסיכויים לקואליציות שונות לאחר הבחירות: קדימה-ליכוד-מפלגות ימין | K35: c18 | AK35: =COUNTA(D35:AI35) -> 1 | AM35: =COUNTA(G35:P35,S35:T35) -> 1
A36: הסיכויים לקואליציות שונות לאחר הבחירות: קדימה-עבודה-מרצ | K36: c21 | AK36: =COUNTA(D36:AI36) -> 1 | AM36: =COUNTA(G36:P36,S36:T36) -> 1
A37: הסיכויים לקואליציות שונות לאחר הבחירות: קדימה-עבודה-ליכוד-מפלגות ימין-מפלגות חרדיות (אחדות לאומית) | K37: c24 | L37: b56 | AK37: =COUNTA(D37:AI37) -> 2 | AM37: =COUNTA(G37:P37,S37:T37) -> 2
A38: הסיכויים לקואליציות שונות לאחר הבחירות: ליכוד-ימין-דתיים | L38: b47 | AK38: =COUNTA(D38:AI38) -> 1 | AM38: =COUNTA(G38:P38,S38:T38) -> 1
A39: הסיכויים לקואליציות שונות לאחר הבחירות: ליכוד-עבודה-שינוי (בלי חרדים) | L39: b50 | AK39: =COUNTA(D39:AI39) -> 1 | AM39: =COUNTA(G39:P39,S39:T39) -> 1
A40: הסיכויים לקואליציות שונות לאחר הבחירות: עבודה-מרצ-ערבים | L40: b53 | AK40: =COUNTA(D40:AI40) -> 1 | AM40: =COUNTA(G40:P40,S40:T40) -> 1
A41: מה מידת התמיכה שלך בכל אחת מן הקואליציות הבאות: קדימה-עבודה | K41: c27 | AK41: =COUNTA(D41:AI41) -> 1 | AM41: =COUNTA(G41:P41,S41:T41) -> 1
A42: מה מידת התמיכה שלך בכל אחת מן הקואליציות הבאות: קדימה-ליכוד | K42: c28 | AK42: =COUNTA(D42:AI42) -> 1 | AM42: =COUNTA(G42:P42,S42:T42) -> 1
A43: מה מידת התמיכה שלך בכל אחת מן הקואליציות הבאות: קדימה-ליכוד-מפלגות חרדיות | K43: c29 | AK43: =COUNTA(D43:AI43) -> 1 | AM43: =COUNTA(G43:P43,S43:T43) -> 1
A44: מה מידת התמיכה שלך בכל אחת מן הקואליציות הבאות: קדימה-עבודה-מפלגות חרדיות | K44: c30 | AK44: =COUNTA(D44:AI44) -> 1 | AM44: =COUNTA(G44:P44,S44:T44) -> 1
A45: מה מידת התמיכה שלך בכל אחת מן הקואליציות הבאות: קדימה-ליכוד-מפלגות ימין | K45: c32 | AK45: =COUNTA(D45:AI45) -> 1 | AM45: =COUNTA(G45:P45,S45:T45) -> 1
A46: מה מידת התמיכה שלך בכל אחת מן הקואליציות הבאות: קדימה-עבודה-מרצ | K46: c32 | AK46: =COUNTA(D46:AI46) -> 1 | AM46: =COUNTA(G46:P46,S46:T46) -> 1
A47: מה מידת התמיכה שלך בכל אחת מן הקואליציות הבאות: קדימה-עבודה-ליכוד-מפלגות ימין-מפלגות חרדיות (אחדות לאומית) | K47: c33 | L47: b62 | AK47: =COUNTA(D47:AI47) -> 2 | AM47: =COUNTA(G47:P47,S47:T47) -> 2
A48: מה מידת התמיכה שלך בכל אחת מן הקואליציות הבאות: ליכוד-ימין-דתיים | L48: b59 | AK48: =COUNTA(D48:AI48) -> 1 | AM48: =COUNTA(G48:P48,S48:T48) -> 1
A49: מה מידת התמיכה שלך בכל אחת מן הקואליציות הבאות: ליכוד-עבודה-שינוי | L49: b60 | AK49: =COUNTA(D49:AI49) -> 1 | AM49: =COUNTA(G49:P49,S49:T49) -> 1
A50: מה מידת התמיכה שלך בכל אחת מן הקואליציות הבאות: עבודה-מרצ-ערבים | L50: b61 | AK50: =COUNTA(D50:AI50) -> 1 | AM50: =COUNTA(G50:P50,S50:T50) -> 1
A51: בסיכומו של דבר, מבין הקואליציות האלה, איזו קואליציה אתה מעדיף? | K51: c34 | Y51: b8 | AK51: =COUNTA(D51:AI51) -> 2 | AM51: =COUNTA(G51:P51,S51:T51) -> 1
A52: האם היית רוצה שאחרי הבחירות תקום ממשלת אחדות לאומית? | N52: c9 | O52: ccc15 | P52: a59 | R52: b70 | S52: f73 | AC52: g49 | AK52: =COUNTA(C52:AI52) -> 6 | AM52: =COUNTA(G52:P52,S52:T52) -> 4
A53: האם יש להקים היום ממשלת אחדות לאומית? | AD53: f9 | AK53: =COUNTA(C53:AI53) -> 1 | AM53: =COUNTA(G53:P53,S53:T53) -> 0
A54: לדעתך, האם אחרי הבחירות הממשלה תתבסס על: | C54: v106 | D54: v106 | E54: v106 | F54: c106 | G54: v106 | H54: v99 | AK54: =COUNTA(C54:AI54) -> 6 | AM54: =COUNTA(G54:P54,S54:T54) -> 2
A55: ואיזו ממשלה מבין הבאות אתה מעדיף? | C55: v107 | D55: v107 | E55: v107 | F55: c107 | G55: v107 | H55: v100 | AK55: =COUNTA(C55:AI55) -> 6 | AM55: =COUNTA(G55:P55,S55:T55) -> 2
A56: באיזו מידה ביום הבחירות היה חשוב לך באופן אישי אם הממשלה הבאה תהיה ממשלת ימין או ממשלת שמאל? | D56: F4 | E56: E4_after | F56: D4 | G56: v4_after | H56: after_v5 | AK56: =COUNTA(C56:AI56) -> 5 | AM56: =COUNTA(G56:P56,S56:T56) -> 2
A57: ועתה, לאחר תוצאות הבחירות - איזו קואליציה אתה הכי מעדיף? | C57: F9 | D57: F9 | E57: E9_after | F57: D9 | G57: v9_after | H57: after_v9 | I57: a_v16 | J57: q5 | K57: d8 | AK57: =COUNTA(C57:AI57) -> 9 | AM57: =COUNTA(G57:P57,S57:T57) -> 5
A58: באופן כללי, האם אתה מרוצה או לא מרוצה מתוצאות הבחירות? | J58: q6 | K58: d10 | X58: c11 | AK58: =COUNTA(C58:AI58) -> 3 | AM58: =COUNTA(G58:P58,S58:T58) -> 2
A59: מבין שתי האפשרויות הבאות, מה אתה מעדיף? | D59: N2 | AK59: =COUNTA(C59:AI59) -> 1 | AM59: =COUNTA(G59:P59,S59:T59) -> 0
A60: באיזו מידה אכפת לך באופן אישי מי יהיה ראש הממשלה לאחר הבחירות? | J60: v161 | AK60: =COUNTA(C60:AI60) -> 1 | AM60: =COUNTA(G60:P60,S60:T60) -> 1
A61: האם בגלל ההתקוממות בשטחים (האינתיפאדה) השתנו או לא השתנו לגביך כל אחד מן הדברים הבאים: הערכתך לגבי תוצאות הבחירות? | R61: b49 | S61: f51 | AK61: =COUNTA(C61:AI61) -> 2 | AM61: =COUNTA(G61:P61,S61:T61) -> 1
A62: את מי מבין האישים הבאים היית רוצה לראות כראש ממשלה לאחר הבחירות לכנסת? | U62: b100 | V62: a120 | W62: v104 | X62: c10 | Y62: b5 | AA62: v99 | AK62: =COUNTA(C62:AI62) -> 6 | AM62: =COUNTA(G62:P62,S62:T62) -> 0
A63: את מי היית רוצה לראות כשר הבטחון לאחר הבחירות לכנסת? | U63: b101 | V63: a121 | AK63: =COUNTA(C63:AI63) -> 2 | AM63: =COUNTA(G63:P63,S63:T63) -> 0
A64: את מי היית רוצה לראות כשר האוצר לאחר הבחירות לכנסת? | U64: b102 | V64: a122 | AK64: =COUNTA(C64:AI64) -> 2 | AM64: =COUNTA(G64:P64,S64:T64) -> 0
A65: את מי היית רוצה לראות כשר החוץ לאחר הבחירות לכנסת? | U65: b103 | V65: a123 | AK65: =COUNTA(C65:AI65) -> 2 | AM65: =COUNTA(G65:P65,S65:T65) -> 0
A66: באיזו מידה אתה רוצה או לא רוצה לראות את המפד"ל בממשלה הבאה? | U66: b105 | V66: a117 | W66: v108 | AK66: =COUNTA(C66:AI66) -> 3 | AM66: =COUNTA(G66:P66,S66:T66) -> 0
A67: מי לדעתך המתחרה הרציני ביותר של המערך בבחירות לכנסת? | V67: a116 | W67: v112 | AA67: v95 | AK67: =COUNTA(C67:AI67) -> 3 | AM67: =COUNTA(G67:P67,S67:T67) -> 0
A68: אם ההרכב הקואליציוני של הממשלה יהיה דומה לזה של הממשלה היוצאת, האם צריך לחול שינוי בהרכב האישי של חברי הממשלה מטעם המערך? | AB68: h38 | AK68: =COUNTA(C68:AI68) -> 1 | AM68: =COUNTA(G68:P68,S68:T68) -> 0
A69: האם לדעתך מלחמת יום כיפור שינתה את סיכויי המערך בבחירות לכנסת לעומת אלו שהיו לפני המלחמה? | AD69: f35 | AK69: =COUNTA(C69:AI69) -> 1 | AM69: =COUNTA(G69:P69,S69:T69) -> 0
A70: האם לדעתך מלחמת יום כיפור שינתה את סיכויי הליכוד בבחירות לכנסת לעומת אלו שהיו לפני המלחמה? | AD70: f36 | AK70: =COUNTA(C70:AI70) -> 1 | AM70: =COUNTA(G70:P70,S70:T70) -> 0
A71: האם לדעתך מלחמת יום כיפור שינתה את סיכויי הרשימות הבאות: מוקד, מר"י, העולם הזה, שולמית אלוני, הפנתרים השחורים; לעומת אלו שהיו לפני המלחמה? | AD71: f37 | AK71: =COUNTA(C71:AI71) -> 1 | AM71: =COUNTA(G71:P71,S71:T71) -> 0
A72: מה לדעתך סיכויי הרשימה עבורה תצביע להיות בעלת השפעה ומשקל בכנסת הבאה? | AG72: b53 | AH72: b47 | AI72: b53 | AK72: =COUNTA(C72:AI72) -> 3 | AM72: =COUNTA(G72:P72,S72:T72) -> 0
A73: כשאת/ה חושב/ת על המשברים שישראל מתמודדת איתם כיום, עד כמה את/ ה בטוח/ה שהמדינה תוכל להשתקם מהם בכל אחד מההיבטים הבאים: מבחינה בטחונית | B73: v415
A74: כשאת/ה חושב/ת על המשברים שישראל מתמודדת איתם כיום, עד כמה את/ ה בטוח/ה שהמדינה תוכל להשתקם מהם בכל אחד מההיבטים הבאים: מבחינה כלכלית | B74: v416
A75: כשאת/ה חושב/ת על המשברים שישראל מתמודדת איתם כיום, עד כמה את/ ה בטוח/ה שהמדינה תוכל להשתקם מהם בכל אחד מההיבטים הבאים: מבחינה חברתית | B75: v417
A76: כשאת/ה חושב/ת על המשברים שישראל מתמודדת איתם כיום, עד כמה את/ ה בטוח/ה שהמדינה תוכל להשתקם מהם בכל אחד מההיבטים הבאים: מבחינת מעמד בינלואמי | B76: v418

Sheet סוגיות
A1: שאלה | B1: 2022 | C1: 2021 | D1: 2020 | E1: 43709 | F1: 43556 | G1: 2015 | H1: 2013 | I1: 2009 | J1: 2006 | K1: 2003 | L1: 2001 | M1: 1999 | N1: 1996 | O1: 1992 | P1: 1987* | Q1: 1988* | R1: 1988 | S1: 1984 | T1: 1981 - 3 | U1: 1981 - 2 | V1: 1981 - 1 | W1: 1977 - 4 | X1: 1977 - 3 | Y1: 1977 - 2 | Z1: 1977 - 1 | AA1: 1973 - 5 | AB1: 1973 - 4 | AC1: 1973 - 3 | AD1: 1973 - 2 | AE1: 1973 - 1 | AF1: 1969 - 3 | AG1: 1969 - 2 | AH1: 1969 - 1 | AJ1: מספר חזרות | AL1: ספירה 84-19 | AN1: סה"כ מעל שתי חזרות
A2: בסה"כ לדעתך, על מה היו הבחירות האחרונות בעיקר? | B2: F7 | C2: F7 | D2: E7_after | E2: D7 | F2: v7_after | G2: after_v8 | H2: a_v15 | I2: q20 | J2: d28 | M2: d21 | AJ2: =COUNTA(B2:AH2) -> 10 | AL2: =COUNTA(F2:O2,R2:S2) -> 6 | AN2: =COUNTIF(AL2:AL70,">=2") -> 13
A3: יש כל מיני דעות "על מה" היו הבחירות האחרונות. באיזו מידה אתה מסכים או לא מסכים עם כל אחד מהמשפטים הבאים: הבחירות האלה היו משאל עם על נתניהו | F3: v6A_after | G3: after_v7a | H3: a_v5A | M3: d17 | AJ3: =COUNTA(B3:AH3) -> 4 | AL3: =COUNTA(F3:O3,R3:S3) -> 4
A4: הבחירות מצביעות על חוסר אמון בנתניהו | H4: 1_v5B | AJ4: =COUNTA(B4:AH4) -> 1 | AL4: =COUNTA(F4:O4,R4:S4) -> 1
A5: הבחירות האלה היו בעיקר על עתיד הדמוקרטיה בישראל | F5: v6B_after | AJ5: =COUNTA(B5:AH5) -> 1 | AL5: =COUNTA(F5:O5,R5:S5) -> 1
A6: הבחירות מצביעות בעיקר על כך שלעם נמאס שהתקשורת נגד נתניהו | F6: v6C_after | G6: after_v7d | AJ6: =COUNTA(B6:AH6) -> 2 | AL6: =COUNTA(F6:O6,R6:S6) -> 2
A7: הבחירות היו בעיקר על איך להתמודד עם האיומים הביטחוניים שמסביבנו | F7: v6D_after | G7: after_v7f | H7: a_v12 | I7: q15 | J7: d26 | AJ7: =COUNTA(B7:AH7) -> 5 | AL7: =COUNTA(F7:O7,R7:S7) -> 5
A8: הבחירות הראו שהעם מרוצה מהמצב הכלכלי-חברתי | F8: v6E_after | AJ8: =COUNTA(B8:AH8) -> 1 | AL8: =COUNTA(F8:O8,R8:S8) -> 1
A9: הבחירות היו על מקומם של האזרחים הערבים בישראל לאור חוק הלאום | F9: v6F_after | AJ9: =COUNTA(B9:AH9) -> 1 | AL9: =COUNTA(F9:O9,R9:S9) -> 1
A10: הבחירות מצביעות על כך שהעם רוצה מפלגות גדולות | F10: v6G_after | G10: after_v7j | AJ10: =COUNTA(B10:AH10) -> 2 | AL10: =COUNTA(F10:O10,R10:S10) -> 2
A11: הבחירות מצביעות על כך שהעם רוצה ימין | F11: v6H_after | G11: after_v7k | H11: a_v7A | I11: q10 | AJ11: =COUNTA(B11:AH11) -> 4 | AL11: =COUNTA(F11:O11,R11:S11) -> 4
A12: הבחירות מצביעות על כך שהעם רוצה מרכז | H12: a_v7B | AJ12: =COUNTA(B12:AH12) -> 1 | AL12: =COUNTA(F12:O12,R12:S12) -> 1
A13: הבחירות היו בעיקר על פרשות השחיתות | F13: v6I_after | J13: d25 | AJ13: =COUNTA(B13:AH13) -> 2 | AL13: =COUNTA(F13:O13,R13:S13) -> 2
A14: הבחירות מצביעות על כך שהעם רוצה מדיניות כלכלית שתהיה חברתית יותר | G14: after_v7b | AJ14: =COUNTA(B14:AH14) -> 1 | AL14: =COUNTA(F14:O14,R14:S14) -> 1
A15: הבחירות מצביעות על כך שהעם לא רוצה שכסף ממדיניות זרות יקבע את תוצאות הבחירות | G15: after_v7c | AJ15: =COUNTA(B15:AH15) -> 1 | AL15: =COUNTA(F15:O15,R15:S15) -> 1
A16: הבחירות היו בעיקר על הנושאים המדיניים - המו"מ עם הפלסטינים והמדינה הפלסטינית | G16: after_v7e | H16: a_v9 | I16: q13 | AJ16: =COUNTA(B16:AH16) -> 3 | AL16: =COUNTA(F16:O16,R16:S16) -> 3
A17: הבחירות היו בעיקר על הגרעין האיראני | G17: after_v7g | H17: a_v11 | AJ17: =COUNTA(B17:AH17) -> 2 | AL17: =COUNTA(F17:O17,R17:S17) -> 2
A18: הבחירות היו בעיקר על יוקר המחייה ובעיות הדיור | G18: after_v7h | H18: a_v13 | AJ18: =COUNTA(B18:AH18) -> 2 | AL18: =COUNTA(F18:O18,R18:S18) -> 2
A19: הבחירות מצביעות על כך שהעם התגייס כדי שערבים לא יקבעו את תוצאות הבחירות | G19: after_v7i | AJ19: =COUNTA(B19:AH19) -> 1 | AL19: =COUNTA(F19:O19,R19:S19) -> 1
A20: הבחירות מצביעות על כך שהעם רוצה פוליטיקה אחרת ומנהיגים חדשים | H20: a_v6 | AJ20: =COUNTA(B20:AH20) -> 1 | AL20: =COUNTA(F20:O20,R20:S20) -> 1
A21: הבחירות מצביעות על כך שהעם רוצה מתונים ולא קיצונים | H21: a_v8 | AJ21: =COUNTA(B21:AH21) -> 1 | AL21: =COUNTA(F21:O21,R21:S21) -> 1
A22: הבחירות היו בעיקר על המדיניות הכלכלית והתקציב המתאימים לישראל בימים אלה | H22: a_v10 | AJ22: =COUNTA(B22:AH22) -> 1 | AL22: =COUNTA(F22:O22,R22:S22) -> 1
A23: הבחירות היו בעיקר על חלוקת הנטל ושרות צבאי או לאומי לכל | H23: a_v14 | AJ23: =COUNTA(B23:AH23) -> 1 | AL23: =COUNTA(F23:O23,R23:S23) -> 1
A24: הבחירות היו על מי מתאים להנהיג את ישראל בתקופה זו | I24: q11 | AJ24: =COUNTA(B24:AH24) -> 1 | AL24: =COUNTA(F24:O24,R24:S24) -> 1
A25: הבחירות מצביעות על כך שהציבור רוצה מועמד נקי כפיים | I25: q12 | AJ25: =COUNTA(B25:AH25) -> 1 | AL25: =COUNTA(F25:O25,R25:S25) -> 1
A26: הבחירות היו בעיקר על איזו תוכנית כלכלית תוציא את המדינה מהבוץ | I26: q14 | AJ26: =COUNTA(B26:AH26) -> 1 | AL26: =COUNTA(F26:O26,R26:S26) -> 1
A27: הבחירות היו בעיקר על יחסי יהודים-ערבים בתוך ישראל והקשר בין אזרחות לנאמנות | I27: q17 | AJ27: =COUNTA(B27:AH27) -> 1 | AL27: =COUNTA(F27:O27,R27:S27) -> 1
A28: הבחירות מצביעות על כך ש"קדימה" היא לא תופעה חולפת | I28: q16 | AJ28: =COUNTA(B28:AH28) -> 1 | AL28: =COUNTA(F28:O28,R28:S28) -> 1
A29: הבחירות מצביעות על כך שהציבור חושב שאישה מתאימה להיות ראש ממשלה | I29: q18 | AJ29: =COUNTA(B29:AH29) -> 1 | AL29: =COUNTA(F29:O29,R29:S29) -> 1
A30: הבחירות היו על המצב הכלכלי והפערים במדינה | J30: d23 | AJ30: =COUNTA(B30:AH30) -> 1 | AL30: =COUNTA(F30:O30,R30:S30) -> 1
A31: הבחירות היו על תכנית ההתנקות ועתיד ההתנחלויות | J31: d24 | AJ31: =COUNTA(B31:AH31) -> 1 | AL31: =COUNTA(F31:O31,R31:S31) -> 1
A32: הבחירות היו בעיקר מחאה נגד הממסד | J32: d27 | AJ32: =COUNTA(B32:AH32) -> 1 | AL32: =COUNTA(F32:O32,R32:S32) -> 1
A33: הבחירות מלמדות שחייבים לשנות את השיטה הנוכחית לשיטה שתביא לממשלה יציבה ל-4 שנים | I33: q19 | AJ33: =COUNTA(B33:AH33) -> 1 | AL33: =COUNTA(F33:O33,R33:S33) -> 1
A34: הבחירות היו בעיקר על היחסים בין דתיים וחילונים במדינה | M34: d15 | AJ34: =COUNTA(B34:AH34) -> 1 | AL34: =COUNTA(F34:O34,R34:S34) -> 1
A35: הנצחון של ברק מראה שהציבור חושב שהוא ישמור יותר טוב על שלטון החוק במדינה | M35: d16 | AJ35: =COUNTA(B35:AH35) -> 1 | AL35: =COUNTA(F35:O35,R35:S35) -> 1
A36: הבחירות היו בעיקר על מי ינהל טוב יותר את המו"מ עם הפלסטינים על ירושלים ועל הסדר קבע | M36: d18 | AJ36: =COUNTA(B36:AH36) -> 1 | AL36: =COUNTA(F36:O36,R36:S36) -> 1
A37: נתניהו הפסיד בעיקר בגלל האבטלה והמצב הכלכלי | M37: d19 | AJ37: =COUNTA(B37:AH37) -> 1 | AL37: =COUNTA(F37:O37,R37:S37) -> 1
A38: הנצחון של ברק על נתניהו מראה שהציבור רוצה בהמשך תהליך השלום ומוכן לפשרה עם הפלסטינים | M38: d20 | AJ38: =COUNTA(B38:AH38) -> 1 | AL38: =COUNTA(F38:O38,R38:S38) -> 1
A39: האם לדעתך ניתן או לא ניתן לראות בבחירות שהיו, משאל עם על תוכניתו של אולמרט להתנתקות נוספת ביו"ש שאמורה לקבוע את גבולות הפלסטינים? | J39: d29 | AJ39: =COUNTA(B39:AH39) -> 1 | AL39: =COUNTA(F39:O39,R39:S39) -> 1
A40: האם לדעתך הבחירה הישירה לראש הממשלה מביאה לשיטת ממשל טובה יותר או גרועה יותר למדינה? | L40: b12 | M40: c10 | N40: ccc19 | O40: i38 | AJ40: =COUNTA(B40:AH40) -> 4 | AL40: =COUNTA(F40:O40,R40:S40) -> 4
A41: האם לדעתך הבחירות המקדימות (פריימריז) מביאות לשיטת ממשל טובה יותר או גרועה יותר במדינה? | N41: ccc21 | AJ41: =COUNTA(B41:AH41) -> 1 | AL41: =COUNTA(F41:O41,R41:S41) -> 1
A42: האם השתתפת בפריימריז (בחירות מקדימות)? | N42: ccc22 | AJ42: =COUNTA(B42:AH42) -> 1 | AL42: =COUNTA(F42:O42,R42:S42) -> 1
A43: מבין הנושאים הבאים, איזה נושא לדעתך עומד במרכז מערכת הבחירות? | I43: v133 | J43: b60 | AJ43: =COUNTA(B43:AH43) -> 2 | AL43: =COUNTA(F43:O43,R43:S43) -> 2
A44: כידוע לך נבחרים כעת חברי כנסת בבחירות כלל ארציות. יש הצעה להנהיג שיטה לפיה חלק מהם ייבחרו בבחירות אזוריות. האם אתה חושב שצריך להמשיך בשיטה הקיימת או לשנות את השיטה? | Q44: c14 | R44: g17 | U44: a62 | AJ44: =COUNTA(B44:AH44) -> 3 | AL44: =COUNTA(F44:O44,R44:S44) -> 1
A45: באיזו מידה ישפיע או לא ישפיע לדעתך הנושא של פשרה טריטוריאלית על תוצאות הבחירות הקרובות לכנסת? | S45: v13 | V45: v10 | AJ45: =COUNTA(B45:AH45) -> 2 | AL45: =COUNTA(F45:O45,R45:S45) -> 1
A46: לאחרונה שמענו הרבה על אינפלציה בארץ. באיזו מידה אתה חושב שנושא זה ישפיע על תוצאות הבחירות הקורובת לכנסת? | S46: v17 | V46: v13 | AJ46: =COUNTA(B46:AH46) -> 2 | AL46: =COUNTA(F46:O46,R46:S46) -> 1
A47: באיזו מידה ישפיע או לא ישפיע לדעתך נושא השטחים על תוצאות הבחירות הקרובות לכנסת? | Q47: b54 | R47: f56 | Z47: v14 | AE47: v50 | AJ47: =COUNTA(B47:AH47) -> 4 | AL47: =COUNTA(F47:O47,R47:S47) -> 1
A48: באיזו מידה ישפיע או לא ישפיע לדעתך הנושא הכלכלי על תוצאות הבחירות הקרובות לכנסת? | Q48: b64 | R48: f67 | Z48: v23 | AE48: v42 | AJ48: =COUNTA(B48:AH48) -> 4 | AL48: =COUNTA(F48:O48,R48:S48) -> 1
A49: באיזו מידה ישפיע או לא ישפיע לדעתך הנושא הבטחוני על תוצאות הבחירות הקרובות לכנסת? | T49: b11 | AJ49: =COUNTA(B49:AH49) -> 1 | AL49: =COUNTA(F49:O49,R49:S49) -> 0
A50: לאחרונה שמענו הרבה על תכנית ארידור. באיזו מידה אתה חושב שנושא זה ישפיע על תוצאות הבחירות הקרובות לכנסת? | T50: b25 | AJ50: =COUNTA(B50:AH50) -> 1 | AL50: =COUNTA(F50:O50,R50:S50) -> 0
A51: האם ענייני הבטחון צריכים או לא צריכים להיות נושא במערכת הבחירות לכנסת? | U51: a8 | AJ51: =COUNTA(B51:AH51) -> 1 | AL51: =COUNTA(F51:O51,R51:S51) -> 0
A52: יש האומרים שדיין הוא מנהיג זקן שטעה יותר מדי (יום כיפור) ואין לתת לו לחזור לשלטון ויש כאלה האומרים שיש לדיין רעיונות טובים והוא סוג המנהיג שחסר לנו כעת, מה דעתך בנושא זה? | V52: v107 | AJ52: =COUNTA(B52:AH52) -> 1 | AL52: =COUNTA(F52:O52,R52:S52) -> 0
A53: באיזו מידה הוכיח הליכוד כי הוא מסוגל או שאינו מסוגל להיות תחליף למערך בשלטון? | U53: a118 | V53: v109 | AB53: g51 | AC53: f46 | AD53: d38 | AE53: b8 | AJ53: =COUNTA(B53:AH53) -> 6 | AL53: =COUNTA(F53:O53,R53:S53) -> 0
A54: לאחרונה שמענו הרבה על שחיתות בקרב אנשי ציבור. באיזו מידה אתה חושב שנושא זה ישפיע על תוצאות הבחירות? | Z54: v18 | AD54: d2 | AJ54: =COUNTA(B54:AH54) -> 2 | AL54: =COUNTA(F54:O54,R54:S54) -> 0
A55: יש הטוענים שפרישת מפ"ם תשפיע על תוצאות הבחירות, ויש הטוענים שלא תשפיע. מה דעתך? | Z55: v92 | AJ55: =COUNTA(B55:AH55) -> 1 | AL55: =COUNTA(F55:O55,R55:S55) -> 0
A56: האם ההתמודדות הפנימית במפלגת העבודה חיזקה או החלישה את המפלגה? | Z56: v93 | AJ56: =COUNTA(B56:AH56) -> 1 | AL56: =COUNTA(F56:O56,R56:S56) -> 0
A57: האם ההתמודדות הפנימית במפלגת העבודה חיזקה את הדמוקרטיה במפלגה או פגעה בדמוקרטיה? | Z57: v94 | AJ57: =COUNTA(B57:AH57) -> 1 | AL57: =COUNTA(F57:O57,R57:S57) -> 0
A58: באיזו מידה אתה מעריך את הראיון שנתן חיים בר-לב לעיתונות חוץ כמעשה חיובי או שלילי? | AC58: f11 | AJ58: =COUNTA(B58:AH58) -> 1 | AL58: =COUNTA(F58:O58,R58:S58) -> 0
A59: האם לדעתך יש לקיים את הבחירות לכנסת ב-31 לדצמבר או לדחות אותן למועד מאוחר יותר? | AC59: f12 | AJ59: =COUNTA(B59:AH59) -> 1 | AL59: =COUNTA(F59:O59,R59:S59) -> 0
A60: לכמה זמן, לדעתך, צריך לדחות את הבחירות? | AC60: f13 | AJ60: =COUNTA(B60:AH60) -> 1 | AL60: =COUNTA(F60:O60,R60:S60) -> 0
A61: האם שמעת על הליכוד החדש? | AD61: d33 | AJ61: =COUNTA(B61:AH61) -> 1 | AL61: =COUNTA(F61:O61,R61:S61) -> 0
A62: האם ידוע לך מי הן המפלגות המרכיבות את הליכוד הזה? | AD62: d34 | AJ62: =COUNTA(B62:AH62) -> 1 | AL62: =COUNTA(F62:O62,R62:S62) -> 0
A63: האם לדעתך רצוי שהמפלגות אלה ירוצו לבחירות לכנסת ביחד? | AD63: d35 | AJ63: =COUNTA(B63:AH63) -> 1 | AL63: =COUNTA(F63:O63,R63:S63) -> 0
A64: לאחרונה נידונו בכנסת הצעה לשינוי שיטת הבחירות, עד כמה ידוע לך מהי הצעה זו? | Z64: v26 | AJ64: =COUNTA(B64:AH64) -> 1 | AL64: =COUNTA(F64:O64,R64:S64) -> 0
A65: ישראל הולכת עכשיו בפעם השלישית לבחירות בתוך פחות משנה. מבין הדברים הבאים, מה הכי מפריע לך, אם בכלל, במצב שנוצר: | D65: v501 | AJ65: =COUNTA(B65:AH65) -> 1 | AL65: =COUNTA(F65:O65,R65:S65) -> 0
A66: ישראל הולכת לבחירות בפעם הרביעית בתוך פחות משנתיים. מבין הדברים הבאים, מהי לדעתך הסיבה המרכזית לכך? | B66: v601 | C66: v601 | AJ66: =COUNTA(B66:AH66) -> 2 | AL66: =COUNTA(F66:O66,R66:S66) -> 0
A67: מה דעתך על הדרך שבה הממשלה מטפלת במשבר הקורונה? | C67: v604 | AJ67: =COUNTA(B67:AH67) -> 1 | AL67: =COUNTA(F67:O67,R67:S67) -> 0
A68: מי לדעתך יטפל יותר טוב במשבר הקורונה? | C68: v607 | AJ68: =COUNTA(B68:AH68) -> 1 | AL68: =COUNTA(F68:O68,R68:S68) -> 0
A69: באיזו מידה אתה תומך או מתנגד לצירוף של שרים מטעם מפלגות ערביות לממשלה? | L69: b13 | M69: c11 | N69: ccc20 | AJ69: =COUNTA(B69:AH69) -> 3 | AL69: =COUNTA(F69:O69,R69:S69) -> 3
A70: לגבי שיתוף פעולה עם מפלגות ערביות בהקמת הממשלה, האם אתה: | B70: N1 | C70: N1 | AJ70: =COUNTA(B70:AH70) -> 2 | AL70: =COUNTA(F70:O70,R70:S70) -> 0
A71: מה דעתך על השתתפולה של רע"מ בראשות מנסור עבאס בקואליציה האחרונה? | B71: v705

Sheet כלכלה-חברה
A1: שאלה | B1: 2025 | C1: 2022 | D1: 2021 | E1: 2020 | F1: 43709 | G1: 43556 | H1: 2015 | I1: 2013 | J1: 2009 | K1: 2006 | L1: 2003 | M1: 2001 | N1: 1999 | O1: 1996 | P1: 1992 | Q1: 1987* | R1: 1988* | S1: 1988 | T1: 1984 | U1: 1981 - 3 | V1: 1981 - 2 | W1: 1981 - 1 | X1: 1977 - 4 | Y1: 1977 - 3 | Z1: 1977 - 2 | AA1: 1977 - 1 | AB1: 1973 - 5 | AC1: 1973 - 4 | AD1: 1973 - 3 | AE1: 1973 - 2 | AF1: 1973 - 1 | AG1: 1969 - 3 | AH1: 1969 - 2 | AI1: 1969 - 1 | AK1: מספר חזרות | AM1: ספירה 84-19 | AO1: סה"כ מעל שתי חזרות
A2: בקשר למבנה החיים הכלכליים בארץ, האם אתה תומך יותר בגישה הסוציאליסטית או בגישה הקפיטליסטית? | B2: v20 | C2: v20 | D2: v20 | E2: v20 | F2: c20 | G2: v20 | H2: v32 | I2: v31 | J2: v41 | K2: a45 | L2: a77 | M2: a55 | N2: v56 | O2: c70 | P2: a52 | R2: b61 | S2: f64 | T2: v27 | W2: v114 | AA2: v97 | AG2: c26 | AH2: c33 | AK2: =COUNTA(C2:AI2) -> 21 | AM2: =COUNTA(G2:P2,S2:T2) -> 12 | AO2: =COUNTIF(AM2:AM118,">=2") -> 32
A3: לעמדה של מי אתה קרוב יותר בכל אחד מהנושאים הבאים: כלכלה | O3: cc20 | T3: v21 | U3: b27 | V3: a131 | W3: v115 | Z3: a5 | AK3: =COUNTA(C3:AI3) -> 6 | AM3: =COUNTA(G3:P3,S3:T3) -> 2
A4: איזו מפלגה משקפת בצורה הטובה ביותר את עמדותיך בנושא כלכלה? | P4: a55 | R4: b66 | S4: f69 | T4: v20 | W4: v16 | AA4: v25 | AE4: c59 | AF4: v44 | AK4: =COUNTA(C4:AI4) -> 9 | AM4: =COUNTA(G4:P4,S4:T4) -> 3
A5: מי לדעתך יטפל טוב יותר בבעיית הכלכלה והחברה של המדינה? | C5: v47 | E5: v47 | G5: v47 | H5: v57 | AK5: =COUNTA(C5:AI5) -> 4 | AM5: =COUNTA(G5:P5,S5:T5) -> 2
A6: מי לדעתך יטפל יותר טוב בבעיות הכלכליות של המדינה? | I6: v48 | J6: v72a | K6: a78 | L6: a47 | M6: a64 | N6: i3 | O6: cc23 | P6: a57 | R6: b68 | S6: f71 | T6: v23 | U6: b18 | AK6: =COUNTA(C6:AI6) -> 12 | AM6: =COUNTA(G6:P6,S6:T6) -> 10
A7: ומי במקום השני? | J7: v72b | K7: a79 | N7: i4 | AK7: =COUNTA(C7:AI7) -> 3 | AM7: =COUNTA(G7:P7,S7:T7) -> 3
A8: מי לדעתך יטפל יותר טוב בבעיות החברתיות של המדינה? | I8: v49 | J8: v73a | K8: a80 | AK8: =COUNTA(C8:AI8) -> 3 | AM8: =COUNTA(G8:P8,S8:T8) -> 3
A9: ומי במקום השני? | J9: v73b | K9: a81 | AK9: =COUNTA(C9:AI9) -> 2 | AM9: =COUNTA(G9:P9,S9:T9) -> 2
A10: האם יש מפלגה שרחוקה בהרבה מעמדתך בנושא הכלכלי-חברתי? | AF10: v45 | AK10: =COUNTA(C10:AI10) -> 1 | AM10: =COUNTA(G10:P10,S10:T10) -> 0
A11: האם לדעתך המצב הכלכלי במדינה ב-4 השנים האחרונות השתפר, לא השתנה או נעשה גרוע יותר? | B11: v9 | C11: v9 | G11: v9 | H11: v9 | I11: v9 | J11: v9 | K11: a10 | N11: v8 | AF11: v3 | AK11: =COUNTA(C11:AI11) -> 8 | AM11: =COUNTA(G11:P11,S11:T11) -> 6
A12: ומה לגבי מצבך האישי; האם היית אומר שב-4 השנים האחרונות מצבך האישי: | B12: v10 | C12: v10 | G12: v10 | H12: v10 | I12: v10 | J12: v10 | K12: a11 | L12: a10 | N12: v9 | AF12: v2 | AK12: =COUNTA(C12:AI12) -> 9 | AM12: =COUNTA(G12:P12,S12:T12) -> 7
A13: באיזו מידה אה מסכים או לא מסכים למשפטים הבאים? אנשים עם הכנסה גבוהה צריכים לשלם יותר מיסים ממה שהם משלמים היום | G13: v23 | H13: v48 | I13: v37 | J13: v51 | AK13: =COUNTA(C13:AI13) -> 4 | AM13: =COUNTA(G13:P13,S13:T13) -> 4
A14: יש החושבים כי על הממשלה לדאוג שלכל אדם תהיה עבודה ורמת חיים סבירה. אחרים חושבים שעל הממשלה לא להתערב ולתת לכל אדם להסתדר בעצמו. ומה דעתך? | C14: v702 | H14: v22 | I14: v23 | J14: v34 | K14: a38 | AK14: =COUNTA(C14:AI14) -> 5 | AM14: =COUNTA(G14:P14,S14:T14) -> 4
A15: האם אתה מוכן או לא מוכן שיעלו בארץ את המסים, כלומר שגם אתה תשלם יותר, כדי לטפל בבעיות השונות שהמדינה ניצבת בפניהן? | H15: v72 | I15: v71 | J15: v98 | K15: b25 | L15: a64 | N15: i40 | O15: cc27 | P15: a63 | Q15: v101 | AK15: =COUNTA(C15:AI15) -> 9 | AM15: =COUNTA(G15:P15,S15:T15) -> 8
A16: לגבי כל אחד מהסעיפים הבאים, ציין האם לדעתך על המדינה להוציא יותר כספים, פחות כספים או כמו עכשיו: חינוך | H16: v73 | I16: v72 | J16: v99 | K16: b26 | L16: a65 | N16: i41 | O16: cc28 | P16: a65 | AK16: =COUNTA(C16:AI16) -> 8 | AM16: =COUNTA(G16:P16,S16:T16) -> 8
A17: מוסדות דת וישיבות | H17: v74 | I17: v73 | J17: v101 | K17: b28 | L17: a67 | N17: i43 | O17: cc30 | P17: a67 | AK17: =COUNTA(C17:AI17) -> 8 | AM17: =COUNTA(G17:P17,S17:T17) -> 8
A18: בריאות | H18: v75 | I18: v74 | J18: v102 | K18: b29 | L18: a68 | N18: i44 | O18: cc31 | P18: a68 | AK18: =COUNTA(C18:AI18) -> 8 | AM18: =COUNTA(G18:P18,S18:T18) -> 8
A19: משטרה | H19: v76 | I19: v75 | AK19: =COUNTA(C19:AI19) -> 2 | AM19: =COUNTA(G19:P19,S19:T19) -> 2
A20: צבא ובטחון | H20: v77 | I20: v76 | J20: v103 | K20: b30 | L20: a69 | N20: i45 | O20: cc32 | P20: a69 | AK20: =COUNTA(C20:AI20) -> 8 | AM20: =COUNTA(G20:P20,S20:T20) -> 8
A21: קיצבאות (אבטלה, זקנה, נכות, ילדים) | H21: v78 | J21: v104 | K21: b31 | AK21: =COUNTA(C21:AI21) -> 3 | AM21: =COUNTA(G21:P21,S21:T21) -> 3
A22: קיצבאות אבטלה | I22: v77 | L22: a70 | N22: i47 | O22: cc34 | P22: a71 | AK22: =COUNTA(C22:AI22) -> 5 | AM22: =COUNTA(G22:P22,S22:T22) -> 5
A23: קיצבאות זקנה | I23: v78 | AK23: =COUNTA(C23:AI23) -> 1 | AM23: =COUNTA(G23:P23,S23:T23) -> 1
A24: קיצבאות ילדים | I24: v79 | AK24: =COUNTA(C24:AI24) -> 1 | AM24: =COUNTA(G24:P24,S24:T24) -> 1
A25: התיישבות בשטחים | H25: v79 | I25: v80 | J25: v105 | K25: b32 | L25: a71 | N25: i48 | O25: cc35 | P25: a72 | AK25: =COUNTA(C25:AI25) -> 8 | AM25: =COUNTA(G25:P25,S25:T25) -> 8
A26: המגזר הערבי | H26: v80 | I26: v81 | J26: v106 | K26: b33 | L26: a72 | N26: i49 | O26: cc36 | AK26: =COUNTA(C26:AI26) -> 7 | AM26: =COUNTA(G26:P26,S26:T26) -> 7
A27: יצירת מקומות תעסוקה | I27: v82 | J27: v107 | K27: b34 | L27: a73 | N27: i50 | O27: cc37 | P27: a73 | AK27: =COUNTA(C27:AI27) -> 7 | AM27: =COUNTA(G27:P27,S27:T27) -> 7
A28: פתרונות לבעיית הדיור | I28: v83 | AK28: =COUNTA(C28:AI28) -> 1 | AM28: =COUNTA(G28:P28,S28:T28) -> 1
A29: שמירת הטבע והאקולוגיה | J29: v100 | K29: b27 | L29: a66 | N29: i42 | O29: cc29 | P29: a66 | AK29: =COUNTA(C29:AI29) -> 6 | AM29: =COUNTA(G29:P29,S29:T29) -> 6
A30: כבישים ותאונות דרכים | J30: v108 | K30: b35 | N30: i51 | O30: cc38 | AK30: =COUNTA(C30:AI30) -> 4 | AM30: =COUNTA(G30:P30,S30:T30) -> 4
A31: קליטת עליה | N31: i46 | O31: cc33 | P31: a70 | AK31: =COUNTA(C31:AI31) -> 3 | AM31: =COUNTA(G31:P31,S31:T31) -> 3
A32: האם אתה מסכים או לא מסכים לכך שיש להעביר כספים מתקציב הבטחון לנושאים חברתיים, כמו חינוך ובריאות? | H32: v81 | AK32: =COUNTA(C32:AI32) -> 1 | AM32: =COUNTA(G32:P32,S32:T32) -> 1
A33: האם מוצדק או לא מוצדק לדעתך לקצץ בשירותים חברתיים כדי להגדיל את תקציב הבטחון? | Q33: v109 | AK33: =COUNTA(C33:AI33) -> 1 | AM33: =COUNTA(G33:P33,S33:T33) -> 0
A34: האם תמכת או השתתפת במחאה החברתית של קיץ 2011? | H34: v90 | I34: v98_B | AK34: =COUNTA(C34:AI34) -> 2 | AM34: =COUNTA(G34:P34,S34:T34) -> 2
A35: מדברים היום הרבה גם על נושאי כלכלה וחברה. כיצד היית מדרג את עצמך על פני הרצף הכלכלי-חברתי, כאשר 0 משמעו גישה סוציאל-דמוקרטית; 10 משמעו גישה קפיטליסטית ו-5 משמעו אמצע | I35: v69 | AK35: =COUNTA(C35:AI35) -> 1 | AM35: =COUNTA(G35:P35,S35:T35) -> 1
A36: יש הטוענים שאין מספיק שוויון חברתי וכלכלי בארץ. באיזו מידה אתה מסכים או לא מסכים עם דעה זו? | N36: i52 | O36: cc39 | P36: a74 | AK36: =COUNTA(C36:AI36) -> 3 | AM36: =COUNTA(G36:P36,S36:T36) -> 3
A37: באיזו מידה יש לדעתך אפליה עדתית בישראל? | N37: i53 | O37: cc40 | P37: i36 | R37: c12 | S37: g15 | T37: a16 | AK37: =COUNTA(C37:AI37) -> 6 | AM37: =COUNTA(G37:P37,S37:T37) -> 5
A38: באיזו מידה נפגעת באופן אישי מאפליה עדתית? | N38: i54 | O38: cc41 | P38: i37 | R38: c13 | S38: g16 | T38: a17 | AK38: =COUNTA(C38:AI38) -> 6 | AM38: =COUNTA(G38:P38,S38:T38) -> 5
A39: האם לדעתך יש לקצץ את תקציב הבטחון, להשאירו כמו שהוא או להגדיל אותו? | Q39: v107 | AK39: =COUNTA(C39:AI39) -> 1 | AM39: =COUNTA(G39:P39,S39:T39) -> 0
A40: אם המצב הכלכלי יחמיר ביותר והמשק יהיה בשפל, האם אז יש לקצץ את תקציב הבטחון, להשאירו כמו שהוא או להגדילו? | Q40: v108 | AK40: =COUNTA(C40:AI40) -> 1 | AM40: =COUNTA(G40:P40,S40:T40) -> 0
A41: איזה מהמשפטים הבאים משקף בצורה הטובה ביותר את עמדתך לגבי החברה בה אנו חיים? | Q41: a34 | AK41: =COUNTA(C41:AI41) -> 1 | AM41: =COUNTA(G41:P41,S41:T41) -> 0
A42: האם אתה בעד או נגד שינוי הסטטוס של ישובים ערבים גדולים בארץ ממועצות מקומיות לערים? | R42: c29 | S42: g42 | AK42: =COUNTA(C42:AI42) -> 2 | AM42: =COUNTA(G42:P42,S42:T42) -> 1
A43: כמה אחוזים לדעתך בציבור היהודי מתנגדים לשינוי הסטטוס של ישובים ערבים גדולים לערים? | R43: c30 | S43: g43 | AK43: =COUNTA(C43:AI43) -> 2 | AM43: =COUNTA(G43:P43,S43:T43) -> 1
A44: לפי מה נתת את הערכה הזו? איך ידעת להגיד לי את האחוז הזה? האם היה משהו שחשבת עליו שעזר לך לתת את הערכה? | R44: c31 | S44: g45 | AK44: =COUNTA(C44:AI44) -> 2 | AM44: =COUNTA(G44:P44,S44:T44) -> 1
A45: האם לדעתך נטל השירות הצבאי במילואים מתחלק באופן צודק או לא צודק בין אנשי המילואים? | R45: c38 | S45: g57 | AK45: =COUNTA(C45:AI45) -> 2 | AM45: =COUNTA(G45:P45,S45:T45) -> 1
A46: כמה אחוזים בציבור חושבים שנטל השירות הצבאי במילואים מתחלק באופן לא צודק? | R46: c39 | S46: g58 | AK46: =COUNTA(C46:AI46) -> 2 | AM46: =COUNTA(G46:P46,S46:T46) -> 1
A47: לפי מה נתת את הערכה הזו? איך ידעת להגיד לי את האחוז הזה? האם היה משהו שחשבת עליו שעזר לך לתת את הערכה? | R47: c40 | S47: g60 | AK47: =COUNTA(C47:AI47) -> 2 | AM47: =COUNTA(G47:P47,S47:T47) -> 1
A48: מהי דעתך על הדרך בה מטפלת הממשלה בבעיות הכלכליות של המדינה? | T48: v16 | U48: b15 | W48: v12 | AA48: v20 | AK48: =COUNTA(C48:AI48) -> 4 | AM48: =COUNTA(G48:P48,S48:T48) -> 1
A49: איזו משתי המפלגות הגדולות אחראית יותר לדעתך לכל אחת מהתופעות הבאות בארץ: אלימות | T49: a19 | AK49: =COUNTA(C49:AI49) -> 1 | AM49: =COUNTA(G49:P49,S49:T49) -> 1
A50: איזו משתי המפלגות הגדולות אחראית יותר לדעתך לכל אחת מהתופעות הבאות בארץ: ירידה מהארץ | T50: a20 | AK50: =COUNTA(C50:AI50) -> 1 | AM50: =COUNTA(G50:P50,S50:T50) -> 1
A51: איזו משתי המפלגות הגדולות אחראית יותר לדעתך לכל אחת מהתופעות הבאות בארץ: אינפלציה גבוהה | T51: a21 | AK51: =COUNTA(C51:AI51) -> 1 | AM51: =COUNTA(G51:P51,S51:T51) -> 1
A52: איזו משתי המפלגות הגדולות אחראית יותר לדעתך לכל אחת מהתופעות הבאות בארץ: מוסר ירוד (שחיתות) | T52: a22 | AK52: =COUNTA(C52:AI52) -> 1 | AM52: =COUNTA(G52:P52,S52:T52) -> 1
A53: איזו משתי המפלגות הגדולות אחראית יותר לדעתך לכל אחת מהתופעות הבאות בארץ: פשע במדינה | T53: a23 | AK53: =COUNTA(C53:AI53) -> 1 | AM53: =COUNTA(G53:P53,S53:T53) -> 1
A54: איזו משתי המפלגות הגדולות אחראית יותר לדעתך לכל אחת מהתופעות הבאות בארץ: פער עדתי | T54: a24 | AK54: =COUNTA(C54:AI54) -> 1 | AM54: =COUNTA(G54:P54,S54:T54) -> 1
A55: באיזו מידה לדעתך מקום עבודתך בסך הכל טוב יותר או פחות טוב ממקומות עבודה אחרים באותו ענף? | T55: a61 | AK55: =COUNTA(C55:AI55) -> 1 | AM55: =COUNTA(G55:P55,S55:T55) -> 1
A56: באיזו מידה ההנהלה המקומית במקום עבודתך מתחשבת או לא מתחשבת בעובדים? | T56: a62 | AK56: =COUNTA(C56:AI56) -> 1 | AM56: =COUNTA(G56:P56,S56:T56) -> 1
A57: אם יש הנהלה ארצית, באיזו מידה ההנהלה הארצית של החברה מתחשבת או לא מחשבת בעובדים? | T57: a63 | AK57: =COUNTA(C57:AI57) -> 1 | AM57: =COUNTA(G57:P57,S57:T57) -> 1
A58: באיזו מידה תנאי העבודה והשכר במקום עבודתך טובים יותר או פחות ממקומות עבודה דומים באותו ענף? | T58: a64 | AK58: =COUNTA(C58:AI58) -> 1 | AM58: =COUNTA(G58:P58,S58:T58) -> 1
A59: עד כמה ברורה לך התכנית של שר האוצר הנוכחי, יורם ארידור? | U59: b19 | V59: a125 | AK59: =COUNTA(C59:AI59) -> 2 | AM59: =COUNTA(G59:P59,S59:T59) -> 0
A60: עד כמה ברורה לך התכנית הכלכלית של מועמד המערך לתפקיד שר האוצר, פרופ' חיים בן שחר? | U60: b20 | V60: a126 | AK60: =COUNTA(C60:AI60) -> 2 | AM60: =COUNTA(G60:P60,S60:T60) -> 0
A61: עד כמה התכנית הכלכלית של יורם ארידור עוזרת לאנשים כמוך? | U61: b21 | V61: a127 | W61: v100 | AK61: =COUNTA(C61:AI61) -> 3 | AM61: =COUNTA(G61:P61,S61:T61) -> 0
A62: עד כמה התכנית הכלכלית של פרופ' חיים בן שחר עוזרת לאנשים כמוך? | U62: b22 | V62: a128 | AK62: =COUNTA(C62:AI62) -> 2 | AM62: =COUNTA(G62:P62,S62:T62) -> 0
A63: עד כמה התכנית הכלכלית של יורם ארידור עוזרת לכלכלה ולמשק של מדינת ישראל? | U63: b23 | V63: a129 | AK63: =COUNTA(C63:AI63) -> 2 | AM63: =COUNTA(G63:P63,S63:T63) -> 0
A64: עד כמה התכנית הכלכלית של פרופ' חיים בן שחר עוזרת לכלכלה ולמשק של מדינת ישראל? | U64: b24 | V64: a130 | AK64: =COUNTA(C64:AI64) -> 2 | AM64: =COUNTA(G64:P64,S64:T64) -> 0
A65: באיזו מידה תצליח או לא תצליח מדיניותו של השר ארידור לשפר את המצב הכלכלי של המדינה? | W65: v97 | AK65: =COUNTA(C65:AI65) -> 1 | AM65: =COUNTA(G65:P65,S65:T65) -> 0
A66: אם הליכוד יהיו בשלטון לאחר הבחירות, מהם לדעתך הסיכויים לכך שהמדיניות הכלכלית שהנהיג השר ארידור תמשך או לא תמשך? | W66: v98 | AK66: =COUNTA(C66:AI66) -> 1 | AM66: =COUNTA(G66:P66,S66:T66) -> 0
A67: לאיזו שכבה בציבור עוזרת ביותר לדעתך המדיניות הכלכלית החדשה של השר ארידור? | W67: v99 | AK67: =COUNTA(C67:AI67) -> 1 | AM67: =COUNTA(G67:P67,S67:T67) -> 0
A68: האם קנית לאחרונה או שיש בכוונתך לקנות בזמן הקרוב מכונית, ריהוט לבית, טלוויזיה צבעונית או מכשירי חשמל אחרים שהוזלו במסגרת מדיניות האוצר? | W68: v101 | AK68: =COUNTA(C68:AI68) -> 1 | AM68: =COUNTA(G68:P68,S68:T68) -> 0
A69: על סולם 1-10, עד כמה את קרוב או רחוק בנושאי כלכלה-חברה מהמפלגות הבאות: העבודה | L69: a41 | AK69: =COUNTA(C69:AI69) -> 1 | AM69: =COUNTA(G69:P69,S69:T69) -> 1
A70: על סולם 1-10, עד כמה את קרוב או רחוק בנושאי כלכלה-חברה מהמפלגות הבאות: הליכוד | L70: a42 | AK70: =COUNTA(C70:AI70) -> 1 | AM70: =COUNTA(G70:P70,S70:T70) -> 1
A71: על סולם 1-10, עד כמה את קרוב או רחוק בנושאי כלכלה-חברה מהמפלגות הבאות: שינוי | L71: a43 | AK71: =COUNTA(C71:AI71) -> 1 | AM71: =COUNTA(G71:P71,S71:T71) -> 1
A72: על סולם 1-10, עד כמה אתה קרוב או רחוק בנושאי כלכלה-חברה מ: בנימין נתניהו | N72: v74 | AK72: =COUNTA(C72:AI72) -> 1 | AM72: =COUNTA(G72:P72,S72:T72) -> 1
A73: על סולם 1-10, עד כמה אתה קרוב או רחוק בנושאי כלכלה-חברה מ: אהוד ברק | N73: v75 | AK73: =COUNTA(C73:AI73) -> 1 | AM73: =COUNTA(G73:P73,S73:T73) -> 1
A74: על סולם 1-10, עד כמה אתה קרוב או רחוק בנושאי כלכלה-חברה מ: איציק מרדכי | N74: v76 | AK74: =COUNTA(C74:AI74) -> 1 | AM74: =COUNTA(G74:P74,S74:T74) -> 1
A75: על סולם 1-10, עד כמה אתה קרוב או רחוק בנושאי כלכלה-חברה מ: בני בגין | N75: v77 | AK75: =COUNTA(C75:AI75) -> 1 | AM75: =COUNTA(G75:P75,S75:T75) -> 1
A76: על סולם 1-10, עד כמה אתה קרוב או רחוק בנושאי כלכלה-חברה מ: עזמי בשארה | N76: v78 | AK76: =COUNTA(C76:AI76) -> 1 | AM76: =COUNTA(G76:P76,S76:T76) -> 1
A77: איפה עומדת המדינה, לדעתך מבחינה כלכלית היום? | U77: b73 | W77: v33 | AH77: b4 | AI77: a47 | AK77: =COUNTA(C77:AI77) -> 4 | AM77: =COUNTA(G77:P77,S77:T77) -> 0
A78: ולפני ארבע שנים, מה היה מצב המדינה מבחינה כלכלית? | U78: b74 | W78: v34 | AH78: b5 | AI78: a48 | AK78: =COUNTA(C78:AI78) -> 4 | AM78: =COUNTA(G78:P78,S78:T78) -> 0
A79: ובעוד ארבע שנים, מה יהיה מצב המדינה במבחינה כלכלית? | U79: b75 | W79: v35 | AH79: b6 | AI79: a49 | AK79: =COUNTA(C79:AI79) -> 4 | AM79: =COUNTA(G79:P79,S79:T79) -> 0
A80: איפה עומדת המדינה לדעתך מבחינת המצב החברתי כיום? | AI80: a54 | AK80: =COUNTA(C80:AI80) -> 1 | AM80: =COUNTA(G80:P80,S80:T80) -> 0
A81: ולפני ארבע שנים, מה היה מצב המדינה מבחינת המצב החברתי? | AI81: a55 | AK81: =COUNTA(C81:AI81) -> 1 | AM81: =COUNTA(G81:P81,S81:T81) -> 0
A82: ובעוד ארבע שנים, מה יהיה מצב המדינה מבחינ המצב החברתי? | AI82: a56 | AK82: =COUNTA(C82:AI82) -> 1 | AM82: =COUNTA(G82:P82,S82:T82) -> 0
A83: האם תצביע בבחירות הקרובות להסתדרות? | AE83: d50 | AK83: =COUNTA(C83:AI83) -> 1 | AM83: =COUNTA(G83:P83,S83:T83) -> 0
A84: עבור מי הצבעת בבחירות האחרונות להסתדרות? | O84: ccc41 | T84: a46 | U84: b124 | V84: a135 | W84: v133 | X84: c18 | AC84: g57 | AD84: f51 | AG84: c10 | AH84: b82 | AK84: =COUNTA(C84:AI84) -> 10 | AM84: =COUNTA(G84:P84,S84:T84) -> 2
A85: ולמי הצבעת בבחירות להסתדרות במערכת הקודמת לזו האחרונה? | X85: c17 | AK85: =COUNTA(C85:AI85) -> 1 | AM85: =COUNTA(G85:P85,S85:T85) -> 0
A86: מה הסיבה העיקרית שהצבעת עבור רשימה זו? | V86: a137 | AK86: =COUNTA(C86:AI86) -> 1 | AM86: =COUNTA(G86:P86,S86:T86) -> 0
A87: וסיבה נוספת בגללה הצבעת עבור רשימה זו? | V87: a138 | AK87: =COUNTA(C87:AI87) -> 1 | AM87: =COUNTA(G87:P87,S87:T87) -> 0
A88: מה הסיבה העיקרית שבגלל לא השתתפת בבחירות להסתדרות? | V88: a139 | AE88: d52 | AH88: b84 | AK88: =COUNTA(C88:AI88) -> 3 | AM88: =COUNTA(G88:P88,S88:T88) -> 0
A89: באיזה אופן מסע הבחירות השפיע על החלטתך איך להצביע בבחירות להסתדרות? | AH89: b83 | AK89: =COUNTA(C89:AI89) -> 1 | AM89: =COUNTA(G89:P89,S89:T89) -> 0
A90: מי משתי המפלגות ניצחה לדעתך, בבחירות להסתדרות - המערך או הליכוד? | U90: b122 | V90: a134 | AK90: =COUNTA(C90:AI90) -> 2 | AM90: =COUNTA(G90:P90,S90:T90) -> 0
A91: להסתדרות (באמצעות חברת עובדים) יש מפעלים כלכליים כמו כור, סולל-בונה, סופרמרקטים וכו'. האם לדעתך זה בסדר או לא בסדר שיש להסתדרות מפעלים כלכליים? | R91: b62 | S91: f65 | T91: v26 | AF91: v65 | AK91: =COUNTA(C91:AI91) -> 4 | AM91: =COUNTA(G91:P91,S91:T91) -> 2
A92: האם אתה מסכים או שאינך מסכים שההסתדרות תהיה גם בעלת מפעלים וגם נציגת העובדים? | W92: v128 | AK92: =COUNTA(C92:AI92) -> 1 | AM92: =COUNTA(G92:P92,S92:T92) -> 0
A93: באיזו מידה אתה מסכים ליוזמות תעשיתיות וניהול מפעלים ע"י ההסתדרות? | AI93: b13 | AK93: =COUNTA(C93:AI93) -> 1 | AM93: =COUNTA(G93:P93,S93:T93) -> 0
A94: אילו היו מתקיימות היום הבחירות להסתדרות עבור איזו רשימה היית מצביע? | W94: v131 | AE94: d51 | AK94: =COUNTA(C94:AI94) -> 2 | AM94: =COUNTA(G94:P94,S94:T94) -> 0
A95: באיזו מידה ממשלה בראשות הליכוד תחזק או תחליש את המצב הכלכלי והחברתי במדינה? | X95: c5 | AK95: =COUNTA(C95:AI95) -> 1 | AM95: =COUNTA(G95:P95,S95:T95) -> 0
A96: נניח שהליכוד יעלה לשלטון. האם בענייני הפער הכלכלי והחברתי, זה יביא לשינוי לטובה או לרעה? | AE96: d39 | AF96: b9 | AK96: =COUNTA(C96:AI96) -> 2 | AM96: =COUNTA(G96:P96,S96:T96) -> 0
A97: יש גישות שונות לטיפול במצב הכלכלי. יש הטוענים שחשוב יותר למנוע אבטלה אפילו אם היא מלווה באינפלציה, ויש כאלה שחושבים שעדיף להפסיק את האינפלציה אפילו אם יהיה אבטלה. מה דעתך? | Z97: a3 | AK97: =COUNTA(C97:AI97) -> 1 | AM97: =COUNTA(G97:P97,S97:T97) -> 0
A98: כידוע לך בעיות הכלכלה העומדות בפני המדינה הינן בעיות קשות מאוד. באיזו מידה לדעתך מתאימים השרים המופקדים על ענייני הכלכלה לטיפול בבעיות אלה? | Z98: a4 | AK98: =COUNTA(C98:AI98) -> 1 | AM98: =COUNTA(G98:P98,S98:T98) -> 0
A99: באיזו מידה אתה מסכים כי יש במדינה פער כלכל וחברתי גדול מדי? | AE99: c58 | AF99: v41 | AK99: =COUNTA(C99:AI99) -> 2 | AM99: =COUNTA(G99:P99,S99:T99) -> 0
A100: עבור איזה שירות ציבורי שהעירייה שלך נותנת לאזרחים היית מוכן לשלם יותר מיסים? | AE100: e15 | AK100: =COUNTA(C100:AI100) -> 1 | AM100: =COUNTA(G100:P100,S100:T100) -> 0
...

Sheet דת ומדינה
A1: שאלה | B1: 2025 | C1: 2022 | D1: 2021 | E1: 2020 | F1: 43709 | G1: 43556 | H1: 2015 | I1: 2013 | J1: 2009 | K1: 2006 | L1: 2003 | M1: 2001 | N1: 1999 | O1: 1996 | P1: 1992 | Q1: 1987* | R1: 1988* | S1: 1988 | T1: 1984 | U1: 1981 - 3 | V1: 1981 - 2 | W1: 1981 - 1 | X1: 1977 - 4 | Y1: 1977 - 3 | Z1: 1977 - 2 | AA1: 1977 - 1 | AB1: 1973 - 5 | AC1: 1973 - 4 | AD1: 1973 - 3 | AE1: 1973 - 2 | AF1: 1973 - 1 | AG1: 1969 - 3 | AH1: 1969 - 2 | AI1: 1969 - 1 | AK1: מספר חזרות | AM1: ספירה 84-19 | AO1: סה"כ מעל שתי חזרות
A2: אם אנו חושבים על כיווני התפתחות אפשריים של מדינת ישראל, ישנם 4 ערכים חשובים שבמידה מסוימת מתנגשים זה עם זה, והם חשובים לאנשים שונים במידות שונות. מבין ארבעת הערכים הבאים, איזה החשוב לך ביותר? | B2: v15 | C2: v15a | D2: v15A | E2: v15 | G2: v15 | H2: v17 | I2: v18 | J2: v22 | K2: a25 | L2: a23 | M2: a40 | N2: v36 | O2: c48 | P2: a76 | R2: c42 | S2: g62 | AK2: =COUNTA(C2:AI2) -> 15 | AM2: =COUNTA(G2:P2,S2:T2) -> 11 | AO2: =COUNTIF(AM2:AM38,">=2") -> 7
A3: ואיזה שני בחשיבותו? | B3: v16 | C3: v15b | D3: v15B | E3: v16 | G3: v16 | H3: v18 | I3: v19 | J3: v23 | K3: a26 | L3: a24 | M3: a41 | N3: v37 | O3: c49 | P3: a77 | R3: c43 | S3: g63 | AK3: =COUNTA(C3:AI3) -> 15 | AM3: =COUNTA(G3:P3,S3:T3) -> 11
A4: ומה השלישי בחשיבותו? | B4: v17 | C4: v15c | G4: v17 | H4: v19 | I4: v20 | J4: v24 | K4: a27 | L4: a25 | M4: a42 | N4: v38 | O4: c50 | P4: a78 | R4: c44 | S4: g64 | AK4: =COUNTA(C4:AI4) -> 13 | AM4: =COUNTA(G4:P4,S4:T4) -> 11
A5: ומה הרביעי בחשיבותו? | G5: v18 | H5: v20 | I5: v21 | J5: v25 | K5: a28 | L5: a26 | M5: a43 | N5: v39 | O5: c51 | P5: a79 | R5: c45 | S5: g65 | AK5: =COUNTA(C5:AI5) -> 12 | AM5: =COUNTA(G5:P5,S5:T5) -> 11
A6: האם לדעתך ממשלת ישראל צריכה או לא צריכה לדאוג לכך שהחיים הציבורים במדינה יתנהלו על פי המסורת הדתית היהודית? | B6: v21 | C6: v21 | D6: v21 | E6: v21 | F6: c21 | G6: v21 | H6: v31 | I6: v30 | J6: v40 | K6: a44 | L6: a76 | M6: a76 | N6: i58 | O6: cc49 | P6: a80 | R6: c11 | S6: g14 | W6: v113 | AA6: v96 | AG6: c25 | AH6: c32 | AK6: =COUNTA(C6:AI6) -> 20 | AM6: =COUNTA(G6:P6,S6:T6) -> 11
A7: עד כמה חשובה לך הזהות שלך כישראלי? | G7: v117 | AK7: =COUNTA(C7:AI7) -> 1 | AM7: =COUNTA(G7:P7,S7:T7) -> 1
A8: ועד כמה חשובה לך הזהות שלך כיהודי (לערבים "כפלשתיני")? | G8: v118 | AK8: =COUNTA(C8:AI8) -> 1 | AM8: =COUNTA(G8:P8,S8:T8) -> 1
A9: יש מצבים בהם קיימת סתירה בין הדמוקרטיה לבין ההלכה היהודית. במקרה של סתירה, האם יש להעדיף את השמירה על עקרונות הדמוקרטיה, או שיש להעדיף את השמירה על ציווי ההלכה היהודית? | H9: v21 | I9: v22 | J9: v33 | K9: a37 | M9: a44 | N9: v15 | O9: c19 | AK9: =COUNTA(C9:AI9) -> 7 | AM9: =COUNTA(G9:P9,S9:T9) -> 7
A10: באיזו מידה אתה מסכים או לא מסכים עם המשפטים הבאים: יש להנהיג נישואים אזרחיים בנוסף לנישואים דתיים בישראל | B10: v36 | C10: v36 | H10: v36 | I10: v36 | J10: v49 | AK10: =COUNTA(C10:AI10) -> 4 | AM10: =COUNTA(G10:P10,S10:T10) -> 3
A11: באיזו מידה אתה מסכים או לא מסכים עם המשפטים הבאים: יש לחייב את החרדים לשרת בצה"ל או בשירות הלאומי | I11: v41 | AK11: =COUNTA(C11:AI11) -> 1 | AM11: =COUNTA(G11:P11,S11:T11) -> 1
A12: באיזו מידה אתה מסכים או לא מסכים עם המשפטים הבאים: יש להפריד את הדת מהמדינה | N12: v13 | AK12: =COUNTA(C12:AI12) -> 1 | AM12: =COUNTA(G12:P12,S12:T12) -> 1
A13: יש מקרים בהם קיימת סתירה בין היות מדינת ישראל מדינה יהודית והיותה המדינה של כל האזרחים החיים בה. במקרה של סתירה, האם יש להעדיף את העקרון של מדינה יהודית או את העקרון של מדינת כל אזרחיה? | I13: v25 | AK13: =COUNTA(C13:AI13) -> 1 | AM13: =COUNTA(G13:P13,S13:T13) -> 1
A14: על סולם 1-10, כד כמה אתה קרוב או רחוק בנושאי דת ומדינה מהמפלגות הבאות: העבודה | L14: a44 | AK14: =COUNTA(C14:AI14) -> 1 | AM14: =COUNTA(G14:P14,S14:T14) -> 1
A15: על סולם 1-10, כד כמה אתה קרוב או רחוק בנושאי דת ומדינה מהמפלגות הבאות: הליכוד | L15: a45 | AK15: =COUNTA(C15:AI15) -> 1 | AM15: =COUNTA(G15:P15,S15:T15) -> 1
A16: על סולם 1-10, כד כמה אתה קרוב או רחוק בנושאי דת ומדינה מהמפלגות הבאות: שינוי | L16: a46 | AK16: =COUNTA(C16:AI16) -> 1 | AM16: =COUNTA(G16:P16,S16:T16) -> 1
A17: אם אנו חושבים על כיווני התפתחות אפשריים של מדינת ישראל, ישנם 4 ערכים חשובים שבמידה מסוימת מתנגשים זה עם זה, והם חשובים לאנשים שונים במידות שונות. מבין ארבעת הערכים הבאים, איזה החשוב לך ביותר? (אחרי הבחירות) | N17: d31 | AK17: =COUNTA(C17:AI17) -> 1 | AM17: =COUNTA(G17:P17,S17:T17) -> 1
A18: ואיזה שני בחשיבותו? (אחרי הבחירות) | N18: d32 | AK18: =COUNTA(C18:AI18) -> 1 | AM18: =COUNTA(G18:P18,S18:T18) -> 1
A19: ומה השלישי בחשיבותו? (אחרי הבחירות) | N19: d33 | AK19: =COUNTA(C19:AI19) -> 1 | AM19: =COUNTA(G19:P19,S19:T19) -> 1
A20: ומה הרביעי בחשיבותו? (אחרי הבחירות) | N20: d34 | AK20: =COUNTA(C20:AI20) -> 1 | AM20: =COUNTA(G20:P20,S20:T20) -> 1
