Workbook

Sheet codebooks_data
A1: survey_name | B1: category | C1: record | D1: columns | E1: question_id | F1: question_title | G1: question_description | H1: question_data_type | I1: answers
A2: 2006 | E2: Election | F2: Study 2006
A3: 2006 | B3: Case Identification | C3: 1 | D3: 1-4 | E3: CASEID | F3: Case ID | H3: numeric
A4: 2006 | B4: Case Identification | C4: 1 | D4: 5-8 | E4: id_svv_2 | F4: Respondent's ID in all consecutive surveys | H4: numeric
A5: 2006 | B5: Pre-Election Survey | C5: 1 | D5: 9 | E5: a6 | F5: Israeli condition in general | G5: 6. In your opinion, what is Israel's general situation? | H5: numeric | I5: 1: Very good; 2: Good; 3: So so; 4: Not good; 5: Bad
A6: 2006 | B6: Pre-Election Survey | C6: 1 | D6: 10 | E6: a7 | F6: The way government handles problems | G6: 7. What do you think about the way the government is handling the problems that exist in Israel today? | H6: numeric | I6: 1: Very good way; 2: Good way; 3: Bad way; 4: Very badly
A7: 2006 | B7: Pre-Election Survey | C7: 1 | D7: 11-12 | E7: a8 | F7: Most important problem for government | G7: 8. What do you think is the most important problem the government must take care of? | H7: numeric
A8: 2006 | B8: Pre-Election Survey | C8: 1 | D8: 13 | E8: a10 | F8: Economic situation in past 3 years | G8: 10. Do you think that the economic situation in the past 3 years has improved, didn't change, or got worse? | H8: numeric | I8: 1: Improved a lot; 2: Improved a bit; 3: Didn't change; 4: Got a bit worse; 5: Got much worse
A9: 2006 | B9: Pre-Election Survey | C9: 1 | D9: 14 | E9: a11 | F9: Personal economic situation in past year | G9: 11. And what about your own personal economic status? Would you say that for the past year your personal status: | H9: numeric | I9: 1: Improved a lot; 2: Improved a bit; 3: Didn't change; 4: Got a bit worse; 5: Got much worse
A10: 2006 | B10: Pre-Election Survey | C10: 1 | D10: 15 | E10: a12 | F10: National security today | G10: Here is a 9 step ladder that depicts where the country might be in terms of national security. The top of the ladder is 9 and that is the best possible situation that you can think of and 1 is the worst. One which rank do you think the country is? | H10: numeric | I10: 1: Worst situation; 9: Best situation
A11: 2006 | B11: Pre-Election Survey | C11: 1 | D11: 16 | E11: a13 | F11: National security in last 5 years | G11: Here is a 9 step ladder that depicts where the country might be in terms of national security. The top of the ladder is 9 and that is the best possible situation that you can think of and 1 is the worst. One which rank do you think the country is? | H11: numeric | I11: 1: Worst situation; 9: Best situation
A12: 2006 | B12: Pre-Election Survey | C12: 1 | D12: 17 | E12: a14 | F12: National security in next 5 years | G12: Here is a 9 step ladder that depicts where the country might be in terms of national security. The top of the ladder is 9 and that is the best possible situation that you can think of and 1 is the worst. One which rank do you think the country is? | H12: numeric | I12: 1: Worst situation; 9: Best situation
A13: 2006 | B13: Pre-Election Survey | C13: 1 | D13: 18 | E13: a15 | F13: Territories should be exchanged for peace | G13: 15. In a peace agreement with the Palestinians, should Israel agree or disagree to a territorial compromise and to the evacuation of settlements in Judea and Samaria? | H13: numeric | I13: 1: Should definitely agree; 2: Should agree; 3: Should disagree; 4: Should definitely disagree
A14: 2006 | B14: Pre-Election Survey | C14: 1 | D14: 19 | E14: a16 | F14: Israel should decide on borders and unilaterally withdraw | G14: 16. And if it would not be possible to achieve a peace agreement with the Palestinians in the next few years, should Israel undertake another unilateral separation? | H14: numeric | I14: 1: Yes definitely; 2: Yes; 3: No; 4: Definitely no
A15: 2006 | B15: Pre-Election Survey | C15: 1 | D15: 20-21 | E15: a17 | F15: Chances of Olmert's disengagement | G15: 17. If Ehud Olmert will be elected prime minister, what are the chances odds that he would undertake unilateral separation in Judea and Samaria? | H15: numeric | I15: 1: Great odds; 2: Medium odds; 3: Low odds; 4: No chance
A16: 2006 | B16: Pre-Election Survey | C16: 1 | D16: 22 | E16: a18 | F16: Chances of peace between Israel and Arabs in next 3 years | G16: 18. What are the odds that the peace between Israel and the Arab states will grow stronger in the next 3 years? | H16: numeric | I16: 1: Great odds; 2: Medium odds; 3: Low odds; 4: Very low odds
A17: 2006 | B17: Pre-Election Survey | C17: 1 | D17: 23-24 | E17: a19 | F17: Chances of war in next 3 years | G17: 19. And what are the odds for a war to break out between Israel and an Arab state in the next 3 years? | H17: numeric | I17: 1: Great odds; 2: Medium odds; 3: Low odds; 4: Very low odds
A18: 2006 | B18: Pre-Election Survey | C18: 1 | D18: 25 | E18: a20 | F18: Chances of peace agreement | G18: 20. Do you think it is possible to achieve a peace agreement with the Palestinians? | H18: numeric | I18: 1: Yes definitely; 2: I think so; 3: I dont think so; 4: Definitely no
A19: 2006 | B19: Pre-Election Survey | C19: 1 | D19: 26 | E19: a21 | F19: Evaluation of Arab aspirations | G19: 21. What do you think are the aspirations of the in the long run? | H19: numeric | I19: 1: Return part of territories occupied in the six days war; 2: Return all the territories occupied in the six days war; 3: To conquer the state of Israel; 4: Conquer the state of Israel and to destroy a significant part of the Jewish population in Israel
... A63: 2006 | B63: Support/Rejection of a Group or a Person | C63: 1 | D63: 77-78 | E63: a66 | F63: Your favorite party | G63: 66. In sum, among these parties, which one do you support most? | H63: numeric | I63: 59: Kadima; 60: Avoda; 61: Likud; 62: Meretz; 63: Ihud Leumi Mafdal; 64: Israel Beitenu; 65: Shas; 66: Another Party; 67: No Favorite Party
A64: 2006 | B64: Support/Rejection of a Group or a Person | C64: 1 | D64: 79-80 | E64: a68 | F64: Support: Olmert | H64: numeric | I64: 1: Hate/rejection; 10: Love/support
A65: 2006 | B65: Support/Rejection of a Group or a Person | C65: 1 | D65: 81-82 | E65: a69 | F65: Support: Peretz | H65: numeric | I65: 1: Hate/rejection; 10: Love/support
A66: 2006 | B66: Support/Rejection of a Group or a Person | C66: 1 | D66: 83-84 | E66: a70 | F66: Support: Netanyahu | H66: numeric | I66: 1: Hate/rejection; 10: Love/support
A67: 2006 | B67: Support/Rejection of a Group or a Person | C67: 1 | D67: 85-86 | E67: a71 | F67: Support: Peres | H67: numeric | I67: 1: Hate/rejection; 10: Love/support
A68: 2006 | B68: Support/Rejection of a Group or a Person | C68: 1 | D68: 87-88 | E68: a72 | F68: Support: Yishai | H68: numeric | I68: 1: Hate/rejection; 10: Love/support
A69: 2006 | B69: Support/Rejection of a Group or a Person | C69: 1 | D69: 89-90 | E69: a73 | F69: Support: Sharon | H69: numeric | I69: 1: Hate/rejection; 10: Love/support
A70: 2006 | B70: Support/Rejection of a Group or a Person | C70: 1 | D70: 91-92 | E70: a74 | F70: Support: Liberman | H70: numeric | I70: 1: Hate/rejection; 10: Love/support
A71: 2006 | B71: Support/Rejection of a Group or a Person | C71: 1 | D71: 93-94 | E71: a75 | F71: Support: Beilin | H71: numeric | I71: 1: Hate/rejection; 10: Love/support
A72: 2006 | B72: Support/Rejection of a Group or a Person | C72: 1 | D72: 95-96 | E72: a76 | F72: Support: Eylon | H72: numeric | I72: 1: Hate/rejection; 10: Love/support
A73: 2006 | B73: Support/Rejection of a Group or a Person | C73: 1 | D73: 97-98 | E73: a77 | F73: Support: Sharanskiy | H73: numeric | I73: 1: Hate/rejection; 10: Love/support
A74: 2006 | B74: Support/Rejection of a Group or a Person | C74: 1 | D74: 99 | E74: a78 | F74: Party leaders to deal best with economy | G74: 78  79. Who do you think will deal best with the economic problems of Israel: Kadima leaders, the Likud leaders, to Labor's leaders? Who is in second place? | H74: numeric | I74: 1: Kadima leaders; 2: Likud leaders; 3: Avoda leaders; 4: All of them to the same deggree; 5: None of them; 6: Another party
A75: 2006 | B75: Support/Rejection of a Group or a Person | C75: 1 | D75: 100 | E75: a79 | F75: In second place | G75: 79  79. Who do you think will deal best with the economic problems of Israel: Kadima leaders, the Likud leaders, to Labor's leaders? Who is in second place? | H75: numeric | I75: 1: Kadima leaders; 2: Likud leaders; 3: Avoda leaders; 4: All of them to the same deggree; 5: None of them; 6: Another party
A76: 2006 | B76: Support/Rejection of a Group or a Person | C76: 1 | D76: 101 | E76: a80 | F76: Party leaders to deal best with the social problems | G76: 80  81. And regarding the social problems in Israel? | H76: numeric | I76: 1: Kadima leaders; 2: Likud leaders; 3: Avoda leaders; 4: All of them to the same deggree; 5: None of them; 6: Another party
A77: 2006 | B77: Support/Rejection of a Group or a Person | C77: 1 | D77: 102 | E77: a81 | F77: In second place | G77: 81  81. And regarding the social problems in Israel? | H77: numeric | I77: 1: Kadima leaders; 2: Likud leaders; 3: Avoda leaders; 4: All of them to the same deggree; 5: None of them; 6: Another party
A78: 2006 | B78: Support/Rejection of a Group or a Person | C78: 1 | D78: 103 | E78: a82 | F78: Party leaders to deal best with foreign and security issues in Israel | G78: 82  83. And regarding the foreign and security issues in Israel? | H78: numeric | I78: 1: Kadima leaders; 2: Likud leaders; 3: Avoda leaders; 4: All of them to the same deggree; 5: None of them; 6: Another party
A79: 2006 | B79: Support/Rejection of a Group or a Person | C79: 1 | D79: 104 | E79: a83 | F79: In second place | G79: 83  83. And regarding the foreign and security issues in Israel? | H79: numeric | I79: 1: Kadima leaders; 2: Likud leaders; 3: Avoda leaders; 4: All of them to the same deggree; 5: None of them; 6: Another party
A80: 2006 | B80: Party Differences | C80: 1 | D80: 105 | E80: a84 | F80: Party differences on the following issue:Jerusalem | G80: Do you think there are or are not differences among the parties on the following issues? | H80: numeric | I80: 1: Great differences; 5: Almost no differences
A81: 2006 | B81: Party Differences | C81: 1 | D81: 106 | E81: a85 | F81: Party differences on the following issue:Economy | G81: Do you think there are or are not differences among the parties on the following issues? | H81: numeric | I81: 1: Great differences; 5: Almost no differences
A82: 2006 | B82: Party Differences | C82: 1 | D82: 107 | E82: a86 | F82: Party differences on the following issue:Social policy | G82: Do you think there are or are not differences among the parties on the following issues? | H82: numeric | I82: 1: Great differences; 5: Almost no differences
A83: 2006 | B83: Party Differences | C83: 1 | D83: 108 | E83: a87 | F83: Party differences on the following issue:State and Religion | G83: Do you think there are or are not differences among the parties on the following issues? | H83: numeric | I83: 1: Great differences; 5: Almost no differences
A84: 2006 | B84: Party Differences | C84: 1 | D84: 109 | E84: a88 | F84: Party differences on the following issue:'Peace and Territories | G84: Do you think there are or are not differences among the parties on the following issues? | H84: numeric | I84: 1: Great differences; 5: Almost no differences
A85: 2006 | B85: Party Differences | C85: 1 | D85: 110 | E85: a89 | F85: Party differences on the following issue:Terror | G85: Do you think there are or are not differences among the parties on the following issues? | H85: numeric | I85: 1: Great differences; 5: Almost no differences
... A141: 2006 | B141: Newspaper/TV | C141: 1 | D141: 174 | E141: b63 | F141: Frequency of reading daily newspaper | G141: 63. Do you read a daily newspaper every day? | H141: numeric | I141: 1: Almost never; 2: Every now and then; 3: Approximately once a week; 4: Twice or three times a week; 5: One daily newspaper almost once a day; 6: More than one newspaper amost every day
A142: 2006 | B142: Newspaper/TV | C142: 1 | D142: 175-176 | E142: b64 | F142: Newspaper usually read | G142: 64. Which newspaper do you usually read, which is your main newspaper? (do not read) | H142: numeric
A143: 2006 | B143: Newspaper/TV | C143: 1 | D143: 177 | E143: b66 | F143: News on TV | G143: 66. Do you usually watch the news on TV? | H143: numeric | I143: 1: Almost never; 2: Not so often; 3: Once a week or so; 4: 2-3 times a week; 5: At least once a day; 6: More than once a day
A144: 2006 | B144: Newspaper/TV | C144: 1 | D144: 178-179 | E144: b67 | F144: Which TV channel | G144: 67. And which TV channel do you usually watch? (do not read) | H144: numeric | I144: 1: Channel 1; 2: Channel 2; 3: Channel 9 (Israel+); 4: Channel 10; 5: RTVI; 6: Al-Jazira; 7: MBC; 8: Other; 9: More than one in Hebrew; 10: ORT (Russian); 11: CNN; 12: RTVI and Israel+; 13: RTVI and/or Israel+ and Hebrew channel; 14: Israel+ and ORT; 15: Euronews; 16: More than one in Arabic; 17: More thane one in Arabic and Hebrew; 18: El-Manar; 19: BBC; 20: TV-5 (France); 21: NTV (Russian)
A145: 2006 | B145: Newspaper/TV | C145: 1 | D145: 180 | E145: b69 | F145: Election campaign broadcasts on TV | G145: 69. Do you usually watch the election campaign broadcasts on TV?(for interviews before the beginning of broadcasts (March 7, 2006): Do you intend to watch the campaign broadcasts on TV?) | H145: numeric | I145: 1: Every day; 2: Usually; 3: Sometimes; 4: Not very often; 5: Never
A146: 2006 | B146: Newspaper/TV | C146: 1 | D146: 181 | E146: b70 | F146: Sites of political parties | G146: 70. Do you surf sites of political parties? | H146: numeric | I146: 1: Do not surf the internet at all; 2: Surf but not sites of parties; 3: Surf once in a while the sites of parties; 4: Yes quite often
A147: 2006 | B147: Newspaper/TV | C147: 1 | D147: 182 | E147: b71 | F147: Which paties' sites | G147: 71. Those who answered 3 or 4 ask: Which parties' sites do you surf? | H147: numeric | I147: 1: The ones which I support; 2: Only parties which I dislike; 3: All kinds of parties
A148: 2006 | B148: Chance the Party to be in the Next Government | C148: 1 | D148: 183 | E148: b72 | F148: Supporter or member of any party | G148: 72. Are you a member, supporter, or an activist of any of the parties? | H148: numeric | I148: 1: Not a supporter or an activist in any of the parties; 2: Supporter of a party but not a member; 3: Member; 4: Active member; 5: A member and hold a position in a party
A149: 2006 | B149: Chance the Party to be in the Next Government | C149: 1 | D149: 184-185 | E149: b73 | F149: Respondent party vote if elections were held today | G149: 73. If the elections for Knesset were held today, for which party would you vote for? (do not read answers) | H149: numeric | I149: 1: Kadima; 2: Likud; 3: Avoda; 4: Yisrael Beitenu (Liberman); 5: Ihud Leumi-Mafdal; 6: Yahadut Ha Tora; 7: Shas; 8: Meretz; 9: Shinui; 10: Hetz (Poraz); 11: The Green Party; 12: Ale Yarok; 13: The Pensioners; 14: Hazit Leumit Yehudit (Marzel); 15: Herut; 16: Tafnit; 17: Balad; 18: Raam-Taal; 19: Hadash; 20: Zionut Hadasha; 21: Daam; 22: Lehem; 96: Blank ballot; 97: Undecided; 98: Do not intend to vote; 99: Refuse to answer
A150: 2006 | B150: Chance the Party to be in the Next Government | C150: 1 | D150: 186-188 | E150: b75 | F150: Likelihood of Kadima to be in the coalition | G150: And now we would like to ask you about the chance of each one of the following parties to be a member of the coalition after the elections. Here you have a scale between 0 to 10, where 10 means you think there is no chance the party will be a member of the coalition, 50 means that the party's chances are half and half, and 100 means that it will certainly be a member of the coalition. What's the chance that Kadima will be in the next government? | H150: numeric
A151: 2006 | B151: Chance the Party to be in the Next Government | C151: 1 | D151: 189-191 | E151: b78 | F151: Likelihood of Avoda to be in the coalition | G151: And now we would like to ask you about the chance of each one of the following parties to be a member of the coalition after the elections. Here you have a scale between 0 to 10, where 10 means you think there is no chance the party will be a member of the coalition, 50 means that the party's chances are half and half, and 100 means that it will certainly be a member of the coalition. The Labor? | H151: numeric
A152: 2006 | B152: Chance the Party to be in the Next Government | C152: 1 | D152: 192-194 | E152: b81 | F152: Likelihood of Likud to be in the coalition | G152: And now we would like to ask you about the chance of each one of the following parties to be a member of the coalition after the elections. Here you have a scale between 0 to 10, where 10 means you think there is no chance the party will be a member of the coalition, 50 means that the party's chances are half and half, and 100 means that it will certainly be a member of the coalition. The Likud? | H152: numeric
A153: 2006 | B153: Chance the Party to be in the Next Government | C153: 1 | D153: 195-197 | E153: b84 | F153: Likelihood of the party he said he will vote for | G153: And now we would like to ask you about the chance of each one of the following parties to be a member of the coalition after the elections. Here you have a scale between 0 to 10, where 10 means you think there is no chance the party will be a member of the coalition, 50 means that the party's chances are half and half, and 100 means that it will certainly be a member of the coalition. And (the party he said he will vote for in the previous question) | H153: numeric
A154: 2006 | B154: Chance the Party to be in the Next Government | C154: 1 | D154: 198-200 | E154: b87 | F154: Number of seats you think Kadima will win | G154: And what about the number of MKs these parties will have in the next Knesset? How many MKs will have? Kadima? | H154: numeric
A155: 2006 | B155: Chance the Party to be in the Next Government | C155: 1 | D155: 201-203 | E155: b89 | F155: Number of seats you think Avoda will win | G155: And what about the number of MKs these parties will have in the next Knesset? How many MKs will have? Labor? | H155: numeric
A156: 2006 | B156: Chance the Party to be in the Next Government | C156: 1 | D156: 204-206 | E156: b91 | F156: Number of seats you think Likud will win | G156: And what about the number of MKs these parties will have in the next Knesset? How many MKs will have? Likud? | H156: numeric
A157: 2006 | B157: Chance the Party to be in the Next Government | C157: 1 | D157: 207-209 | E157: b93 | F157: Number of seats you think the party you vote will win | G157: And what about the number of MKs these parties will have in the next Knesset? How many MKs will have? And (the party he said he will vote for in the previous question) | H157: numeric
A158: 2006 | B158: Different Coalitions after the Elections | C158: 1 | D158: 210-212 | E158: c6 | F158: Chances for Kadima-Labor coalition | G158: And now we want to ask you about the chances of different coalitions after the elections. On a scale of 0 to 100, 0 means you give no chance for a certain coalition, 50 means that the coalition's chances are half and half, and 100 means that you are sure this coalition will exist. Naturally you can give any number between 0 to 100. On such a scale, what are the chances that after the elections, there will be a coalition between: | H158: numeric
A159: 2006 | B159: Different Coalitions after the Elections | C159: 1 | D159: 213-215 | E159: c9 | F159: Chances for Kadima-Likud coalition | G159: And now we want to ask you about the chances of different coalitions after the elections. On a scale of 0 to 100, 0 means you give no chance for a certain coalition, 50 means that the coalition's chances are half and half, and 100 means that you are sure this coalition will exist. Naturally you can give any number between 0 to 100. On such a scale, what are the chances that after the elections, there will be a coalition between: | H159: numeric
A160: 2006 | B160: Different Coalitions after the Elections | C160: 1 | D160: 216-218 | E160: c12 | F160: Chances for Kadima-Likud-Haredim coalition | G160: And now we want to ask you about the chances of different coalitions after the elections. On a scale of 0 to 100, 0 means you give no chance for a certain coalition, 50 means that the coalition's chances are half and half, and 100 means that you are sure this coalition will exist. Naturally you can give any number between 0 to 100. On such a scale, what are the chances that after the elections, there will be a coalition between: | H160: numeric
A161: 2006 | B161: Different Coalitions after the Elections | C161: 1 | D161: 219-221 | E161: c15 | F161: Chances for Kadima-Labor-Haredim coalition | G161: And now we want to ask you about the chances of different coalitions after the elections. On a scale of 0 to 100, 0 means you give no chance for a certain coalition, 50 means that the coalition's chances are half and half, and 100 means that you are sure this coalition will exist. Naturally you can give any number between 0 to 100. On such a scale, what are the chances that after the elections, there will be a coalition between: | H161: numeric
... A164: 2006 | B164: Different Coalitions after the Elections | C164: 1 | D164: 228-230 | E164: c24 | F164: Chances for Kadima-Labor-Likud-Right parties and Haredim coalition | G164: And now we want to ask you about the chances of different coalitions after the elections. On a scale of 0 to 100, 0 means you give no chance for a certain coalition, 50 means that the coalition's chances are half and half, and 100 means that you are sure this coalition will exist. Naturally you can give any number between 0 to 100. On such a scale, what are the chances that after the elections, there will be a coalition between: | H164: numeric
A165: 2006 | B165: Different Coalitions after the Elections | C165: 1 | D165: 231-232 | E165: c27 | F165: Will support Kadima-Labor coalition | G165: And how supportive would you be of the following coalitions after the elections (read the coalitions in a different order) on a 10 point scale where '1' means strong rejection and '10' means strong support, and the rest are levels in between: | H165: numeric | I165: 1: Reject; 10: Support
A166: 2006 | B166: Different Coalitions after the Elections | C166: 1 | D166: 233-234 | E166: c28 | F166: Will support Kadima-Likud coalition | G166: And how supportive would you be of the following coalitions after the elections (read the coalitions in a different order) on a 10 point scale where '1' means strong rejection and '10' means strong support, and the rest are levels in between: | H166: numeric | I166: 1: Reject; 10: Support
A167: 2006 | B167: Different Coalitions after the Elections | C167: 1 | D167: 235-237 | E167: c29 | F167: Will support Kadima-Likud-Haredim coalition | G167: And how supportive would you be of the following coalitions after the elections (read the coalitions in a different order) on a 10 point scale where '1' means strong rejection and '10' means strong support, and the rest are levels in between: | H167: numeric | I167: 1: Reject; 10: Support
A168: 2006 | B168: Different Coalitions after the Elections | C168: 1 | D168: 238-240 | E168: c30 | F168: Will support Kadima-Labor-Haredim coalition | G168: And how supportive would you be of the following coalitions after the elections (read the coalitions in a different order) on a 10 point scale where '1' means strong rejection and '10' means strong support, and the rest are levels in between: | H168: numeric | I168: 1: Reject; 10: Support
A169: 2006 | B169: Different Coalitions after the Elections | C169: 1 | D169: 241-243 | E169: c31 | F169: Will support Kadima-Likud-Right coalition | G169: And how supportive would you be of the following coalitions after the elections (read the coalitions in a different order) on a 10 point scale where '1' means strong rejection and '10' means strong support, and the rest are levels in between: | H169: numeric | I169: 1: Reject; 10: Support
A170: 2006 | B170: Different Coalitions after the Elections | C170: 1 | D170: 244-245 | E170: c32 | F170: Will support Kadima-Labor-Meretz coalition | G170: And how supportive would you be of the following coalitions after the elections (read the coalitions in a different order) on a 10 point scale where '1' means strong rejection and '10' means strong support, and the rest are levels in between: | H170: numeric | I170: 1: Reject; 10: Support
A171: 2006 | B171: Different Coalitions after the Elections | C171: 1 | D171: 246-248 | E171: c33 | F171: Will support Kadima-Labor-Likud-Right parties and Haredim coalition | G171: And how supportive would you be of the following coalitions after the elections (read the coalitions in a different order) on a 10 point scale where '1' means strong rejection and '10' means strong support, and the rest are levels in between: | H171: numeric | I171: 1: Reject; 10: Support
A172: 2006 | B172: Different Coalitions after the Elections | C172: 1 | D172: 249-250 | E172: c34 | F172: Preferable coalition | G172: 34. And in the final analysis, among these possibilities, which would you prefer? | H172: numeric | I172: 27: Kadima-Avoda; 28: Kadima-Likud; 29: Kadima-Likud-Haredim; 30: Kadima-Avoda-Haredim; 31: Kadima-Likud-Right; 32: Kadima-Avoda-Meretz; 33: Memshelet Ahdut Leumit; 34: Kadima-Avoda-Liberman; 35: Kadima-Avoda-Likud-Liberman; 36: Kadima-Likud-Liberman; 37: Likud-Avoda; 38: Kadima-Avoda-Likud; 39: Likud-Right-Haredim; 40: Kadima-Avoda-Merets-Arabs; 41: Likud-Avoda-Haredim; 42: Kadima-small parties
A173: 2006 | B173: Previous Elections | C173: 1 | D173: 251-252 | E173: c36 | F173: Respondent vote for PM if elections for PM were held | G173: 36. And if there were two ballots in the coming elections, one for Prime Minister and one for the Knesset, for whom would you vote for Prime Minister? | H173: numeric | I173: 1: Peretz; 2: Olmert; 3: Netanyahu; 4: Other; 5: Blank ballot; 6: Don't know; 7: Wouldn't vote; 9: Refuse; 10: Peres; 11: Liberman; 12: Sharanskiy; 13: Dery; 14: Ishai; 15: Porush; 16: Gafni; 17: Ami Ayalon; 18: Ramon; 19: Uzi Landau; 20: Ariel Sharon; 21: Eitam; 22: Feiglin; 23: Sarid; 24: Beilin; 25: Marzel; 26: Livni; 27: Bishara; 28: Tibi; 29: Taleb Sane; 30: Eli Landau; 31: Poraz; 32: M. Elyahu; 33: Beni Begin; 34: Uzi Dayan; 35: Mofaz; 36: Barak
A174: 2006 | B174: Previous Elections | C174: 1 | D174: 253-254 | E174: c38 | F174: Respondent party vote if elections for PM were also held | G174: 38. And for the Knesset? (for the interviewer: use the code in question 73) | H174: numeric | I174: 1: Kadima; 2: Likud; 3: Avoda; 4: Liberman; 5: Ihud Leumi-Mafdal; 6: Yahadut Ha Tora; 7: Shas; 8: Meretz; 9: Shinui; 10: Hetz (Poraz); 11: Green Party; 12: Ale Yarok; 13: Pensioners; 14: Hazit Leumit Yehudit (Marzel); 15: Herut; 16: Tafnit; 17: Balad; 18: Raam; 19: Hadash; 96: Blank ballot; 97: Undecided; 98: Do not intend to vote; 99: Refuse to answer
A175: 2006 | B175: Previous Elections | C175: 1 | D175: 255-256 | E175: c40 | F175: Vote in 2003 elections | G175: 40. For which party did you vote in the previous elections in 2003? (do not read the answers) | H175: numeric | I175: 1: Likud; 2: Avoda-Meimad; 3: Shinui; 4: Meretz; 5: Ihud Leumi; 6: Mafdal; 7: Yahadut Hatora; 8: Shas; 9: Am Ehad; 10: Israel Bealiya; 11: Green party; 12: Balad; 13: Raam; 14: Hadash; 15: Another; 16: Ale Yarok; 17: Hazit Leumit Yehudit (Marzel); 18: Herut; 19: Daam; 90: Don't remember; 96: Blank ballot; 97: Didn't vote although had the right to vote; 98: Didn't vote / did not have the right to vote; 99: Refuse to answer
A176: 2006 | B176: Previous Elections | C176: 1 | D176: 257 | E176: c42 | F176: Vote for PM in 2001 elections | G176: 42. For whom did you vote for prime minister in 2001? | H176: numeric | I176: 1: Barak; 2: Sharon; 3: Blank ballot; 4: Didn't vote although had the right to vote; 5: Didn't vote / did not have the right to vote; 6: Don't remember; 9: Refuse to answer
... A187: 2006 | B187: Self-identity | C187: 1 | D187: 268 | E187: c53 | F187: The Knesset's chairman | G187: 53. To the best of your knowledge, who is the Knesset's chairman? (do not read answers) | H187: numeric | I187: 1: Rivlin; 2: Wrong answer; 8: Do not know
A188: 2006 | B188: Rersonal and Household Details | C188: 1 | D188: 269-270 | E188: c54 | F188: Age | G188: 54. How old are you? | H188: numeric
A189: 2006 | B189: Rersonal and Household Details | C189: 1 | D189: 271 | E189: c56 | F189: Religious observance | G189: 56. To what extent do you observe religious tradition? | H189: numeric | I189: 1: Not at all; 2: A little bit; 3: A lot; 4: I observe all of it
A190: 2006 | B190: Rersonal and Household Details | C190: 1 | D190: 272-273 | E190: c57 | F190: Country of birth | G190: 57. (not for Arabs): Where were you born? (write a state) (if in the former USSR, write the name of the republic) | H190: numeric
A191: 2006 | B191: Rersonal and Household Details | C191: 1 | D191: 274-275 | E191: c60 | F191: Year of immigration | G191: 60-61. (not for Arabs): for those who were not born here: When did you come to Israel? | H191: numeric
A192: 2006 | B192: Rersonal and Household Details | C192: 1 | D192: 276 | E192: c62 | F192: Russian immigrant after 1989 (not for Arabs) | G192: 62. (not for Arabs): for the interviewer: if R came from the USSR after 1989, circle: 1. from the USSR | H192: numeric | I192: 1: New immigrant
A193: 2006 | B193: Rersonal and Household Details | C193: 1 | D193: 277-278 | E193: c63 | F193: City in former USSR (only for immigrants from the former USSR) | G193: 63. (only for immigrants from the former USSR): in what city did you live before you came to Israel? | H193: numeric | I193: 1: Moscow; 2: St.Perersburg; 3: Large cities in Euro-Russia; 4: Small cities in Euro-Russia; 5: Large cities in Asian-Russia; 6: Small cities in Asian-Russia; 7: Birobidjan & Habarovsk; 8: Russian Kavkazian autonomies; 9: Kiev and large cities in East/South Ukraine; 10: Towns in East/South Ukraine; 11: West/Central Ukrainian towns; 12: Kishinev; 13: Rest of Moldavia; 14: Minsk; 15: Rest of Belorussia; 16: Yerevan; 17: Rest of Armenia; 18: Baku; 19: Rest of Azerbaijan; 20: Tbilisi; 21: Rest of Georgia; 22: Tashkent; 23: Almaty; 24: Rest of Kazahstan; 25: Turkmenistan, Tajikistan, Kirgyzstan; 26: Samarkand; 27: Riga; 28: Rest of Latvia; 29: Vilnius; 30: Rest of Lithuania; 31: Tallin; 32: Rest of Estonia; 33: Uzbek's towns
A194: 2006 | B194: Rersonal and Household Details | C194: 1 | D194: 279-280 | E194: c65 | F194: Nationality in passport in USSR (only for immigrants from the former USSR) | G194: 65. (only for immigrants from the former USSR): what was the nationality written in your internal Soviet passport? | H194: numeric | I194: 1: Jewish; 2: Other; 3: Nothing; 4: No passport; 5: Don't remember; 10: Russian; 11: Ukrainian; 12: Moldavian; 13: Yakutian; 14: Gorskiy Evrei; 15: Armenian; 16: Belorussian; 17: Mordovi
A195: 2006 | B195: Rersonal and Household Details | C195: 1 | D195: 281 | E195: c67 | F195: Friends in Israel (only for immigrants from the former USSR) | G195: 67. (only for immigrants from the former USSR): Regarding your friends in Israel, would you say that most of them are: | H195: numeric | I195: 1: New immigrant; 2: Veterans; 3: Half and half
A196: 2006 | B196: Rersonal and Household Details | C196: 1 | D196: 282 | E196: c68 | F196: Russian party participation in elections (only for immigrants from the former USSR) | G196: 68. (only for immigrants from the former USSR): would you like to see a Russian party participating in the coming elections? | H196: numeric | I196: 1: Of course; 2: I think so; 3: I don't think so; 4: Of course not
A197: 2006 | B197: Rersonal and Household Details | C197: 1 | D197: 283-285 | E197: c69 | F197: Father's country of birth (not for Arabs) | G197: 69. (not for Arabs): where was your father born? (write the name of the state): if in the USSR, write the name of the republic) | H197: numeric
A198: 2006 | B198: Rersonal and Household Details | C198: 1 | D198: 286-288 | E198: c72 | F198: Mother's country of birth (not for Arabs) | G198: 72. (not for Arabs): where was your mother born? (write the name of the state): if in the USSR, write the name of the republic) | H198: numeric
A199: 2006 | B199: Rersonal and Household Details | C199: 1 | D199: 289-290 | E199: c75 | F199: Years of schooling | G199: 75. How many years did you study? (including elementary school) | H199: numeric
A200: 2006 | B200: Rersonal and Household Details | C200: 1 | D200: 291 | E200: c77 | F200: Academic degree | G200: 77. (for those who finished 12 years and more): Do you have an academic degree? | H200: numeric | I200: 1: Yes; 2: No
A201: 2006 | B201: Rersonal and Household Details | C201: 1 | D201: 292-293 | E201: c78 | F201: Profession | G201: 78. Describe your profession or your main job (if R is not working, his last job) (to the interviewer: be specific as you can: not just a doctor but an eye doctor etc.) | H201: character
A202: 2006 | B202: Rersonal and Household Details | C202: 1 | D202: 294-295 | E202: c80 | F202: Monthly family expenditure (relative to average of 9,300 NIS) | G202: 80. The average monthly expenditure for a family of 4 people was NIS 9,300 last month. Does your family spend: | H202: numeric | I202: 1: Much more; 2: A little more; 3: About the average; 4: A little less; 5: Much less
A203: 2006 | B203: Rersonal and Household Details | C203: 1 | D203: 296-297 | E203: c81 | F203: Are you worried about losing your job? | G203: 81. Are you worried of losing your job? | H203: numeric | I203: 1: Not at all; 2: A little worried; 3: Very worried; 4: Lost job lately and looking for one; 5: Not working and not looking for a job
A204: 2006 | B204: Rersonal and Household Details | C204: 1 | D204: 298-299 | E204: c82 | F204: Rooms in dwelling | G204: 82. How many rooms do you have in your house? | H204: numeric
A205: 2006 | B205: Rersonal and Household Details | C205: 1 | D205: 300-301 | E205: c84 | F205: Number of persons in household | G205: 84. How many people are living in the house? (including soldiers): | H205: numeric
A206: 2006 | B206: Rersonal and Household Details | C206: 1 | D206: 302 | E206: c86 | F206: Social class (self identified) | G206: 86. What is your social class? | H206: numeric | I206: 1: High; 2: Medium-high; 3: Medium; 4: Low
A207: 2006 | B207: Rersonal and Household Details | C207: 1 | D207: 303-304 | E207: c87 | F207: Religion | G207: 87. Religion | H207: numeric | I207: 1: Jewish; 2: Muslim; 3: Christian; 4: Druze; 5: No religion
A208: 2006 | B208: Rersonal and Household Details | C208: 1 | D208: 305 | E208: c88 | F208: Religious self-definition (not for Arabs) | G208: 88. (not for Arabs): How would you define yourself? | H208: numeric | I208: 1: Secular; 2: Traditional; 3: Religious; 4: Haredi
A209: 2006 | B209: Rersonal and Household Details | C209: 1 | D209: 306 | E209: c89 | F209: Sex | G209: 89. Gender | H209: numeric | I209: 1: Male; 2: Female
A210: 2006 | B210: Rersonal and Household Details | C210: 1 | D210: 307-309 | E210: c90 | F210: Locality of residency | G210: 90. Place of residency | H210: numeric
...

Sheet codebooks_data_reordered
A1: Question Id | B1: Election | C1: category2 | D1: record | E1: columns | F1: question_title | G1: question_description | H1: question_data_type | I1: answers
A2: CASEID | B2: 2006 | F2: Study 2006
A3: id_svv_2 | B3: 2006 | C3: Case Identification | D3: 1 | E3: 1-4 | F3: Case ID | H3: numeric
A4: a6 | B4: 2006 | C4: Case Identification | D4: 1 | E4: 5-8 | F4: Respondent's ID in all consecutive surveys | H4: numeric
A5: a7 | B5: 2006 | C5: Pre-Election Survey | D5: 1 | E5: 9 | F5: Israeli condition in general | G5: 6. In your opinion, what is Israel's general situation? | H5: numeric | I5: 1: Very good; 2: Good; 3: So so; 4: Not good; 5: Bad
A6: a8 | B6: 2006 | C6: Pre-Election Survey | D6: 1 | E6: 10 | F6: The way government handles problems | G6: 7. What do you think about the way the government is handling the problems that exist in Israel today? | H6: numeric | I6: 1: Very good way; 2: Good way; 3: Bad way; 4: Very badly
A7: a10 | B7: 2006 | C7: Pre-Election Survey | D7: 1 | E7: 11-12 | F7: Most important problem for government | G7: 8. What do you think is the most important problem the government must take care of? | H7: numeric
A8: a11 | B8: 2006 | C8: Pre-Election Survey | D8: 1 | E8: 13 | F8: Economic situation in past 3 years | G8: 10. Do you think that the economic situation in the past 3 years has improved, didn't change, or got worse? | H8: numeric | I8: 1: Improved a lot; 2: Improved a bit; 3: Didn't change; 4: Got a bit worse; 5: Got much worse
A9: a12 | B9: 2006 | C9: Pre-Election Survey | D9: 1 | E9: 14 | F9: Personal economic situation in past year | G9: 11. And what about your own personal economic status? Would you say that for the past year your personal status: | H9: numeric | I9: 1: Improved a lot; 2: Improved a bit; 3: Didn't change; 4: Got a bit worse; 5: Got much worse
A10: a13 | B10: 2006 | C10: Pre-Election Survey | D10: 1 | E10: 15 | F10: National security today | G10: Here is a 9 step ladder that depicts where the country might be in terms of national security. The top of the ladder is 9 and that is the best possible situation that you can think of and 1 is the worst. One which rank do you think the country is? | H10: numeric | I10: 1: Worst situation; 9: Best situation
A11: a14 | B11: 2006 | C11: Pre-Election Survey | D11: 1 | E11: 16 | F11: National security in last 5 years | G11: Here is a 9 step ladder that depicts where the country might be in terms of national security. The top of the ladder is 9 and that is the best possible situation that you can think of and 1 is the worst. One which rank do you think the country is? | H11: numeric | I11: 1: Worst situation; 9: Best situation
A12: a15 | B12: 2006 | C12: Pre-Election Survey | D12: 1 | E12: 17 | F12: National security in next 5 years | G12: Here is a 9 step ladder that depicts where the country might be in terms of national security. The top of the ladder is 9 and that is the best possible situation that you can think of and 1 is the worst. One which rank do you think the country is? | H12: numeric | I12: 1: Worst situation; 9: Best situation
A13: a16 | B13: 2006 | C13: Pre-Election Survey | D13: 1 | E13: 18 | F13: Territories should be exchanged for peace | G13: 15. In a peace agreement with the Palestinians, should Israel agree or disagree to a territorial compromise and to the evacuation of settlements in Judea and Samaria? | H13: numeric | I13: 1: Should definitely agree; 2: Should agree; 3: Should disagree; 4: Should definitely disagree
A14: a17 | B14: 2006 | C14: Pre-Election Survey | D14: 1 | E14: 19 | F14: Israel should decide on borders and unilaterally withdraw | G14: 16. And if it would not be possible to achieve a peace agreement with the Palestinians in the next few years, should Israel undertake another unilateral separation? | H14: numeric | I14: 1: Yes definitely; 2: Yes; 3: No; 4: Definitely no
A15: a18 | B15: 2006 | C15: Pre-Election Survey | D15: 1 | E15: 20-21 | F15: Chances of Olmert's disengagement | G15: 17. If Ehud Olmert will be elected prime minister, what are the chances odds that he would undertake unilateral separation in Judea and Samaria? | H15: numeric | I15: 1: Great odds; 2: Medium odds; 3: Low odds; 4: No chance
A16: a19 | B16: 2006 | C16: Pre-Election Survey | D16: 1 | E16: 22 | F16: Chances of peace between Israel and Arabs in next 3 years | G16: 18. What are the odds that the peace between Israel and the Arab states will grow stronger in the next 3 years? | H16: numeric | I16: 1: Great odds; 2: Medium odds; 3: Low odds; 4: Very low odds
A17: a20 | B17: 2006 | C17: Pre-Election Survey | D17: 1 | E17: 23-24 | F17: Chances of war in next 3 years | G17: 19. And what are the odds for a war to break out between Israel and an Arab state in the next 3 years? | H17: numeric | I17: 1: Great odds; 2: Medium odds; 3: Low odds; 4: Very low odds
A18: a21 | B18: 2006 | C18: Pre-Election Survey | D18: 1 | E18: 25 | F18: Chances of peace agreement | G18: 20. Do you think it is possible to achieve a peace agreement with the Palestinians? | H18: numeric | I18: 1: Yes definitely; 2: I think so; 3: I dont think so; 4: Definitely no
A19: a22 | B19: 2006 | C19: Pre-Election Survey | D19: 1 | E19: 26 | F19: Evaluation of Arab aspirations | G19: 21. What do you think are the aspirations of the in the long run? | H19: numeric | I19: 1: Return part of territories occupied in the six days war; 2: Return all the territories occupied in the six days war; 3: To conquer the state of Israel; 4: Conquer the state of Israel and to destroy a significant part of the Jewish population in Israel
... A63: a68 | B63: 2006 | C63: Support/Rejection of a Group or a Person | D63: 1 | E63: 77-78 | F63: Your favorite party | G63: 66. In sum, among these parties, which one do you support most? | H63: numeric | I63: 59: Kadima; 60: Avoda; 61: Likud; 62: Meretz; 63: Ihud Leumi Mafdal; 64: Israel Beitenu; 65: Shas; 66: Another Party; 67: No Favorite Party
A64: a69 | B64: 2006 | C64: Support/Rejection of a Group or a Person | D64: 1 | E64: 79-80 | F64: Support: Olmert | H64: numeric | I64: 1: Hate/rejection; 10: Love/support
A65: a70 | B65: 2006 | C65: Support/Rejection of a Group or a Person | D65: 1 | E65: 81-82 | F65: Support: Peretz | H65: numeric | I65: 1: Hate/rejection; 10: Love/support
A66: a71 | B66: 2006 | C66: Support/Rejection of a Group or a Person | D66: 1 | E66: 83-84 | F66: Support: Netanyahu | H66: numeric | I66: 1: Hate/rejection; 10: Love/support
A67: a72 | B67: 2006 | C67: Support/Rejection of a Group or a Person | D67: 1 | E67: 85-86 | F67: Support: Peres | H67: numeric | I67: 1: Hate/rejection; 10: Love/support
A68: a73 | B68: 2006 | C68: Support/Rejection of a Group or a Person | D68: 1 | E68: 87-88 | F68: Support: Yishai | H68: numeric | I68: 1: Hate/rejection; 10: Love/support
A69: a74 | B69: 2006 | C69: Support/Rejection of a Group or a Person | D69: 1 | E69: 89-90 | F69: Support: Sharon | H69: numeric | I69: 1: Hate/rejection; 10: Love/support
A70: a75 | B70: 2006 | C70: Support/Rejection of a Group or a Person | D70: 1 | E70: 91-92 | F70: Support: Liberman | H70: numeric | I70: 1: Hate/rejection; 10: Love/support
A71: a76 | B71: 2006 | C71: Support/Rejection of a Group or a Person | D71: 1 | E71: 93-94 | F71: Support: Beilin | H71: numeric | I71: 1: Hate/rejection; 10: Love/support
A72: a77 | B72: 2006 | C72: Support/Rejection of a Group or a Person | D72: 1 | E72: 95-96 | F72: Support: Eylon | H72: numeric | I72: 1: Hate/rejection; 10: Love/support
A73: a78 | B73: 2006 | C73: Support/Rejection of a Group or a Person | D73: 1 | E73: 97-98 | F73: Support: Sharanskiy | H73: numeric | I73: 1: Hate/rejection; 10: Love/support
A74: a79 | B74: 2006 | C74: Support/Rejection of a Group or a Person | D74: 1 | E74: 99 | F74: Party leaders to deal best with economy | G74: 78  79. Who do you think will deal best with the economic problems of Israel: Kadima leaders, the Likud leaders, to Labor's leaders? Who is in second place? | H74: numeric | I74: 1: Kadima leaders; 2: Likud leaders; 3: Avoda leaders; 4: All of them to the same deggree; 5: None of them; 6: Another party
A75: a80 | B75: 2006 | C75: Support/Rejection of a Group or a Person | D75: 1 | E75: 100 | F75: In second place | G75: 79  79. Who do you think will deal best with the economic problems of Israel: Kadima leaders, the Likud leaders, to Labor's leaders? Who is in second place? | H75: numeric | I75: 1: Kadima leaders; 2: Likud leaders; 3: Avoda leaders; 4: All of them to the same deggree; 5: None of them; 6: Another party
A76: a81 | B76: 2006 | C76: Support/Rejection of a Group or a Person | D76: 1 | E76: 101 | F76: Party leaders to deal best with the social problems | G76: 80  81. And regarding the social problems in Israel? | H76: numeric | I76: 1: Kadima leaders; 2: Likud leaders; 3: Avoda leaders; 4: All of them to the same deggree; 5: None of them; 6: Another party
A77: a82 | B77: 2006 | C77: Support/Rejection of a Group or a Person | D77: 1 | E77: 102 | F77: In second place | G77: 81  81. And regarding the social problems in Israel? | H77: numeric | I77: 1: Kadima leaders; 2: Likud leaders; 3: Avoda leaders; 4: All of them to the same deggree; 5: None of them; 6: Another party
A78: a83 | B78: 2006 | C78: Support/Rejection of a Group or a Person | D78: 1 | E78: 103 | F78: Party leaders to deal best with foreign and security issues in Israel | G78: 82  83. And regarding the foreign and security issues in Israel? | H78: numeric | I78: 1: Kadima leaders; 2: Likud leaders; 3: Avoda leaders; 4: All of them to the same deggree; 5: None of them; 6: Another party
A79: a84 | B79: 2006 | C79: Support/Rejection of a Group or a Person | D79: 1 | E79: 104 | F79: In second place | G79: 83  83. And regarding the foreign and security issues in Israel? | H79: numeric | I79: 1: Kadima leaders; 2: Likud leaders; 3: Avoda leaders; 4: All of them to the same deggree; 5: None of them; 6: Another party
A80: a85 | B80: 2006 | C80: Party Differences | D80: 1 | E80: 105 | F80: Party differences on the following issue:Jerusalem | G80: Do you think there are or are not differences among the parties on the following issues? | H80: numeric | I80: 1: Great differences; 5: Almost no differences
A81: a86 | B81: 2006 | C81: Party Differences | D81: 1 | E81: 106 | F81: Party differences on the following issue:Economy | G81: Do you think there are or are not differences among the parties on the following issues? | H81: numeric | I81: 1: Great differences; 5: Almost no differences
A82: a87 | B82: 2006 | C82: Party Differences | D82: 1 | E82: 107 | F82: Party differences on the following issue:Social policy | G82: Do you think there are or are not differences among the parties on the following issues? | H82: numeric | I82: 1: Great differences; 5: Almost no differences
A83: a88 | B83: 2006 | C83: Party Differences | D83: 1 | E83: 108 | F83: Party differences on the following issue:State and Religion | G83: Do you think there are or are not differences among the parties on the following issues? | H83: numeric | I83: 1: Great differences; 5: Almost no differences
A84: a89 | B84: 2006 | C84: Party Differences | D84: 1 | E84: 109 | F84: Party differences on the following issue:'Peace and Territories | G84: Do you think there are or are not differences among the parties on the following issues? | H84: numeric | I84: 1: Great differences; 5: Almost no differences
A85: a90 | B85: 2006 | C85: Party Differences | D85: 1 | E85: 110 | F85: Party differences on the following issue:Terror | G85: Do you think there are or are not differences among the parties on the following issues? | H85: numeric | I85: 1: Great differences; 5: Almost no differences
... A141: b64 | B141: 2006 | C141: Newspaper/TV | D141: 1 | E141: 174 | F141: Frequency of reading daily newspaper | G141: 63. Do you read a daily newspaper every day? | H141: numeric | I141: 1: Almost never; 2: Every now and then; 3: Approximately once a week; 4: Twice or three times a week; 5: One daily newspaper almost once a day; 6: More than one newspaper amost every day
A142: b66 | B142: 2006 | C142: Newspaper/TV | D142: 1 | E142: 175-176 | F142: Newspaper usually read | G142: 64. Which newspaper do you usually read, which is your main newspaper? (do not read) | H142: numeric
A143: b67 | B143: 2006 | C143: Newspaper/TV | D143: 1 | E143: 177 | F143: News on TV | G143: 66. Do you usually watch the news on TV? | H143: numeric | I143: 1: Almost never; 2: Not so often; 3: Once a week or so; 4: 2-3 times a week; 5: At least once a day; 6: More than once a day
A144: b69 | B144: 2006 | C144: Newspaper/TV | D144: 1 | E144: 178-179 | F144: Which TV channel | G144: 67. And which TV channel do you usually watch? (do not read) | H144: numeric | I144: 1: Channel 1; 2: Channel 2; 3: Channel 9 (Israel+); 4: Channel 10; 5: RTVI; 6: Al-Jazira; 7: MBC; 8: Other; 9: More than one in Hebrew; 10: ORT (Russian); 11: CNN; 12: RTVI and Israel+; 13: RTVI and/or Israel+ and Hebrew channel; 14: Israel+ and ORT; 15: Euronews; 16: More than one in Arabic; 17: More thane one in Arabic and Hebrew; 18: El-Manar; 19: BBC; 20: TV-5 (France); 21: NTV (Russian)
A145: b70 | B145: 2006 | C145: Newspaper/TV | D145: 1 | E145: 180 | F145: Election campaign broadcasts on TV | G145: 69. Do you usually watch the election campaign broadcasts on TV?(for interviews before the beginning of broadcasts (March 7, 2006): Do you intend to watch the campaign broadcasts on TV?) | H145: numeric | I145: 1: Every day; 2: Usually; 3: Sometimes; 4: Not very often; 5: Never
A146: b71 | B146: 2006 | C146: Newspaper/TV | D146: 1 | E146: 181 | F146: Sites of political parties | G146: 70. Do you surf sites of political parties? | H146: numeric | I146: 1: Do not surf the internet at all; 2: Surf but not sites of parties; 3: Surf once in a while the sites of parties; 4: Yes quite often
A147: b72 | B147: 2006 | C147: Newspaper/TV | D147: 1 | E147: 182 | F147: Which paties' sites | G147: 71. Those who answered 3 or 4 ask: Which parties' sites do you surf? | H147: numeric | I147: 1: The ones which I support; 2: Only parties which I dislike; 3: All kinds of parties
A148: b73 | B148: 2006 | C148: Chance the Party to be in the Next Government | D148: 1 | E148: 183 | F148: Supporter or member of any party | G148: 72. Are you a member, supporter, or an activist of any of the parties? | H148: numeric | I148: 1: Not a supporter or an activist in any of the parties; 2: Supporter of a party but not a member; 3: Member; 4: Active member; 5: A member and hold a position in a party
A149: b75 | B149: 2006 | C149: Chance the Party to be in the Next Government | D149: 1 | E149: 184-185 | F149: Respondent party vote if elections were held today | G149: 73. If the elections for Knesset were held today, for which party would you vote for? (do not read answers) | H149: numeric | I149: 1: Kadima; 2: Likud; 3: Avoda; 4: Yisrael Beitenu (Liberman); 5: Ihud Leumi-Mafdal; 6: Yahadut Ha Tora; 7: Shas; 8: Meretz; 9: Shinui; 10: Hetz (Poraz); 11: The Green Party; 12: Ale Yarok; 13: The Pensioners; 14: Hazit Leumit Yehudit (Marzel); 15: Herut; 16: Tafnit; 17: Balad; 18: Raam-Taal; 19: Hadash; 20: Zionut Hadasha; 21: Daam; 22: Lehem; 96: Blank ballot; 97: Undecided; 98: Do not intend to vote; 99: Refuse to answer
A150: b78 | B150: 2006 | C150: Chance the Party to be in the Next Government | D150: 1 | E150: 186-188 | F150: Likelihood of Kadima to be in the coalition | G150: And now we would like to ask you about the chance of each one of the following parties to be a member of the coalition after the elections. Here you have a scale between 0 to 10, where 10 means you think there is no chance the party will be a member of the coalition, 50 means that the party's chances are half and half, and 100 means that it will certainly be a member of the coalition. What's the chance that Kadima will be in the next government? | H150: numeric
A151: b81 | B151: 2006 | C151: Chance the Party to be in the Next Government | D151: 1 | E151: 189-191 | F151: Likelihood of Avoda to be in the coalition | G151: And now we would like to ask you about the chance of each one of the following parties to be a member of the coalition after the elections. Here you have a scale between 0 to 10, where 10 means you think there is no chance the party will be a member of the coalition, 50 means that the party's chances are half and half, and 100 means that it will certainly be a member of the coalition. The Labor? | H151: numeric
A152: b84 | B152: 2006 | C152: Chance the Party to be in the Next Government | D152: 1 | E152: 192-194 | F152: Likelihood of Likud to be in the coalition | G152: And now we would like to ask you about the chance of each one of the following parties to be a member of the coalition after the elections. Here you have a scale between 0 to 10, where 10 means you think there is no chance the party will be a member of the coalition, 50 means that the party's chances are half and half, and 100 means that it will certainly be a member of the coalition. The Likud? | H152: numeric
A153: b87 | B153: 2006 | C153: Chance the Party to be in the Next Government | D153: 1 | E153: 195-197 | F153: Likelihood of the party he said he will vote for | G153: And now we would like to ask you about the chance of each one of the following parties to be a member of the coalition after the elections. Here you have a scale between 0 to 10, where 10 means you think there is no chance the party will be a member of the coalition, 50 means that the party's chances are half and half, and 100 means that it will certainly be a member of the coalition. And (the party he said he will vote for in the previous question) | H153: numeric
A154: b89 | B154: 2006 | C154: Chance the Party to be in the Next Government | D154: 1 | E154: 198-200 | F154: Number of seats you think Kadima will win | G154: And what about the number of MKs these parties will have in the next Knesset? How many MKs will have? Kadima? | H154: numeric
A155: b91 | B155: 2006 | C155: Chance the Party to be in the Next Government | D155: 1 | E155: 201-203 | F155: Number of seats you think Avoda will win | G155: And what about the number of MKs these parties will have in the next Knesset? How many MKs will have? Labor? | H155: numeric
A156: b93 | B156: 2006 | C156: Chance the Party to be in the Next Government | D156: 1 | E156: 204-206 | F156: Number of seats you think Likud will win | G156: And what about the number of MKs these parties will have in the next Knesset? How many MKs will have? Likud? | H156: numeric
A157: c6 | B157: 2006 | C157: Chance the Party to be in the Next Government | D157: 1 | E157: 207-209 | F157: Number of seats you think the party you vote will win | G157: And what about the number of MKs these parties will have in the next Knesset? How many MKs will have? And (the party he said he will vote for in the previous question) | H157: numeric
A158: c9 | B158: 2006 | C158: Different Coalitions after the Elections | D158: 1 | E158: 210-212 | F158: Chances for Kadima-Labor coalition | G158: And now we want to ask you about the chances of different coalitions after the elections. On a scale of 0 to 100, 0 means you give no chance for a certain coalition, 50 means that the coalition's chances are half and half, and 100 means that you are sure this coalition will exist. Naturally you can give any number between 0 to 100. On such a scale, what are the chances that after the elections, there will be a coalition between: | H158: numeric
A159: c12 | B159: 2006 | C159: Different Coalitions after the Elections | D159: 1 | E159: 213-215 | F159: Chances for Kadima-Likud coalition | G159: And now we want to ask you about the chances of different coalitions after the elections. On a scale of 0 to 100, 0 means you give no chance for a certain coalition, 50 means that the coalition's chances are half and half, and 100 means that you are sure this coalition will exist. Naturally you can give any number between 0 to 100. On such a scale, what are the chances that after the elections, there will be a coalition between: | H159: numeric
A160: c15 | B160: 2006 | C160: Different Coalitions after the Elections | D160: 1 | E160: 216-218 | F160: Chances for Kadima-Likud-Haredim coalition | G160: And now we want to ask you about the chances of different coalitions after the elections. On a scale of 0 to 100, 0 means you give no chance for a certain coalition, 50 means that the coalition's chances are half and half, and 100 means that you are sure this coalition will exist. Naturally you can give any number between 0 to 100. On such a scale, what are the chances that after the elections, there will be a coalition between: | H160: numeric
A161: c18 | B161: 2006 | C161: Different Coalitions after the Elections | D161: 1 | E161: 219-221 | F161: Chances for Kadima-Labor-Haredim coalition | G161: And now we want to ask you about the chances of different coalitions after the elections. On a scale of 0 to 100, 0 means you give no chance for a certain coalition, 50 means that the coalition's chances are half and half, and 100 means that you are sure this coalition will exist. Naturally you can give any number between 0 to 100. On such a scale, what are the chances that after the elections, there will be a coalition between: | H161: numeric
... A164: c27 | B164: 2006 | C164: Different Coalitions after the Elections | D164: 1 | E164: 228-230 | F164: Chances for Kadima-Labor-Likud-Right parties and Haredim coalition | G164: And now we want to ask you about the chances of different coalitions after the elections. On a scale of 0 to 100, 0 means you give no chance for a certain coalition, 50 means that the coalition's chances are half and half, and 100 means that you are sure this coalition will exist. Naturally you can give any number between 0 to 100. On such a scale, what are the chances that after the elections, there will be a coalition between: | H164: numeric
A165: c28 | B165: 2006 | C165: Different Coalitions after the Elections | D165: 1 | E165: 231-232 | F165: Will support Kadima-Labor coalition | G165: And how supportive would you be of the following coalitions after the elections (read the coalitions in a different order) on a 10 point scale where '1' means strong rejection and '10' means strong support, and the rest are levels in between: | H165: numeric | I165: 1: Reject; 10: Support
A166: c29 | B166: 2006 | C166: Different Coalitions after the Elections | D166: 1 | E166: 233-234 | F166: Will support Kadima-Likud coalition | G166: And how supportive would you be of the following coalitions after the elections (read the coalitions in a different order) on a 10 point scale where '1' means strong rejection and '10' means strong support, and the rest are levels in between: | H166: numeric | I166: 1: Reject; 10: Support
A167: c30 | B167: 2006 | C167: Different Coalitions after the Elections | D167: 1 | E167: 235-237 | F167: Will support Kadima-Likud-Haredim coalition | G167: And how supportive would you be of the following coalitions after the elections (read the coalitions in a different order) on a 10 point scale where '1' means strong rejection and '10' means strong support, and the rest are levels in between: | H167: numeric | I167: 1: Reject; 10: Support
A168: c31 | B168: 2006 | C168: Different Coalitions after the Elections | D168: 1 | E168: 238-240 | F168: Will support Kadima-Labor-Haredim coalition | G168: And how supportive would you be of the following coalitions after the elections (read the coalitions in a different order) on a 10 point scale where '1' means strong rejection and '10' means strong support, and the rest are levels in between: | H168: numeric | I168: 1: Reject; 10: Support
A169: c32 | B169: 2006 | C169: Different Coalitions after the Elections | D169: 1 | E169: 241-243 | F169: Will support Kadima-Likud-Right coalition | G169: And how supportive would you be of the following coalitions after the elections (read the coalitions in a different order) on a 10 point scale where '1' means strong rejection and '10' means strong support, and the rest are levels in between: | H169: numeric | I169: 1: Reject; 10: Support
A170: c33 | B170: 2006 | C170: Different Coalitions after the Elections | D170: 1 | E170: 244-245 | F170: Will support Kadima-Labor-Meretz coalition | G170: And how supportive would you be of the following coalitions after the elections (read the coalitions in a different order) on a 10 point scale where '1' means strong rejection and '10' means strong support, and the rest are levels in between: | H170: numeric | I170: 1: Reject; 10: Support
A171: c34 | B171: 2006 | C171: Different Coalitions after the Elections | D171: 1 | E171: 246-248 | F171: Will support Kadima-Labor-Likud-Right parties and Haredim coalition | G171: And how supportive would you be of the following coalitions after the elections (read the coalitions in a different order) on a 10 point scale where '1' means strong rejection and '10' means strong support, and the rest are levels in between: | H171: numeric | I171: 1: Reject; 10: Support
A172: c36 | B172: 2006 | C172: Different Coalitions after the Elections | D172: 1 | E172: 249-250 | F172: Preferable coalition | G172: 34. And in the final analysis, among these possibilities, which would you prefer? | H172: numeric | I172: 27: Kadima-Avoda; 28: Kadima-Likud; 29: Kadima-Likud-Haredim; 30: Kadima-Avoda-Haredim; 31: Kadima-Likud-Right; 32: Kadima-Avoda-Meretz; 33: Memshelet Ahdut Leumit; 34: Kadima-Avoda-Liberman; 35: Kadima-Avoda-Likud-Liberman; 36: Kadima-Likud-Liberman; 37: Likud-Avoda; 38: Kadima-Avoda-Likud; 39: Likud-Right-Haredim; 40: Kadima-Avoda-Merets-Arabs; 41: Likud-Avoda-Haredim; 42: Kadima-small parties
A173: c38 | B173: 2006 | C173: Previous Elections | D173: 1 | E173: 251-252 | F173: Respondent vote for PM if elections for PM were held | G173: 36. And if there were two ballots in the coming elections, one for Prime Minister and one for the Knesset, for whom would you vote for Prime Minister? | H173: numeric | I173: 1: Peretz; 2: Olmert; 3: Netanyahu; 4: Other; 5: Blank ballot; 6: Don't know; 7: Wouldn't vote; 9: Refuse; 10: Peres; 11: Liberman; 12: Sharanskiy; 13: Dery; 14: Ishai; 15: Porush; 16: Gafni; 17: Ami Ayalon; 18: Ramon; 19: Uzi Landau; 20: Ariel Sharon; 21: Eitam; 22: Feiglin; 23: Sarid; 24: Beilin; 25: Marzel; 26: Livni; 27: Bishara; 28: Tibi; 29: Taleb Sane; 30: Eli Landau; 31: Poraz; 32: M. Elyahu; 33: Beni Begin; 34: Uzi Dayan; 35: Mofaz; 36: Barak
A174: c40 | B174: 2006 | C174: Previous Elections | D174: 1 | E174: 253-254 | F174: Respondent party vote if elections for PM were also held | G174: 38. And for the Knesset? (for the interviewer: use the code in question 73) | H174: numeric | I174: 1: Kadima; 2: Likud; 3: Avoda; 4: Liberman; 5: Ihud Leumi-Mafdal; 6: Yahadut Ha Tora; 7: Shas; 8: Meretz; 9: Shinui; 10: Hetz (Poraz); 11: Green Party; 12: Ale Yarok; 13: Pensioners; 14: Hazit Leumit Yehudit (Marzel); 15: Herut; 16: Tafnit; 17: Balad; 18: Raam; 19: Hadash; 96: Blank ballot; 97: Undecided; 98: Do not intend to vote; 99: Refuse to answer
A175: c42 | B175: 2006 | C175: Previous Elections | D175: 1 | E175: 255-256 | F175: Vote in 2003 elections | G175: 40. For which party did you vote in the previous elections in 2003? (do not read the answers) | H175: numeric | I175: 1: Likud; 2: Avoda-Meimad; 3: Shinui; 4: Meretz; 5: Ihud Leumi; 6: Mafdal; 7: Yahadut Hatora; 8: Shas; 9: Am Ehad; 10: Israel Bealiya; 11: Green party; 12: Balad; 13: Raam; 14: Hadash; 15: Another; 16: Ale Yarok; 17: Hazit Leumit Yehudit (Marzel); 18: Herut; 19: Daam; 90: Don't remember; 96: Blank ballot; 97: Didn't vote although had the right to vote; 98: Didn't vote / did not have the right to vote; 99: Refuse to answer
A176: c43 | B176: 2006 | C176: Previous Elections | D176: 1 | E176: 257 | F176: Vote for PM in 2001 elections | G176: 42. For whom did you vote for prime minister in 2001? | H176: numeric | I176: 1: Barak; 2: Sharon; 3: Blank ballot; 4: Didn't vote although had the right to vote; 5: Didn't vote / did not have the right to vote; 6: Don't remember; 9: Refuse to answer
... A187: c54 | B187: 2006 | C187: Self-identity | D187: 1 | E187: 268 | F187: The Knesset's chairman | G187: 53. To the best of your knowledge, who is the Knesset's chairman? (do not read answers) | H187: numeric | I187: 1: Rivlin; 2: Wrong answer; 8: Do not know
A188: c56 | B188: 2006 | C188: Rersonal and Household Details | D188: 1 | E188: 269-270 | F188: Age | G188: 54. How old are you? | H188: numeric
A189: c57 | B189: 2006 | C189: Rersonal and Household Details | D189: 1 | E189: 271 | F189: Religious observance | G189: 56. To what extent do you observe religious tradition? | H189: numeric | I189: 1: Not at all; 2: A little bit; 3: A lot; 4: I observe all of it
A190: c60 | B190: 2006 | C190: Rersonal and Household Details | D190: 1 | E190: 272-273 | F190: Country of birth | G190: 57. (not for Arabs): Where were you born? (write a state) (if in the former USSR, write the name of the republic) | H190: numeric
A191: c62 | B191: 2006 | C191: Rersonal and Household Details | D191: 1 | E191: 274-275 | F191: Year of immigration | G191: 60-61. (not for Arabs): for those who were not born here: When did you come to Israel? | H191: numeric
A192: c63 | B192: 2006 | C192: Rersonal and Household Details | D192: 1 | E192: 276 | F192: Russian immigrant after 1989 (not for Arabs) | G192: 62. (not for Arabs): for the interviewer: if R came from the USSR after 1989, circle: 1. from the USSR | H192: numeric | I192: 1: New immigrant
A193: c65 | B193: 2006 | C193: Rersonal and Household Details | D193: 1 | E193: 277-278 | F193: City in former USSR (only for immigrants from the former USSR) | G193: 63. (only for immigrants from the former USSR): in what city did you live before you came to Israel? | H193: numeric | I193: 1: Moscow; 2: St.Perersburg; 3: Large cities in Euro-Russia; 4: Small cities in Euro-Russia; 5: Large cities in Asian-Russia; 6: Small cities in Asian-Russia; 7: Birobidjan & Habarovsk; 8: Russian Kavkazian autonomies; 9: Kiev and large cities in East/South Ukraine; 10: Towns in East/South Ukraine; 11: West/Central Ukrainian towns; 12: Kishinev; 13: Rest of Moldavia; 14: Minsk; 15: Rest of Belorussia; 16: Yerevan; 17: Rest of Armenia; 18: Baku; 19: Rest of Azerbaijan; 20: Tbilisi; 21: Rest of Georgia; 22: Tashkent; 23: Almaty; 24: Rest of Kazahstan; 25: Turkmenistan, Tajikistan, Kirgyzstan; 26: Samarkand; 27: Riga; 28: Rest of Latvia; 29: Vilnius; 30: Rest of Lithuania; 31: Tallin; 32: Rest of Estonia; 33: Uzbek's towns
A194: c67 | B194: 2006 | C194: Rersonal and Household Details | D194: 1 | E194: 279-280 | F194: Nationality in passport in USSR (only for immigrants from the former USSR) | G194: 65. (only for immigrants from the former USSR): what was the nationality written in your internal Soviet passport? | H194: numeric | I194: 1: Jewish; 2: Other; 3: Nothing; 4: No passport; 5: Don't remember; 10: Russian; 11: Ukrainian; 12: Moldavian; 13: Yakutian; 14: Gorskiy Evrei; 15: Armenian; 16: Belorussian; 17: Mordovi
A195: c68 | B195: 2006 | C195: Rersonal and Household Details | D195: 1 | E195: 281 | F195: Friends in Israel (only for immigrants from the former USSR) | G195: 67. (only for immigrants from the former USSR): Regarding your friends in Israel, would you say that most of them are: | H195: numeric | I195: 1: New immigrant; 2: Veterans; 3: Half and half
A196: c69 | B196: 2006 | C196: Rersonal and Household Details | D196: 1 | E196: 282 | F196: Russian party participation in elections (only for immigrants from the former USSR) | G196: 68. (only for immigrants from the former USSR): would you like to see a Russian party participating in the coming elections? | H196: numeric | I196: 1: Of course; 2: I think so; 3: I don't think so; 4: Of course not
A197: c72 | B197: 2006 | C197: Rersonal and Household Details | D197: 1 | E197: 283-285 | F197: Father's country of birth (not for Arabs) | G197: 69. (not for Arabs): where was your father born? (write the name of the state): if in the USSR, write the name of the republic) | H197: numeric
A198: c75 | B198: 2006 | C198: Rersonal and Household Details | D198: 1 | E198: 286-288 | F198: Mother's country of birth (not for Arabs) | G198: 72. (not for Arabs): where was your mother born? (write the name of the state): if in the USSR, write the name of the republic) | H198: numeric
A199: c77 | B199: 2006 | C199: Rersonal and Household Details | D199: 1 | E199: 289-290 | F199: Years of schooling | G199: 75. How many years did you study? (including elementary school) | H199: numeric
A200: c78 | B200: 2006 | C200: Rersonal and Household Details | D200: 1 | E200: 291 | F200: Academic degree | G200: 77. (for those who finished 12 years and more): Do you have an academic degree? | H200: numeric | I200: 1: Yes; 2: No
A201: c80 | B201: 2006 | C201: Rersonal and Household Details | D201: 1 | E201: 292-293 | F201: Profession | G201: 78. Describe your profession or your main job (if R is not working, his last job) (to the interviewer: be specific as you can: not just a doctor but an eye doctor etc.) | H201: character
A202: c81 | B202: 2006 | C202: Rersonal and Household Details | D202: 1 | E202: 294-295 | F202: Monthly family expenditure (relative to average of 9,300 NIS) | G202: 80. The average monthly expenditure for a family of 4 people was NIS 9,300 last month. Does your family spend: | H202: numeric | I202: 1: Much more; 2: A little more; 3: About the average; 4: A little less; 5: Much less
A203: c82 | B203: 2006 | C203: Rersonal and Household Details | D203: 1 | E203: 296-297 | F203: Are you worried about losing your job? | G203: 81. Are you worried of losing your job? | H203: numeric | I203: 1: Not at all; 2: A little worried; 3: Very worried; 4: Lost job lately and looking for one; 5: Not working and not looking for a job
A204: c84 | B204: 2006 | C204: Rersonal and Household Details | D204: 1 | E204: 298-299 | F204: Rooms in dwelling | G204: 82. How many rooms do you have in your house? | H204: numeric
A205: c86 | B205: 2006 | C205: Rersonal and Household Details | D205: 1 | E205: 300-301 | F205: Number of persons in household | G205: 84. How many people are living in the house? (including soldiers): | H205: numeric
A206: c87 | B206: 2006 | C206: Rersonal and Household Details | D206: 1 | E206: 302 | F206: Social class (self identified) | G206: 86. What is your social class? | H206: numeric | I206: 1: High; 2: Medium-high; 3: Medium; 4: Low
A207: c88 | B207: 2006 | C207: Rersonal and Household Details | D207: 1 | E207: 303-304 | F207: Religion | G207: 87. Religion | H207: numeric | I207: 1: Jewish; 2: Muslim; 3: Christian; 4: Druze; 5: No religion
A208: c89 | B208: 2006 | C208: Rersonal and Household Details | D208: 1 | E208: 305 | F208: Religious self-definition (not for Arabs) | G208: 88. (not for Arabs): How would you define yourself? | H208: numeric | I208: 1: Secular; 2: Traditional; 3: Religious; 4: Haredi
A209: c90 | B209: 2006 | C209: Rersonal and Household Details | D209: 1 | E209: 306 | F209: Sex | G209: 89. Gender | H209: numeric | I209: 1: Male; 2: Female
A210: c93 | B210: 2006 | C210: Rersonal and Household Details | D210: 1 | E210: 307-309 | F210: Locality of residency | G210: 90. Place of residency | H210: numeric
...

Sheet comments_data
A1: Sheet Name | B1: Cell Address | C1: Comment | D1: finalType | E1: Content Only | F1: Question Id | G1: Survey | H1: category | I1: record | J1: columns | K1: question_title | L1: question_description | M1: answers | N1: Affected Surveys | O1: Answers but better
A2: דמוגרפיה | B2: $L$3 | C2: יניב שפירא: 1 = ינואר 2 = פברואר | D2: scale | E2: 1 = ינואר 2 = פברואר | F2: b51 | G2: =VLOOKUP($F2, codebooks_data_reordered!$A:$I, 2, FALSE) -> 2006 | H2: =VLOOKUP($F2, codebooks_data_reordered!$A:$I, 3, FALSE) -> Most/Less Suitable Characteristic of the Party | I2: =VLOOKUP($F2, codebooks_data_reordered!$A:$I, 4, FALSE) -> 1 | J2: =VLOOKUP($F2, codebooks_data_reordered!$A:$I, 5, FALSE) -> 161 | K2: =VLOOKUP($F2, codebooks_data_reordered!$A:$I, 6, FALSE) -> Most suitable characteristic of the party: Leadership abilites | L2: =VLOOKUP($F2, codebooks_data_reordered!$A:$I, 7, FALSE) -> Below is a list of characteristics of leaders. Please tell which politician suits the characteristic best: Ehud Ulmert, Binyamin Netanyahu or Amir Peretz? Do not read 4 and 5. To those who said 1, 2 or 3, ask to whom this characteristic suits the least. Leadership abilities | M2: =VLOOKUP($F2, codebooks_data_reordered!$A:$I, 9, FALSE) -> 1: Olmert; 2: Netanyahu; 3: Peretz; 4: All; 5: None | O2: =SUBSTITUTE(M2, ";", CHAR(10)) -> 1: Olmert 2: Netanyahu 3: Peretz 4: All 5: None
A3: דמוגרפיה | B3: $A$5 | C3: יניב שפירא: שאלה 145 אין קידוד בstata גם ב2020 וגם ב2019 גם ב2021 | D3: scale | E3: שאלה 145 אין קידוד בstata גם ב2020 וגם ב2019 גם ב2021 | F3: מקום הראיון | G3: =VLOOKUP($F3, codebooks_data_reordered!$A:$I, 2, FALSE) -> #N/A | H3: =VLOOKUP($F3, codebooks_data_reordered!$A:$I, 3, FALSE) -> #N/A | I3: =VLOOKUP($F3, codebooks_data_reordered!$A:$I, 4, FALSE) -> #N/A | J3: =VLOOKUP($F3, codebooks_data_reordered!$A:$I, 5, FALSE) -> #N/A | K3: =VLOOKUP($F3, codebooks_data_reordered!$A:$I, 6, FALSE) -> #N/A | L3: =VLOOKUP($F3, codebooks_data_reordered!$A:$I, 7, FALSE) -> #N/A | M3: =VLOOKUP($F3, codebooks_data_reordered!$A:$I, 9, FALSE) -> #N/A | N3: 2020, 2019, 2021 | O3: =SUBSTITUTE(M3, ";", CHAR(10)) -> #N/A
A4: דמוגרפיה | B4: $D$6 | C4: יניב שפירא: 1 = יהודי 2 = ערבי | D4: scale | E4: 1 = יהודי 2 = ערבי | F4: sector | G4: =VLOOKUP($F4, codebooks_data_reordered!$A:$I, 2, FALSE) -> #N/A | H4: =VLOOKUP($F4, codebooks_data_reordered!$A:$I, 3, FALSE) -> #N/A | I4: =VLOOKUP($F4, codebooks_data_reordered!$A:$I, 4, FALSE) -> #N/A | J4: =VLOOKUP($F4, codebooks_data_reordered!$A:$I, 5, FALSE) -> #N/A | K4: =VLOOKUP($F4, codebooks_data_reordered!$A:$I, 6, FALSE) -> #N/A | L4: =VLOOKUP($F4, codebooks_data_reordered!$A:$I, 7, FALSE) -> #N/A | M4: =VLOOKUP($F4, codebooks_data_reordered!$A:$I, 9, FALSE) -> #N/A | O4: =SUBSTITUTE(M4, ";", CHAR(10)) -> #N/A
A5: דמוגרפיה | B5: $F$8 | C5: יניב שפירא: 1 = גרסה A 2 = גרסה B | D5: scale | E5: 1 = גרסה A 2 = גרסה B | F5: version | G5: =VLOOKUP($F5, codebooks_data_reordered!$A:$I, 2, FALSE) -> #N/A | H5: =VLOOKUP($F5, codebooks_data_reordered!$A:$I, 3, FALSE) -> #N/A | I5: =VLOOKUP($F5, codebooks_data_reordered!$A:$I, 4, FALSE) -> #N/A | J5: =VLOOKUP($F5, codebooks_data_reordered!$A:$I, 5, FALSE) -> #N/A | K5: =VLOOKUP($F5, codebooks_data_reordered!$A:$I, 6, FALSE) -> #N/A | L5: =VLOOKUP($F5, codebooks_data_reordered!$A:$I, 7, FALSE) -> #N/A | M5: =VLOOKUP($F5, codebooks_data_reordered!$A:$I, 9, FALSE) -> #N/A | O5: =SUBSTITUTE(M5, ";", CHAR(10)) -> #N/A
A6: דמוגרפיה | B6: $I$8 | C6: יניב שפירא: a , b, c | D6: scale | E6: a , b, c | F6: version | G6: =VLOOKUP($F6, codebooks_data_reordered!$A:$I, 2, FALSE) -> #N/A | H6: =VLOOKUP($F6, codebooks_data_reordered!$A:$I, 3, FALSE) -> #N/A | I6: =VLOOKUP($F6, codebooks_data_reordered!$A:$I, 4, FALSE) -> #N/A | J6: =VLOOKUP($F6, codebooks_data_reordered!$A:$I, 5, FALSE) -> #N/A | K6: =VLOOKUP($F6, codebooks_data_reordered!$A:$I, 6, FALSE) -> #N/A | L6: =VLOOKUP($F6, codebooks_data_reordered!$A:$I, 7, FALSE) -> #N/A | M6: =VLOOKUP($F6, codebooks_data_reordered!$A:$I, 9, FALSE) -> #N/A | O6: =SUBSTITUTE(M6, ";", CHAR(10)) -> #N/A
A7: דמוגרפיה | B7: $L$9 | C7: יניב שפירא: 1 = עברית 2 = ערבית 3 = רוסית | D7: scale | E7: 1 = עברית 2 = ערבית 3 = רוסית | F7: b55 | G7: =VLOOKUP($F7, codebooks_data_reordered!$A:$I, 2, FALSE) -> 2006 | H7: =VLOOKUP($F7, codebooks_data_reordered!$A:$I, 3, FALSE) -> Most/Less Suitable Characteristic of the Party | I7: =VLOOKUP($F7, codebooks_data_reordered!$A:$I, 4, FALSE) -> 1 | J7: =VLOOKUP($F7, codebooks_data_reordered!$A:$I, 5, FALSE) -> 165 | K7: =VLOOKUP($F7, codebooks_data_reordered!$A:$I, 6, FALSE) -> Most suitable characteristic of the party: Prefers the country | L7: =VLOOKUP($F7, codebooks_data_reordered!$A:$I, 7, FALSE) -> Below is a list of characteristics of leaders. Please tell which politician suits the characteristic best: Ehud Ulmert, Binyamin Netanyahu or Amir Peretz? Do not read 4 and 5. To those who said 1, 2 or 3, ask to whom this characteristic suits the least. Prefers the country's good to other interests | M7: =VLOOKUP($F7, codebooks_data_reordered!$A:$I, 9, FALSE) -> 1: Olmert; 2: Netanyahu; 3: Peretz; 4: All; 5: None | O7: =SUBSTITUTE(M7, ";", CHAR(10)) -> 1: Olmert 2: Netanyahu 3: Peretz 4: All 5: None
A8: דמוגרפיה | B8: $W$10 | C8: יניב שפירא: 1 = 20-25 2 = 25-29 3 = 30-34 4 = 35-39 5 = 40-44 6 = 45-49 7 = 50-54 8 = 55-64 9 = 65+ | D8: scale | E8: 1 = 20-25 2 = 25-29 3 = 30-34 4 = 35-39 5 = 40-44 6 = 45-49 7 = 50-54 8 = 55-64 9 = 65+ | F8: c24 | G8: =VLOOKUP($F8, codebooks_data_reordered!$A:$I, 2, FALSE) -> 2006 | H8: =VLOOKUP($F8, codebooks_data_reordered!$A:$I, 3, FALSE) -> Different Coalitions after the Elections | I8: =VLOOKUP($F8, codebooks_data_reordered!$A:$I, 4, FALSE) -> 1 | J8: =VLOOKUP($F8, codebooks_data_reordered!$A:$I, 5, FALSE) -> 225-227 | K8: =VLOOKUP($F8, codebooks_data_reordered!$A:$I, 6, FALSE) -> Chances for Kadima-Labor-Meretz coalition | L8: =VLOOKUP($F8, codebooks_data_reordered!$A:$I, 7, FALSE) -> And now we want to ask you about the chances of different coalitions after the elections. On a scale of 0 to 100, 0 means you give no chance for a certain coalition, 50 means that the coalition's chances are half and half, and 100 means that you are sure this coalition will exist. Naturally you can give any number between 0 to 100. On such a scale, what are the chances that after the elections, there will be a coalition between: | M8: =VLOOKUP($F8, codebooks_data_reordered!$A:$I, 9, FALSE) -> 0 | O8: =SUBSTITUTE(M8, ";", CHAR(10)) -> 0
A9: דמוגרפיה | B9: $AB$10 | C9: יניב שפירא: 1 = 20-24 2 = 25-29 3 = 30-34 4 = 35-39 5 = 40-44 6 = 45-49 7 = 50-54 8 = 55-64 9 = 65+ | D9: scale | E9: 1 = 20-24 2 = 25-29 3 = 30-34 4 = 35-39 5 = 40-44 6 = 45-49 7 = 50-54 8 = 55-64 9 = 65+ | F9: g62 | G9: =VLOOKUP($F9, codebooks_data_reordered!$A:$I, 2, FALSE) -> 1988_N=873 | H9: =VLOOKUP($F9, codebooks_data_reordered!$A:$I, 3, FALSE) -> FOR WHICH PARTIES WOULD YOU VOTE FOR IF NO LIMITATION IS POSED | I9: =VLOOKUP($F9, codebooks_data_reordered!$A:$I, 4, FALSE) -> 1 | J9: =VLOOKUP($F9, codebooks_data_reordered!$A:$I, 5, FALSE) -> 175-176 | K9: =VLOOKUP($F9, codebooks_data_reordered!$A:$I, 6, FALSE) -> Basis for above estimate | L9: =VLOOKUP($F9, codebooks_data_reordered!$A:$I, 7, FALSE) -> 0 | M9: =VLOOKUP($F9, codebooks_data_reordered!$A:$I, 9, FALSE) -> 0 | O9: =SUBSTITUTE(M9, ";", CHAR(10)) -> 0
A10: דמוגרפיה | B10: $AH$10 | C10: יניב שפירא: 1 = 18-24 2 = 25-29 3 = 30-34 4 = 35-39 5 = 40-44 6 = 45-49 7 = 50-54 8 = 55-64 9 = 65+ | D10: scale | E10: 1 = 18-24 2 = 25-29 3 = 30-34 4 = 35-39 5 = 40-44 6 = 45-49 7 = 50-54 8 = 55-64 9 = 65+ | F10: c79 | G10: =VLOOKUP($F10, codebooks_data_reordered!$A:$I, 2, FALSE) -> 1969_1 | H10: =VLOOKUP($F10, codebooks_data_reordered!$A:$I, 3, FALSE) -> SUPPORT OR OPPOSITION FOR GOVERNMENT OWNERSHIP OF THE FOLLOWING: | I10: =VLOOKUP($F10, codebooks_data_reordered!$A:$I, 4, FALSE) -> 3 | J10: =VLOOKUP($F10, codebooks_data_reordered!$A:$I, 5, FALSE) -> 58 | K10: =VLOOKUP($F10, codebooks_data_reordered!$A:$I, 6, FALSE) -> Mother's country of birth | L10: =VLOOKUP($F10, codebooks_data_reordered!$A:$I, 7, FALSE) -> 0 | M10: =VLOOKUP($F10, codebooks_data_reordered!$A:$I, 9, FALSE) -> 0: No answer; 1: Israel; 2: Central and Eastern Europe; 3: Southern Europe; 4: Western Europe; 5: English-speaking countries; 6: North African countries; 7: Near and Middle Eastern countries; 8: Far Eastern countries; 9: South and Gentral America | O10: =SUBSTITUTE(M10, ";", CHAR(10)) -> 0: No answer 1: Israel 2: Central and Eastern Europe 3: Southern Europe 4: Western Europe 5: English-speaking countries 6: North African countries 7: Near and Middle Eastern countries 8: Far Eastern countries 9: South and Gentral America
A11: דמוגרפיה | B11: $D$12 | C11: יניב שפירא: 1 = 18-22 2 = 23-29 3 = 30-39 4 = 40-49 5 = 50-59 6 = 60-69 7 = 70-79 8 = 80 ומעלה | D11: scale | E11: 1 = 18-22 2 = 23-29 3 = 30-39 4 = 40-49 5 = 50-59 6 = 60-69 7 = 70-79 8 = 80 ומעלה | F11: agegroup | G11: =VLOOKUP($F11, codebooks_data_reordered!$A:$I, 2, FALSE) -> #N/A | H11: =VLOOKUP($F11, codebooks_data_reordered!$A:$I, 3, FALSE) -> #N/A | I11: =VLOOKUP($F11, codebooks_data_reordered!$A:$I, 4, FALSE) -> #N/A | J11: =VLOOKUP($F11, codebooks_data_reordered!$A:$I, 5, FALSE) -> #N/A | K11: =VLOOKUP($F11, codebooks_data_reordered!$A:$I, 6, FALSE) -> #N/A | L11: =VLOOKUP($F11, codebooks_data_reordered!$A:$I, 7, FALSE) -> #N/A | M11: =VLOOKUP($F11, codebooks_data_reordered!$A:$I, 9, FALSE) -> #N/A | O11: =SUBSTITUTE(M11, ";", CHAR(10)) -> #N/A
A12: דמוגרפיה | B12: $D$13 | C12: יניב שפירא: 1 = male 2 = female | D12: scale | E12: 1 = male 2 = female | F12: gender | G12: =VLOOKUP($F12, codebooks_data_reordered!$A:$I, 2, FALSE) -> #N/A | H12: =VLOOKUP($F12, codebooks_data_reordered!$A:$I, 3, FALSE) -> #N/A | I12: =VLOOKUP($F12, codebooks_data_reordered!$A:$I, 4, FALSE) -> #N/A | J12: =VLOOKUP($F12, codebooks_data_reordered!$A:$I, 5, FALSE) -> #N/A | K12: =VLOOKUP($F12, codebooks_data_reordered!$A:$I, 6, FALSE) -> #N/A | L12: =VLOOKUP($F12, codebooks_data_reordered!$A:$I, 7, FALSE) -> #N/A | M12: =VLOOKUP($F12, codebooks_data_reordered!$A:$I, 9, FALSE) -> #N/A | O12: =SUBSTITUTE(M12, ";", CHAR(10)) -> #N/A
A13: דמוגרפיה | B13: $M$13 | C13: יניב שפירא: 1 = אישה 2 = גבר | D13: scale | E13: 1 = אישה 2 = גבר | F13: c39 | G13: =VLOOKUP($F13, codebooks_data_reordered!$A:$I, 2, FALSE) -> 1999_1 | H13: =VLOOKUP($F13, codebooks_data_reordered!$A:$I, 3, FALSE) -> RESPONDENT'S DEMOGRAPHIC DETAILS | I13: =VLOOKUP($F13, codebooks_data_reordered!$A:$I, 4, FALSE) -> 3 | J13: =VLOOKUP($F13, codebooks_data_reordered!$A:$I, 5, FALSE) -> 48 | K13: =VLOOKUP($F13, codebooks_data_reordered!$A:$I, 6, FALSE) -> Self-definition of religious identity | L13: =VLOOKUP($F13, codebooks_data_reordered!$A:$I, 7, FALSE) -> 0 | M13: =VLOOKUP($F13, codebooks_data_reordered!$A:$I, 9, FALSE) -> 1: Secular; 2: Traditional; 3: Orthodox; 4: Ultra orthodox | O13: =SUBSTITUTE(M13, ";", CHAR(10)) -> 1: Secular 2: Traditional 3: Orthodox 4: Ultra orthodox
A14: דמוגרפיה | B14: $N$13 | C14: יניב שפירא: 1 = זכר 2 = נקבה | D14: scale | E14: 1 = זכר 2 = נקבה | F14: ccc56 | G14: =VLOOKUP($F14, codebooks_data_reordered!$A:$I, 2, FALSE) -> 1996_Jews | H14: =VLOOKUP($F14, codebooks_data_reordered!$A:$I, 3, FALSE) -> PERSONAL DATA | I14: =VLOOKUP($F14, codebooks_data_reordered!$A:$I, 4, FALSE) -> 1 | J14: =VLOOKUP($F14, codebooks_data_reordered!$A:$I, 5, FALSE) -> 204 | K14: =VLOOKUP($F14, codebooks_data_reordered!$A:$I, 6, FALSE) -> Ethnic self definition | L14: =VLOOKUP($F14, codebooks_data_reordered!$A:$I, 7, FALSE) -> 0 | M14: =VLOOKUP($F14, codebooks_data_reordered!$A:$I, 9, FALSE) -> 1: Ashkenazi; 2: Sephardi; 3: Neither | O14: =SUBSTITUTE(M14, ";", CHAR(10)) -> 1: Ashkenazi 2: Sephardi 3: Neither
A15: דמוגרפיה | B15: $O$13 | C15: יניב שפירא: 1 = אישה 2 = גבר | D15: scale | E15: 1 = אישה 2 = גבר | F15: i67 | G15: =VLOOKUP($F15, codebooks_data_reordered!$A:$I, 2, FALSE) -> 1999_1 | H15: =VLOOKUP($F15, codebooks_data_reordered!$A:$I, 3, FALSE) -> EVALUATE PARTIES AND CANDIDATES | I15: =VLOOKUP($F15, codebooks_data_reordered!$A:$I, 4, FALSE) -> 2 | J15: =VLOOKUP($F15, codebooks_data_reordered!$A:$I, 5, FALSE) -> 69 | K15: =VLOOKUP($F15, codebooks_data_reordered!$A:$I, 6, FALSE) -> Corrupt party | L15: =VLOOKUP($F15, codebooks_data_reordered!$A:$I, 7, FALSE) -> 0 | M15: =VLOOKUP($F15, codebooks_data_reordered!$A:$I, 9, FALSE) -> 1: Labor; 2: Likud; 3: Equally; 4: None of them | O15: =SUBSTITUTE(M15, ";", CHAR(10)) -> 1: Labor 2: Likud 3: Equally 4: None of them
... A46: דמוגרפיה | B46: $D$26 | C46: יניב שפירא: 1 = לא למד 2 = למד במסגרת דתית | D46: scale | E46: 1 = לא למד 2 = למד במסגרת דתית | F46: v137 | G46: =VLOOKUP($F46, codebooks_data_reordered!$A:$I, 2, FALSE) -> 1981_1 | H46: =VLOOKUP($F46, codebooks_data_reordered!$A:$I, 3, FALSE) -> CHARACTERIZATION OF MOSHE DAYAN, GRADED SCALE 1-6 | I46: =VLOOKUP($F46, codebooks_data_reordered!$A:$I, 4, FALSE) -> 1 | J46: =VLOOKUP($F46, codebooks_data_reordered!$A:$I, 5, FALSE) -> 138 | K46: =VLOOKUP($F46, codebooks_data_reordered!$A:$I, 6, FALSE) -> Years of schooling | L46: =VLOOKUP($F46, codebooks_data_reordered!$A:$I, 7, FALSE) -> 0 | M46: =VLOOKUP($F46, codebooks_data_reordered!$A:$I, 9, FALSE) -> 1: Did not study; 2: Up to 4 years; 3: 5-8; 4: 9-10; 5: 11; 6: 12; 7: 13+, without academic degree; 8: University degree | O46: =SUBSTITUTE(M46, ";", CHAR(10)) -> 1: Did not study 2: Up to 4 years 3: 5-8 4: 9-10 5: 11 6: 12 7: 13+, without academic degree 8: University degree
A47: דמוגרפיה | B47: $A$27 | C47: יניב שפירא: ב2022 הוצאה עמדה על 16,000 ₪ ב2019 הוצאה עמדה על 15,000 ₪ ב2015 ההוצאה עמדה על 14,000 ₪ | D47: scale | E47: ב2022 הוצאה עמדה על 16,000 ₪ ב2019 הוצאה עמדה על 15,000 ₪ ב2015 ההוצאה עמדה על 14,000 ₪ | F47: ההוצאה החודשית הממוצעת של משפחה בישראל היא כ-16,500 ₪. בהתחשב בכל ההוצאות של משפחתכם, האם אתם מוציאים: | G47: =VLOOKUP($F47, codebooks_data_reordered!$A:$I, 2, FALSE) -> #N/A | H47: =VLOOKUP($F47, codebooks_data_reordered!$A:$I, 3, FALSE) -> #N/A | I47: =VLOOKUP($F47, codebooks_data_reordered!$A:$I, 4, FALSE) -> #N/A | J47: =VLOOKUP($F47, codebooks_data_reordered!$A:$I, 5, FALSE) -> #N/A | K47: =VLOOKUP($F47, codebooks_data_reordered!$A:$I, 6, FALSE) -> #N/A | L47: =VLOOKUP($F47, codebooks_data_reordered!$A:$I, 7, FALSE) -> #N/A | M47: =VLOOKUP($F47, codebooks_data_reordered!$A:$I, 9, FALSE) -> #N/A | N47: 2022, 2019, 2015 | O47: =SUBSTITUTE(M47, ";", CHAR(10)) -> #N/A
A48: דמוגרפיה | B48: $D$27 | C48: יניב שפירא: 1 = הרבה מתחת לממוצע 2 = מעט מתחת לממוצע 3 = כמו הממוצע 4 = מעט מעל הממוצע 5 = הרבה מעל הממוצע | D48: scale | E48: 1 = הרבה מתחת לממוצע 2 = מעט מתחת לממוצע 3 = כמו הממוצע 4 = מעט מעל הממוצע 5 = הרבה מעל הממוצע | F48: v139 | G48: =VLOOKUP($F48, codebooks_data_reordered!$A:$I, 2, FALSE) -> 1981_1 | H48: =VLOOKUP($F48, codebooks_data_reordered!$A:$I, 3, FALSE) -> CHARACTERIZATION OF MOSHE DAYAN, GRADED SCALE 1-6 | I48: =VLOOKUP($F48, codebooks_data_reordered!$A:$I, 4, FALSE) -> 1 | J48: =VLOOKUP($F48, codebooks_data_reordered!$A:$I, 5, FALSE) -> 140 | K48: =VLOOKUP($F48, codebooks_data_reordered!$A:$I, 6, FALSE) -> Year of Aliyah (immigration) | L48: =VLOOKUP($F48, codebooks_data_reordered!$A:$I, 7, FALSE) -> 0 | M48: =VLOOKUP($F48, codebooks_data_reordered!$A:$I, 9, FALSE) -> 0: 1980+; 1: Born in Israel; 2: Before 1948; 3: 1948-1954; 4: 1955-1960; 5: 1961-1966; 6: 1967-1972; 7: 1973-1977; 8: 1978-1978 | O48: =SUBSTITUTE(M48, ";", CHAR(10)) -> 0: 1980+ 1: Born in Israel 2: Before 1948 3: 1948-1954 4: 1955-1960 5: 1961-1966 6: 1967-1972 7: 1973-1977 8: 1978-1978
A49: דמוגרפיה | B49: $I$27 | C49: יניב שפירא: 1 = הרבה מעל הממוצע 2 = מעט מעל הממוצע 3 = כמו הממוצע 4 = מעט מתחת לממוצע 5 = הרבה מתחת לממוצע | D49: scale | E49: 1 = הרבה מעל הממוצע 2 = מעט מעל הממוצע 3 = כמו הממוצע 4 = מעט מתחת לממוצע 5 = הרבה מתחת לממוצע | F49: v184 | G49: =VLOOKUP($F49, codebooks_data_reordered!$A:$I, 2, FALSE) -> #N/A | H49: =VLOOKUP($F49, codebooks_data_reordered!$A:$I, 3, FALSE) -> #N/A | I49: =VLOOKUP($F49, codebooks_data_reordered!$A:$I, 4, FALSE) -> #N/A | J49: =VLOOKUP($F49, codebooks_data_reordered!$A:$I, 5, FALSE) -> #N/A | K49: =VLOOKUP($F49, codebooks_data_reordered!$A:$I, 6, FALSE) -> #N/A | L49: =VLOOKUP($F49, codebooks_data_reordered!$A:$I, 7, FALSE) -> #N/A | M49: =VLOOKUP($F49, codebooks_data_reordered!$A:$I, 9, FALSE) -> #N/A | O49: =SUBSTITUTE(M49, ";", CHAR(10)) -> #N/A
A50: דמוגרפיה | B50: $S$27 | C50: יניב שפירא: 1 = הרבה מתחת לממוצע 2 = מעט מתחת לממוצע 3 = כמו הממוצע 4 = מעט מעל הממוצע 5 = הרבה מעל הממוצע | D50: scale | E50: 1 = הרבה מתחת לממוצע 2 = מעט מתחת לממוצע 3 = כמו הממוצע 4 = מעט מעל הממוצע 5 = הרבה מעל הממוצע | F50: a55 | G50: =VLOOKUP($F50, codebooks_data_reordered!$A:$I, 2, FALSE) -> 2006 | H50: =VLOOKUP($F50, codebooks_data_reordered!$A:$I, 3, FALSE) -> Agree/Disagree with the Different Statements | I50: =VLOOKUP($F50, codebooks_data_reordered!$A:$I, 4, FALSE) -> 1 | J50: =VLOOKUP($F50, codebooks_data_reordered!$A:$I, 5, FALSE) -> 58 | K50: =VLOOKUP($F50, codebooks_data_reordered!$A:$I, 6, FALSE) -> Affect government policy | L50: =VLOOKUP($F50, codebooks_data_reordered!$A:$I, 7, FALSE) -> 54. To what extent can you and your friends effect government policy? | M50: =VLOOKUP($F50, codebooks_data_reordered!$A:$I, 9, FALSE) -> 1: A great amount; 2: A certain amount; 3: A small amount; 4: Not at all | O50: =SUBSTITUTE(M50, ";", CHAR(10)) -> 1: A great amount 2: A certain amount 3: A small amount 4: Not at all
A51: דמוגרפיה | B51: $T$28 | C51: יניב שפירא: 1 = עד 1,000 2 = 1,001-1,500 3 = 1,501-2,000 4 = 2,001-2,500 5 = 2,501-3,000 6 = 3,001-4,000 7 = 4,001-5,000 8 = 5,001-6,000 9 = 6,001-7,000 10 = 7,001 + | D51: scale | E51: 1 = עד 1,000 2 = 1,001-1,500 3 = 1,501-2,000 4 = 2,001-2,500 5 = 2,501-3,000 6 = 3,001-4,000 7 = 4,001-5,000 8 = 5,001-6,000 9 = 6,001-7,000 10 = 7,001 + | F51: b158 | G51: =VLOOKUP($F51, codebooks_data_reordered!$A:$I, 2, FALSE) -> 1981_3 | H51: =VLOOKUP($F51, codebooks_data_reordered!$A:$I, 3, FALSE) -> INTERVIEWEE EVALUATION OF THE STATE OF ISRAEL | I51: =VLOOKUP($F51, codebooks_data_reordered!$A:$I, 4, FALSE) -> 1 | J51: =VLOOKUP($F51, codebooks_data_reordered!$A:$I, 5, FALSE) -> 168 | K51: =VLOOKUP($F51, codebooks_data_reordered!$A:$I, 6, FALSE) -> Political tendency interviewee identifies with | L51: =VLOOKUP($F51, codebooks_data_reordered!$A:$I, 7, FALSE) -> 0 | M51: =VLOOKUP($F51, codebooks_data_reordered!$A:$I, 9, FALSE) -> 1: Left; 2: Moderate left; 3: Center; 4: Moderate right; 5: Right; 6: Religious; 7: Does not identify with any tendency | O51: =SUBSTITUTE(M51, ";", CHAR(10)) -> 1: Left 2: Moderate left 3: Center 4: Moderate right 5: Right 6: Religious 7: Does not identify with any tendency
A52: דמוגרפיה | B52: $T$29 | C52: יניב שפירא: 1 = חדר אחד 2 = שני חדרים 3 = שלושה חדרים 4 = ארבעה חדרים 5 = חמישה חדרים 6 = שישה חדרים 7 = שבעה חדרים 8 = שמונה חדרים 9 = תשעה חדשים ויותר | D52: scale | E52: 1 = חדר אחד 2 = שני חדרים 3 = שלושה חדרים 4 = ארבעה חדרים 5 = חמישה חדרים 6 = שישה חדרים 7 = שבעה חדרים 8 = שמונה חדרים 9 = תשעה חדשים ויותר | F52: b149 | G52: =VLOOKUP($F52, codebooks_data_reordered!$A:$I, 2, FALSE) -> 1981_3 | H52: =VLOOKUP($F52, codebooks_data_reordered!$A:$I, 3, FALSE) -> INTERVIEWEE EVALUATION OF THE STATE OF ISRAEL | I52: =VLOOKUP($F52, codebooks_data_reordered!$A:$I, 4, FALSE) -> 1 | J52: =VLOOKUP($F52, codebooks_data_reordered!$A:$I, 5, FALSE) -> 155 | K52: =VLOOKUP($F52, codebooks_data_reordered!$A:$I, 6, FALSE) -> Number of times interviewee goes to synagogue during the year | L52: =VLOOKUP($F52, codebooks_data_reordered!$A:$I, 7, FALSE) -> 0 | M52: =VLOOKUP($F52, codebooks_data_reordered!$A:$I, 9, FALSE) -> 1: Every day; 2: Almost every Sabbath and holiday; 3: A few times; 4: Only on Yom Kippur; 5: Never | O52: =SUBSTITUTE(M52, ";", CHAR(10)) -> 1: Every day 2: Almost every Sabbath and holiday 3: A few times 4: Only on Yom Kippur 5: Never
A53: דמוגרפיה | B53: $T$30 | C53: יניב שפירא: 1 = 1 2 = 2 3 = 3 4 = 4 5 = 5 6 = 6 7 = 7 8 = 8 9 = 9+ | D53: scale | E53: 1 = 1 2 = 2 3 = 3 4 = 4 5 = 5 6 = 6 7 = 7 8 = 8 9 = 9+ | F53: b151 | G53: =VLOOKUP($F53, codebooks_data_reordered!$A:$I, 2, FALSE) -> 1981_3 | H53: =VLOOKUP($F53, codebooks_data_reordered!$A:$I, 3, FALSE) -> INTERVIEWEE EVALUATION OF THE STATE OF ISRAEL | I53: =VLOOKUP($F53, codebooks_data_reordered!$A:$I, 4, FALSE) -> 1 | J53: =VLOOKUP($F53, codebooks_data_reordered!$A:$I, 5, FALSE) -> 156 | K53: =VLOOKUP($F53, codebooks_data_reordered!$A:$I, 6, FALSE) -> Number of rooms in dwelling | L53: =VLOOKUP($F53, codebooks_data_reordered!$A:$I, 7, FALSE) -> 0 | M53: =VLOOKUP($F53, codebooks_data_reordered!$A:$I, 9, FALSE) -> 1: One room; 2: 2; 3: 3; 4: 4; 5: 5; 6: 6; 7: 7; 8: 8; 9: 9+ | O53: =SUBSTITUTE(M53, ";", CHAR(10)) -> 1: One room 2: 2 3: 3 4: 4 5: 5 6: 6 7: 7 8: 8 9: 9+
A54: דמוגרפיה | B54: $AF$30 | C54: יניב שפירא: מס' הילדים שגרים בבית | D54: rephrase | E54: מס' הילדים שגרים בבית | F54: c52 | G54: =VLOOKUP($F54, codebooks_data_reordered!$A:$I, 2, FALSE) -> 2006 | H54: =VLOOKUP($F54, codebooks_data_reordered!$A:$I, 3, FALSE) -> Self-identity | I54: =VLOOKUP($F54, codebooks_data_reordered!$A:$I, 4, FALSE) -> 1 | J54: =VLOOKUP($F54, codebooks_data_reordered!$A:$I, 5, FALSE) -> 266 | K54: =VLOOKUP($F54, codebooks_data_reordered!$A:$I, 6, FALSE) -> Minimum threshold for representation in the Knesset | L54: =VLOOKUP($F54, codebooks_data_reordered!$A:$I, 7, FALSE) -> 51. To the best of your knowledge, what is the minimum threshold for representation in the Knesset? | M54: =VLOOKUP($F54, codebooks_data_reordered!$A:$I, 9, FALSE) -> 1: 2%; 2: Wrong answer; 8: Don't know | O54: =SUBSTITUTE(M54, ";", CHAR(10)) -> 1: 2% 2: Wrong answer 8: Don't know
A55: דמוגרפיה | B55: $S$31 | C55: יניב שפירא: צפיפות מדד אחד לחדרים\נפשות | D55: scale | E55: צפיפות מדד אחד לחדרים\נפשות | F55: a57 | G55: =VLOOKUP($F55, codebooks_data_reordered!$A:$I, 2, FALSE) -> 2006 | H55: =VLOOKUP($F55, codebooks_data_reordered!$A:$I, 3, FALSE) -> Personal Status | I55: =VLOOKUP($F55, codebooks_data_reordered!$A:$I, 4, FALSE) -> 1 | J55: =VLOOKUP($F55, codebooks_data_reordered!$A:$I, 5, FALSE) -> 60 | K55: =VLOOKUP($F55, codebooks_data_reordered!$A:$I, 6, FALSE) -> Your personal status 5 years ago | L55: =VLOOKUP($F55, codebooks_data_reordered!$A:$I, 7, FALSE) -> Here you have a 9 stages scale describing different situations a person can be on. The top of the ladder is 9 and that is the best possible situation that you can think of and 1 is the worst. On which rank would you place yourself? | M55: =VLOOKUP($F55, codebooks_data_reordered!$A:$I, 9, FALSE) -> 1: Worst; 9: Best | O55: =SUBSTITUTE(M55, ";", CHAR(10)) -> 1: Worst 9: Best
A56: דמוגרפיה | B56: $AF$31 | C56: יניב שפירא: 1 = עד ולא כולל 1 2 = 1-1.99 2 = 2-2.99 3 = 3-3.99 4 = 4+ | D56: scale | E56: 1 = עד ולא כולל 1 2 = 1-1.99 2 = 2-2.99 3 = 3-3.99 4 = 4+ | F56: c50 | G56: =VLOOKUP($F56, codebooks_data_reordered!$A:$I, 2, FALSE) -> 2006 | H56: =VLOOKUP($F56, codebooks_data_reordered!$A:$I, 3, FALSE) -> Self-identity | I56: =VLOOKUP($F56, codebooks_data_reordered!$A:$I, 4, FALSE) -> 1 | J56: =VLOOKUP($F56, codebooks_data_reordered!$A:$I, 5, FALSE) -> 264 | K56: =VLOOKUP($F56, codebooks_data_reordered!$A:$I, 6, FALSE) -> Self-identity for Arabs (third) | L56: =VLOOKUP($F56, codebooks_data_reordered!$A:$I, 7, FALSE) -> (for Arabs): Which of the following concepts best defines your identity? (read) and the second? And the third? And the fourth? | M56: =VLOOKUP($F56, codebooks_data_reordered!$A:$I, 9, FALSE) -> 1: Israeli; 2: Palestinian; 3: Arab; 4: Muslim/Christian/Druze | O56: =SUBSTITUTE(M56, ";", CHAR(10)) -> 1: Israeli 2: Palestinian 3: Arab 4: Muslim/Christian/Druze
A57: דמוגרפיה | B57: $D$32 | C57: יניב שפירא: 1 = יהודי 2 = מוסלמי 3 = נוצרי 4 = דרוזי 5 = אחר | D57: scale | E57: 1 = יהודי 2 = מוסלמי 3 = נוצרי 4 = דרוזי 5 = אחר | F57: v143_code | G57: =VLOOKUP($F57, codebooks_data_reordered!$A:$I, 2, FALSE) -> #N/A | H57: =VLOOKUP($F57, codebooks_data_reordered!$A:$I, 3, FALSE) -> #N/A | I57: =VLOOKUP($F57, codebooks_data_reordered!$A:$I, 4, FALSE) -> #N/A | J57: =VLOOKUP($F57, codebooks_data_reordered!$A:$I, 5, FALSE) -> #N/A | K57: =VLOOKUP($F57, codebooks_data_reordered!$A:$I, 6, FALSE) -> #N/A | L57: =VLOOKUP($F57, codebooks_data_reordered!$A:$I, 7, FALSE) -> #N/A | M57: =VLOOKUP($F57, codebooks_data_reordered!$A:$I, 9, FALSE) -> #N/A | O57: =SUBSTITUTE(M57, ";", CHAR(10)) -> #N/A
A58: דמוגרפיה | B58: $K$32 | C58: יניב שפירא: לא ליהודים 1 = מוסלמי 2 = נוצרי 3 = דרוזי | D58: scale | E58: לא ליהודים 1 = מוסלמי 2 = נוצרי 3 = דרוזי | F58: b90 | G58: =VLOOKUP($F58, codebooks_data_reordered!$A:$I, 2, FALSE) -> 2003 | H58: =VLOOKUP($F58, codebooks_data_reordered!$A:$I, 3, FALSE) -> Respondent's demographic details | I58: =VLOOKUP($F58, codebooks_data_reordered!$A:$I, 4, FALSE) -> 1 | J58: =VLOOKUP($F58, codebooks_data_reordered!$A:$I, 5, FALSE) -> 198 | K58: =VLOOKUP($F58, codebooks_data_reordered!$A:$I, 6, FALSE) -> Social class (self identified) | L58: =VLOOKUP($F58, codebooks_data_reordered!$A:$I, 7, FALSE) -> To which social class do you belong? | M58: =VLOOKUP($F58, codebooks_data_reordered!$A:$I, 9, FALSE) -> 1: Upper class; 2: Middle upper; 3: Middle; 4: Lower | O58: =SUBSTITUTE(M58, ";", CHAR(10)) -> 1: Upper class 2: Middle upper 3: Middle 4: Lower
A59: דמוגרפיה | B59: $L$32 | C59: יניב שפירא: 5 = מוסלמי 6 = נוצרי 7 = דרוזי | D59: scale | E59: 5 = מוסלמי 6 = נוצרי 7 = דרוזי | F59: b28 | G59: =VLOOKUP($F59, codebooks_data_reordered!$A:$I, 2, FALSE) -> 2006 | H59: =VLOOKUP($F59, codebooks_data_reordered!$A:$I, 3, FALSE) -> State expenditures on Different Issues | I59: =VLOOKUP($F59, codebooks_data_reordered!$A:$I, 4, FALSE) -> 1 | J59: =VLOOKUP($F59, codebooks_data_reordered!$A:$I, 5, FALSE) -> 138 | K59: =VLOOKUP($F59, codebooks_data_reordered!$A:$I, 6, FALSE) -> State expenditures on Ecology | L59: =VLOOKUP($F59, codebooks_data_reordered!$A:$I, 7, FALSE) -> Should the country spend more money, less money or the same as it does today on the following issues: | M59: =VLOOKUP($F59, codebooks_data_reordered!$A:$I, 9, FALSE) -> 1: More; 2: Less; 3: The same as today | O59: =SUBSTITUTE(M59, ";", CHAR(10)) -> 1: More 2: Less 3: The same as today
... A158: ישראל כללי | B158: $S$11 | C158: יניב שפירא: 1 = המערך 2 = הליכוד 3 = שניהם אותו דבר 4 = אף אחד מהם | D158: scale | E158: 1 = המערך 2 = הליכוד 3 = שניהם אותו דבר 4 = אף אחד מהם | F158: v25 | G158: =VLOOKUP($F158, codebooks_data_reordered!$A:$I, 2, FALSE) -> 1999_1 | H158: =VLOOKUP($F158, codebooks_data_reordered!$A:$I, 3, FALSE) -> GENERAL POLITICAL ATTITUDE | I158: =VLOOKUP($F158, codebooks_data_reordered!$A:$I, 4, FALSE) -> 1 | J158: =VLOOKUP($F158, codebooks_data_reordered!$A:$I, 5, FALSE) -> 30 | K158: =VLOOKUP($F158, codebooks_data_reordered!$A:$I, 6, FALSE) -> What should be emphasized to prevent war between Israel and the Arab world? | L158: =VLOOKUP($F158, codebooks_data_reordered!$A:$I, 7, FALSE) -> 0 | M158: =VLOOKUP($F158, codebooks_data_reordered!$A:$I, 9, FALSE) -> 1: Focus on Peace talks; 2: Increase military power | O158: =SUBSTITUTE(M158, ";", CHAR(10)) -> 1: Focus on Peace talks 2: Increase military power
A159: ישראל כללי | B159: $A$12 | C159: יניב שפירא: אין קידוד גם ב2020 וגם ב2021 | D159: scale | E159: אין קידוד גם ב2020 וגם ב2021 | F159: מבין הדברים הבאים, מה לדעתך הכי מאיים על המערכת הפוליטית כיום? | G159: =VLOOKUP($F159, codebooks_data_reordered!$A:$I, 2, FALSE) -> #N/A | H159: =VLOOKUP($F159, codebooks_data_reordered!$A:$I, 3, FALSE) -> #N/A | I159: =VLOOKUP($F159, codebooks_data_reordered!$A:$I, 4, FALSE) -> #N/A | J159: =VLOOKUP($F159, codebooks_data_reordered!$A:$I, 5, FALSE) -> #N/A | K159: =VLOOKUP($F159, codebooks_data_reordered!$A:$I, 6, FALSE) -> #N/A | L159: =VLOOKUP($F159, codebooks_data_reordered!$A:$I, 7, FALSE) -> #N/A | M159: =VLOOKUP($F159, codebooks_data_reordered!$A:$I, 9, FALSE) -> #N/A | N159: 2020, 2021 | O159: =SUBSTITUTE(M159, ";", CHAR(10)) -> #N/A
A160: ישראל כללי | B160: $D$12 | C160: יניב שפירא: 1 = שחיתות 2 = פוליטיקאים שלא מקיימים הבטחות 3 = גורמים שמתערבים בבחירות כך שהתוצאות לא מייצגות את רצון הבוחר 4 = שיטת הבחירות שמעוותת את רצון הבוחרים | D160: scale | E160: 1 = שחיתות 2 = פוליטיקאים שלא מקיימים הבטחות 3 = גורמים שמתערבים בבחירות כך שהתוצאות לא מייצגות את רצון הבוחר 4 = שיטת הבחירות שמעוותת את רצון הבוחרים | F160: 0 | G160: =VLOOKUP($F160, codebooks_data_reordered!$A:$I, 2, FALSE) -> #N/A | H160: =VLOOKUP($F160, codebooks_data_reordered!$A:$I, 3, FALSE) -> #N/A | I160: =VLOOKUP($F160, codebooks_data_reordered!$A:$I, 4, FALSE) -> #N/A | J160: =VLOOKUP($F160, codebooks_data_reordered!$A:$I, 5, FALSE) -> #N/A | K160: =VLOOKUP($F160, codebooks_data_reordered!$A:$I, 6, FALSE) -> #N/A | L160: =VLOOKUP($F160, codebooks_data_reordered!$A:$I, 7, FALSE) -> #N/A | M160: =VLOOKUP($F160, codebooks_data_reordered!$A:$I, 9, FALSE) -> #N/A | O160: =SUBSTITUTE(M160, ";", CHAR(10)) -> #N/A
A161: ישראל כללי | B161: $D$13 | C161: יניב שפירא: 1-10 1 = כלל לא מרוצה 10 = מרוצה לגמרי | D161: scale | E161: 1-10 1 = כלל לא מרוצה 10 = מרוצה לגמרי | F161: v116 | G161: =VLOOKUP($F161, codebooks_data_reordered!$A:$I, 2, FALSE) -> 1988_Panel_N=416 | H161: =VLOOKUP($F161, codebooks_data_reordered!$A:$I, 3, FALSE) -> WHICH OF THE FOLLOWING WOULD YOU BE WILLING TO GIVE TO MAINTAIN/STRENGTHEN THE SECURITY | I161: =VLOOKUP($F161, codebooks_data_reordered!$A:$I, 4, FALSE) -> 1 | J161: =VLOOKUP($F161, codebooks_data_reordered!$A:$I, 5, FALSE) -> 112 | K161: =VLOOKUP($F161, codebooks_data_reordered!$A:$I, 6, FALSE) -> Should security considerations override other social/ecconomic considerations | L161: =VLOOKUP($F161, codebooks_data_reordered!$A:$I, 7, FALSE) -> 0 | M161: =VLOOKUP($F161, codebooks_data_reordered!$A:$I, 9, FALSE) -> 1: Security considerations should override all others; 7: Security should not override | O161: =SUBSTITUTE(M161, ";", CHAR(10)) -> 1: Security considerations should override all others 7: Security should not override
A162: ישראל כללי | B162: $A$14 | C162: יניב שפירא: שאלות 12A-14A בפוסט בחירות 2019 לא מקודדות בstata | D162: stataIsNotCoded | E162: שאלות 12A-14A בפוסט בחירות 2019 לא מקודדות בstata | F162: כאשר אתה חושב על תולדות מדינת ישראל ועם ישראל, איזה אירוע מהעבר נראה לך החשוב ביותר? | G162: =VLOOKUP($F162, codebooks_data_reordered!$A:$I, 2, FALSE) -> #N/A | H162: =VLOOKUP($F162, codebooks_data_reordered!$A:$I, 3, FALSE) -> #N/A | I162: =VLOOKUP($F162, codebooks_data_reordered!$A:$I, 4, FALSE) -> #N/A | J162: =VLOOKUP($F162, codebooks_data_reordered!$A:$I, 5, FALSE) -> #N/A | K162: =VLOOKUP($F162, codebooks_data_reordered!$A:$I, 6, FALSE) -> #N/A | L162: =VLOOKUP($F162, codebooks_data_reordered!$A:$I, 7, FALSE) -> #N/A | M162: =VLOOKUP($F162, codebooks_data_reordered!$A:$I, 9, FALSE) -> #N/A | N162: 2019 | O162: =SUBSTITUTE(M162, ";", CHAR(10)) -> #N/A
A163: ישראל כללי | B163: $B$14 | C163: adi: שאלות 709-711 לא מקודדות בנתונים | D163: stataIsNotCoded | E163: שאלות 709-711 לא מקודדות בנתונים | F163: 0 | G163: =VLOOKUP($F163, codebooks_data_reordered!$A:$I, 2, FALSE) -> #N/A | H163: =VLOOKUP($F163, codebooks_data_reordered!$A:$I, 3, FALSE) -> #N/A | I163: =VLOOKUP($F163, codebooks_data_reordered!$A:$I, 4, FALSE) -> #N/A | J163: =VLOOKUP($F163, codebooks_data_reordered!$A:$I, 5, FALSE) -> #N/A | K163: =VLOOKUP($F163, codebooks_data_reordered!$A:$I, 6, FALSE) -> #N/A | L163: =VLOOKUP($F163, codebooks_data_reordered!$A:$I, 7, FALSE) -> #N/A | M163: =VLOOKUP($F163, codebooks_data_reordered!$A:$I, 9, FALSE) -> #N/A | O163: =SUBSTITUTE(M163, ";", CHAR(10)) -> #N/A
A164: ישראל כללי | B164: $B$15 | C164: adi: שאלות 709-711 לא מקודדות בנתונים | D164: stataIsNotCoded | E164: שאלות 709-711 לא מקודדות בנתונים | F164: 0 | G164: =VLOOKUP($F164, codebooks_data_reordered!$A:$I, 2, FALSE) -> #N/A | H164: =VLOOKUP($F164, codebooks_data_reordered!$A:$I, 3, FALSE) -> #N/A | I164: =VLOOKUP($F164, codebooks_data_reordered!$A:$I, 4, FALSE) -> #N/A | J164: =VLOOKUP($F164, codebooks_data_reordered!$A:$I, 5, FALSE) -> #N/A | K164: =VLOOKUP($F164, codebooks_data_reordered!$A:$I, 6, FALSE) -> #N/A | L164: =VLOOKUP($F164, codebooks_data_reordered!$A:$I, 7, FALSE) -> #N/A | M164: =VLOOKUP($F164, codebooks_data_reordered!$A:$I, 9, FALSE) -> #N/A | O164: =SUBSTITUTE(M164, ";", CHAR(10)) -> #N/A
A165: ישראל כללי | B165: $B$16 | C165: adi: שאלות 709-711 לא מקודדות בנתונים | D165: stataIsNotCoded | E165: שאלות 709-711 לא מקודדות בנתונים | F165: 0 | G165: =VLOOKUP($F165, codebooks_data_reordered!$A:$I, 2, FALSE) -> #N/A | H165: =VLOOKUP($F165, codebooks_data_reordered!$A:$I, 3, FALSE) -> #N/A | I165: =VLOOKUP($F165, codebooks_data_reordered!$A:$I, 4, FALSE) -> #N/A | J165: =VLOOKUP($F165, codebooks_data_reordered!$A:$I, 5, FALSE) -> #N/A | K165: =VLOOKUP($F165, codebooks_data_reordered!$A:$I, 6, FALSE) -> #N/A | L165: =VLOOKUP($F165, codebooks_data_reordered!$A:$I, 7, FALSE) -> #N/A | M165: =VLOOKUP($F165, codebooks_data_reordered!$A:$I, 9, FALSE) -> #N/A | O165: =SUBSTITUTE(M165, ";", CHAR(10)) -> #N/A
A166: ישראל כללי | B166: $G$17 | C166: יניב שפירא: 1 = בהחלט לא מסכים 2 = לא מסכים 3 = מסכים 4 = מסכים מאד | D166: scale | E166: 1 = בהחלט לא מסכים 2 = לא מסכים 3 = מסכים 4 = מסכים מאד | F166: v33 | G166: =VLOOKUP($F166, codebooks_data_reordered!$A:$I, 2, FALSE) -> 1999_1 | H166: =VLOOKUP($F166, codebooks_data_reordered!$A:$I, 3, FALSE) -> VALUES AND TRUST | I166: =VLOOKUP($F166, codebooks_data_reordered!$A:$I, 4, FALSE) -> 1 | J166: =VLOOKUP($F166, codebooks_data_reordered!$A:$I, 5, FALSE) -> 38 | K166: =VLOOKUP($F166, codebooks_data_reordered!$A:$I, 6, FALSE) -> Extend of faith in the Supreme Court | L166: =VLOOKUP($F166, codebooks_data_reordered!$A:$I, 7, FALSE) -> 0 | M166: =VLOOKUP($F166, codebooks_data_reordered!$A:$I, 9, FALSE) -> 1: Not at all; 2: A little faith; 3: Some faith; 4: Strong faith | O166: =SUBSTITUTE(M166, ";", CHAR(10)) -> 1: Not at all 2: A little faith 3: Some faith 4: Strong faith
A167: ישראל כללי | B167: $H$18 | C167: יניב שפירא: 1 = בהחלט לא מסכים 2 = לא מסכים 3 = מסכים 4 = מסכים מאד | D167: scale | E167: 1 = בהחלט לא מסכים 2 = לא מסכים 3 = מסכים 4 = מסכים מאד | F167: v40 | G167: =VLOOKUP($F167, codebooks_data_reordered!$A:$I, 2, FALSE) -> 1999_1 | H167: =VLOOKUP($F167, codebooks_data_reordered!$A:$I, 3, FALSE) -> VALUES AND TRUST | I167: =VLOOKUP($F167, codebooks_data_reordered!$A:$I, 4, FALSE) -> 1 | J167: =VLOOKUP($F167, codebooks_data_reordered!$A:$I, 5, FALSE) -> 45 | K167: =VLOOKUP($F167, codebooks_data_reordered!$A:$I, 6, FALSE) -> Peace as a significant value | L167: =VLOOKUP($F167, codebooks_data_reordered!$A:$I, 7, FALSE) -> 0 | M167: =VLOOKUP($F167, codebooks_data_reordered!$A:$I, 9, FALSE) -> 1: Most important value; 2: Second value; 3: Third value; 4: Fourth value | O167: =SUBSTITUTE(M167, ";", CHAR(10)) -> 1: Most important value 2: Second value 3: Third value 4: Fourth value
A168: ישראל כללי | B168: $G$19 | C168: יניב שפירא: 1 = שמירה על כלכלה יציבה 2 = יצירה של סביבה אנושית יותר, שמדגישה יותר יחסי אנוש 3 = יצירת סביבה בה רעיונות נחשבים יותר מכסף 4 = מלחמה בפשע | D168: scale | E168: 1 = שמירה על כלכלה יציבה 2 = יצירה של סביבה אנושית יותר, שמדגישה יותר יחסי אנוש 3 = יצירת סביבה בה רעיונות נחשבים יותר מכסף 4 = מלחמה בפשע | F168: v107 | G168: =VLOOKUP($F168, codebooks_data_reordered!$A:$I, 2, FALSE) -> 1988_Panel_N=416 | H168: =VLOOKUP($F168, codebooks_data_reordered!$A:$I, 3, FALSE) -> WHICH OF THE FOLLOWING WOULD YOU BE WILLING TO GIVE TO MAINTAIN/STRENGTHEN THE SECURITY | I168: =VLOOKUP($F168, codebooks_data_reordered!$A:$I, 4, FALSE) -> 1 | J168: =VLOOKUP($F168, codebooks_data_reordered!$A:$I, 5, FALSE) -> 103 | K168: =VLOOKUP($F168, codebooks_data_reordered!$A:$I, 6, FALSE) -> What is your opinion on the length of military service | L168: =VLOOKUP($F168, codebooks_data_reordered!$A:$I, 7, FALSE) -> 0 | M168: =VLOOKUP($F168, codebooks_data_reordered!$A:$I, 9, FALSE) -> 1: Too long; 2: Appropriate; 3: Too short | O168: =SUBSTITUTE(M168, ";", CHAR(10)) -> 1: Too long 2: Appropriate 3: Too short
A169: ישראל כללי | B169: $I$21 | C169: יניב שפירא: סולם 1-9 1 = מצב גרוע ביותר 9 = מצב טוב ביותר | D169: scale | E169: סולם 1-9 1 = מצב גרוע ביותר 9 = מצב טוב ביותר | F169: v57 | G169: =VLOOKUP($F169, codebooks_data_reordered!$A:$I, 2, FALSE) -> 1999_1 | H169: =VLOOKUP($F169, codebooks_data_reordered!$A:$I, 3, FALSE) -> MORE ATTITUDES TOWARD PARTIES AND CANDIDATES | I169: =VLOOKUP($F169, codebooks_data_reordered!$A:$I, 4, FALSE) -> 1 | J169: =VLOOKUP($F169, codebooks_data_reordered!$A:$I, 5, FALSE) -> 62 | K169: =VLOOKUP($F169, codebooks_data_reordered!$A:$I, 6, FALSE) -> Capitalism or socialism for Israel's economy | L169: =VLOOKUP($F169, codebooks_data_reordered!$A:$I, 7, FALSE) -> Extent of support on 1-10 scale, 1=total rejection, 10=strong support | M169: =VLOOKUP($F169, codebooks_data_reordered!$A:$I, 9, FALSE) -> 1: Definitely prefer capitalism; 2: More capitalist than socialist; 3: More socialist than capitalist; 4: Definitely prefer socialism | O169: =SUBSTITUTE(M169, ";", CHAR(10)) -> 1: Definitely prefer capitalism 2: More capitalist than socialist 3: More socialist than capitalist 4: Definitely prefer socialism
A170: ישראל כללי | B170: $T$21 | C170: יניב שפירא: ארבע שנים ולא חמש סולם 1-10 1 = החיים הטובים ביותר 10 = החיים הגרועים ביותר | D170: scale | E170: ארבע שנים ולא חמש סולם 1-10 1 = החיים הטובים ביותר 10 = החיים הגרועים ביותר | F170: b61 | G170: =VLOOKUP($F170, codebooks_data_reordered!$A:$I, 2, FALSE) -> 2006 | H170: =VLOOKUP($F170, codebooks_data_reordered!$A:$I, 3, FALSE) -> Most/Less Suitable Characteristic of the Party | I170: =VLOOKUP($F170, codebooks_data_reordered!$A:$I, 4, FALSE) -> 1 | J170: =VLOOKUP($F170, codebooks_data_reordered!$A:$I, 5, FALSE) -> 171 | K170: =VLOOKUP($F170, codebooks_data_reordered!$A:$I, 6, FALSE) -> Issues at the center of campaign | L170: =VLOOKUP($F170, codebooks_data_reordered!$A:$I, 7, FALSE) -> 60. Among the following issues, which in your opinion is at the center of the election campaign? Are these elections mainly about the political process with the Palestinians, or the defense situation, or the socio-economic situation, the religious- nonreligious relationships, corruption and the rule by law or the unity of the people? (Read answers 1-3 in changing order). | M170: =VLOOKUP($F170, codebooks_data_reordered!$A:$I, 9, FALSE) -> 1: Peace process with the Palestinians; 2: The security situation; 3: Socio-economic situation; 4: Relationships between religious and nonreligious; 5: Corruption and the rule of law; 6: The unity of the people; 7: Other; 8: Do not know; 9: More than one answer | O170: =SUBSTITUTE(M170, ";", CHAR(10)) -> 1: Peace process with the Palestinians 2: The security situation 3: Socio-economic situation 4: Relationships between religious and nonreligious 5: Corruption and the rule of law 6: The unity of the people 7: Other 8: Do not know 9: More than one answer
A171: ישראל כללי | B171: $V$21 | C171: יניב שפירא: ארבע שנים ולא חמש סולם 1-10 1 = החיים הטובים ביותר 10 = החיים הגרועים ביותר | D171: scale | E171: ארבע שנים ולא חמש סולם 1-10 1 = החיים הטובים ביותר 10 = החיים הגרועים ביותר | F171: v25 | G171: =VLOOKUP($F171, codebooks_data_reordered!$A:$I, 2, FALSE) -> 1999_1 | H171: =VLOOKUP($F171, codebooks_data_reordered!$A:$I, 3, FALSE) -> GENERAL POLITICAL ATTITUDE | I171: =VLOOKUP($F171, codebooks_data_reordered!$A:$I, 4, FALSE) -> 1 | J171: =VLOOKUP($F171, codebooks_data_reordered!$A:$I, 5, FALSE) -> 30 | K171: =VLOOKUP($F171, codebooks_data_reordered!$A:$I, 6, FALSE) -> What should be emphasized to prevent war between Israel and the Arab world? | L171: =VLOOKUP($F171, codebooks_data_reordered!$A:$I, 7, FALSE) -> 0 | M171: =VLOOKUP($F171, codebooks_data_reordered!$A:$I, 9, FALSE) -> 1: Focus on Peace talks; 2: Increase military power | O171: =SUBSTITUTE(M171, ";", CHAR(10)) -> 1: Focus on Peace talks 2: Increase military power
A172: ישראל כללי | B172: $AG$21 | C172: יניב שפירא: סולם 0-10 0 = המצב הגרוע ביותר 10 = המצב הטוב ביותר | D172: scale | E172: סולם 0-10 0 = המצב הגרוע ביותר 10 = המצב הטוב ביותר | F172: a11 | G172: =VLOOKUP($F172, codebooks_data_reordered!$A:$I, 2, FALSE) -> 2006 | H172: =VLOOKUP($F172, codebooks_data_reordered!$A:$I, 3, FALSE) -> Pre-Election Survey | I172: =VLOOKUP($F172, codebooks_data_reordered!$A:$I, 4, FALSE) -> 1 | J172: =VLOOKUP($F172, codebooks_data_reordered!$A:$I, 5, FALSE) -> 13 | K172: =VLOOKUP($F172, codebooks_data_reordered!$A:$I, 6, FALSE) -> Economic situation in past 3 years | L172: =VLOOKUP($F172, codebooks_data_reordered!$A:$I, 7, FALSE) -> 10. Do you think that the economic situation in the past 3 years has improved, didn't change, or got worse? | M172: =VLOOKUP($F172, codebooks_data_reordered!$A:$I, 9, FALSE) -> 1: Improved a lot; 2: Improved a bit; 3: Didn't change; 4: Got a bit worse; 5: Got much worse | O172: =SUBSTITUTE(M172, ";", CHAR(10)) -> 1: Improved a lot 2: Improved a bit 3: Didn't change 4: Got a bit worse 5: Got much worse
A173: ישראל כללי | B173: $AD$24 | C173: יניב שפירא: 1 = תשנה את מצבי באופן אישי 2 = תשנה את המצב במדינה ולכן זה ישנה את מצבי 3 = לא תשנה את מצבי | D173: scale | E173: 1 = תשנה את מצבי באופן אישי 2 = תשנה את המצב במדינה ולכן זה ישנה את מצבי 3 = לא תשנה את מצבי | F173: d44 | G173: =VLOOKUP($F173, codebooks_data_reordered!$A:$I, 2, FALSE) -> 1973_2 | H173: =VLOOKUP($F173, codebooks_data_reordered!$A:$I, 3, FALSE) -> DO YOU AGREE WITH THE FOLLOWING STATEMENT | I173: =VLOOKUP($F173, codebooks_data_reordered!$A:$I, 4, FALSE) -> 2 | J173: =VLOOKUP($F173, codebooks_data_reordered!$A:$I, 5, FALSE) -> 47 | K173: =VLOOKUP($F173, codebooks_data_reordered!$A:$I, 6, FALSE) -> Are you active in any public organization(workers union, Wizo, B'nei Brith, etc) | L173: =VLOOKUP($F173, codebooks_data_reordered!$A:$I, 7, FALSE) -> 0 | M173: =VLOOKUP($F173, codebooks_data_reordered!$A:$I, 9, FALSE) -> 0: No answer; 1: Very active; 2: Active; 3: Not so active; 4: Not at all | O173: =SUBSTITUTE(M173, ";", CHAR(10)) -> 0: No answer 1: Very active 2: Active 3: Not so active 4: Not at all
A174: ישראל כללי | B174: $B$25 | C174: adi: באיזו מידה את/ה תומך/ת או מתנגד/ת להשתתפות של מפלגות ערביות בקואליציה? 1 = מתנגד/ת לחלוטין 2 = מתנגד/ת להשתתפותן בקואלציה, אך בעד תמיכתן מבחוץ 3 = תומך/ת בהשתתפותן בקואליציה, ללא תפקידי שרים 4 = תומך/ת בהשתתפותן בקואליציה, כולל תפקידי שרים | D174: scale | E174: באיזו מידה את/ה תומך/ת או מתנגד/ת להשתתפות של מפלגות ערביות בקואליציה? 1 = מתנגד/ת לחלוטין 2 = מתנגד/ת להשתתפותן בקואלציה, אך בעד תמיכתן מבחוץ 3 = תומך/ת בהשתתפותן בקואליציה, ללא תפקידי שרים 4 = תומך/ת בהשתתפותן בקואליציה, כולל תפקידי שרים | F174: v704 | G174: =VLOOKUP($F174, codebooks_data_reordered!$A:$I, 2, FALSE) -> #N/A | H174: =VLOOKUP($F174, codebooks_data_reordered!$A:$I, 3, FALSE) -> #N/A | I174: =VLOOKUP($F174, codebooks_data_reordered!$A:$I, 4, FALSE) -> #N/A | J174: =VLOOKUP($F174, codebooks_data_reordered!$A:$I, 5, FALSE) -> #N/A | K174: =VLOOKUP($F174, codebooks_data_reordered!$A:$I, 6, FALSE) -> #N/A | L174: =VLOOKUP($F174, codebooks_data_reordered!$A:$I, 7, FALSE) -> #N/A | M174: =VLOOKUP($F174, codebooks_data_reordered!$A:$I, 9, FALSE) -> #N/A | O174: =SUBSTITUTE(M174, ";", CHAR(10)) -> #N/A
A175: ישראל כללי | B175: $L$25 | C175: יניב שפירא: 1 = מתנגד מאד 2 = מתנגד במידה מסוימת 3 = תומך במידה מסוימת 4 = תומך מאד | D175: scale | E175: 1 = מתנגד מאד 2 = מתנגד במידה מסוימת 3 = תומך במידה מסוימת 4 = תומך מאד | F175: b13 | G175: =VLOOKUP($F175, codebooks_data_reordered!$A:$I, 2, FALSE) -> 2006 | H175: =VLOOKUP($F175, codebooks_data_reordered!$A:$I, 3, FALSE) -> Ranking on a Right/Left Political Scale | I175: =VLOOKUP($F175, codebooks_data_reordered!$A:$I, 4, FALSE) -> 1 | J175: =VLOOKUP($F175, codebooks_data_reordered!$A:$I, 5, FALSE) -> 122-123 | K175: =VLOOKUP($F175, codebooks_data_reordered!$A:$I, 6, FALSE) -> Ranking on a right/left political scale:Likud | L175: =VLOOKUP($F175, codebooks_data_reordered!$A:$I, 7, FALSE) -> How would you rate the following parties on the left-right scale from 0 to 10, 0 stands for left, and 10 stands for right and 5 is in the middle. | M175: =VLOOKUP($F175, codebooks_data_reordered!$A:$I, 9, FALSE) -> 0: Left; 10: Right | O175: =SUBSTITUTE(M175, ";", CHAR(10)) -> 0: Left 10: Right
A176: ישראל כללי | B176: $M$25 | C176: יניב שפירא: 1 = תומך מאד 2 = תומך במידה מסוימת 3 = מתנגד במידה מסוימת 4 = מתנגד מאד | D176: scale | E176: 1 = תומך מאד 2 = תומך במידה מסוימת 3 = מתנגד במידה מסוימת 4 = מתנגד מאד | F176: c11 | G176: =VLOOKUP($F176, codebooks_data_reordered!$A:$I, 2, FALSE) -> 1999_1 | H176: =VLOOKUP($F176, codebooks_data_reordered!$A:$I, 3, FALSE) -> VOTING PATTERNS | I176: =VLOOKUP($F176, codebooks_data_reordered!$A:$I, 4, FALSE) -> 3 | J176: =VLOOKUP($F176, codebooks_data_reordered!$A:$I, 5, FALSE) -> 13 | K176: =VLOOKUP($F176, codebooks_data_reordered!$A:$I, 6, FALSE) -> Direct election for PM's impact on the government system | L176: =VLOOKUP($F176, codebooks_data_reordered!$A:$I, 7, FALSE) -> 0 | M176: =VLOOKUP($F176, codebooks_data_reordered!$A:$I, 9, FALSE) -> 1: Improves government system; 2: Makes it worse; 3: No change | O176: =SUBSTITUTE(M176, ";", CHAR(10)) -> 1: Improves government system 2: Makes it worse 3: No change
A177: ישראל כללי | B177: $M$26 | C177: יניב שפירא: 1 = האינטרסים של המדינה חשובים יותר 2 = באותה מידה 3 = האינטרסים של הפרט חשובים יותר | D177: scale | E177: 1 = האינטרסים של המדינה חשובים יותר 2 = באותה מידה 3 = האינטרסים של הפרט חשובים יותר | F177: i55 | G177: =VLOOKUP($F177, codebooks_data_reordered!$A:$I, 2, FALSE) -> 1999_1 | H177: =VLOOKUP($F177, codebooks_data_reordered!$A:$I, 3, FALSE) -> MAIN POLITICAL ISSUES | I177: =VLOOKUP($F177, codebooks_data_reordered!$A:$I, 4, FALSE) -> 2 | J177: =VLOOKUP($F177, codebooks_data_reordered!$A:$I, 5, FALSE) -> 57 | K177: =VLOOKUP($F177, codebooks_data_reordered!$A:$I, 6, FALSE) -> Personal experience of ethnic discrimination | L177: =VLOOKUP($F177, codebooks_data_reordered!$A:$I, 7, FALSE) -> 0 | M177: =VLOOKUP($F177, codebooks_data_reordered!$A:$I, 9, FALSE) -> 1: A great amount of discrimination; 2: Much discrimination; 3: Some discrimination; 4: Very little discrimination; 5: No discrimination at all | O177: =SUBSTITUTE(M177, ";", CHAR(10)) -> 1: A great amount of discrimination 2: Much discrimination 3: Some discrimination 4: Very little discrimination 5: No discrimination at all
... A389: זיקה רגשית | B389: $G$7 | C389: יניב שפירא: בבחירות האלו המחנה הציוני | D389: scale | E389: בבחירות האלו המחנה הציוני | F389: v51B | G389: =VLOOKUP($F389, codebooks_data_reordered!$A:$I, 2, FALSE) -> #N/A | H389: =VLOOKUP($F389, codebooks_data_reordered!$A:$I, 3, FALSE) -> #N/A | I389: =VLOOKUP($F389, codebooks_data_reordered!$A:$I, 4, FALSE) -> #N/A | J389: =VLOOKUP($F389, codebooks_data_reordered!$A:$I, 5, FALSE) -> #N/A | K389: =VLOOKUP($F389, codebooks_data_reordered!$A:$I, 6, FALSE) -> #N/A | L389: =VLOOKUP($F389, codebooks_data_reordered!$A:$I, 7, FALSE) -> #N/A | M389: =VLOOKUP($F389, codebooks_data_reordered!$A:$I, 9, FALSE) -> #N/A | O389: =SUBSTITUTE(M389, ";", CHAR(10)) -> #N/A
A390: זיקה רגשית | B390: $A$10 | C390: יניב שפירא: בבחירות 2015 התאחדו עם העבודה ויצרו את "המחנה הציוני" | D390: scale | E390: בבחירות 2015 התאחדו עם העבודה ויצרו את "המחנה הציוני" | F390: מה יחסך לכל אחת מן המפלגות הבאות? התנועה | G390: =VLOOKUP($F390, codebooks_data_reordered!$A:$I, 2, FALSE) -> #N/A | H390: =VLOOKUP($F390, codebooks_data_reordered!$A:$I, 3, FALSE) -> #N/A | I390: =VLOOKUP($F390, codebooks_data_reordered!$A:$I, 4, FALSE) -> #N/A | J390: =VLOOKUP($F390, codebooks_data_reordered!$A:$I, 5, FALSE) -> #N/A | K390: =VLOOKUP($F390, codebooks_data_reordered!$A:$I, 6, FALSE) -> #N/A | L390: =VLOOKUP($F390, codebooks_data_reordered!$A:$I, 7, FALSE) -> #N/A | M390: =VLOOKUP($F390, codebooks_data_reordered!$A:$I, 9, FALSE) -> #N/A | N390: 2015 | O390: =SUBSTITUTE(M390, ";", CHAR(10)) -> #N/A
A391: זיקה רגשית | B391: $E$11 | C391: יניב שפירא: המחנה הדמוקרטי (עם שפיר וברק) | D391: scale | E391: המחנה הדמוקרטי (עם שפיר וברק) | F391: c49_f | G391: =VLOOKUP($F391, codebooks_data_reordered!$A:$I, 2, FALSE) -> #N/A | H391: =VLOOKUP($F391, codebooks_data_reordered!$A:$I, 3, FALSE) -> #N/A | I391: =VLOOKUP($F391, codebooks_data_reordered!$A:$I, 4, FALSE) -> #N/A | J391: =VLOOKUP($F391, codebooks_data_reordered!$A:$I, 5, FALSE) -> #N/A | K391: =VLOOKUP($F391, codebooks_data_reordered!$A:$I, 6, FALSE) -> #N/A | L391: =VLOOKUP($F391, codebooks_data_reordered!$A:$I, 7, FALSE) -> #N/A | M391: =VLOOKUP($F391, codebooks_data_reordered!$A:$I, 9, FALSE) -> #N/A | O391: =SUBSTITUTE(M391, ";", CHAR(10)) -> #N/A
A392: זיקה רגשית | B392: $A$12 | C392: יניב שפירא: רק מגזר יהודי! | D392: sector | E392: רק מגזר יהודי! | F392: מה יחסך לכל אחת מן המפלגות הבאות? ימינה | G392: =VLOOKUP($F392, codebooks_data_reordered!$A:$I, 2, FALSE) -> #N/A | H392: =VLOOKUP($F392, codebooks_data_reordered!$A:$I, 3, FALSE) -> #N/A | I392: =VLOOKUP($F392, codebooks_data_reordered!$A:$I, 4, FALSE) -> #N/A | J392: =VLOOKUP($F392, codebooks_data_reordered!$A:$I, 5, FALSE) -> #N/A | K392: =VLOOKUP($F392, codebooks_data_reordered!$A:$I, 6, FALSE) -> #N/A | L392: =VLOOKUP($F392, codebooks_data_reordered!$A:$I, 7, FALSE) -> #N/A | M392: =VLOOKUP($F392, codebooks_data_reordered!$A:$I, 9, FALSE) -> #N/A | O392: =SUBSTITUTE(M392, ";", CHAR(10)) -> #N/A
A393: זיקה רגשית | B393: $A$13 | C393: יניב שפירא: רק מגזר יהודי | D393: sector | E393: רק מגזר יהודי | F393: מה יחסך לכל אחת מן המפלגות הבאות? תקווה חדשה | G393: =VLOOKUP($F393, codebooks_data_reordered!$A:$I, 2, FALSE) -> #N/A | H393: =VLOOKUP($F393, codebooks_data_reordered!$A:$I, 3, FALSE) -> #N/A | I393: =VLOOKUP($F393, codebooks_data_reordered!$A:$I, 4, FALSE) -> #N/A | J393: =VLOOKUP($F393, codebooks_data_reordered!$A:$I, 5, FALSE) -> #N/A | K393: =VLOOKUP($F393, codebooks_data_reordered!$A:$I, 6, FALSE) -> #N/A | L393: =VLOOKUP($F393, codebooks_data_reordered!$A:$I, 7, FALSE) -> #N/A | M393: =VLOOKUP($F393, codebooks_data_reordered!$A:$I, 9, FALSE) -> #N/A | O393: =SUBSTITUTE(M393, ";", CHAR(10)) -> #N/A
A394: זיקה רגשית | B394: $A$14 | C394: יניב שפירא: רק מגזר יהודי | D394: sector | E394: רק מגזר יהודי | F394: מה יחסך לכל אחת מהמפלגות הבאות? הבית היהודי/מפד"ל | G394: =VLOOKUP($F394, codebooks_data_reordered!$A:$I, 2, FALSE) -> #N/A | H394: =VLOOKUP($F394, codebooks_data_reordered!$A:$I, 3, FALSE) -> #N/A | I394: =VLOOKUP($F394, codebooks_data_reordered!$A:$I, 4, FALSE) -> #N/A | J394: =VLOOKUP($F394, codebooks_data_reordered!$A:$I, 5, FALSE) -> #N/A | K394: =VLOOKUP($F394, codebooks_data_reordered!$A:$I, 6, FALSE) -> #N/A | L394: =VLOOKUP($F394, codebooks_data_reordered!$A:$I, 7, FALSE) -> #N/A | M394: =VLOOKUP($F394, codebooks_data_reordered!$A:$I, 9, FALSE) -> #N/A | O394: =SUBSTITUTE(M394, ";", CHAR(10)) -> #N/A
A395: זיקה רגשית | B395: $B$14 | C395: adi: יחס עם עוצמה יהודית | D395: partyChange | E395: יחס עם עוצמה יהודית | F395: v49s | G395: =VLOOKUP($F395, codebooks_data_reordered!$A:$I, 2, FALSE) -> #N/A | H395: =VLOOKUP($F395, codebooks_data_reordered!$A:$I, 3, FALSE) -> #N/A | I395: =VLOOKUP($F395, codebooks_data_reordered!$A:$I, 4, FALSE) -> #N/A | J395: =VLOOKUP($F395, codebooks_data_reordered!$A:$I, 5, FALSE) -> #N/A | K395: =VLOOKUP($F395, codebooks_data_reordered!$A:$I, 6, FALSE) -> #N/A | L395: =VLOOKUP($F395, codebooks_data_reordered!$A:$I, 7, FALSE) -> #N/A | M395: =VLOOKUP($F395, codebooks_data_reordered!$A:$I, 9, FALSE) -> #N/A | O395: =SUBSTITUTE(M395, ";", CHAR(10)) -> #N/A
A396: זיקה רגשית | B396: $C$14 | C396: יניב שפירא: הציונות הדתית | D396: partyChange | E396: הציונות הדתית | F396: v49S | G396: =VLOOKUP($F396, codebooks_data_reordered!$A:$I, 2, FALSE) -> #N/A | H396: =VLOOKUP($F396, codebooks_data_reordered!$A:$I, 3, FALSE) -> #N/A | I396: =VLOOKUP($F396, codebooks_data_reordered!$A:$I, 4, FALSE) -> #N/A | J396: =VLOOKUP($F396, codebooks_data_reordered!$A:$I, 5, FALSE) -> #N/A | K396: =VLOOKUP($F396, codebooks_data_reordered!$A:$I, 6, FALSE) -> #N/A | L396: =VLOOKUP($F396, codebooks_data_reordered!$A:$I, 7, FALSE) -> #N/A | M396: =VLOOKUP($F396, codebooks_data_reordered!$A:$I, 9, FALSE) -> #N/A | O396: =SUBSTITUTE(M396, ";", CHAR(10)) -> #N/A
A397: זיקה רגשית | B397: $J$14 | C397: יניב שפירא: מפד"ל-האיחוד הלאומי | D397: partyChange | E397: מפד"ל-האיחוד הלאומי | F397: a63 | G397: =VLOOKUP($F397, codebooks_data_reordered!$A:$I, 2, FALSE) -> 2006 | H397: =VLOOKUP($F397, codebooks_data_reordered!$A:$I, 3, FALSE) -> Support/Rejection of a Group or a Person | I397: =VLOOKUP($F397, codebooks_data_reordered!$A:$I, 4, FALSE) -> 1 | J397: =VLOOKUP($F397, codebooks_data_reordered!$A:$I, 5, FALSE) -> 69-70 | K397: =VLOOKUP($F397, codebooks_data_reordered!$A:$I, 6, FALSE) -> Support: Meretz | L397: =VLOOKUP($F397, codebooks_data_reordered!$A:$I, 7, FALSE) -> Here is a scale from 1 to 10 to express support or rejection of a group or a person. '1' describes strong rejection/ hate, and '10' describes strong support/ love. | M397: =VLOOKUP($F397, codebooks_data_reordered!$A:$I, 9, FALSE) -> 1: Hate/rejection; 10: Love/support | O397: =SUBSTITUTE(M397, ";", CHAR(10)) -> 1: Hate/rejection 10: Love/support
A398: זיקה רגשית | B398: $A$15 | C398: יניב שפירא: רק מגזר יהודי! בחירות 2013 רצו עם הליכוד | D398: scale | E398: רק מגזר יהודי! בחירות 2013 רצו עם הליכוד | F398: מה יחסך לכל אחת מן המפלגות הבאות? ישראל ביתנו | G398: =VLOOKUP($F398, codebooks_data_reordered!$A:$I, 2, FALSE) -> #N/A | H398: =VLOOKUP($F398, codebooks_data_reordered!$A:$I, 3, FALSE) -> #N/A | I398: =VLOOKUP($F398, codebooks_data_reordered!$A:$I, 4, FALSE) -> #N/A | J398: =VLOOKUP($F398, codebooks_data_reordered!$A:$I, 5, FALSE) -> #N/A | K398: =VLOOKUP($F398, codebooks_data_reordered!$A:$I, 6, FALSE) -> #N/A | L398: =VLOOKUP($F398, codebooks_data_reordered!$A:$I, 7, FALSE) -> #N/A | M398: =VLOOKUP($F398, codebooks_data_reordered!$A:$I, 9, FALSE) -> #N/A | N398: 2013 | O398: =SUBSTITUTE(M398, ";", CHAR(10)) -> #N/A
A399: זיקה רגשית | B399: $K$15 | C399: יניב שפירא: האיחוד הלאומי | D399: partyChange | E399: האיחוד הלאומי | F399: a32 | G399: =VLOOKUP($F399, codebooks_data_reordered!$A:$I, 2, FALSE) -> 2006 | H399: =VLOOKUP($F399, codebooks_data_reordered!$A:$I, 3, FALSE) -> Threat of Different Issues | I399: =VLOOKUP($F399, codebooks_data_reordered!$A:$I, 4, FALSE) -> 1 | J399: =VLOOKUP($F399, codebooks_data_reordered!$A:$I, 5, FALSE) -> 36 | K399: =VLOOKUP($F399, codebooks_data_reordered!$A:$I, 6, FALSE) -> Threat of no democracy in Israel | L399: =VLOOKUP($F399, codebooks_data_reordered!$A:$I, 7, FALSE) -> To what extent do you consider each of the following situations as a threat? | M399: =VLOOKUP($F399, codebooks_data_reordered!$A:$I, 9, FALSE) -> 1: Not at all threatening; 7: Very threatening | O399: =SUBSTITUTE(M399, ";", CHAR(10)) -> 1: Not at all threatening 7: Very threatening
A400: זיקה רגשית | B400: $A$16 | C400: יניב שפירא: רק מגזר יהודי! | D400: sector | E400: רק מגזר יהודי! | F400: מה יחסך לכל אחת מן המפלגות הבאות? ש"ס | G400: =VLOOKUP($F400, codebooks_data_reordered!$A:$I, 2, FALSE) -> #N/A | H400: =VLOOKUP($F400, codebooks_data_reordered!$A:$I, 3, FALSE) -> #N/A | I400: =VLOOKUP($F400, codebooks_data_reordered!$A:$I, 4, FALSE) -> #N/A | J400: =VLOOKUP($F400, codebooks_data_reordered!$A:$I, 5, FALSE) -> #N/A | K400: =VLOOKUP($F400, codebooks_data_reordered!$A:$I, 6, FALSE) -> #N/A | L400: =VLOOKUP($F400, codebooks_data_reordered!$A:$I, 7, FALSE) -> #N/A | M400: =VLOOKUP($F400, codebooks_data_reordered!$A:$I, 9, FALSE) -> #N/A | O400: =SUBSTITUTE(M400, ";", CHAR(10)) -> #N/A
A401: זיקה רגשית | B401: $A$18 | C401: יניב שפירא: רק מגזר יהודי! | D401: sector | E401: רק מגזר יהודי! | F401: מה יחסך לכל אחת מן המפלגות הבאות? עוצמה יהודית | G401: =VLOOKUP($F401, codebooks_data_reordered!$A:$I, 2, FALSE) -> #N/A | H401: =VLOOKUP($F401, codebooks_data_reordered!$A:$I, 3, FALSE) -> #N/A | I401: =VLOOKUP($F401, codebooks_data_reordered!$A:$I, 4, FALSE) -> #N/A | J401: =VLOOKUP($F401, codebooks_data_reordered!$A:$I, 5, FALSE) -> #N/A | K401: =VLOOKUP($F401, codebooks_data_reordered!$A:$I, 6, FALSE) -> #N/A | L401: =VLOOKUP($F401, codebooks_data_reordered!$A:$I, 7, FALSE) -> #N/A | M401: =VLOOKUP($F401, codebooks_data_reordered!$A:$I, 9, FALSE) -> #N/A | O401: =SUBSTITUTE(M401, ";", CHAR(10)) -> #N/A
A402: זיקה רגשית | B402: $A$19 | C402: יניב שפירא: רק מגזר יהודי! | D402: sector | E402: רק מגזר יהודי! | F402: מה יחסך לכל אחת מן המפלגות הבאות? יהדות התורה | G402: =VLOOKUP($F402, codebooks_data_reordered!$A:$I, 2, FALSE) -> #N/A | H402: =VLOOKUP($F402, codebooks_data_reordered!$A:$I, 3, FALSE) -> #N/A | I402: =VLOOKUP($F402, codebooks_data_reordered!$A:$I, 4, FALSE) -> #N/A | J402: =VLOOKUP($F402, codebooks_data_reordered!$A:$I, 5, FALSE) -> #N/A | K402: =VLOOKUP($F402, codebooks_data_reordered!$A:$I, 6, FALSE) -> #N/A | L402: =VLOOKUP($F402, codebooks_data_reordered!$A:$I, 7, FALSE) -> #N/A | M402: =VLOOKUP($F402, codebooks_data_reordered!$A:$I, 9, FALSE) -> #N/A | O402: =SUBSTITUTE(M402, ";", CHAR(10)) -> #N/A
A403: זיקה רגשית | B403: $B$21 | C403: adi: חד"ש תע"ל | D403: scale | E403: חד"ש תע"ל | F403: v49j | G403: =VLOOKUP($F403, codebooks_data_reordered!$A:$I, 2, FALSE) -> #N/A | H403: =VLOOKUP($F403, codebooks_data_reordered!$A:$I, 3, FALSE) -> #N/A | I403: =VLOOKUP($F403, codebooks_data_reordered!$A:$I, 4, FALSE) -> #N/A | J403: =VLOOKUP($F403, codebooks_data_reordered!$A:$I, 5, FALSE) -> #N/A | K403: =VLOOKUP($F403, codebooks_data_reordered!$A:$I, 6, FALSE) -> #N/A | L403: =VLOOKUP($F403, codebooks_data_reordered!$A:$I, 7, FALSE) -> #N/A | M403: =VLOOKUP($F403, codebooks_data_reordered!$A:$I, 9, FALSE) -> #N/A | O403: =SUBSTITUTE(M403, ";", CHAR(10)) -> #N/A
A404: זיקה רגשית | B404: $F$21 | C404: יניב שפירא: רק חד"ש-תע"ל | D404: sector | E404: רק חד"ש-תע"ל | F404: v49J | G404: =VLOOKUP($F404, codebooks_data_reordered!$A:$I, 2, FALSE) -> #N/A | H404: =VLOOKUP($F404, codebooks_data_reordered!$A:$I, 3, FALSE) -> #N/A | I404: =VLOOKUP($F404, codebooks_data_reordered!$A:$I, 4, FALSE) -> #N/A | J404: =VLOOKUP($F404, codebooks_data_reordered!$A:$I, 5, FALSE) -> #N/A | K404: =VLOOKUP($F404, codebooks_data_reordered!$A:$I, 6, FALSE) -> #N/A | L404: =VLOOKUP($F404, codebooks_data_reordered!$A:$I, 7, FALSE) -> #N/A | M404: =VLOOKUP($F404, codebooks_data_reordered!$A:$I, 9, FALSE) -> #N/A | O404: =SUBSTITUTE(M404, ";", CHAR(10)) -> #N/A
A405: זיקה רגשית | B405: $A$22 | C405: יניב שפירא: רק ערבים | D405: sector | E405: רק ערבים | F405: מה יחסך לכל אחת מן המפלגות הבאות? רע"מ-בל"ד | G405: =VLOOKUP($F405, codebooks_data_reordered!$A:$I, 2, FALSE) -> #N/A | H405: =VLOOKUP($F405, codebooks_data_reordered!$A:$I, 3, FALSE) -> #N/A | I405: =VLOOKUP($F405, codebooks_data_reordered!$A:$I, 4, FALSE) -> #N/A | J405: =VLOOKUP($F405, codebooks_data_reordered!$A:$I, 5, FALSE) -> #N/A | K405: =VLOOKUP($F405, codebooks_data_reordered!$A:$I, 6, FALSE) -> #N/A | L405: =VLOOKUP($F405, codebooks_data_reordered!$A:$I, 7, FALSE) -> #N/A | M405: =VLOOKUP($F405, codebooks_data_reordered!$A:$I, 9, FALSE) -> #N/A | O405: =SUBSTITUTE(M405, ";", CHAR(10)) -> #N/A
A406: זיקה רגשית | B406: $A$23 | C406: יניב שפירא: רק ערבים | D406: sector | E406: רק ערבים | F406: מה יחסך לכל אחת מן המפלגות הבאות? רע"מ-תע"ל | G406: =VLOOKUP($F406, codebooks_data_reordered!$A:$I, 2, FALSE) -> #N/A | H406: =VLOOKUP($F406, codebooks_data_reordered!$A:$I, 3, FALSE) -> #N/A | I406: =VLOOKUP($F406, codebooks_data_reordered!$A:$I, 4, FALSE) -> #N/A | J406: =VLOOKUP($F406, codebooks_data_reordered!$A:$I, 5, FALSE) -> #N/A | K406: =VLOOKUP($F406, codebooks_data_reordered!$A:$I, 6, FALSE) -> #N/A | L406: =VLOOKUP($F406, codebooks_data_reordered!$A:$I, 7, FALSE) -> #N/A | M406: =VLOOKUP($F406, codebooks_data_reordered!$A:$I, 9, FALSE) -> #N/A | O406: =SUBSTITUTE(M406, ";", CHAR(10)) -> #N/A
A407: זיקה רגשית | B407: $A$24 | C407: יניב שפירא: ערבים בלבד | D407: sector | E407: ערבים בלבד | F407: מה יחסך לכל אחת מן המפלגות הבאות? חד"ש | G407: =VLOOKUP($F407, codebooks_data_reordered!$A:$I, 2, FALSE) -> #N/A | H407: =VLOOKUP($F407, codebooks_data_reordered!$A:$I, 3, FALSE) -> #N/A | I407: =VLOOKUP($F407, codebooks_data_reordered!$A:$I, 4, FALSE) -> #N/A | J407: =VLOOKUP($F407, codebooks_data_reordered!$A:$I, 5, FALSE) -> #N/A | K407: =VLOOKUP($F407, codebooks_data_reordered!$A:$I, 6, FALSE) -> #N/A | L407: =VLOOKUP($F407, codebooks_data_reordered!$A:$I, 7, FALSE) -> #N/A | M407: =VLOOKUP($F407, codebooks_data_reordered!$A:$I, 9, FALSE) -> #N/A | O407: =SUBSTITUTE(M407, ";", CHAR(10)) -> #N/A
A408: זיקה רגשית | B408: $A$25 | C408: יניב שפירא: ערבים בלבד | D408: sector | E408: ערבים בלבד | F408: מה יחסך לכל אחת מן המפלגות הבאות? תע"ל | G408: =VLOOKUP($F408, codebooks_data_reordered!$A:$I, 2, FALSE) -> #N/A | H408: =VLOOKUP($F408, codebooks_data_reordered!$A:$I, 3, FALSE) -> #N/A | I408: =VLOOKUP($F408, codebooks_data_reordered!$A:$I, 4, FALSE) -> #N/A | J408: =VLOOKUP($F408, codebooks_data_reordered!$A:$I, 5, FALSE) -> #N/A | K408: =VLOOKUP($F408, codebooks_data_reordered!$A:$I, 6, FALSE) -> #N/A | L408: =VLOOKUP($F408, codebooks_data_reordered!$A:$I, 7, FALSE) -> #N/A | M408: =VLOOKUP($F408, codebooks_data_reordered!$A:$I, 9, FALSE) -> #N/A | O408: =SUBSTITUTE(M408, ";", CHAR(10)) -> #N/A
A409: זיקה רגשית | B409: $A$26 | C409: יניב שפירא: ערבים בלבד | D409: sector | E409: ערבים בלבד | F409: מה יחסך לכל אחת מן המפלגות הבאות? רע"מ | G409: =VLOOKUP($F409, codebooks_data_reordered!$A:$I, 2, FALSE) -> #N/A | H409: =VLOOKUP($F409, codebooks_data_reordered!$A:$I, 3, FALSE) -> #N/A | I409: =VLOOKUP($F409, codebooks_data_reordered!$A:$I, 4, FALSE) -> #N/A | J409: =VLOOKUP($F409, codebooks_data_reordered!$A:$I, 5, FALSE) -> #N/A | K409: =VLOOKUP($F409, codebooks_data_reordered!$A:$I, 6, FALSE) -> #N/A | L409: =VLOOKUP($F409, codebooks_data_reordered!$A:$I, 7, FALSE) -> #N/A | M409: =VLOOKUP($F409, codebooks_data_reordered!$A:$I, 9, FALSE) -> #N/A | O409: =SUBSTITUTE(M409, ";", CHAR(10)) -> #N/A
A410: זיקה רגשית | B410: $A$27 | C410: יניב שפירא: ערבים בלבד | D410: sector | E410: ערבים בלבד | F410: מה יחסך לכל אחת מן המפלגות הבאות? בל"ד | G410: =VLOOKUP($F410, codebooks_data_reordered!$A:$I, 2, FALSE) -> #N/A | H410: =VLOOKUP($F410, codebooks_data_reordered!$A:$I, 3, FALSE) -> #N/A | I410: =VLOOKUP($F410, codebooks_data_reordered!$A:$I, 4, FALSE) -> #N/A | J410: =VLOOKUP($F410, codebooks_data_reordered!$A:$I, 5, FALSE) -> #N/A | K410: =VLOOKUP($F410, codebooks_data_reordered!$A:$I, 6, FALSE) -> #N/A | L410: =VLOOKUP($F410, codebooks_data_reordered!$A:$I, 7, FALSE) -> #N/A | M410: =VLOOKUP($F410, codebooks_data_reordered!$A:$I, 9, FALSE) -> #N/A | O410: =SUBSTITUTE(M410, ";", CHAR(10)) -> #N/A
... A646: הצבעה | B646: $T$28 | C646: יניב שפירא: בחירות 1969 | D646: rephrase | E646: בחירות 1969 | F646: b99 | G646: =VLOOKUP($F646, codebooks_data_reordered!$A:$I, 2, FALSE) -> 2003 | H646: =VLOOKUP($F646, codebooks_data_reordered!$A:$I, 3, FALSE) -> Respondent's demographic details | I646: =VLOOKUP($F646, codebooks_data_reordered!$A:$I, 4, FALSE) -> 1 | J646: =VLOOKUP($F646, codebooks_data_reordered!$A:$I, 5, FALSE) -> 207 | K646: =VLOOKUP($F646, codebooks_data_reordered!$A:$I, 6, FALSE) -> Month of interview | L646: =VLOOKUP($F646, codebooks_data_reordered!$A:$I, 7, FALSE) -> Date of interview - month | M646: =VLOOKUP($F646, codebooks_data_reordered!$A:$I, 9, FALSE) -> 0 | O646: =SUBSTITUTE(M646, ";", CHAR(10)) -> 0
A647: הצבעה | B647: $J$29 | C647: יניב שפירא: שתי מערכות בחירות אחורה הבחירות לרה"מ 2001 1 = ברק 2 = שרון 3 = פתק לבן 4 = לא הצבעתי למרות שהייתה לי זכות הצבעה 5 = לא הצבעתי כי לא הייתה לי זכות הצבעה | D647: scale | E647: שתי מערכות בחירות אחורה הבחירות לרה"מ 2001 1 = ברק 2 = שרון 3 = פתק לבן 4 = לא הצבעתי למרות שהייתה לי זכות הצבעה 5 = לא הצבעתי כי לא הייתה לי זכות הצבעה | F647: c42 | G647: =VLOOKUP($F647, codebooks_data_reordered!$A:$I, 2, FALSE) -> 2006 | H647: =VLOOKUP($F647, codebooks_data_reordered!$A:$I, 3, FALSE) -> Previous Elections | I647: =VLOOKUP($F647, codebooks_data_reordered!$A:$I, 4, FALSE) -> 1 | J647: =VLOOKUP($F647, codebooks_data_reordered!$A:$I, 5, FALSE) -> 255-256 | K647: =VLOOKUP($F647, codebooks_data_reordered!$A:$I, 6, FALSE) -> Vote in 2003 elections | L647: =VLOOKUP($F647, codebooks_data_reordered!$A:$I, 7, FALSE) -> 40. For which party did you vote in the previous elections in 2003? (do not read the answers) | M647: =VLOOKUP($F647, codebooks_data_reordered!$A:$I, 9, FALSE) -> 1: Likud; 2: Avoda-Meimad; 3: Shinui; 4: Meretz; 5: Ihud Leumi; 6: Mafdal; 7: Yahadut Hatora; 8: Shas; 9: Am Ehad; 10: Israel Bealiya; 11: Green party; 12: Balad; 13: Raam; 14: Hadash; 15: Another; 16: Ale Yarok; 17: Hazit Leumit Yehudit (Marzel); 18: Herut; 19: Daam; 90: Don't remember; 96: Blank ballot; 97: Didn't vote although had the right to vote; 98: Didn't vote / did not have the right to vote; 99: Refuse to answer | N647: 2001 | O647: =SUBSTITUTE(M647, ";", CHAR(10)) -> 1: Likud 2: Avoda-Meimad 3: Shinui 4: Meretz 5: Ihud Leumi 6: Mafdal 7: Yahadut Hatora 8: Shas 9: Am Ehad 10: Israel Bealiya 11: Green party 12: Balad 13: Raam 14: Hadash 15: Another 16: Ale Yarok 17: Hazit Leumit Yehudit (Marzel) 18: Herut 19: Daam 90: Don't remember 96: Blank ballot 97: Didn't vote although had the right to vote 98: Didn't vote / did not have the right to vote 99: Refuse to answer
A648: הצבעה | B648: $K$29 | C648: יניב שפירא: 1 = ברק 2 = נתניהו 3 = לא הצבעתי למרות שהייתה לי זכות 4 = לא הצבעתי כי לא הייתה לי זכות | D648: scale | E648: 1 = ברק 2 = נתניהו 3 = לא הצבעתי למרות שהייתה לי זכות 4 = לא הצבעתי כי לא הייתה לי זכות | F648: b69 | G648: =VLOOKUP($F648, codebooks_data_reordered!$A:$I, 2, FALSE) -> 2006 | H648: =VLOOKUP($F648, codebooks_data_reordered!$A:$I, 3, FALSE) -> Newspaper/TV | I648: =VLOOKUP($F648, codebooks_data_reordered!$A:$I, 4, FALSE) -> 1 | J648: =VLOOKUP($F648, codebooks_data_reordered!$A:$I, 5, FALSE) -> 178-179 | K648: =VLOOKUP($F648, codebooks_data_reordered!$A:$I, 6, FALSE) -> Which TV channel | L648: =VLOOKUP($F648, codebooks_data_reordered!$A:$I, 7, FALSE) -> 67. And which TV channel do you usually watch? (do not read) | M648: =VLOOKUP($F648, codebooks_data_reordered!$A:$I, 9, FALSE) -> 1: Channel 1; 2: Channel 2; 3: Channel 9 (Israel+); 4: Channel 10; 5: RTVI; 6: Al-Jazira; 7: MBC; 8: Other; 9: More than one in Hebrew; 10: ORT (Russian); 11: CNN; 12: RTVI and Israel+; 13: RTVI and/or Israel+ and Hebrew channel; 14: Israel+ and ORT; 15: Euronews; 16: More than one in Arabic; 17: More thane one in Arabic and Hebrew; 18: El-Manar; 19: BBC; 20: TV-5 (France); 21: NTV (Russian) | O648: =SUBSTITUTE(M648, ";", CHAR(10)) -> 1: Channel 1 2: Channel 2 3: Channel 9 (Israel+) 4: Channel 10 5: RTVI 6: Al-Jazira 7: MBC 8: Other 9: More than one in Hebrew 10: ORT (Russian) 11: CNN 12: RTVI and Israel+ 13: RTVI and/or Israel+ and Hebrew channel 14: Israel+ and ORT 15: Euronews 16: More than one in Arabic 17: More thane one in Arabic and Hebrew 18: El-Manar 19: BBC 20: TV-5 (France) 21: NTV (Russian)
A649: הצבעה | B649: $D$30 | C649: יניב שפירא: 1 = כן 2 = לא 3 = פתק לבן | D649: scale | E649: 1 = כן 2 = לא 3 = פתק לבן | F649: E1_after | G649: =VLOOKUP($F649, codebooks_data_reordered!$A:$I, 2, FALSE) -> #N/A | H649: =VLOOKUP($F649, codebooks_data_reordered!$A:$I, 3, FALSE) -> #N/A | I649: =VLOOKUP($F649, codebooks_data_reordered!$A:$I, 4, FALSE) -> #N/A | J649: =VLOOKUP($F649, codebooks_data_reordered!$A:$I, 5, FALSE) -> #N/A | K649: =VLOOKUP($F649, codebooks_data_reordered!$A:$I, 6, FALSE) -> #N/A | L649: =VLOOKUP($F649, codebooks_data_reordered!$A:$I, 7, FALSE) -> #N/A | M649: =VLOOKUP($F649, codebooks_data_reordered!$A:$I, 9, FALSE) -> #N/A | O649: =SUBSTITUTE(M649, ";", CHAR(10)) -> #N/A
A650: הצבעה | B650: $D$31 | C650: יניב שפירא: 1 = הליכוד (בנימין נתניהו) 2 = כחול-לבן (בני גנץ) 3 = העבודה-גשר-מרצ (עמיר פרץ) 4 = ימינה (נפתלי בנט) 5 = עוצמה יהודית (איתמר בן גביר) 7 = יהדות התורה 8 = ש"ס 9 = ישראל ביתנו 11 = הרשימה המשותפת 30 = אחר 94 = לא הצבעתי 96 = פתק לבן 98 = לא יודע 99 = מסרב לענות | D650: scale | E650: 1 = הליכוד (בנימין נתניהו) 2 = כחול-לבן (בני גנץ) 3 = העבודה-גשר-מרצ (עמיר פרץ) 4 = ימינה (נפתלי בנט) 5 = עוצמה יהודית (איתמר בן גביר) 7 = יהדות התורה 8 = ש"ס 9 = ישראל ביתנו 11 = הרשימה המשותפת 30 = אחר 94 = לא הצבעתי 96 = פתק לבן 98 = לא יודע 99 = מסרב לענות | F650: E2_after | G650: =VLOOKUP($F650, codebooks_data_reordered!$A:$I, 2, FALSE) -> #N/A | H650: =VLOOKUP($F650, codebooks_data_reordered!$A:$I, 3, FALSE) -> #N/A | I650: =VLOOKUP($F650, codebooks_data_reordered!$A:$I, 4, FALSE) -> #N/A | J650: =VLOOKUP($F650, codebooks_data_reordered!$A:$I, 5, FALSE) -> #N/A | K650: =VLOOKUP($F650, codebooks_data_reordered!$A:$I, 6, FALSE) -> #N/A | L650: =VLOOKUP($F650, codebooks_data_reordered!$A:$I, 7, FALSE) -> #N/A | M650: =VLOOKUP($F650, codebooks_data_reordered!$A:$I, 9, FALSE) -> #N/A | O650: =SUBSTITUTE(M650, ";", CHAR(10)) -> #N/A
A651: הצבעה | B651: $F$31 | C651: יניב שפירא: 1 = הליכוד (בנימין נתניהו) 2 = כחול-לבן (בני גנץ ויאיר לפיד) 3 = העבודה (אבי גבאי) 4 = הימין החדש (בנט ושקד) 5 = איחוד מפלגות הימין 6 = מרצ 7 = יהדות התורה 8 = ש"ס 9 = ישראל ביתנו (ליברמן) 10 = כולנו (כחלון) 11 = חד"ש-תע"ל 12 = רע"ם-בל"ד 13 = יחד (אלי ישי) 14 = זהות (פייגלין) 15 = גשר (אורלי לוי-אבקסיס) 16 = אחי ישראל (עדינה בר שלום) 17 = מגן (גל הירש) 18 = ביח"ד (יום טוס סמיה) 30 = אחר 94 = לא מתכוון להצביע 96 = פתק לבן 97 = לא החליט/מתלבט 98 = לא יודע 99 = מסרב לענות | D651: scale | E651: 1 = הליכוד (בנימין נתניהו) 2 = כחול-לבן (בני גנץ ויאיר לפיד) 3 = העבודה (אבי גבאי) 4 = הימין החדש (בנט ושקד) 5 = איחוד מפלגות הימין 6 = מרצ 7 = יהדות התורה 8 = ש"ס 9 = ישראל ביתנו (ליברמן) 10 = כולנו (כחלון) 11 = חד"ש-תע"ל 12 = רע"ם-בל"ד 13 = יחד (אלי ישי) 14 = זהות (פייגלין) 15 = גשר (אורלי לוי-אבקסיס) 16 = אחי ישראל (עדינה בר שלום) 17 = מגן (גל הירש) 18 = ביח"ד (יום טוס סמיה) 30 = אחר 94 = לא מתכוון להצביע 96 = פתק לבן 97 = לא החליט/מתלבט 98 = לא יודע 99 = מסרב לענות | F651: v2_after | G651: =VLOOKUP($F651, codebooks_data_reordered!$A:$I, 2, FALSE) -> #N/A | H651: =VLOOKUP($F651, codebooks_data_reordered!$A:$I, 3, FALSE) -> #N/A | I651: =VLOOKUP($F651, codebooks_data_reordered!$A:$I, 4, FALSE) -> #N/A | J651: =VLOOKUP($F651, codebooks_data_reordered!$A:$I, 5, FALSE) -> #N/A | K651: =VLOOKUP($F651, codebooks_data_reordered!$A:$I, 6, FALSE) -> #N/A | L651: =VLOOKUP($F651, codebooks_data_reordered!$A:$I, 7, FALSE) -> #N/A | M651: =VLOOKUP($F651, codebooks_data_reordered!$A:$I, 9, FALSE) -> #N/A | O651: =SUBSTITUTE(M651, ";", CHAR(10)) -> #N/A
A652: הצבעה | B652: $M$32 | C652: יניב שפירא: 1 = כן 2 = לא | D652: scale | E652: 1 = כן 2 = לא | F652: d10 | G652: =VLOOKUP($F652, codebooks_data_reordered!$A:$I, 2, FALSE) -> 2006 | H652: =VLOOKUP($F652, codebooks_data_reordered!$A:$I, 3, FALSE) -> Post-Election Survey | I652: =VLOOKUP($F652, codebooks_data_reordered!$A:$I, 4, FALSE) -> 1 | J652: =VLOOKUP($F652, codebooks_data_reordered!$A:$I, 5, FALSE) -> 321-322 | K652: =VLOOKUP($F652, codebooks_data_reordered!$A:$I, 6, FALSE) -> Favored coalition | L652: =VLOOKUP($F652, codebooks_data_reordered!$A:$I, 7, FALSE) -> 8. And among the following coalitions, which coalition do you favor? (Interviewer: record the exact answer) | M652: =VLOOKUP($F652, codebooks_data_reordered!$A:$I, 9, FALSE) -> 0 | O652: =SUBSTITUTE(M652, ";", CHAR(10)) -> 0
A653: הצבעה | B653: $M$33 | C653: יניב שפירא: d11 d12 d13 | D653: scale | E653: d11 d12 d13 | F653: d11 | G653: =VLOOKUP($F653, codebooks_data_reordered!$A:$I, 2, FALSE) -> 2006 | H653: =VLOOKUP($F653, codebooks_data_reordered!$A:$I, 3, FALSE) -> Post-Election Survey | I653: =VLOOKUP($F653, codebooks_data_reordered!$A:$I, 4, FALSE) -> 1 | J653: =VLOOKUP($F653, codebooks_data_reordered!$A:$I, 5, FALSE) -> 323 | K653: =VLOOKUP($F653, codebooks_data_reordered!$A:$I, 6, FALSE) -> Pleased with election results | L653: =VLOOKUP($F653, codebooks_data_reordered!$A:$I, 7, FALSE) -> 10. In general, are you pleased or not pleased with the election results? | M653: =VLOOKUP($F653, codebooks_data_reordered!$A:$I, 9, FALSE) -> 1: Very pleased; 2: Pleased; 3: Not very pleased; 4: Not pleased at all | O653: =SUBSTITUTE(M653, ";", CHAR(10)) -> 1: Very pleased 2: Pleased 3: Not very pleased 4: Not pleased at all
A654: הצבעה | B654: $Y$35 | C654: יניב שפירא: 1 = מתלבט הרבה יותר 2 = מתלבט יותר 3 = מתלבט פחות 4 = מתלבט הרבה פחות 5 = קודם לא התלבטתי וגם עכשיו לא 6 = ממשיך להתלבט כמו קודם | D654: scale | E654: 1 = מתלבט הרבה יותר 2 = מתלבט יותר 3 = מתלבט פחות 4 = מתלבט הרבה פחות 5 = קודם לא התלבטתי וגם עכשיו לא 6 = ממשיך להתלבט כמו קודם | F654: a11 | G654: =VLOOKUP($F654, codebooks_data_reordered!$A:$I, 2, FALSE) -> 2006 | H654: =VLOOKUP($F654, codebooks_data_reordered!$A:$I, 3, FALSE) -> Pre-Election Survey | I654: =VLOOKUP($F654, codebooks_data_reordered!$A:$I, 4, FALSE) -> 1 | J654: =VLOOKUP($F654, codebooks_data_reordered!$A:$I, 5, FALSE) -> 13 | K654: =VLOOKUP($F654, codebooks_data_reordered!$A:$I, 6, FALSE) -> Economic situation in past 3 years | L654: =VLOOKUP($F654, codebooks_data_reordered!$A:$I, 7, FALSE) -> 10. Do you think that the economic situation in the past 3 years has improved, didn't change, or got worse? | M654: =VLOOKUP($F654, codebooks_data_reordered!$A:$I, 9, FALSE) -> 1: Improved a lot; 2: Improved a bit; 3: Didn't change; 4: Got a bit worse; 5: Got much worse | O654: =SUBSTITUTE(M654, ";", CHAR(10)) -> 1: Improved a lot 2: Improved a bit 3: Didn't change 4: Got a bit worse 5: Got much worse
A655: הצבעה | B655: $M$36 | C655: יניב שפירא: 1 = נתניהו 2 = ברק 3 = פתק לבן 4 = לא הצבעתי | D655: scale | E655: 1 = נתניהו 2 = ברק 3 = פתק לבן 4 = לא הצבעתי | F655: d3 | G655: =VLOOKUP($F655, codebooks_data_reordered!$A:$I, 2, FALSE) -> 1973_2 | H655: =VLOOKUP($F655, codebooks_data_reordered!$A:$I, 3, FALSE) -> DO YOU AGREE WITH THE FOLLOWING STATEMENT | I655: =VLOOKUP($F655, codebooks_data_reordered!$A:$I, 4, FALSE) -> 2 | J655: =VLOOKUP($F655, codebooks_data_reordered!$A:$I, 5, FALSE) -> 5 | K655: =VLOOKUP($F655, codebooks_data_reordered!$A:$I, 6, FALSE) -> To what extent do you think corruption will influence the election results | L655: =VLOOKUP($F655, codebooks_data_reordered!$A:$I, 7, FALSE) -> 0 | M655: =VLOOKUP($F655, codebooks_data_reordered!$A:$I, 9, FALSE) -> 0: No answer; 1: To a great extent; 2: To a certain extent; 3: To a small extent; 4: Not at all | O655: =SUBSTITUTE(M655, ";", CHAR(10)) -> 0: No answer 1: To a great extent 2: To a certain extent 3: To a small extent 4: Not at all
A656: הצבעה | B656: $M$37 | C656: יניב שפירא: 1 = נתניהו 2 = ברק 3 = מרדכי 4 = בגין 5 = בשארה | D656: scale | E656: 1 = נתניהו 2 = ברק 3 = מרדכי 4 = בגין 5 = בשארה | F656: d4 | G656: =VLOOKUP($F656, codebooks_data_reordered!$A:$I, 2, FALSE) -> 1973_2 | H656: =VLOOKUP($F656, codebooks_data_reordered!$A:$I, 3, FALSE) -> DO YOU AGREE WITH THE FOLLOWING STATEMENT | I656: =VLOOKUP($F656, codebooks_data_reordered!$A:$I, 4, FALSE) -> 2 | J656: =VLOOKUP($F656, codebooks_data_reordered!$A:$I, 5, FALSE) -> 6 | K656: =VLOOKUP($F656, codebooks_data_reordered!$A:$I, 6, FALSE) -> To what extent do you think there are differences between parties on corruption | L656: =VLOOKUP($F656, codebooks_data_reordered!$A:$I, 7, FALSE) -> 0 | M656: =VLOOKUP($F656, codebooks_data_reordered!$A:$I, 9, FALSE) -> 0: No answer; 1: There certainly are differences; 2: There are differences; 3: Maybe there are differences; 4: There are no differences | O656: =SUBSTITUTE(M656, ";", CHAR(10)) -> 0: No answer 1: There certainly are differences 2: There are differences 3: Maybe there are differences 4: There are no differences
A657: הצבעה | B657: $M$38 | C657: יניב שפירא: 1 = כן 2 = לא | D657: scale | E657: 1 = כן 2 = לא | F657: d5 | G657: =VLOOKUP($F657, codebooks_data_reordered!$A:$I, 2, FALSE) -> 2006 | H657: =VLOOKUP($F657, codebooks_data_reordered!$A:$I, 3, FALSE) -> Rersonal and Household Details | I657: =VLOOKUP($F657, codebooks_data_reordered!$A:$I, 4, FALSE) -> 1 | J657: =VLOOKUP($F657, codebooks_data_reordered!$A:$I, 5, FALSE) -> 316-317 | K657: =VLOOKUP($F657, codebooks_data_reordered!$A:$I, 6, FALSE) -> Origin in categories | L657: =VLOOKUP($F657, codebooks_data_reordered!$A:$I, 7, FALSE) -> 0 | M657: =VLOOKUP($F657, codebooks_data_reordered!$A:$I, 9, FALSE) -> 1: North Africa; 2: Asia; 3: Eastern Europe; 4: West and Central Europe; 5: America Australia South Africa; 6: Israel Israel; 7: Israel North Africa; 8: Israel Asia; 9: Israel Eastern Europe; 10: Israel West Central Europe; 11: Israel America Australia South Africa | O657: =SUBSTITUTE(M657, ";", CHAR(10)) -> 1: North Africa 2: Asia 3: Eastern Europe 4: West and Central Europe 5: America Australia South Africa 6: Israel Israel 7: Israel North Africa 8: Israel Asia 9: Israel Eastern Europe 10: Israel West Central Europe 11: Israel America Australia South Africa
A658: הצבעה | B658: $M$39 | C658: יניב שפירא: 1 = נתניהו-ברק 2 = מרדכי-נתניהו 3 = בגין-נתניהו 4 = מרדכי-ברק 5 = בגין-בשארה 6 = בשארה-ברק 7 = מרדכי=בשארה 8 = אחר | D658: scale | E658: 1 = נתניהו-ברק 2 = מרדכי-נתניהו 3 = בגין-נתניהו 4 = מרדכי-ברק 5 = בגין-בשארה 6 = בשארה-ברק 7 = מרדכי=בשארה 8 = אחר | F658: d6 | G658: =VLOOKUP($F658, codebooks_data_reordered!$A:$I, 2, FALSE) -> 2006 | H658: =VLOOKUP($F658, codebooks_data_reordered!$A:$I, 3, FALSE) -> Post-Election Survey | I658: =VLOOKUP($F658, codebooks_data_reordered!$A:$I, 4, FALSE) -> 1 | J658: =VLOOKUP($F658, codebooks_data_reordered!$A:$I, 5, FALSE) -> 318 | K658: =VLOOKUP($F658, codebooks_data_reordered!$A:$I, 6, FALSE) -> Voted in the last Knesset elections | L658: =VLOOKUP($F658, codebooks_data_reordered!$A:$I, 7, FALSE) -> 5. Did you vote in the last Knesset elections? | M658: =VLOOKUP($F658, codebooks_data_reordered!$A:$I, 9, FALSE) -> 1: Yes; 2: No | O658: =SUBSTITUTE(M658, ";", CHAR(10)) -> 1: Yes 2: No
A659: הצבעה | B659: $A$41 | C659: יניב שפירא: לא למצביעי הליכוד וכחול-לבן | D659: sector | E659: לא למצביעי הליכוד וכחול-לבן | F659: בבחירות האלה אחוז החסימה מאפשר רק למפלגה שתקבל ארבעה מנדטים לפחות להכנס לכנסת. אם הסקרים שיפורסמו קרוב לבחירות יראו שלא בטוח שהמפלגה עבורה אתה מתכוון להצביע תעבור את אחוז החסימה, האם זה יגרום לך לשנות את הצבעתך? | G659: =VLOOKUP($F659, codebooks_data_reordered!$A:$I, 2, FALSE) -> #N/A | H659: =VLOOKUP($F659, codebooks_data_reordered!$A:$I, 3, FALSE) -> #N/A | I659: =VLOOKUP($F659, codebooks_data_reordered!$A:$I, 4, FALSE) -> #N/A | J659: =VLOOKUP($F659, codebooks_data_reordered!$A:$I, 5, FALSE) -> #N/A | K659: =VLOOKUP($F659, codebooks_data_reordered!$A:$I, 6, FALSE) -> #N/A | L659: =VLOOKUP($F659, codebooks_data_reordered!$A:$I, 7, FALSE) -> #N/A | M659: =VLOOKUP($F659, codebooks_data_reordered!$A:$I, 9, FALSE) -> #N/A | O659: =SUBSTITUTE(M659, ";", CHAR(10)) -> #N/A
... A661: הצבעה | B661: $A$42 | C661: יניב שפירא: רק מי שענה 2 בשאלה הקודמת | D661: followupQuestion | E661: רק מי שענה 2 בשאלה הקודמת | F661: לאיזו מפלגה תעבור? | G661: =VLOOKUP($F661, codebooks_data_reordered!$A:$I, 2, FALSE) -> #N/A | H661: =VLOOKUP($F661, codebooks_data_reordered!$A:$I, 3, FALSE) -> #N/A | I661: =VLOOKUP($F661, codebooks_data_reordered!$A:$I, 4, FALSE) -> #N/A | J661: =VLOOKUP($F661, codebooks_data_reordered!$A:$I, 5, FALSE) -> #N/A | K661: =VLOOKUP($F661, codebooks_data_reordered!$A:$I, 6, FALSE) -> #N/A | L661: =VLOOKUP($F661, codebooks_data_reordered!$A:$I, 7, FALSE) -> #N/A | M661: =VLOOKUP($F661, codebooks_data_reordered!$A:$I, 9, FALSE) -> #N/A | O661: =SUBSTITUTE(M661, ";", CHAR(10)) -> #N/A
A662: הצבעה | B662: $A$43 | C662: יניב שפירא: מי שענה 1 בשאלה על אחוז החסימה (2015) | D662: followupQuestion | E662: מי שענה 1 בשאלה על אחוז החסימה (2015) | F662: מדוע זה לא ישנה את הצבעתך? | G662: =VLOOKUP($F662, codebooks_data_reordered!$A:$I, 2, FALSE) -> #N/A | H662: =VLOOKUP($F662, codebooks_data_reordered!$A:$I, 3, FALSE) -> #N/A | I662: =VLOOKUP($F662, codebooks_data_reordered!$A:$I, 4, FALSE) -> #N/A | J662: =VLOOKUP($F662, codebooks_data_reordered!$A:$I, 5, FALSE) -> #N/A | K662: =VLOOKUP($F662, codebooks_data_reordered!$A:$I, 6, FALSE) -> #N/A | L662: =VLOOKUP($F662, codebooks_data_reordered!$A:$I, 7, FALSE) -> #N/A | M662: =VLOOKUP($F662, codebooks_data_reordered!$A:$I, 9, FALSE) -> #N/A | N662: 2015 | O662: =SUBSTITUTE(M662, ";", CHAR(10)) -> #N/A
A663: הצבעה | B663: $G$43 | C663: יניב שפירא: 1 = כי אי אפשר לסמוך על סקרים 2 = כי חשוב לך לבטא את דעתך ואחוז החסימה לא מהווה שיקול בהחלטתך 3 = כי המפלגה שאתה תומך בה עוברת בוודאות את אחוז החסימה | D663: scale | E663: 1 = כי אי אפשר לסמוך על סקרים 2 = כי חשוב לך לבטא את דעתך ואחוז החסימה לא מהווה שיקול בהחלטתך 3 = כי המפלגה שאתה תומך בה עוברת בוודאות את אחוז החסימה | F663: v96 | G663: =VLOOKUP($F663, codebooks_data_reordered!$A:$I, 2, FALSE) -> 1988_Panel_N=416 | H663: =VLOOKUP($F663, codebooks_data_reordered!$A:$I, 3, FALSE) -> WHICH OF THE FOLLOWING IS A REASON FOR THE ARABS OBJECTING TO ISRAEL'S EXISTENCE | I663: =VLOOKUP($F663, codebooks_data_reordered!$A:$I, 4, FALSE) -> 1 | J663: =VLOOKUP($F663, codebooks_data_reordered!$A:$I, 5, FALSE) -> 92 | K663: =VLOOKUP($F663, codebooks_data_reordered!$A:$I, 6, FALSE) -> Reason for the arabs objecting to Israels' existence:Our technological advantage scares them | L663: =VLOOKUP($F663, codebooks_data_reordered!$A:$I, 7, FALSE) -> 0 | M663: =VLOOKUP($F663, codebooks_data_reordered!$A:$I, 9, FALSE) -> 1: Is a reason; 2: Is not a reason | O663: =SUBSTITUTE(M663, ";", CHAR(10)) -> 1: Is a reason 2: Is not a reason
A664: הצבעה | B664: $F$44 | C664: יניב שפירא: 1 = ביום הבחירות עצמו 2 = יומיים-שלושה לפני הבחירות 3 = כשבוע לפני הבחירות 4 = כחודש לפני הבחירות 5 = כמה חודשים לפני הבחירות 6 = ידעת מלכתחילה למי להצביע | D664: scale | E664: 1 = ביום הבחירות עצמו 2 = יומיים-שלושה לפני הבחירות 3 = כשבוע לפני הבחירות 4 = כחודש לפני הבחירות 5 = כמה חודשים לפני הבחירות 6 = ידעת מלכתחילה למי להצביע | F664: v3_after | G664: =VLOOKUP($F664, codebooks_data_reordered!$A:$I, 2, FALSE) -> #N/A | H664: =VLOOKUP($F664, codebooks_data_reordered!$A:$I, 3, FALSE) -> #N/A | I664: =VLOOKUP($F664, codebooks_data_reordered!$A:$I, 4, FALSE) -> #N/A | J664: =VLOOKUP($F664, codebooks_data_reordered!$A:$I, 5, FALSE) -> #N/A | K664: =VLOOKUP($F664, codebooks_data_reordered!$A:$I, 6, FALSE) -> #N/A | L664: =VLOOKUP($F664, codebooks_data_reordered!$A:$I, 7, FALSE) -> #N/A | M664: =VLOOKUP($F664, codebooks_data_reordered!$A:$I, 9, FALSE) -> #N/A | O664: =SUBSTITUTE(M664, ";", CHAR(10)) -> #N/A
A665: הצבעה | B665: $M$44 | C665: יניב שפירא: 1 = לפני מס' חודשים 2 = בשבועות האחרונים 3 = אחרי פרישת בשארה, בגין ומרדכי 4 = ביום הבחירות | D665: scale | E665: 1 = לפני מס' חודשים 2 = בשבועות האחרונים 3 = אחרי פרישת בשארה, בגין ומרדכי 4 = ביום הבחירות | F665: d8 | G665: =VLOOKUP($F665, codebooks_data_reordered!$A:$I, 2, FALSE) -> 2006 | H665: =VLOOKUP($F665, codebooks_data_reordered!$A:$I, 3, FALSE) -> Post-Election Survey | I665: =VLOOKUP($F665, codebooks_data_reordered!$A:$I, 4, FALSE) -> 1 | J665: =VLOOKUP($F665, codebooks_data_reordered!$A:$I, 5, FALSE) -> 319-320 | K665: =VLOOKUP($F665, codebooks_data_reordered!$A:$I, 6, FALSE) -> List voted for in the last Knesset elections | L665: =VLOOKUP($F665, codebooks_data_reordered!$A:$I, 7, FALSE) -> 6. For which list did you vote in the last Knesset elections? (do not read answers) | M665: =VLOOKUP($F665, codebooks_data_reordered!$A:$I, 9, FALSE) -> 1: Kadima; 2: Likud; 3: Avoda; 4: Israel Beiteinu (Liberman); 5: Ihud Leumi + Mafdal; 6: Yahadut Ha'tora; 7: Shas; 8: Meretz/Yachad; 9: Shinui (Levental); 10: Hetz (Poraz); 11: Green Party; 12: Green Leaf; 13: Pensioners; 14: Hazit Leumit Yehudit (Marzel); 15: Herut (Kleiner); 16: Tafnit (Dayan); 17: Balad; 18: Raam  Taal; 19: Hadash; 20: Lehem; 21: War on banks; 95: Other; 96: Blank ballot; 99: Refused to answer | O665: =SUBSTITUTE(M665, ";", CHAR(10)) -> 1: Kadima 2: Likud 3: Avoda 4: Israel Beiteinu (Liberman) 5: Ihud Leumi + Mafdal 6: Yahadut Ha'tora 7: Shas 8: Meretz/Yachad 9: Shinui (Levental) 10: Hetz (Poraz) 11: Green Party 12: Green Leaf 13: Pensioners 14: Hazit Leumit Yehudit (Marzel) 15: Herut (Kleiner) 16: Tafnit (Dayan) 17: Balad 18: Raam  Taal 19: Hadash 20: Lehem 21: War on banks 95: Other 96: Blank ballot 99: Refused to answer
A666: הצבעה | B666: $AA$44 | C666: יניב שפירא: 1 = מזמן 2 = מאז המלחמה או סמוך לה 3 = בימים הסמוכים לבחירות 4 = ביום הבחירות 5 = לא הלכתי להצביע | D666: scale | E666: 1 = מזמן 2 = מאז המלחמה או סמוך לה 3 = בימים הסמוכים לבחירות 4 = ביום הבחירות 5 = לא הלכתי להצביע | F666: h29 | G666: =VLOOKUP($F666, codebooks_data_reordered!$A:$I, 2, FALSE) -> 1973_5 | H666: =VLOOKUP($F666, codebooks_data_reordered!$A:$I, 3, FALSE) -> POLITICAL LEADERS AND HOW INTERVIEWEE RELATES TO THEM, HOW IMPORTANT THIS FACTOR WAS TO INTERVIEWEE'S VOTE | I666: =VLOOKUP($F666, codebooks_data_reordered!$A:$I, 4, FALSE) -> 1 | J666: =VLOOKUP($F666, codebooks_data_reordered!$A:$I, 5, FALSE) -> 28 | K666: =VLOOKUP($F666, codebooks_data_reordered!$A:$I, 6, FALSE) -> To what extent interviewee is certain in the future he will continue to support party he supported these elections | L666: =VLOOKUP($F666, codebooks_data_reordered!$A:$I, 7, FALSE) -> 0 | M666: =VLOOKUP($F666, codebooks_data_reordered!$A:$I, 9, FALSE) -> 1: Very certain; 2: Certain; 3: Not so certain; 4: Not at all | O666: =SUBSTITUTE(M666, ";", CHAR(10)) -> 1: Very certain 2: Certain 3: Not so certain 4: Not at all
A667: הצבעה | B667: $AB$44 | C667: יניב שפירא: 1 = מזמן 2 = מאז המלחמה או סמוך לה 3 = עם תחילת מערכת הבחירות 4 = היום 5 = בימים הקרובים אחליט 6 = אחליט ביום הבחירות 7 = לא מצביע | D667: scale | E667: 1 = מזמן 2 = מאז המלחמה או סמוך לה 3 = עם תחילת מערכת הבחירות 4 = היום 5 = בימים הקרובים אחליט 6 = אחליט ביום הבחירות 7 = לא מצביע | F667: g39 | G667: =VLOOKUP($F667, codebooks_data_reordered!$A:$I, 2, FALSE) -> 1973_4 | H667: =VLOOKUP($F667, codebooks_data_reordered!$A:$I, 3, FALSE) -> December 1973 | I667: =VLOOKUP($F667, codebooks_data_reordered!$A:$I, 4, FALSE) -> 1 | J667: =VLOOKUP($F667, codebooks_data_reordered!$A:$I, 5, FALSE) -> 43 | K667: =VLOOKUP($F667, codebooks_data_reordered!$A:$I, 6, FALSE) -> To what extent interviewee is certain about whom to vote for | L667: =VLOOKUP($F667, codebooks_data_reordered!$A:$I, 7, FALSE) -> 0 | M667: =VLOOKUP($F667, codebooks_data_reordered!$A:$I, 9, FALSE) -> 1: To a great extent; 2: To a certain extent; 3: To a small extent; 4: Not at all; 5: Will not vote | O667: =SUBSTITUTE(M667, ";", CHAR(10)) -> 1: To a great extent 2: To a certain extent 3: To a small extent 4: Not at all 5: Will not vote
A668: הצבעה | B668: $A$45 | C668: יניב שפירא: למי שענה 1,2,3 בשאלה הקודמת (שאלה 3) | D668: scale | E668: למי שענה 1,2,3 בשאלה הקודמת (שאלה 3) | F668: מה בסופו של דבר הביא אותך להצביע כמו שהצבעת? | G668: =VLOOKUP($F668, codebooks_data_reordered!$A:$I, 2, FALSE) -> #N/A | H668: =VLOOKUP($F668, codebooks_data_reordered!$A:$I, 3, FALSE) -> #N/A | I668: =VLOOKUP($F668, codebooks_data_reordered!$A:$I, 4, FALSE) -> #N/A | J668: =VLOOKUP($F668, codebooks_data_reordered!$A:$I, 5, FALSE) -> #N/A | K668: =VLOOKUP($F668, codebooks_data_reordered!$A:$I, 6, FALSE) -> #N/A | L668: =VLOOKUP($F668, codebooks_data_reordered!$A:$I, 7, FALSE) -> #N/A | M668: =VLOOKUP($F668, codebooks_data_reordered!$A:$I, 9, FALSE) -> #N/A | O668: =SUBSTITUTE(M668, ";", CHAR(10)) -> #N/A
A669: הצבעה | B669: $G$45 | C669: יניב שפירא: יש אופציה ל-3 תשובות מקודדות: after_v4a_1 after_v4a_2 after_v4a_3 | D669: scale | E669: יש אופציה ל-3 תשובות מקודדות: after_v4a_1 after_v4a_2 after_v4a_3 | F669: after_v4a | G669: =VLOOKUP($F669, codebooks_data_reordered!$A:$I, 2, FALSE) -> #N/A | H669: =VLOOKUP($F669, codebooks_data_reordered!$A:$I, 3, FALSE) -> #N/A | I669: =VLOOKUP($F669, codebooks_data_reordered!$A:$I, 4, FALSE) -> #N/A | J669: =VLOOKUP($F669, codebooks_data_reordered!$A:$I, 5, FALSE) -> #N/A | K669: =VLOOKUP($F669, codebooks_data_reordered!$A:$I, 6, FALSE) -> #N/A | L669: =VLOOKUP($F669, codebooks_data_reordered!$A:$I, 7, FALSE) -> #N/A | M669: =VLOOKUP($F669, codebooks_data_reordered!$A:$I, 9, FALSE) -> #N/A | O669: =SUBSTITUTE(M669, ";", CHAR(10)) -> #N/A
A670: הצבעה | B670: $A$46 | C670: יניב שפירא: רק מי שענה שלא הצביע/שם פתק לבן | D670: followupQuestion | E670: רק מי שענה שלא הצביע/שם פתק לבן | F670: מדוע החלטת לא להצביע בבחירות/לשים פתק לבן? | G670: =VLOOKUP($F670, codebooks_data_reordered!$A:$I, 2, FALSE) -> #N/A | H670: =VLOOKUP($F670, codebooks_data_reordered!$A:$I, 3, FALSE) -> #N/A | I670: =VLOOKUP($F670, codebooks_data_reordered!$A:$I, 4, FALSE) -> #N/A | J670: =VLOOKUP($F670, codebooks_data_reordered!$A:$I, 5, FALSE) -> #N/A | K670: =VLOOKUP($F670, codebooks_data_reordered!$A:$I, 6, FALSE) -> #N/A | L670: =VLOOKUP($F670, codebooks_data_reordered!$A:$I, 7, FALSE) -> #N/A | M670: =VLOOKUP($F670, codebooks_data_reordered!$A:$I, 9, FALSE) -> #N/A | O670: =SUBSTITUTE(M670, ";", CHAR(10)) -> #N/A
A671: הצבעה | B671: $L$46 | C671: יניב שפירא: שאלה טרום בחירות למי שענה שלא מתכוון ללכת להצביע/פתק לבן | D671: scale | E671: שאלה טרום בחירות למי שענה שלא מתכוון ללכת להצביע/פתק לבן | F671: b17 | G671: =VLOOKUP($F671, codebooks_data_reordered!$A:$I, 2, FALSE) -> 2006 | H671: =VLOOKUP($F671, codebooks_data_reordered!$A:$I, 3, FALSE) -> Ranking on a Right/Left Political Scale | I671: =VLOOKUP($F671, codebooks_data_reordered!$A:$I, 4, FALSE) -> 1 | J671: =VLOOKUP($F671, codebooks_data_reordered!$A:$I, 5, FALSE) -> 126-127 | K671: =VLOOKUP($F671, codebooks_data_reordered!$A:$I, 6, FALSE) -> Ranking on a right/left political scale:Kadima | L671: =VLOOKUP($F671, codebooks_data_reordered!$A:$I, 7, FALSE) -> How would you rate the following parties on the left-right scale from 0 to 10, 0 stands for left, and 10 stands for right and 5 is in the middle. | M671: =VLOOKUP($F671, codebooks_data_reordered!$A:$I, 9, FALSE) -> 0: Left; 10: Right | O671: =SUBSTITUTE(M671, ";", CHAR(10)) -> 0: Left 10: Right
A672: הצבעה | B672: $N$46 | C672: יניב שפירא: 1 = אף אחד לא נראה מתאים 2 = הבעת מחאה 3 = הרב אמר 4 = בעיות טכניות 5 = אחר | D672: scale | E672: 1 = אף אחד לא נראה מתאים 2 = הבעת מחאה 3 = הרב אמר 4 = בעיות טכניות 5 = אחר | F672: ccc29 | G672: =VLOOKUP($F672, codebooks_data_reordered!$A:$I, 2, FALSE) -> 1996_Jews | H672: =VLOOKUP($F672, codebooks_data_reordered!$A:$I, 3, FALSE) -> WHICH PM CANDID. BEST SUITS EACH DESCRIPTION? | I672: =VLOOKUP($F672, codebooks_data_reordered!$A:$I, 4, FALSE) -> 1 | J672: =VLOOKUP($F672, codebooks_data_reordered!$A:$I, 5, FALSE) -> 177 | K672: =VLOOKUP($F672, codebooks_data_reordered!$A:$I, 6, FALSE) -> Vote for PM, if elections were held today | L672: =VLOOKUP($F672, codebooks_data_reordered!$A:$I, 7, FALSE) -> 0 | M672: =VLOOKUP($F672, codebooks_data_reordered!$A:$I, 9, FALSE) -> 1: Binyamin Netanyahu; 2: Shimon Peres; 3: Blank note; 4: I will not vote; 5: Have not decided yet; 6: Refuses to answer | O672: =SUBSTITUTE(M672, ";", CHAR(10)) -> 1: Binyamin Netanyahu 2: Shimon Peres 3: Blank note 4: I will not vote 5: Have not decided yet 6: Refuses to answer
A673: הצבעה | B673: $F$47 | C673: יניב שפירא: 1 = בכלל לא 2 = במידה מועטה 3 = במידה בינונית 4 = במידה רבה 5 = במידה רבה מאד | D673: scale | E673: 1 = בכלל לא 2 = במידה מועטה 3 = במידה בינונית 4 = במידה רבה 5 = במידה רבה מאד | F673: v5_after | G673: =VLOOKUP($F673, codebooks_data_reordered!$A:$I, 2, FALSE) -> #N/A | H673: =VLOOKUP($F673, codebooks_data_reordered!$A:$I, 3, FALSE) -> #N/A | I673: =VLOOKUP($F673, codebooks_data_reordered!$A:$I, 4, FALSE) -> #N/A | J673: =VLOOKUP($F673, codebooks_data_reordered!$A:$I, 5, FALSE) -> #N/A | K673: =VLOOKUP($F673, codebooks_data_reordered!$A:$I, 6, FALSE) -> #N/A | L673: =VLOOKUP($F673, codebooks_data_reordered!$A:$I, 7, FALSE) -> #N/A | M673: =VLOOKUP($F673, codebooks_data_reordered!$A:$I, 9, FALSE) -> #N/A | O673: =SUBSTITUTE(M673, ";", CHAR(10)) -> #N/A
A674: הצבעה | B674: $AA$47 | C674: יניב שפירא: 1 = במידה רבה 2 = במידה מסוימת 3 = במידה מועטה 4 = כלל לא | D674: scale | E674: 1 = במידה רבה 2 = במידה מסוימת 3 = במידה מועטה 4 = כלל לא | F674: h51 | G674: =VLOOKUP($F674, codebooks_data_reordered!$A:$I, 2, FALSE) -> 1973_5 | H674: =VLOOKUP($F674, codebooks_data_reordered!$A:$I, 3, FALSE) -> POLITICAL LEADERS AND HOW INTERVIEWEE RELATES TO THEM, HOW IMPORTANT THIS FACTOR WAS TO INTERVIEWEE'S VOTE | I674: =VLOOKUP($F674, codebooks_data_reordered!$A:$I, 4, FALSE) -> 1 | J674: =VLOOKUP($F674, codebooks_data_reordered!$A:$I, 5, FALSE) -> 50 | K674: =VLOOKUP($F674, codebooks_data_reordered!$A:$I, 6, FALSE) -> To what extent interviewee read public opinion polls before the elections | L674: =VLOOKUP($F674, codebooks_data_reordered!$A:$I, 7, FALSE) -> 0 | M674: =VLOOKUP($F674, codebooks_data_reordered!$A:$I, 9, FALSE) -> 1: To a great extent; 2: To a certain extent; 3: To a small extent; 4: Not at all | O674: =SUBSTITUTE(M674, ";", CHAR(10)) -> 1: To a great extent 2: To a certain extent 3: To a small extent 4: Not at all
... A699: הצבעה | B699: $G$58 | C699: יניב שפירא: 1 = כן 2 = לא 3 = אולי | D699: scale | E699: 1 = כן 2 = לא 3 = אולי | F699: v93 | G699: =VLOOKUP($F699, codebooks_data_reordered!$A:$I, 2, FALSE) -> 1988_Panel_N=416 | H699: =VLOOKUP($F699, codebooks_data_reordered!$A:$I, 3, FALSE) -> ISRAEL'S CAPABILITY OF COPING WITH VARIOUS SITUATIONS | I699: =VLOOKUP($F699, codebooks_data_reordered!$A:$I, 4, FALSE) -> 1 | J699: =VLOOKUP($F699, codebooks_data_reordered!$A:$I, 5, FALSE) -> 89 | K699: =VLOOKUP($F699, codebooks_data_reordered!$A:$I, 6, FALSE) -> Estimate of the Arabs' ultimate goal | L699: =VLOOKUP($F699, codebooks_data_reordered!$A:$I, 7, FALSE) -> 0 | M699: =VLOOKUP($F699, codebooks_data_reordered!$A:$I, 9, FALSE) -> 1: To retrieve part of the territories seized during the 6 Day War; 2: To retrieve all of the territories seized during the 6 Day War; 3: To conquer Israel; 4: To conquer Israel and annihilate most of the Jewish population | O699: =SUBSTITUTE(M699, ";", CHAR(10)) -> 1: To retrieve part of the territories seized during the 6 Day War 2: To retrieve all of the territories seized during the 6 Day War 3: To conquer Israel 4: To conquer Israel and annihilate most of the Jewish population
...
